Workbook

Sheet README
A1: AUTOMETRIC — KOL DISCOVERY BRAND MATCH ENGINE
A2: Specification and calculation workbook. Twelve sheets: two of inputs, one engine, seven views, one lookup sheet and this page. Generated by scripts/build-brand-match-workbook.mjs and verified by scripts/verify-brand-match-workbook.mjs.
A4: 1. PURPOSE
B5: This workbook is the source of truth for the Autometric KOL Discovery Brand Match calculation. It is not a mock-up: every score on every sheet is an Excel formula over the values in Brand_Profile and KOL_Database, weighted by the constants on Lookup_Lists. Change an input and the workbook re-answers. Hand it to a backend developer and the formulas are the specification — there is no second document that says what the code should do.
B6: It exists because the product needs a Brand Match today and the KOL database cannot supply one: feature.brand_fit_analysis holds 0 rows, which is why four of the eight Smart Preset chips in the running prototype are disabled. The logic has to be agreed and written down before the pipeline is built, not after.
A7: 2. BRAND_PROFILE — the brand half of the inputs
B8: Four sections, matching the Brand Profile & Matching UI: A. Company Profile, B. Target Audience, C. Brand Identification, D. Ideal Creator Profile. A fifth block, E. Matching Configuration, holds the switches that decide which rules act as hard filters.
B9: Columns D, E and F are the three brands. Column G is whichever brand cell B4 names, and that is the column the active-brand views (Match_Explanation, Discovery_Ranking) read. Two calculated blocks sit under the fields: a token helper that splits the comma-separated list fields into five addressable slots, and the audience sub-weights, which move weight onto whichever dimension Audience Demographics Priority names.
A10: 3. KOL_DATABASE — the creator half of the inputs
B11: Thirty creators on Instagram and TikTok, in six blocks: identity, performance, audience, content, commercial, safety — plus the exclusion state and the freshness columns Discovery needs. Tier, CPV, CPE, CPM, Estimated Reach, Estimated ROI, View-to-Follower Ratio, Cost Efficiency, Data Completeness and Data Status are calculated from the columns beside them.
B12: Several creators are missing a field on purpose — a blank Median Views, a blank rate card, a blank audience city. The real roster is full of holes, the Confidence column exists to report them, and every formula here is written to survive one without printing #DIV/0!.
A13: 4. THE SIX COMPONENTS
A14: Brand & Business Relevance | B14: Brand Industry, Product / Service Category, Main Business Keywords, Brand Keywords and Brand Niche against the creator Category, Sub Category, Content Topics and Audience Interests. Industry Match 40%, Category Match 30%, Keyword Match 30% — the last being the two keyword lists scored separately and averaged.
A15: Target Audience Relevance | B15: Age 25%, Gender 15%, Location 30%, Interest 30% — before Audience Demographics Priority moves 12 points onto one of them and takes a third of that off each of the others.
A16: Content & Category Relevance | B16: Preferred Category 30%, Preferred Sub Category 20%, Preferred Content Topics 30%, Preferred Content Style 20%.
A17: Brand Personality Fit | B17: Personality 35%, Tone against Content Style 25%, Values overlap 25%, Communication Style 15%. Related matches count: Innovative is answered by a Tech-savvy or Creative creator, not only by one who calls themselves Innovative.
A18: Performance Quality | B18: Engagement Rate 35%, Audience Quality 20%, Consistency 20%, Community 10%, Average Views 10%, Recent Growth 5%, each normalised to 0–100 against a calibration target on Lookup_Lists.
A19: Brand Safety | B19: Brand Safety Score 80%, head-room from Competitor Saturation 20%, multiplied by the Risk Flag discount (High 0.6, Medium 0.85, Low 0.95). Saturation lowers the score; it never excludes on its own.
A20: 5. WEIGHTING — the master formula
A21: FINAL MATCH = 20% Brand & Business + 30% Target Audience + 20% Content & Category + 10% Brand Personality + 10% Performance + 10% Brand Safety
B23: The six weights live in the COMPONENT WEIGHTS block on Lookup_Lists and nowhere else. The engine divides by their sum rather than by a literal 100, so a workbook whose weights have been edited still produces a 0–100 score; the CHECK_WEIGHT_TOTAL cell beside them says out loud whether they still total 100.
A24: 6. FORMULA LOGIC — how a comparison becomes a number
A25: Category-style comparisons | B25: A matrix lookup on Lookup_Lists, on the 100 / 80 / 60 / 40 / 20 ladder: exact, strongly related, partially related, weakly related, unrelated. Five matrices — Industry × Category, Category × Category, Brand Personality × Creator Personality, Brand Tone × Content Style, Communication Style × Content Style, Content Style × Content Style. Every cell is editable, which is what makes a disputed score a conversation about one number rather than about a model.
A26: List comparisons | B26: Overlap counting. The brand list is split into five slots by the token helper; each slot is looked for in the creator text with SEARCH; the score is matches ÷ slots filled × 100. A brand that names three keywords is judged out of three.
A27: Numeric comparisons | B27: Normalisation against a target on Lookup_Lists: MIN(100, value ÷ target × 100). Engagement Rate scores 100 at 6%; views per follower at 0.5; 30-day growth at 8%, and 0 at −2%.
A28: Missing data | B28: A blank input scores the neutral 50 where the brand left a preference blank, and 0 where the creator is missing a measurement — those are different situations and the formulas keep them apart. Nothing ever divides by an unguarded cell.
A29: Two inputs that carry no weight | B29: Company Description is free text for the brief. Brand Positioning is carried and printed in the Personality Match Reason, but it is deliberately not weighted: the honest thing to weigh a Premium or Luxury positioning against is production quality, and there is no measured production-quality signal on the roster to weigh it against. Inventing one would be the same mistake as the four Smart Preset chips that used to rank by a hash of the creator id. Give it a weight the day a real signal exists.
A30: 7. HARD FILTERS — remove the creator
B31: Platform, Minimum and Maximum Followers, Minimum Engagement Rate, Tier, Minimum Audience Quality, Minimum Brand Safety, Audience Country and Category (both switchable), Max Competitor Saturation, the four exclusion toggles, and Minimum Brand Match. The engine computes the reason first and the verdict from it, so an excluded creator always carries the sentence that explains why. See Filter_Logic.
A32: 8. SOFT MATCHING — reorder the list
B33: Brand Match, Audience Match, Content Relevance, Personality Fit, Performance, Opportunity, Estimated ROI and Competitor Saturation. A low soft score never removes a creator. Competitor Saturation in particular is a warning, not a rejection: it can only exclude through the explicit Max Competitor Saturation setting.
A34: 9. DISCOVERY RANKING
B35: Default order is Brand Match, then Audience Match, then Content Relevance, then Performance, then Brand Safety, encoded as one Default Sort Key so the tie-break order is inspectable. Thirty presets are defined on Lookup_Lists; the picker on Discovery_Ranking reads the metric column each one names. The "Available today" column tells you which of them the KOL database can actually answer — the prototype ships four of its eight chips disabled for exactly this reason.
A36: 10. MATCH EXPLANATION
B37: Generated, not written. The three strengths are the three highest components and the three considerations the three lowest, read with LARGE and SMALL over the same cells the score came from, so an explanation cannot drift away from the number it explains. Each component also carries its own reason line naming its sub-scores.
A38: 11. SAMPLE BRANDS AND SAMPLE OUTPUT
B39: Three briefs — Technology / SaaS, Beauty & Skincare, Food & Beverage — run against one roster of thirty. Sample_Output puts the three scores for each creator side by side and reports the spread. If the engine were ranking creators globally rather than matching brand to creator, that spread would be zero on every row; the verdict cell says whether it is.
A40: 12. TAXONOMY — the tree everything classifies against
B41: One sheet, because the whole point is that the four things are one object: a creator sub category, a brand niche, a raw kol_categories row and a matching keyword are four views of a single tree. Lookup_Lists derives its Category, Sub Category, Industry and Niche dropdowns from it, so no list in this workbook can drift from another.
A42: Three axes | B42: A label answers one question — what the creator makes, who watches, or how it is shot. public.kol_categories mixes all three: "Moms" is an audience and "Gen Z" is an age band, both sitting in a content column. Only the content axis may feed the Category and Sub Category ladders; the audience axis already has its own 30% of the score.
A43: The crosswalk | B43: Brand Niche is collected on Brand_Profile and read by no formula in the engine. Section E is what would give it weight: it names the sub categories each niche is actually asking for, over a default that comes from matrix 5 rather than from nowhere. The derived value is printed beside every override so an override reads as an override.
A44: What it is for | B44: Category covers 54,1% of the roster, Sub Category has no column at all, and Content Topic has none of its 0 rows filled. Section F is the alias table the backend plan is waiting on, and section G is how the 3.547 creators with no category get one — including the rule that a modelled category may rank but must never act as a hard filter.
A45: 13. FOR THE BACKEND — translating this into code
A46: Shape | B46: One pure function: score(brand, creator) → { components, subScores, final, level, confidence, reasons, exclusion }. No I/O, no database access, deterministic. The Field Key column on Brand_Profile is the payload shape; the KOL_Database headers are the creator shape.
A47: Where the constants live | B47: Load the Lookup_Lists blocks — weights, matrices, calibration, bands — from configuration, not from constants in the source. They are meant to be tuned by whoever owns the matching quality, and a redeploy is the wrong unit of change.
A48: Order of operations | B48: Compute all six components, then the Final Match Score, then evaluate the hard filters (Minimum Brand Match needs the score), then rank. Never fold a hard filter into the SQL when it rests on a computed value — the roster pages server-side, and filtering the page you already fetched gives a result count that means nothing.
A49: Provenance | B49: Carry a per-field basis flag the way @/lib/discover/creatorMatch does with SignalBasis. A score built from modelled inputs is useful for ranking and must never be presented as a measurement, and it must never be used as a hard filter.
A50: What to build first | B50: The columns the KOL database cannot answer today are listed with their coverage on Discovery_Filters. The short list: populate feature.brand_fit_analysis; fill audience_demographics_daily with audience_type='age'; widen feature.{ig,tt}_audience_analysis past 23 creators; fill creator_city; populate l1_silver.unified_rate_card. Until then, a filter that rests on one of those must ship disabled with its reason shown, not silently returning nothing.

Sheet Brand_Profile
A1: BRAND PROFILE · Company Profile · Target Audience · Brand Identification · Ideal Creator Profile
A2: The inputs. Columns D–F are the three brands, each cell typed by hand or picked from a dropdown; column G is whichever brand cell B4 names, and that is the column the engine reads for every active-brand view. Nothing on this sheet is calculated from a creator — it is what the brand says about itself before it has seen the roster.
A4: Active Brand → | B4: BRAND-A | G4: active column → | H4: =MATCH($B$4,$D$6:$F$6,0)
A6: Section | B6: Field | C6: Field Key | D6: BRAND-A | E6: BRAND-B | F6: BRAND-C | G6: Active Value | H6: Input type / allowed values
A7: A. COMPANY PROFILE
A8: COMPANY PROFILE | B8: Brand ID | C8: brand_id | D8: BRAND-A | E8: BRAND-B | F8: BRAND-C | G8: =INDEX($D8:$F8,1,$H$4) | H8: Free text
A9: COMPANY PROFILE | B9: Brand Name | C9: brand_name | D9: Nusatech Cloud | E9: Lumaya Skin | F9: Rasa Nusantara | G9: =INDEX($D9:$F9,1,$H$4) | H9: Free text
A10: COMPANY PROFILE | B10: Industry | C10: industry | D10: Technology / SaaS | E10: Beauty & Skincare | F10: Food & Beverage | G10: =INDEX($D10:$F10,1,$H$4) | H10: Dropdown — Lookup_Lists.Industry
A11: COMPANY PROFILE | B11: Company Description | C11: company_description | D11: Workflow automation and team collaboration for Indonesian SMEs. | E11: Dermatologist-tested skincare for humid-climate skin barriers. | F11: Ready-to-drink archipelago flavours for everyday family tables. | G11: =INDEX($D11:$F11,1,$H$4) | H11: Free text
A12: COMPANY PROFILE | B12: Product / Service Category | C12: product_category | D12: Software & SaaS | E12: Skincare | F12: Coffee & Beverage | G12: =INDEX($D12:$F12,1,$H$4) | H12: Dropdown — Lookup_Lists.SubCategory
A13: COMPANY PROFILE | B13: Main Business Keywords | C13: business_keywords | D13: Technology, Productivity, Business, Education, Finance | E13: Skincare, Beauty, Makeup, Health, Shopping | F13: Food, Cooking, Coffee, Shopping, Entertainment | G13: =INDEX($D13:$F13,1,$H$4) | H13: Up to 5 items, comma-separated
A14: COMPANY PROFILE | B14: Brand Niche | C14: brand_niche | D14: B2B SaaS | E14: Derma Skincare | F14: Ready-to-Drink | G14: =INDEX($D14:$F14,1,$H$4) | H14: Dropdown — Lookup_Lists.Niche
A15: B. TARGET AUDIENCE
A16: TARGET AUDIENCE | B16: Primary Age Range | C16: primary_age_range | D16: 25-34 | E16: 18-24 | F16: 25-34 | G16: =INDEX($D16:$F16,1,$H$4) | H16: Dropdown — Lookup_Lists.AgeBand
A17: TARGET AUDIENCE | B17: Secondary Age Range | C17: secondary_age_range | D17: 18-24 | E17: 25-34 | F17: 35-44 | G17: =INDEX($D17:$F17,1,$H$4) | H17: Dropdown — Lookup_Lists.AgeBand
A18: TARGET AUDIENCE | B18: Gender Majority | C18: gender_majority | D18: Any | E18: Female | F18: Balanced | G18: =INDEX($D18:$F18,1,$H$4) | H18: Dropdown — Lookup_Lists.GenderMajority
A19: TARGET AUDIENCE | B19: Target Country | C19: target_country | D19: Indonesia | E19: Indonesia | F19: Indonesia | G19: =INDEX($D19:$F19,1,$H$4) | H19: Dropdown — Lookup_Lists.Country
A20: TARGET AUDIENCE | B20: Target Region / Province | C20: target_region | D20: DKI Jakarta | E20: Nasional | F20: Nasional | G20: =INDEX($D20:$F20,1,$H$4) | H20: Dropdown — Lookup_Lists.Region
A21: TARGET AUDIENCE | B21: Target City | C21: target_city | D21: Jakarta | E21: Jakarta | F21: Nasional | G21: =INDEX($D21:$F21,1,$H$4) | H21: Dropdown — Lookup_Lists.City
A22: TARGET AUDIENCE | B22: Audience Interests | C22: audience_interests | D22: Technology, Business, Productivity, Education, Finance | E22: Skincare, Beauty, Makeup, Fashion, Shopping | F22: Food, Cooking, Coffee, Travel, Entertainment | G22: =INDEX($D22:$F22,1,$H$4) | H22: Up to 5 items, comma-separated
A23: TARGET AUDIENCE | B23: Audience Demographics Priority | C23: audience_priority | D23: Interest | E23: Gender | F23: Age | G23: =INDEX($D23:$F23,1,$H$4) | H23: Dropdown — Lookup_Lists.AudiencePriority
A24: C. BRAND IDENTIFICATION
A25: BRAND IDENTIFICATION | B25: Brand Personality | C25: brand_personality | D25: Innovative | E25: Premium | F25: Friendly | G25: =INDEX($D25:$F25,1,$H$4) | H25: Dropdown — Lookup_Lists.BrandPersonality
A26: BRAND IDENTIFICATION | B26: Brand Values | C26: brand_values | D26: Innovation, Trust, Transparency, Quality, Empowerment | E26: Quality, Authenticity, Trust, Craftsmanship, Health | F26: Fun, Community, Affordability, Authenticity, Family | G26: =INDEX($D26:$F26,1,$H$4) | H26: Up to 5 items, comma-separated
A27: BRAND IDENTIFICATION | B27: Brand Tone | C27: brand_tone | D27: Informative | E27: Aspirational | F27: Warm | G27: =INDEX($D27:$F27,1,$H$4) | H27: Dropdown — Lookup_Lists.BrandTone
A28: BRAND IDENTIFICATION | B28: Brand Positioning | C28: brand_positioning | D28: Mid-market | E28: Premium | F28: Mass | G28: =INDEX($D28:$F28,1,$H$4) | H28: Dropdown — Lookup_Lists.Positioning
A29: BRAND IDENTIFICATION | B29: Brand Keywords | C29: brand_keywords | D29: Technology, Productivity, Business, Education, Finance | E29: Skincare, Beauty, Health, Makeup, Shopping | F29: Food, Cooking, Coffee, Entertainment, Shopping | G29: =INDEX($D29:$F29,1,$H$4) | H29: Up to 5 items, comma-separated
A30: BRAND IDENTIFICATION | B30: Communication Style | C30: communication_style | D30: Educational | E30: Visual-first | F30: Storytelling | G30: =INDEX($D30:$F30,1,$H$4) | H30: Dropdown — Lookup_Lists.CommStyle
A31: D. IDEAL CREATOR PROFILE
A32: IDEAL CREATOR PROFILE | B32: Preferred Platform | C32: preferred_platform | D32: Instagram, TikTok | E32: Instagram, TikTok | F32: Instagram, TikTok | G32: =INDEX($D32:$F32,1,$H$4) | H32: One or more of the Platform list, comma-separated
A33: IDEAL CREATOR PROFILE | B33: Preferred Category | C33: preferred_category | D33: Tech | E33: Beauty | F33: Food | G33: =INDEX($D33:$F33,1,$H$4) | H33: Dropdown — Lookup_Lists.Category
A34: IDEAL CREATOR PROFILE | B34: Preferred Sub Category | C34: preferred_subcategory | D34: Software & SaaS | E34: Skincare | F34: Culinary Review | G34: =INDEX($D34:$F34,1,$H$4) | H34: Dropdown — Lookup_Lists.SubCategory
A35: IDEAL CREATOR PROFILE | B35: Preferred Tier | C35: preferred_tier | D35: Micro, Mid-tier, Macro | E35: Micro, Mid-tier | F35: Nano, Micro, Mid-tier | G35: =INDEX($D35:$F35,1,$H$4) | H35: One or more of the Tier list, comma-separated
A36: IDEAL CREATOR PROFILE | B36: Preferred Follower Range — Min | C36: preferred_followers_min | D36: 10000 | E36: 10000 | F36: 5000 | G36: =INDEX($D36:$F36,1,$H$4) | H36: Whole number
A37: IDEAL CREATOR PROFILE | B37: Preferred Follower Range — Max | C37: preferred_followers_max | D37: 1000000 | E37: 500000 | F37: 400000 | G37: =INDEX($D37:$F37,1,$H$4) | H37: Whole number
A38: IDEAL CREATOR PROFILE | B38: Minimum Engagement Rate (%) | C38: min_engagement_rate | D38: 2.5 | E38: 3 | F38: 3.5 | G38: =INDEX($D38:$F38,1,$H$4) | H38: Percent, e.g. 3.5 means 3,5%
A39: IDEAL CREATOR PROFILE | B39: Preferred Content Style | C39: preferred_content_style | D39: Educational | E39: Review | F39: Storytelling | G39: =INDEX($D39:$F39,1,$H$4) | H39: Dropdown — Lookup_Lists.ContentStyle
A40: IDEAL CREATOR PROFILE | B40: Preferred Content Topics | C40: preferred_content_topics | D40: Technology, Business, Education, Productivity, Finance | E40: Skincare, Beauty, Makeup, Health, Shopping | F40: Food, Cooking, Coffee, Entertainment, Travel | G40: =INDEX($D40:$F40,1,$H$4) | H40: Up to 5 items, comma-separated
A41: IDEAL CREATOR PROFILE | B41: Preferred Creator Personality | C41: preferred_creator_personality | D41: Educational | E41: Reviewer | F41: Relatable | G41: =INDEX($D41:$F41,1,$H$4) | H41: Dropdown — Lookup_Lists.CreatorPersonality
A42: IDEAL CREATOR PROFILE | B42: Preferred Creator Values | C42: preferred_creator_values | D42: Innovation, Trust, Quality, Transparency, Empowerment | E42: Authenticity, Quality, Trust, Health, Craftsmanship | F42: Fun, Community, Authenticity, Family, Affordability | G42: =INDEX($D42:$F42,1,$H$4) | H42: Up to 5 items, comma-separated
A43: IDEAL CREATOR PROFILE | B43: Minimum Audience Quality | C43: min_audience_quality | D43: 65 | E43: 70 | F43: 60 | G43: =INDEX($D43:$F43,1,$H$4) | H43: 0–100 (0 turns the rule off)
A44: IDEAL CREATOR PROFILE | B44: Minimum Brand Safety | C44: min_brand_safety | D44: 70 | E44: 75 | F44: 65 | G44: =INDEX($D44:$F44,1,$H$4) | H44: 0–100 (0 turns the rule off)
A45: E. MATCHING CONFIGURATION
A46: MATCHING CONFIGURATION | B46: Category is a Hard Filter | C46: category_hard_filter | D46: No | E46: No | F46: No | G46: =INDEX($D46:$F46,1,$H$4) | H46: Dropdown — Lookup_Lists.YesNo
A47: MATCHING CONFIGURATION | B47: Audience Country is a Hard Filter | C47: country_hard_filter | D47: Yes | E47: Yes | F47: Yes | G47: =INDEX($D47:$F47,1,$H$4) | H47: Dropdown — Lookup_Lists.YesNo
A48: MATCHING CONFIGURATION | B48: Max Competitor Saturation (0 = off) | C48: max_competitor_saturation | D48: 0 | E48: 0 | F48: 0 | G48: =INDEX($D48:$F48,1,$H$4) | H48: 0–100 (0 turns the rule off)
A49: MATCHING CONFIGURATION | B49: Minimum Brand Match (0 = off) | C49: min_brand_match | D49: 0 | E49: 0 | F49: 0 | G49: =INDEX($D49:$F49,1,$H$4) | H49: 0–100 (0 turns the rule off)
A50: MATCHING CONFIGURATION | B50: Exclude Already Selected | C50: exclude_already_selected | D50: No | E50: No | F50: No | G50: =INDEX($D50:$F50,1,$H$4) | H50: Dropdown — Lookup_Lists.YesNo
A51: MATCHING CONFIGURATION | B51: Exclude Already in Cart | C51: exclude_in_cart | D51: No | E51: No | F51: No | G51: =INDEX($D51:$F51,1,$H$4) | H51: Dropdown — Lookup_Lists.YesNo
A52: MATCHING CONFIGURATION | B52: Exclude Existing Partner | C52: exclude_existing_partner | D52: No | E52: Yes | F52: No | G52: =INDEX($D52:$F52,1,$H$4) | H52: Dropdown — Lookup_Lists.YesNo
A53: MATCHING CONFIGURATION | B53: Exclude Excluded Creator | C53: exclude_excluded_creator | D53: Yes | E53: Yes | F53: Yes | G53: =INDEX($D53:$F53,1,$H$4) | H53: Dropdown — Lookup_Lists.YesNo
A55: TOKEN HELPER (calculated) · the comma-separated list fields split into five slots, so overlap can be counted with plain formulas rather than an array
A56: List field | B56: Slot | C56: Key | D56: BRAND-A | E56: BRAND-B | F56: BRAND-C | G56: Active Value | H56: How it is built
A57: Main Business Keywords | B57: slot 1 | C57: business_keywords_1 | D57: =TRIM(MID(SUBSTITUTE($D$13,",",REPT(" ",120)),1,120)) | E57: =TRIM(MID(SUBSTITUTE($E$13,",",REPT(" ",120)),1,120)) | F57: =TRIM(MID(SUBSTITUTE($F$13,",",REPT(" ",120)),1,120)) | G57: =INDEX($D57:$F57,1,$H$4) | H57: TRIM(MID(SUBSTITUTE(list, ",", REPT(" ",120)), (slot-1)*120+1, 120)) — the standard non-array split. Empty slots come back as "".
B58: slot 2 | C58: business_keywords_2 | D58: =TRIM(MID(SUBSTITUTE($D$13,",",REPT(" ",120)),121,120)) | E58: =TRIM(MID(SUBSTITUTE($E$13,",",REPT(" ",120)),121,120)) | F58: =TRIM(MID(SUBSTITUTE($F$13,",",REPT(" ",120)),121,120)) | G58: =INDEX($D58:$F58,1,$H$4)
B59: slot 3 | C59: business_keywords_3 | D59: =TRIM(MID(SUBSTITUTE($D$13,",",REPT(" ",120)),241,120)) | E59: =TRIM(MID(SUBSTITUTE($E$13,",",REPT(" ",120)),241,120)) | F59: =TRIM(MID(SUBSTITUTE($F$13,",",REPT(" ",120)),241,120)) | G59: =INDEX($D59:$F59,1,$H$4)
B60: slot 4 | C60: business_keywords_4 | D60: =TRIM(MID(SUBSTITUTE($D$13,",",REPT(" ",120)),361,120)) | E60: =TRIM(MID(SUBSTITUTE($E$13,",",REPT(" ",120)),361,120)) | F60: =TRIM(MID(SUBSTITUTE($F$13,",",REPT(" ",120)),361,120)) | G60: =INDEX($D60:$F60,1,$H$4)
B61: slot 5 | C61: business_keywords_5 | D61: =TRIM(MID(SUBSTITUTE($D$13,",",REPT(" ",120)),481,120)) | E61: =TRIM(MID(SUBSTITUTE($E$13,",",REPT(" ",120)),481,120)) | F61: =TRIM(MID(SUBSTITUTE($F$13,",",REPT(" ",120)),481,120)) | G61: =INDEX($D61:$F61,1,$H$4)
B62: count | C62: business_keywords_count | D62: =IF($D$57="",0,1)+IF($D$58="",0,1)+IF($D$59="",0,1)+IF($D$60="",0,1)+IF($D$61="",0,1) | E62: =IF($E$57="",0,1)+IF($E$58="",0,1)+IF($E$59="",0,1)+IF($E$60="",0,1)+IF($E$61="",0,1) | F62: =IF($F$57="",0,1)+IF($F$58="",0,1)+IF($F$59="",0,1)+IF($F$60="",0,1)+IF($F$61="",0,1) | G62: =INDEX($D62:$F62,1,$H$4) | H62: Denominator for the overlap score. A brand that names three keywords is judged out of three, not out of five.
A63: Audience Interests | B63: slot 1 | C63: audience_interests_1 | D63: =TRIM(MID(SUBSTITUTE($D$22,",",REPT(" ",120)),1,120)) | E63: =TRIM(MID(SUBSTITUTE($E$22,",",REPT(" ",120)),1,120)) | F63: =TRIM(MID(SUBSTITUTE($F$22,",",REPT(" ",120)),1,120)) | G63: =INDEX($D63:$F63,1,$H$4) | H63: TRIM(MID(SUBSTITUTE(list, ",", REPT(" ",120)), (slot-1)*120+1, 120)) — the standard non-array split. Empty slots come back as "".
B64: slot 2 | C64: audience_interests_2 | D64: =TRIM(MID(SUBSTITUTE($D$22,",",REPT(" ",120)),121,120)) | E64: =TRIM(MID(SUBSTITUTE($E$22,",",REPT(" ",120)),121,120)) | F64: =TRIM(MID(SUBSTITUTE($F$22,",",REPT(" ",120)),121,120)) | G64: =INDEX($D64:$F64,1,$H$4)
B65: slot 3 | C65: audience_interests_3 | D65: =TRIM(MID(SUBSTITUTE($D$22,",",REPT(" ",120)),241,120)) | E65: =TRIM(MID(SUBSTITUTE($E$22,",",REPT(" ",120)),241,120)) | F65: =TRIM(MID(SUBSTITUTE($F$22,",",REPT(" ",120)),241,120)) | G65: =INDEX($D65:$F65,1,$H$4)
B66: slot 4 | C66: audience_interests_4 | D66: =TRIM(MID(SUBSTITUTE($D$22,",",REPT(" ",120)),361,120)) | E66: =TRIM(MID(SUBSTITUTE($E$22,",",REPT(" ",120)),361,120)) | F66: =TRIM(MID(SUBSTITUTE($F$22,",",REPT(" ",120)),361,120)) | G66: =INDEX($D66:$F66,1,$H$4)
B67: slot 5 | C67: audience_interests_5 | D67: =TRIM(MID(SUBSTITUTE($D$22,",",REPT(" ",120)),481,120)) | E67: =TRIM(MID(SUBSTITUTE($E$22,",",REPT(" ",120)),481,120)) | F67: =TRIM(MID(SUBSTITUTE($F$22,",",REPT(" ",120)),481,120)) | G67: =INDEX($D67:$F67,1,$H$4)
B68: count | C68: audience_interests_count | D68: =IF($D$63="",0,1)+IF($D$64="",0,1)+IF($D$65="",0,1)+IF($D$66="",0,1)+IF($D$67="",0,1) | E68: =IF($E$63="",0,1)+IF($E$64="",0,1)+IF($E$65="",0,1)+IF($E$66="",0,1)+IF($E$67="",0,1) | F68: =IF($F$63="",0,1)+IF($F$64="",0,1)+IF($F$65="",0,1)+IF($F$66="",0,1)+IF($F$67="",0,1) | G68: =INDEX($D68:$F68,1,$H$4) | H68: Denominator for the overlap score. A brand that names three keywords is judged out of three, not out of five.
A69: Brand Keywords | B69: slot 1 | C69: brand_keywords_1 | D69: =TRIM(MID(SUBSTITUTE($D$29,",",REPT(" ",120)),1,120)) | E69: =TRIM(MID(SUBSTITUTE($E$29,",",REPT(" ",120)),1,120)) | F69: =TRIM(MID(SUBSTITUTE($F$29,",",REPT(" ",120)),1,120)) | G69: =INDEX($D69:$F69,1,$H$4) | H69: TRIM(MID(SUBSTITUTE(list, ",", REPT(" ",120)), (slot-1)*120+1, 120)) — the standard non-array split. Empty slots come back as "".
B70: slot 2 | C70: brand_keywords_2 | D70: =TRIM(MID(SUBSTITUTE($D$29,",",REPT(" ",120)),121,120)) | E70: =TRIM(MID(SUBSTITUTE($E$29,",",REPT(" ",120)),121,120)) | F70: =TRIM(MID(SUBSTITUTE($F$29,",",REPT(" ",120)),121,120)) | G70: =INDEX($D70:$F70,1,$H$4)
B71: slot 3 | C71: brand_keywords_3 | D71: =TRIM(MID(SUBSTITUTE($D$29,",",REPT(" ",120)),241,120)) | E71: =TRIM(MID(SUBSTITUTE($E$29,",",REPT(" ",120)),241,120)) | F71: =TRIM(MID(SUBSTITUTE($F$29,",",REPT(" ",120)),241,120)) | G71: =INDEX($D71:$F71,1,$H$4)
B72: slot 4 | C72: brand_keywords_4 | D72: =TRIM(MID(SUBSTITUTE($D$29,",",REPT(" ",120)),361,120)) | E72: =TRIM(MID(SUBSTITUTE($E$29,",",REPT(" ",120)),361,120)) | F72: =TRIM(MID(SUBSTITUTE($F$29,",",REPT(" ",120)),361,120)) | G72: =INDEX($D72:$F72,1,$H$4)
B73: slot 5 | C73: brand_keywords_5 | D73: =TRIM(MID(SUBSTITUTE($D$29,",",REPT(" ",120)),481,120)) | E73: =TRIM(MID(SUBSTITUTE($E$29,",",REPT(" ",120)),481,120)) | F73: =TRIM(MID(SUBSTITUTE($F$29,",",REPT(" ",120)),481,120)) | G73: =INDEX($D73:$F73,1,$H$4)
B74: count | C74: brand_keywords_count | D74: =IF($D$69="",0,1)+IF($D$70="",0,1)+IF($D$71="",0,1)+IF($D$72="",0,1)+IF($D$73="",0,1) | E74: =IF($E$69="",0,1)+IF($E$70="",0,1)+IF($E$71="",0,1)+IF($E$72="",0,1)+IF($E$73="",0,1) | F74: =IF($F$69="",0,1)+IF($F$70="",0,1)+IF($F$71="",0,1)+IF($F$72="",0,1)+IF($F$73="",0,1) | G74: =INDEX($D74:$F74,1,$H$4) | H74: Denominator for the overlap score. A brand that names three keywords is judged out of three, not out of five.
A75: Brand Values | B75: slot 1 | C75: brand_values_1 | D75: =TRIM(MID(SUBSTITUTE($D$26,",",REPT(" ",120)),1,120)) | E75: =TRIM(MID(SUBSTITUTE($E$26,",",REPT(" ",120)),1,120)) | F75: =TRIM(MID(SUBSTITUTE($F$26,",",REPT(" ",120)),1,120)) | G75: =INDEX($D75:$F75,1,$H$4) | H75: TRIM(MID(SUBSTITUTE(list, ",", REPT(" ",120)), (slot-1)*120+1, 120)) — the standard non-array split. Empty slots come back as "".
B76: slot 2 | C76: brand_values_2 | D76: =TRIM(MID(SUBSTITUTE($D$26,",",REPT(" ",120)),121,120)) | E76: =TRIM(MID(SUBSTITUTE($E$26,",",REPT(" ",120)),121,120)) | F76: =TRIM(MID(SUBSTITUTE($F$26,",",REPT(" ",120)),121,120)) | G76: =INDEX($D76:$F76,1,$H$4)
B77: slot 3 | C77: brand_values_3 | D77: =TRIM(MID(SUBSTITUTE($D$26,",",REPT(" ",120)),241,120)) | E77: =TRIM(MID(SUBSTITUTE($E$26,",",REPT(" ",120)),241,120)) | F77: =TRIM(MID(SUBSTITUTE($F$26,",",REPT(" ",120)),241,120)) | G77: =INDEX($D77:$F77,1,$H$4)
B78: slot 4 | C78: brand_values_4 | D78: =TRIM(MID(SUBSTITUTE($D$26,",",REPT(" ",120)),361,120)) | E78: =TRIM(MID(SUBSTITUTE($E$26,",",REPT(" ",120)),361,120)) | F78: =TRIM(MID(SUBSTITUTE($F$26,",",REPT(" ",120)),361,120)) | G78: =INDEX($D78:$F78,1,$H$4)
B79: slot 5 | C79: brand_values_5 | D79: =TRIM(MID(SUBSTITUTE($D$26,",",REPT(" ",120)),481,120)) | E79: =TRIM(MID(SUBSTITUTE($E$26,",",REPT(" ",120)),481,120)) | F79: =TRIM(MID(SUBSTITUTE($F$26,",",REPT(" ",120)),481,120)) | G79: =INDEX($D79:$F79,1,$H$4)
B80: count | C80: brand_values_count | D80: =IF($D$75="",0,1)+IF($D$76="",0,1)+IF($D$77="",0,1)+IF($D$78="",0,1)+IF($D$79="",0,1) | E80: =IF($E$75="",0,1)+IF($E$76="",0,1)+IF($E$77="",0,1)+IF($E$78="",0,1)+IF($E$79="",0,1) | F80: =IF($F$75="",0,1)+IF($F$76="",0,1)+IF($F$77="",0,1)+IF($F$78="",0,1)+IF($F$79="",0,1) | G80: =INDEX($D80:$F80,1,$H$4) | H80: Denominator for the overlap score. A brand that names three keywords is judged out of three, not out of five.
A81: Preferred Content Topics | B81: slot 1 | C81: preferred_content_topics_1 | D81: =TRIM(MID(SUBSTITUTE($D$40,",",REPT(" ",120)),1,120)) | E81: =TRIM(MID(SUBSTITUTE($E$40,",",REPT(" ",120)),1,120)) | F81: =TRIM(MID(SUBSTITUTE($F$40,",",REPT(" ",120)),1,120)) | G81: =INDEX($D81:$F81,1,$H$4) | H81: TRIM(MID(SUBSTITUTE(list, ",", REPT(" ",120)), (slot-1)*120+1, 120)) — the standard non-array split. Empty slots come back as "".
B82: slot 2 | C82: preferred_content_topics_2 | D82: =TRIM(MID(SUBSTITUTE($D$40,",",REPT(" ",120)),121,120)) | E82: =TRIM(MID(SUBSTITUTE($E$40,",",REPT(" ",120)),121,120)) | F82: =TRIM(MID(SUBSTITUTE($F$40,",",REPT(" ",120)),121,120)) | G82: =INDEX($D82:$F82,1,$H$4)
B83: slot 3 | C83: preferred_content_topics_3 | D83: =TRIM(MID(SUBSTITUTE($D$40,",",REPT(" ",120)),241,120)) | E83: =TRIM(MID(SUBSTITUTE($E$40,",",REPT(" ",120)),241,120)) | F83: =TRIM(MID(SUBSTITUTE($F$40,",",REPT(" ",120)),241,120)) | G83: =INDEX($D83:$F83,1,$H$4)
B84: slot 4 | C84: preferred_content_topics_4 | D84: =TRIM(MID(SUBSTITUTE($D$40,",",REPT(" ",120)),361,120)) | E84: =TRIM(MID(SUBSTITUTE($E$40,",",REPT(" ",120)),361,120)) | F84: =TRIM(MID(SUBSTITUTE($F$40,",",REPT(" ",120)),361,120)) | G84: =INDEX($D84:$F84,1,$H$4)
B85: slot 5 | C85: preferred_content_topics_5 | D85: =TRIM(MID(SUBSTITUTE($D$40,",",REPT(" ",120)),481,120)) | E85: =TRIM(MID(SUBSTITUTE($E$40,",",REPT(" ",120)),481,120)) | F85: =TRIM(MID(SUBSTITUTE($F$40,",",REPT(" ",120)),481,120)) | G85: =INDEX($D85:$F85,1,$H$4)
B86: count | C86: preferred_content_topics_count | D86: =IF($D$81="",0,1)+IF($D$82="",0,1)+IF($D$83="",0,1)+IF($D$84="",0,1)+IF($D$85="",0,1) | E86: =IF($E$81="",0,1)+IF($E$82="",0,1)+IF($E$83="",0,1)+IF($E$84="",0,1)+IF($E$85="",0,1) | F86: =IF($F$81="",0,1)+IF($F$82="",0,1)+IF($F$83="",0,1)+IF($F$84="",0,1)+IF($F$85="",0,1) | G86: =INDEX($D86:$F86,1,$H$4) | H86: Denominator for the overlap score. A brand that names three keywords is judged out of three, not out of five.
A87: Preferred Creator Values | B87: slot 1 | C87: preferred_creator_values_1 | D87: =TRIM(MID(SUBSTITUTE($D$42,",",REPT(" ",120)),1,120)) | E87: =TRIM(MID(SUBSTITUTE($E$42,",",REPT(" ",120)),1,120)) | F87: =TRIM(MID(SUBSTITUTE($F$42,",",REPT(" ",120)),1,120)) | G87: =INDEX($D87:$F87,1,$H$4) | H87: TRIM(MID(SUBSTITUTE(list, ",", REPT(" ",120)), (slot-1)*120+1, 120)) — the standard non-array split. Empty slots come back as "".
B88: slot 2 | C88: preferred_creator_values_2 | D88: =TRIM(MID(SUBSTITUTE($D$42,",",REPT(" ",120)),121,120)) | E88: =TRIM(MID(SUBSTITUTE($E$42,",",REPT(" ",120)),121,120)) | F88: =TRIM(MID(SUBSTITUTE($F$42,",",REPT(" ",120)),121,120)) | G88: =INDEX($D88:$F88,1,$H$4)
B89: slot 3 | C89: preferred_creator_values_3 | D89: =TRIM(MID(SUBSTITUTE($D$42,",",REPT(" ",120)),241,120)) | E89: =TRIM(MID(SUBSTITUTE($E$42,",",REPT(" ",120)),241,120)) | F89: =TRIM(MID(SUBSTITUTE($F$42,",",REPT(" ",120)),241,120)) | G89: =INDEX($D89:$F89,1,$H$4)
B90: slot 4 | C90: preferred_creator_values_4 | D90: =TRIM(MID(SUBSTITUTE($D$42,",",REPT(" ",120)),361,120)) | E90: =TRIM(MID(SUBSTITUTE($E$42,",",REPT(" ",120)),361,120)) | F90: =TRIM(MID(SUBSTITUTE($F$42,",",REPT(" ",120)),361,120)) | G90: =INDEX($D90:$F90,1,$H$4)
B91: slot 5 | C91: preferred_creator_values_5 | D91: =TRIM(MID(SUBSTITUTE($D$42,",",REPT(" ",120)),481,120)) | E91: =TRIM(MID(SUBSTITUTE($E$42,",",REPT(" ",120)),481,120)) | F91: =TRIM(MID(SUBSTITUTE($F$42,",",REPT(" ",120)),481,120)) | G91: =INDEX($D91:$F91,1,$H$4)
B92: count | C92: preferred_creator_values_count | D92: =IF($D$87="",0,1)+IF($D$88="",0,1)+IF($D$89="",0,1)+IF($D$90="",0,1)+IF($D$91="",0,1) | E92: =IF($E$87="",0,1)+IF($E$88="",0,1)+IF($E$89="",0,1)+IF($E$90="",0,1)+IF($E$91="",0,1) | F92: =IF($F$87="",0,1)+IF($F$88="",0,1)+IF($F$89="",0,1)+IF($F$90="",0,1)+IF($F$91="",0,1) | G92: =INDEX($D92:$F92,1,$H$4) | H92: Denominator for the overlap score. A brand that names three keywords is judged out of three, not out of five.
A94: AUDIENCE SUB-WEIGHTS (calculated) · Audience Demographics Priority moves weight onto one dimension and takes a third of the bonus off each of the others
A95: Dimension | B95: Base weight | C95: Key | D95: BRAND-A | E95: BRAND-B | F95: BRAND-C | G95: Active Value | H95: Rule
A96: Age Match | B96: =Lookup_Lists!$D$113 | C96: w_age | D96: =MAX(0,Lookup_Lists!$D$113+IF($D$23="Age",Lookup_Lists!$D$117,IF($D$23="Balanced",0,-Lookup_Lists!$D$117/3))) | E96: =MAX(0,Lookup_Lists!$D$113+IF($E$23="Age",Lookup_Lists!$D$117,IF($E$23="Balanced",0,-Lookup_Lists!$D$117/3))) | F96: =MAX(0,Lookup_Lists!$D$113+IF($F$23="Age",Lookup_Lists!$D$117,IF($F$23="Balanced",0,-Lookup_Lists!$D$117/3))) | G96: =INDEX($D96:$F96,1,$H$4) | H96: base + bonus when priority = Age, base − bonus/3 otherwise
A97: Gender Match | B97: =Lookup_Lists!$D$114 | C97: w_gender | D97: =MAX(0,Lookup_Lists!$D$114+IF($D$23="Gender",Lookup_Lists!$D$117,IF($D$23="Balanced",0,-Lookup_Lists!$D$117/3))) | E97: =MAX(0,Lookup_Lists!$D$114+IF($E$23="Gender",Lookup_Lists!$D$117,IF($E$23="Balanced",0,-Lookup_Lists!$D$117/3))) | F97: =MAX(0,Lookup_Lists!$D$114+IF($F$23="Gender",Lookup_Lists!$D$117,IF($F$23="Balanced",0,-Lookup_Lists!$D$117/3))) | G97: =INDEX($D97:$F97,1,$H$4) | H97: base + bonus when priority = Gender, base − bonus/3 otherwise
A98: Location Match | B98: =Lookup_Lists!$D$115 | C98: w_location | D98: =MAX(0,Lookup_Lists!$D$115+IF($D$23="Location",Lookup_Lists!$D$117,IF($D$23="Balanced",0,-Lookup_Lists!$D$117/3))) | E98: =MAX(0,Lookup_Lists!$D$115+IF($E$23="Location",Lookup_Lists!$D$117,IF($E$23="Balanced",0,-Lookup_Lists!$D$117/3))) | F98: =MAX(0,Lookup_Lists!$D$115+IF($F$23="Location",Lookup_Lists!$D$117,IF($F$23="Balanced",0,-Lookup_Lists!$D$117/3))) | G98: =INDEX($D98:$F98,1,$H$4) | H98: base + bonus when priority = Location, base − bonus/3 otherwise
A99: Interest Match | B99: =Lookup_Lists!$D$116 | C99: w_interest | D99: =MAX(0,Lookup_Lists!$D$116+IF($D$23="Interest",Lookup_Lists!$D$117,IF($D$23="Balanced",0,-Lookup_Lists!$D$117/3))) | E99: =MAX(0,Lookup_Lists!$D$116+IF($E$23="Interest",Lookup_Lists!$D$117,IF($E$23="Balanced",0,-Lookup_Lists!$D$117/3))) | F99: =MAX(0,Lookup_Lists!$D$116+IF($F$23="Interest",Lookup_Lists!$D$117,IF($F$23="Balanced",0,-Lookup_Lists!$D$117/3))) | G99: =INDEX($D99:$F99,1,$H$4) | H99: base + bonus when priority = Interest, base − bonus/3 otherwise

Sheet KOL_Database
A1: KOL DATABASE · 30 creators, Instagram and TikTok
A2: The other half of the inputs. Identity, performance, audience, content, commercial and safety — the same six blocks the creator workspace shows. Tier, CPV, CPE, CPM, Estimated Reach, Estimated ROI, View-to-Follower Ratio, Cost Efficiency, Data Completeness and Data Status are calculated from the columns beside them, so they cannot disagree with their own inputs. Several creators are deliberately missing a field: the real roster is full of holes and every formula here has to survive one.
A3: IDENTITY | J3: PERFORMANCE | W3: AUDIENCE | AI3: CONTENT | AN3: COMMERCIAL | AT3: SAFETY | AW3: EXCLUSION STATE | BA3: FRESHNESS | BC3: DERIVED
A4: KOL ID | B4: Creator Name | C4: Handle | D4: Platform | E4: Category | F4: Sub Category | G4: Tier | H4: Verified | I4: Creator City | J4: Followers | K4: Engagement Rate (%) | L4: Average Views | M4: Median Views | N4: 30D Growth (%) | O4: 90D Growth (%) | P4: Consistency Score | Q4: Community Score | R4: Audience Quality | S4: Audience Authenticity | T4: Share Rate (%) | U4: Save Rate (%) | V4: Recent Performance | W4: Audience Age 13–17 % | X4: Audience Age 18–24 % | Y4: Audience Age 25–34 % | Z4: Audience Age 35–44 % | AA4: Audience Age 45+ % | AB4: Female % | AC4: Male % | AD4: Audience Country | AE4: Audience Region | AF4: Audience City | AG4: Audience Interests | AH4: Purchase Intent | AI4: Content Topics | AJ4: Content Style | AK4: Creator Personality | AL4: Creator Values | AM4: Content Quality | AN4: Rate Card (IDR) | AO4: CPV | AP4: CPE | AQ4: CPM | AR4: Estimated Reach | AS4: Estimated ROI | AT4: Brand Safety Score | AU4: Competitor Saturation | AV4: Risk Flag | AW4: Already Selected | AX4: In Cart | AY4: Existing Partner | AZ4: Excluded Creator | BA4: Added Date | BB4: Last Updated | BC4: View-to-Follower Ratio | BD4: Cost Efficiency | BE4: Data Completeness % | BF4: Data Status
A5: KOL-01 | B5: Ardi Nugraha | C5: @ardidigital | D5: Instagram | E5: Tech | F5: Gadget Review | G5: =IFERROR(INDEX(Lookup_Lists!$A$96:$A$100,MATCH(KOL_Database!$J$5,Lookup_Lists!$B$96:$B$100,1)),"") | H5: Yes | I5: Jakarta | J5: 128000 | K5: 3.8 | L5: 46223 | M5: 37645 | N5: 2.7 | O5: 6.7 | P5: 73 | Q5: 66 | R5: 83 | S5: 75 | T5: 1.65 | U5: 3.46 | V5: 84 | W5: 5 | X5: 23 | Y5: 42 | Z5: 20 | AA5: 10 | AB5: 20 | AC5: 80 | AD5: Indonesia | AE5: DKI Jakarta | AF5: Jakarta | AG5: Technology, Productivity, Business, Gaming, Shopping | AH5: High | AI5: Technology, Productivity, Business | AJ5: Review | AK5: Reviewer | AL5: Quality, Trust, Innovation, Transparency | AM5: 86 | AN5: 3677000 | AO5: =IF(OR(KOL_Database!$AN$5="",KOL_Database!$AN$5=0,KOL_Database!$L$5="",KOL_Database!$L$5=0),"",ROUND(KOL_Database!$AN$5/KOL_Database!$L$5,2)) | AP5: =IF(OR(KOL_Database!$AN$5="",KOL_Database!$AN$5=0,KOL_Database!$L$5="",KOL_Database!$L$5=0,KOL_Database!$K$5="",KOL_Database!$K$5=0),"",ROUND(KOL_Database!$AN$5/(KOL_Database!$L$5*KOL_Database!$K$5/100),0)) | AQ5: =IF(OR(KOL_Database!$AN$5="",KOL_Database!$AN$5=0,KOL_Database!$J$5="",KOL_Database!$J$5=0),"",ROUND(KOL_Database!$AN$5/KOL_Database!$J$5*1000,0)) | AR5: =IF(OR(KOL_Database!$L$5="",KOL_Database!$J$5=""),"",ROUND(KOL_Database!$L$5*Lookup_Lists!$D$147+KOL_Database!$J$5*Lookup_Lists!$D$148,0)) | AS5: =IF(OR(KOL_Database!$AN$5="",KOL_Database!$AN$5=0,KOL_Database!$AR$5=""),"",ROUND(KOL_Database!$AR$5*KOL_Database!$K$5/100*Lookup_Lists!$D$146/KOL_Database!$AN$5,2)) | AT5: 90 | AU5: 56 | AV5: None | AW5: No | AX5: No | AY5: No | AZ5: No | BA5: 46171.708 | BB5: 46234.708 | BC5: =IF(OR(KOL_Database!$J$5="",KOL_Database!$J$5=0,KOL_Database!$L$5=""),"",ROUND(KOL_Database!$L$5/KOL_Database!$J$5,3)) | BD5: =IF(OR(KOL_Database!$AP$5="",KOL_Database!$AP$5=0,Lookup_Lists!$D$149=0),"",MIN(100,ROUND(Lookup_Lists!$D$149/KOL_Database!$AP$5*100,0))) | BE5: =ROUND((IF(KOL_Database!$J$5="",0,1)+IF(KOL_Database!$K$5="",0,1)+IF(KOL_Database!$L$5="",0,1)+IF(KOL_Database!$M$5="",0,1)+IF(KOL_Database!$N$5="",0,1)+IF(KOL_Database!$O$5="",0,1)+IF(KOL_Database!$P$5="",0,1)+IF(KOL_Database!$R$5="",0,1)+IF(KOL_Database!$S$5="",0,1)+IF(KOL_Database!$AE$5="",0,1)+IF(KOL_Database!$AF$5="",0,1)+IF(KOL_Database!$AN$5="",0,1))/12*100,0) | BF5: =IF(KOL_Database!$BE$5>=Lookup_Lists!$D$159,"Live",IF(KOL_Database!$BE$5>=Lookup_Lists!$D$160,"Calculated","Estimated"))
A6: KOL-02 | B6: Rifqi Pratama | C6: @rifqi.codes | D6: TikTok | E6: Tech | F6: Software & SaaS | G6: =IFERROR(INDEX(Lookup_Lists!$A$96:$A$100,MATCH(KOL_Database!$J$6,Lookup_Lists!$B$96:$B$100,1)),"") | H6: No | I6: Bandung | J6: 86000 | K6: 6.2 | L6: 87604 | M6: 64637 | N6: 4.9 | O6: 10.8 | P6: 56 | Q6: 92 | R6: 75 | S6: 89 | T6: 1.15 | U6: 2.52 | V6: 69 | W6: 10 | X6: 35 | Y6: 32 | Z6: 15 | AA6: 8 | AB6: 26 | AC6: 74 | AD6: Indonesia | AE6: Jawa Barat | AF6: Bandung | AG6: Technology, Productivity, Education, Business, Finance | AH6: Medium | AI6: Technology, Productivity, Education, Business | AJ6: Educational | AK6: Educational | AL6: Innovation, Empowerment, Transparency, Quality | AM6: 77 | AN6: 4738000 | AO6: =IF(OR(KOL_Database!$AN$6="",KOL_Database!$AN$6=0,KOL_Database!$L$6="",KOL_Database!$L$6=0),"",ROUND(KOL_Database!$AN$6/KOL_Database!$L$6,2)) | AP6: =IF(OR(KOL_Database!$AN$6="",KOL_Database!$AN$6=0,KOL_Database!$L$6="",KOL_Database!$L$6=0,KOL_Database!$K$6="",KOL_Database!$K$6=0),"",ROUND(KOL_Database!$AN$6/(KOL_Database!$L$6*KOL_Database!$K$6/100),0)) | AQ6: =IF(OR(KOL_Database!$AN$6="",KOL_Database!$AN$6=0,KOL_Database!$J$6="",KOL_Database!$J$6=0),"",ROUND(KOL_Database!$AN$6/KOL_Database!$J$6*1000,0)) | AR6: =IF(OR(KOL_Database!$L$6="",KOL_Database!$J$6=""),"",ROUND(KOL_Database!$L$6*Lookup_Lists!$D$147+KOL_Database!$J$6*Lookup_Lists!$D$148,0)) | AS6: =IF(OR(KOL_Database!$AN$6="",KOL_Database!$AN$6=0,KOL_Database!$AR$6=""),"",ROUND(KOL_Database!$AR$6*KOL_Database!$K$6/100*Lookup_Lists!$D$146/KOL_Database!$AN$6,2)) | AT6: 82 | AU6: 40 | AV6: None | AW6: No | AX6: No | AY6: No | AZ6: No | BA6: 46069.708 | BB6: 46248.708 | BC6: =IF(OR(KOL_Database!$J$6="",KOL_Database!$J$6=0,KOL_Database!$L$6=""),"",ROUND(KOL_Database!$L$6/KOL_Database!$J$6,3)) | BD6: =IF(OR(KOL_Database!$AP$6="",KOL_Database!$AP$6=0,Lookup_Lists!$D$149=0),"",MIN(100,ROUND(Lookup_Lists!$D$149/KOL_Database!$AP$6*100,0))) | BE6: =ROUND((IF(KOL_Database!$J$6="",0,1)+IF(KOL_Database!$K$6="",0,1)+IF(KOL_Database!$L$6="",0,1)+IF(KOL_Database!$M$6="",0,1)+IF(KOL_Database!$N$6="",0,1)+IF(KOL_Database!$O$6="",0,1)+IF(KOL_Database!$P$6="",0,1)+IF(KOL_Database!$R$6="",0,1)+IF(KOL_Database!$S$6="",0,1)+IF(KOL_Database!$AE$6="",0,1)+IF(KOL_Database!$AF$6="",0,1)+IF(KOL_Database!$AN$6="",0,1))/12*100,0) | BF6: =IF(KOL_Database!$BE$6>=Lookup_Lists!$D$159,"Live",IF(KOL_Database!$BE$6>=Lookup_Lists!$D$160,"Calculated","Estimated"))
A7: KOL-03 | B7: Salsa Aulia | C7: @salsabeautydiary | D7: Instagram | E7: Beauty | F7: Skincare | G7: =IFERROR(INDEX(Lookup_Lists!$A$96:$A$100,MATCH(KOL_Database!$J$7,Lookup_Lists!$B$96:$B$100,1)),"") | H7: Yes | I7: Jakarta | J7: 240000 | K7: 4.4 | L7: 71261 | M7: 54519 | N7: 2.7 | O7: 8.5 | P7: 74 | Q7: 68 | R7: 77 | S7: 84 | T7: 1.34 | U7: 2.94 | V7: 74 | W7: 7 | X7: 39 | Y7: 35 | Z7: 14 | AA7: 5 | AB7: 86 | AC7: 14 | AD7: Indonesia | AE7: DKI Jakarta | AF7: Jakarta | AG7: Skincare, Beauty, Makeup, Shopping, Health | AH7: High | AI7: Skincare, Beauty, Health | AJ7: Review | AK7: Reviewer | AL7: Authenticity, Quality, Trust, Health | AM7: 81 | AN7: 6906000 | AO7: =IF(OR(KOL_Database!$AN$7="",KOL_Database!$AN$7=0,KOL_Database!$L$7="",KOL_Database!$L$7=0),"",ROUND(KOL_Database!$AN$7/KOL_Database!$L$7,2)) | AP7: =IF(OR(KOL_Database!$AN$7="",KOL_Database!$AN$7=0,KOL_Database!$L$7="",KOL_Database!$L$7=0,KOL_Database!$K$7="",KOL_Database!$K$7=0),"",ROUND(KOL_Database!$AN$7/(KOL_Database!$L$7*KOL_Database!$K$7/100),0)) | AQ7: =IF(OR(KOL_Database!$AN$7="",KOL_Database!$AN$7=0,KOL_Database!$J$7="",KOL_Database!$J$7=0),"",ROUND(KOL_Database!$AN$7/KOL_Database!$J$7*1000,0)) | AR7: =IF(OR(KOL_Database!$L$7="",KOL_Database!$J$7=""),"",ROUND(KOL_Database!$L$7*Lookup_Lists!$D$147+KOL_Database!$J$7*Lookup_Lists!$D$148,0)) | AS7: =IF(OR(KOL_Database!$AN$7="",KOL_Database!$AN$7=0,KOL_Database!$AR$7=""),"",ROUND(KOL_Database!$AR$7*KOL_Database!$K$7/100*Lookup_Lists!$D$146/KOL_Database!$AN$7,2)) | AT7: 85 | AU7: 45 | AV7: None | AW7: Yes | AX7: No | AY7: No | AZ7: No | BA7: 46088.708 | BB7: 46238.708 | BC7: =IF(OR(KOL_Database!$J$7="",KOL_Database!$J$7=0,KOL_Database!$L$7=""),"",ROUND(KOL_Database!$L$7/KOL_Database!$J$7,3)) | BD7: =IF(OR(KOL_Database!$AP$7="",KOL_Database!$AP$7=0,Lookup_Lists!$D$149=0),"",MIN(100,ROUND(Lookup_Lists!$D$149/KOL_Database!$AP$7*100,0))) | BE7: =ROUND((IF(KOL_Database!$J$7="",0,1)+IF(KOL_Database!$K$7="",0,1)+IF(KOL_Database!$L$7="",0,1)+IF(KOL_Database!$M$7="",0,1)+IF(KOL_Database!$N$7="",0,1)+IF(KOL_Database!$O$7="",0,1)+IF(KOL_Database!$P$7="",0,1)+IF(KOL_Database!$R$7="",0,1)+IF(KOL_Database!$S$7="",0,1)+IF(KOL_Database!$AE$7="",0,1)+IF(KOL_Database!$AF$7="",0,1)+IF(KOL_Database!$AN$7="",0,1))/12*100,0) | BF7: =IF(KOL_Database!$BE$7>=Lookup_Lists!$D$159,"Live",IF(KOL_Database!$BE$7>=Lookup_Lists!$D$160,"Calculated","Estimated"))
A8: KOL-04 | B8: Nadia Puspa | C8: @nadiaglowup | D8: TikTok | E8: Beauty | F8: Makeup | G8: =IFERROR(INDEX(Lookup_Lists!$A$96:$A$100,MATCH(KOL_Database!$J$8,Lookup_Lists!$B$96:$B$100,1)),"") | H8: Yes | I8: Surabaya | J8: 512000 | K8: 7.1 | L8: 663796 | M8: 524778 | N8: 7 | O8: 19.3 | P8: 85 | Q8: 78 | R8: 82 | S8: 85 | T8: 1.63 | U8: 3.35 | V8: 81 | W8: 12 | X8: 44 | Y8: 30 | Z8: 10 | AA8: 4 | AB8: 81 | AC8: 19 | AD8: Indonesia | AE8: Jawa Timur | AF8: Surabaya | AG8: Makeup, Beauty, Fashion, Shopping, Entertainment | AH8: High | AI8: Makeup, Beauty, Fashion | AJ8: Tutorial | AK8: Creative | AL8: Fun, Authenticity, Quality, Empowerment | AM8: 85 | AN8: 14504000 | AO8: =IF(OR(KOL_Database!$AN$8="",KOL_Database!$AN$8=0,KOL_Database!$L$8="",KOL_Database!$L$8=0),"",ROUND(KOL_Database!$AN$8/KOL_Database!$L$8,2)) | AP8: =IF(OR(KOL_Database!$AN$8="",KOL_Database!$AN$8=0,KOL_Database!$L$8="",KOL_Database!$L$8=0,KOL_Database!$K$8="",KOL_Database!$K$8=0),"",ROUND(KOL_Database!$AN$8/(KOL_Database!$L$8*KOL_Database!$K$8/100),0)) | AQ8: =IF(OR(KOL_Database!$AN$8="",KOL_Database!$AN$8=0,KOL_Database!$J$8="",KOL_Database!$J$8=0),"",ROUND(KOL_Database!$AN$8/KOL_Database!$J$8*1000,0)) | AR8: =IF(OR(KOL_Database!$L$8="",KOL_Database!$J$8=""),"",ROUND(KOL_Database!$L$8*Lookup_Lists!$D$147+KOL_Database!$J$8*Lookup_Lists!$D$148,0)) | AS8: =IF(OR(KOL_Database!$AN$8="",KOL_Database!$AN$8=0,KOL_Database!$AR$8=""),"",ROUND(KOL_Database!$AR$8*KOL_Database!$K$8/100*Lookup_Lists!$D$146/KOL_Database!$AN$8,2)) | AT8: 89 | AU8: 78 | AV8: Medium | AW8: No | AX8: No | AY8: Yes | AZ8: No | BA8: 46098.708 | BB8: 46253.708 | BC8: =IF(OR(KOL_Database!$J$8="",KOL_Database!$J$8=0,KOL_Database!$L$8=""),"",ROUND(KOL_Database!$L$8/KOL_Database!$J$8,3)) | BD8: =IF(OR(KOL_Database!$AP$8="",KOL_Database!$AP$8=0,Lookup_Lists!$D$149=0),"",MIN(100,ROUND(Lookup_Lists!$D$149/KOL_Database!$AP$8*100,0))) | BE8: =ROUND((IF(KOL_Database!$J$8="",0,1)+IF(KOL_Database!$K$8="",0,1)+IF(KOL_Database!$L$8="",0,1)+IF(KOL_Database!$M$8="",0,1)+IF(KOL_Database!$N$8="",0,1)+IF(KOL_Database!$O$8="",0,1)+IF(KOL_Database!$P$8="",0,1)+IF(KOL_Database!$R$8="",0,1)+IF(KOL_Database!$S$8="",0,1)+IF(KOL_Database!$AE$8="",0,1)+IF(KOL_Database!$AF$8="",0,1)+IF(KOL_Database!$AN$8="",0,1))/12*100,0) | BF8: =IF(KOL_Database!$BE$8>=Lookup_Lists!$D$159,"Live",IF(KOL_Database!$BE$8>=Lookup_Lists!$D$160,"Calculated","Estimated"))
A9: KOL-05 | B9: Bimo Saputra | C9: @bimomakan | D9: TikTok | E9: Food | F9: Culinary Review | G9: =IFERROR(INDEX(Lookup_Lists!$A$96:$A$100,MATCH(KOL_Database!$J$9,Lookup_Lists!$B$96:$B$100,1)),"") | H9: Yes | I9: Jakarta | J9: 375000 | K9: 8.4 | L9: 360494 | M9: 255180 | N9: 3.6 | O9: 9.5 | P9: 75 | Q9: 67 | R9: 70 | S9: 83 | T9: 1.1 | U9: 2.04 | V9: 61 | W9: 7 | X9: 40 | Y9: 35 | Z9: 13 | AA9: 5 | AB9: 48 | AC9: 52 | AD9: Indonesia | AE9: Nasional | AF9: Jakarta | AG9: Food, Cooking, Travel, Shopping, Entertainment | AH9: High | AI9: Food, Cooking, Travel | AJ9: Review | AK9: Relatable | AL9: Fun, Authenticity, Community, Affordability | AM9: 72 | AN9: 11482000 | AO9: =IF(OR(KOL_Database!$AN$9="",KOL_Database!$AN$9=0,KOL_Database!$L$9="",KOL_Database!$L$9=0),"",ROUND(KOL_Database!$AN$9/KOL_Database!$L$9,2)) | AP9: =IF(OR(KOL_Database!$AN$9="",KOL_Database!$AN$9=0,KOL_Database!$L$9="",KOL_Database!$L$9=0,KOL_Database!$K$9="",KOL_Database!$K$9=0),"",ROUND(KOL_Database!$AN$9/(KOL_Database!$L$9*KOL_Database!$K$9/100),0)) | AQ9: =IF(OR(KOL_Database!$AN$9="",KOL_Database!$AN$9=0,KOL_Database!$J$9="",KOL_Database!$J$9=0),"",ROUND(KOL_Database!$AN$9/KOL_Database!$J$9*1000,0)) | AR9: =IF(OR(KOL_Database!$L$9="",KOL_Database!$J$9=""),"",ROUND(KOL_Database!$L$9*Lookup_Lists!$D$147+KOL_Database!$J$9*Lookup_Lists!$D$148,0)) | AS9: =IF(OR(KOL_Database!$AN$9="",KOL_Database!$AN$9=0,KOL_Database!$AR$9=""),"",ROUND(KOL_Database!$AR$9*KOL_Database!$K$9/100*Lookup_Lists!$D$146/KOL_Database!$AN$9,2)) | AT9: 78 | AU9: 30 | AV9: Low | AW9: No | AX9: No | AY9: No | AZ9: No | BA9: 46157.708 | BB9: 46260.708 | BC9: =IF(OR(KOL_Database!$J$9="",KOL_Database!$J$9=0,KOL_Database!$L$9=""),"",ROUND(KOL_Database!$L$9/KOL_Database!$J$9,3)) | BD9: =IF(OR(KOL_Database!$AP$9="",KOL_Database!$AP$9=0,Lookup_Lists!$D$149=0),"",MIN(100,ROUND(Lookup_Lists!$D$149/KOL_Database!$AP$9*100,0))) | BE9: =ROUND((IF(KOL_Database!$J$9="",0,1)+IF(KOL_Database!$K$9="",0,1)+IF(KOL_Database!$L$9="",0,1)+IF(KOL_Database!$M$9="",0,1)+IF(KOL_Database!$N$9="",0,1)+IF(KOL_Database!$O$9="",0,1)+IF(KOL_Database!$P$9="",0,1)+IF(KOL_Database!$R$9="",0,1)+IF(KOL_Database!$S$9="",0,1)+IF(KOL_Database!$AE$9="",0,1)+IF(KOL_Database!$AF$9="",0,1)+IF(KOL_Database!$AN$9="",0,1))/12*100,0) | BF9: =IF(KOL_Database!$BE$9>=Lookup_Lists!$D$159,"Live",IF(KOL_Database!$BE$9>=Lookup_Lists!$D$160,"Calculated","Estimated"))
A10: KOL-06 | B10: Ayu Lestari | C10: @dapurayu | D10: Instagram | E10: Food | F10: Home Cooking | G10: =IFERROR(INDEX(Lookup_Lists!$A$96:$A$100,MATCH(KOL_Database!$J$10,Lookup_Lists!$B$96:$B$100,1)),"") | H10: No | I10: Yogyakarta | J10: 64000 | K10: 5.2 | L10: 19195 | M10: 14121 | N10: 6 | O10: 18.5 | P10: 63 | Q10: 58 | R10: 73 | S10: 67 | T10: 0.96 | U10: 1.97 | V10: 61 | W10: 1 | X10: 22 | Y10: 46 | Z10: 18 | AA10: 13 | AB10: 86 | AC10: 14 | AD10: Indonesia | AF10: Yogyakarta | AG10: Cooking, Food, Parenting, Home Decor, Health | AH10: Medium | AI10: Cooking, Food, Parenting | AJ10: Tutorial | AK10: Relatable | AL10: Family, Community, Quality, Affordability | AM10: 72 | AN10: 2638000 | AO10: =IF(OR(KOL_Database!$AN$10="",KOL_Database!$AN$10=0,KOL_Database!$L$10="",KOL_Database!$L$10=0),"",ROUND(KOL_Database!$AN$10/KOL_Database!$L$10,2)) | AP10: =IF(OR(KOL_Database!$AN$10="",KOL_Database!$AN$10=0,KOL_Database!$L$10="",KOL_Database!$L$10=0,KOL_Database!$K$10="",KOL_Database!$K$10=0),"",ROUND(KOL_Database!$AN$10/(KOL_Database!$L$10*KOL_Database!$K$10/100),0)) | AQ10: =IF(OR(KOL_Database!$AN$10="",KOL_Database!$AN$10=0,KOL_Database!$J$10="",KOL_Database!$J$10=0),"",ROUND(KOL_Database!$AN$10/KOL_Database!$J$10*1000,0)) | AR10: =IF(OR(KOL_Database!$L$10="",KOL_Database!$J$10=""),"",ROUND(KOL_Database!$L$10*Lookup_Lists!$D$147+KOL_Database!$J$10*Lookup_Lists!$D$148,0)) | AS10: =IF(OR(KOL_Database!$AN$10="",KOL_Database!$AN$10=0,KOL_Database!$AR$10=""),"",ROUND(KOL_Database!$AR$10*KOL_Database!$K$10/100*Lookup_Lists!$D$146/KOL_Database!$AN$10,2)) | AT10: 79 | AU10: 29 | AV10: Low | AW10: No | AX10: No | AY10: No | AZ10: No | BA10: 46053.708 | BB10: 46266.708 | BC10: =IF(OR(KOL_Database!$J$10="",KOL_Database!$J$10=0,KOL_Database!$L$10=""),"",ROUND(KOL_Database!$L$10/KOL_Database!$J$10,3)) | BD10: =IF(OR(KOL_Database!$AP$10="",KOL_Database!$AP$10=0,Lookup_Lists!$D$149=0),"",MIN(100,ROUND(Lookup_Lists!$D$149/KOL_Database!$AP$10*100,0))) | BE10: =ROUND((IF(KOL_Database!$J$10="",0,1)+IF(KOL_Database!$K$10="",0,1)+IF(KOL_Database!$L$10="",0,1)+IF(KOL_Database!$M$10="",0,1)+IF(KOL_Database!$N$10="",0,1)+IF(KOL_Database!$O$10="",0,1)+IF(KOL_Database!$P$10="",0,1)+IF(KOL_Database!$R$10="",0,1)+IF(KOL_Database!$S$10="",0,1)+IF(KOL_Database!$AE$10="",0,1)+IF(KOL_Database!$AF$10="",0,1)+IF(KOL_Database!$AN$10="",0,1))/12*100,0) | BF10: =IF(KOL_Database!$BE$10>=Lookup_Lists!$D$159,"Live",IF(KOL_Database!$BE$10>=Lookup_Lists!$D$160,"Calculated","Estimated"))
A11: KOL-07 | B11: Fajar Ramadhan | C11: @fajarfinance | D11: Instagram | E11: Finance | F11: Personal Finance | G11: =IFERROR(INDEX(Lookup_Lists!$A$96:$A$100,MATCH(KOL_Database!$J$11,Lookup_Lists!$B$96:$B$100,1)),"") | H11: Yes | I11: Jakarta | J11: 152000 | K11: 3.2 | L11: 53466 | M11: 43843 | N11: 3.2 | O11: 8.1 | P11: 83 | Q11: 85 | R11: 86 | S11: 73 | T11: 2.08 | U11: 3.82 | V11: 88 | W11: 6 | X11: 23 | Y11: 41 | Z11: 20 | AA11: 10 | AB11: 21 | AC11: 79 | AD11: Indonesia | AE11: DKI Jakarta | AF11: Jakarta | AG11: Finance, Business, Education, Technology, Productivity | AH11: Medium | AI11: Finance, Business, Education | AJ11: Educational | AK11: Professional | AL11: Trust, Transparency, Empowerment, Quality | AM11: 89 | AN11: 5065000 | AO11: =IF(OR(KOL_Database!$AN$11="",KOL_Database!$AN$11=0,KOL_Database!$L$11="",KOL_Database!$L$11=0),"",ROUND(KOL_Database!$AN$11/KOL_Database!$L$11,2)) | AP11: =IF(OR(KOL_Database!$AN$11="",KOL_Database!$AN$11=0,KOL_Database!$L$11="",KOL_Database!$L$11=0,KOL_Database!$K$11="",KOL_Database!$K$11=0),"",ROUND(KOL_Database!$AN$11/(KOL_Database!$L$11*KOL_Database!$K$11/100),0)) | AQ11: =IF(OR(KOL_Database!$AN$11="",KOL_Database!$AN$11=0,KOL_Database!$J$11="",KOL_Database!$J$11=0),"",ROUND(KOL_Database!$AN$11/KOL_Database!$J$11*1000,0)) | AR11: =IF(OR(KOL_Database!$L$11="",KOL_Database!$J$11=""),"",ROUND(KOL_Database!$L$11*Lookup_Lists!$D$147+KOL_Database!$J$11*Lookup_Lists!$D$148,0)) | AS11: =IF(OR(KOL_Database!$AN$11="",KOL_Database!$AN$11=0,KOL_Database!$AR$11=""),"",ROUND(KOL_Database!$AR$11*KOL_Database!$K$11/100*Lookup_Lists!$D$146/KOL_Database!$AN$11,2)) | AT11: 93 | AU11: 60 | AV11: None | AW11: No | AX11: No | AY11: No | AZ11: No | BA11: 46225.708 | BB11: 46236.708 | BC11: =IF(OR(KOL_Database!$J$11="",KOL_Database!$J$11=0,KOL_Database!$L$11=""),"",ROUND(KOL_Database!$L$11/KOL_Database!$J$11,3)) | BD11: =IF(OR(KOL_Database!$AP$11="",KOL_Database!$AP$11=0,Lookup_Lists!$D$149=0),"",MIN(100,ROUND(Lookup_Lists!$D$149/KOL_Database!$AP$11*100,0))) | BE11: =ROUND((IF(KOL_Database!$J$11="",0,1)+IF(KOL_Database!$K$11="",0,1)+IF(KOL_Database!$L$11="",0,1)+IF(KOL_Database!$M$11="",0,1)+IF(KOL_Database!$N$11="",0,1)+IF(KOL_Database!$O$11="",0,1)+IF(KOL_Database!$P$11="",0,1)+IF(KOL_Database!$R$11="",0,1)+IF(KOL_Database!$S$11="",0,1)+IF(KOL_Database!$AE$11="",0,1)+IF(KOL_Database!$AF$11="",0,1)+IF(KOL_Database!$AN$11="",0,1))/12*100,0) | BF11: =IF(KOL_Database!$BE$11>=Lookup_Lists!$D$159,"Live",IF(KOL_Database!$BE$11>=Lookup_Lists!$D$160,"Calculated","Estimated"))
A12: KOL-08 | B12: Tania Wijaya | C12: @taniainvest | D12: TikTok | E12: Finance | F12: Investing | G12: =IFERROR(INDEX(Lookup_Lists!$A$96:$A$100,MATCH(KOL_Database!$J$12,Lookup_Lists!$B$96:$B$100,1)),"") | H12: No | I12: Jakarta | J12: 98000 | K12: 5.6 | L12: 66537 | M12: 43248 | N12: 3.8 | O12: 12.9 | P12: 77 | Q12: 67 | R12: 64 | S12: 94 | T12: 0.4 | U12: 0.87 | V12: 50 | W12: 9 | X12: 37 | Y12: 33 | Z12: 14 | AA12: 7 | AB12: 68 | AC12: 32 | AD12: Indonesia | AE12: DKI Jakarta | AF12: Jakarta | AG12: Finance, Business, Education, Productivity, Shopping | AH12: Medium | AI12: Finance, Business, Productivity | AJ12: Educational | AK12: Educational | AL12: Empowerment, Transparency, Trust, Innovation | AM12: 63 | AN12: 3492000 | AO12: =IF(OR(KOL_Database!$AN$12="",KOL_Database!$AN$12=0,KOL_Database!$L$12="",KOL_Database!$L$12=0),"",ROUND(KOL_Database!$AN$12/KOL_Database!$L$12,2)) | AP12: =IF(OR(KOL_Database!$AN$12="",KOL_Database!$AN$12=0,KOL_Database!$L$12="",KOL_Database!$L$12=0,KOL_Database!$K$12="",KOL_Database!$K$12=0),"",ROUND(KOL_Database!$AN$12/(KOL_Database!$L$12*KOL_Database!$K$12/100),0)) | AQ12: =IF(OR(KOL_Database!$AN$12="",KOL_Database!$AN$12=0,KOL_Database!$J$12="",KOL_Database!$J$12=0),"",ROUND(KOL_Database!$AN$12/KOL_Database!$J$12*1000,0)) | AR12: =IF(OR(KOL_Database!$L$12="",KOL_Database!$J$12=""),"",ROUND(KOL_Database!$L$12*Lookup_Lists!$D$147+KOL_Database!$J$12*Lookup_Lists!$D$148,0)) | AS12: =IF(OR(KOL_Database!$AN$12="",KOL_Database!$AN$12=0,KOL_Database!$AR$12=""),"",ROUND(KOL_Database!$AR$12*KOL_Database!$K$12/100*Lookup_Lists!$D$146/KOL_Database!$AN$12,2)) | AT12: 72 | AU12: 14 | AV12: Low | AW12: No | AX12: No | AY12: No | AZ12: No | BA12: 46121.708 | BB12: 46265.708 | BC12: =IF(OR(KOL_Database!$J$12="",KOL_Database!$J$12=0,KOL_Database!$L$12=""),"",ROUND(KOL_Database!$L$12/KOL_Database!$J$12,3)) | BD12: =IF(OR(KOL_Database!$AP$12="",KOL_Database!$AP$12=0,Lookup_Lists!$D$149=0),"",MIN(100,ROUND(Lookup_Lists!$D$149/KOL_Database!$AP$12*100,0))) | BE12: =ROUND((IF(KOL_Database!$J$12="",0,1)+IF(KOL_Database!$K$12="",0,1)+IF(KOL_Database!$L$12="",0,1)+IF(KOL_Database!$M$12="",0,1)+IF(KOL_Database!$N$12="",0,1)+IF(KOL_Database!$O$12="",0,1)+IF(KOL_Database!$P$12="",0,1)+IF(KOL_Database!$R$12="",0,1)+IF(KOL_Database!$S$12="",0,1)+IF(KOL_Database!$AE$12="",0,1)+IF(KOL_Database!$AF$12="",0,1)+IF(KOL_Database!$AN$12="",0,1))/12*100,0) | BF12: =IF(KOL_Database!$BE$12>=Lookup_Lists!$D$159,"Live",IF(KOL_Database!$BE$12>=Lookup_Lists!$D$160,"Calculated","Estimated"))
A13: KOL-09 | B13: Gilang Prakoso | C13: @gilangbelajar | D13: TikTok | E13: Education | F13: Study Tips | G13: =IFERROR(INDEX(Lookup_Lists!$A$96:$A$100,MATCH(KOL_Database!$J$13,Lookup_Lists!$B$96:$B$100,1)),"") | H13: Yes | I13: Semarang | J13: 210000 | K13: 6.8 | L13: 310647 | M13: 254639 | N13: 7.3 | O13: 24.7 | P13: 85 | Q13: 83 | R13: 86 | S13: 91 | T13: 2.11 | U13: 3.81 | V13: 86 | W13: 12 | X13: 44 | Y13: 30 | Z13: 10 | AA13: 4 | AB13: 52 | AC13: 48 | AD13: Indonesia | AE13: Jawa Tengah | AF13: Semarang | AG13: Education, Productivity, Technology, Entertainment, Business | AH13: Low | AI13: Education, Productivity, Technology | AJ13: Educational | AK13: Educational | AL13: Empowerment, Community, Trust, Innovation | AM13: 89 | AN13: 4653000 | AO13: =IF(OR(KOL_Database!$AN$13="",KOL_Database!$AN$13=0,KOL_Database!$L$13="",KOL_Database!$L$13=0),"",ROUND(KOL_Database!$AN$13/KOL_Database!$L$13,2)) | AP13: =IF(OR(KOL_Database!$AN$13="",KOL_Database!$AN$13=0,KOL_Database!$L$13="",KOL_Database!$L$13=0,KOL_Database!$K$13="",KOL_Database!$K$13=0),"",ROUND(KOL_Database!$AN$13/(KOL_Database!$L$13*KOL_Database!$K$13/100),0)) | AQ13: =IF(OR(KOL_Database!$AN$13="",KOL_Database!$AN$13=0,KOL_Database!$J$13="",KOL_Database!$J$13=0),"",ROUND(KOL_Database!$AN$13/KOL_Database!$J$13*1000,0)) | AR13: =IF(OR(KOL_Database!$L$13="",KOL_Database!$J$13=""),"",ROUND(KOL_Database!$L$13*Lookup_Lists!$D$147+KOL_Database!$J$13*Lookup_Lists!$D$148,0)) | AS13: =IF(OR(KOL_Database!$AN$13="",KOL_Database!$AN$13=0,KOL_Database!$AR$13=""),"",ROUND(KOL_Database!$AR$13*KOL_Database!$K$13/100*Lookup_Lists!$D$146/KOL_Database!$AN$13,2)) | AT13: 92 | AU13: 61 | AV13: None | AW13: No | AX13: No | AY13: No | AZ13: No | BA13: 46177.708 | BB13: 46272.708 | BC13: =IF(OR(KOL_Database!$J$13="",KOL_Database!$J$13=0,KOL_Database!$L$13=""),"",ROUND(KOL_Database!$L$13/KOL_Database!$J$13,3)) | BD13: =IF(OR(KOL_Database!$AP$13="",KOL_Database!$AP$13=0,Lookup_Lists!$D$149=0),"",MIN(100,ROUND(Lookup_Lists!$D$149/KOL_Database!$AP$13*100,0))) | BE13: =ROUND((IF(KOL_Database!$J$13="",0,1)+IF(KOL_Database!$K$13="",0,1)+IF(KOL_Database!$L$13="",0,1)+IF(KOL_Database!$M$13="",0,1)+IF(KOL_Database!$N$13="",0,1)+IF(KOL_Database!$O$13="",0,1)+IF(KOL_Database!$P$13="",0,1)+IF(KOL_Database!$R$13="",0,1)+IF(KOL_Database!$S$13="",0,1)+IF(KOL_Database!$AE$13="",0,1)+IF(KOL_Database!$AF$13="",0,1)+IF(KOL_Database!$AN$13="",0,1))/12*100,0) | BF13: =IF(KOL_Database!$BE$13>=Lookup_Lists!$D$159,"Live",IF(KOL_Database!$BE$13>=Lookup_Lists!$D$160,"Calculated","Estimated"))
A14: KOL-10 | B14: Mira Handayani | C14: @mirabahasa | D14: Instagram | E14: Education | F14: Language | G14: =IFERROR(INDEX(Lookup_Lists!$A$96:$A$100,MATCH(KOL_Database!$J$14,Lookup_Lists!$B$96:$B$100,1)),"") | H14: No | I14: Bandung | J14: 42000 | K14: 4.9 | L14: 11783 | N14: 1.6 | O14: 4.7 | P14: 94 | Q14: 85 | R14: 75 | S14: 64 | T14: 1.29 | U14: 2.15 | V14: 69 | W14: 6 | X14: 41 | Y14: 36 | Z14: 13 | AA14: 4 | AB14: 70 | AC14: 30 | AD14: Indonesia | AE14: Jawa Barat | AF14: Bandung | AG14: Education, Travel, Productivity, Entertainment, Technology | AH14: Low | AI14: Education, Travel, Productivity | AJ14: Tutorial | AK14: Educational | AL14: Empowerment, Quality, Community, Trust | AM14: 73 | AN14: 1427000 | AO14: =IF(OR(KOL_Database!$AN$14="",KOL_Database!$AN$14=0,KOL_Database!$L$14="",KOL_Database!$L$14=0),"",ROUND(KOL_Database!$AN$14/KOL_Database!$L$14,2)) | AP14: =IF(OR(KOL_Database!$AN$14="",KOL_Database!$AN$14=0,KOL_Database!$L$14="",KOL_Database!$L$14=0,KOL_Database!$K$14="",KOL_Database!$K$14=0),"",ROUND(KOL_Database!$AN$14/(KOL_Database!$L$14*KOL_Database!$K$14/100),0)) | AQ14: =IF(OR(KOL_Database!$AN$14="",KOL_Database!$AN$14=0,KOL_Database!$J$14="",KOL_Database!$J$14=0),"",ROUND(KOL_Database!$AN$14/KOL_Database!$J$14*1000,0)) | AR14: =IF(OR(KOL_Database!$L$14="",KOL_Database!$J$14=""),"",ROUND(KOL_Database!$L$14*Lookup_Lists!$D$147+KOL_Database!$J$14*Lookup_Lists!$D$148,0)) | AS14: =IF(OR(KOL_Database!$AN$14="",KOL_Database!$AN$14=0,KOL_Database!$AR$14=""),"",ROUND(KOL_Database!$AR$14*KOL_Database!$K$14/100*Lookup_Lists!$D$146/KOL_Database!$AN$14,2)) | AT14: 83 | AU14: 32 | AV14: None | AW14: No | AX14: No | AY14: No | AZ14: No | BA14: 46093.708 | BB14: 46239.708 | BC14: =IF(OR(KOL_Database!$J$14="",KOL_Database!$J$14=0,KOL_Database!$L$14=""),"",ROUND(KOL_Database!$L$14/KOL_Database!$J$14,3)) | BD14: =IF(OR(KOL_Database!$AP$14="",KOL_Database!$AP$14=0,Lookup_Lists!$D$149=0),"",MIN(100,ROUND(Lookup_Lists!$D$149/KOL_Database!$AP$14*100,0))) | BE14: =ROUND((IF(KOL_Database!$J$14="",0,1)+IF(KOL_Database!$K$14="",0,1)+IF(KOL_Database!$L$14="",0,1)+IF(KOL_Database!$M$14="",0,1)+IF(KOL_Database!$N$14="",0,1)+IF(KOL_Database!$O$14="",0,1)+IF(KOL_Database!$P$14="",0,1)+IF(KOL_Database!$R$14="",0,1)+IF(KOL_Database!$S$14="",0,1)+IF(KOL_Database!$AE$14="",0,1)+IF(KOL_Database!$AF$14="",0,1)+IF(KOL_Database!$AN$14="",0,1))/12*100,0) | BF14: =IF(KOL_Database!$BE$14>=Lookup_Lists!$D$159,"Live",IF(KOL_Database!$BE$14>=Lookup_Lists!$D$160,"Calculated","Estimated"))
A15: KOL-11 | B15: Dimas Anggara | C15: @dimasfit | D15: Instagram | E15: Fitness | F15: Gym & Strength | G15: =IFERROR(INDEX(Lookup_Lists!$A$96:$A$100,MATCH(KOL_Database!$J$15,Lookup_Lists!$B$96:$B$100,1)),"") | H15: Yes | I15: Jakarta | J15: 178000 | K15: 3.9 | L15: 34767 | M15: 22194 | N15: 2 | O15: 6.1 | P15: 87 | Q15: 79 | R15: 61 | S15: 77 | T15: 0.31 | U15: 0.95 | V15: 48 | W15: 1 | X15: 24 | Y15: 50 | Z15: 20 | AA15: 5 | AB15: 28 | AC15: 72 | AD15: Indonesia | AE15: DKI Jakarta | AF15: Jakarta | AG15: Fitness, Health, Food, Fashion, Shopping | AH15: Medium | AI15: Fitness, Health, Food | AJ15: Demo | AK15: Professional | AL15: Performance, Health, Quality, Trust | AM15: 63 | AN15: 7793000 | AO15: =IF(OR(KOL_Database!$AN$15="",KOL_Database!$AN$15=0,KOL_Database!$L$15="",KOL_Database!$L$15=0),"",ROUND(KOL_Database!$AN$15/KOL_Database!$L$15,2)) | AP15: =IF(OR(KOL_Database!$AN$15="",KOL_Database!$AN$15=0,KOL_Database!$L$15="",KOL_Database!$L$15=0,KOL_Database!$K$15="",KOL_Database!$K$15=0),"",ROUND(KOL_Database!$AN$15/(KOL_Database!$L$15*KOL_Database!$K$15/100),0)) | AQ15: =IF(OR(KOL_Database!$AN$15="",KOL_Database!$AN$15=0,KOL_Database!$J$15="",KOL_Database!$J$15=0),"",ROUND(KOL_Database!$AN$15/KOL_Database!$J$15*1000,0)) | AR15: =IF(OR(KOL_Database!$L$15="",KOL_Database!$J$15=""),"",ROUND(KOL_Database!$L$15*Lookup_Lists!$D$147+KOL_Database!$J$15*Lookup_Lists!$D$148,0)) | AS15: =IF(OR(KOL_Database!$AN$15="",KOL_Database!$AN$15=0,KOL_Database!$AR$15=""),"",ROUND(KOL_Database!$AR$15*KOL_Database!$K$15/100*Lookup_Lists!$D$146/KOL_Database!$AN$15,2)) | AT15: 71 | AU15: 15 | AV15: Low | AW15: No | AX15: No | AY15: No | AZ15: No | BA15: 46092.708 | BB15: 46252.708 | BC15: =IF(OR(KOL_Database!$J$15="",KOL_Database!$J$15=0,KOL_Database!$L$15=""),"",ROUND(KOL_Database!$L$15/KOL_Database!$J$15,3)) | BD15: =IF(OR(KOL_Database!$AP$15="",KOL_Database!$AP$15=0,Lookup_Lists!$D$149=0),"",MIN(100,ROUND(Lookup_Lists!$D$149/KOL_Database!$AP$15*100,0))) | BE15: =ROUND((IF(KOL_Database!$J$15="",0,1)+IF(KOL_Database!$K$15="",0,1)+IF(KOL_Database!$L$15="",0,1)+IF(KOL_Database!$M$15="",0,1)+IF(KOL_Database!$N$15="",0,1)+IF(KOL_Database!$O$15="",0,1)+IF(KOL_Database!$P$15="",0,1)+IF(KOL_Database!$R$15="",0,1)+IF(KOL_Database!$S$15="",0,1)+IF(KOL_Database!$AE$15="",0,1)+IF(KOL_Database!$AF$15="",0,1)+IF(KOL_Database!$AN$15="",0,1))/12*100,0) | BF15: =IF(KOL_Database!$BE$15>=Lookup_Lists!$D$159,"Live",IF(KOL_Database!$BE$15>=Lookup_Lists!$D$160,"Calculated","Estimated"))
A16: KOL-12 | B16: Rani Kusuma | C16: @ranihomeworkout | D16: TikTok | E16: Fitness | F16: Home Workout | G16: =IFERROR(INDEX(Lookup_Lists!$A$96:$A$100,MATCH(KOL_Database!$J$16,Lookup_Lists!$B$96:$B$100,1)),"") | H16: No | I16: Tangerang | J16: 305000 | K16: 6.5 | L16: 343139 | M16: 266395 | N16: 2.7 | O16: 8.5 | P16: 86 | Q16: 88 | R16: 80 | S16: 75 | T16: 1.71 | U16: 3.13 | V16: 79 | W16: 5 | X16: 42 | Y16: 37 | Z16: 13 | AA16: 3 | AB16: 79 | AC16: 21 | AD16: Indonesia | AE16: Banten | AF16: Tangerang | AG16: Fitness, Health, Food, Beauty, Parenting | AH16: Medium | AI16: Fitness, Health, Food | AJ16: Tutorial | AK16: Inspirational | AL16: Health, Empowerment, Community, Performance | AM16: 82 | AN16: 11000000 | AO16: =IF(OR(KOL_Database!$AN$16="",KOL_Database!$AN$16=0,KOL_Database!$L$16="",KOL_Database!$L$16=0),"",ROUND(KOL_Database!$AN$16/KOL_Database!$L$16,2)) | AP16: =IF(OR(KOL_Database!$AN$16="",KOL_Database!$AN$16=0,KOL_Database!$L$16="",KOL_Database!$L$16=0,KOL_Database!$K$16="",KOL_Database!$K$16=0),"",ROUND(KOL_Database!$AN$16/(KOL_Database!$L$16*KOL_Database!$K$16/100),0)) | AQ16: =IF(OR(KOL_Database!$AN$16="",KOL_Database!$AN$16=0,KOL_Database!$J$16="",KOL_Database!$J$16=0),"",ROUND(KOL_Database!$AN$16/KOL_Database!$J$16*1000,0)) | AR16: =IF(OR(KOL_Database!$L$16="",KOL_Database!$J$16=""),"",ROUND(KOL_Database!$L$16*Lookup_Lists!$D$147+KOL_Database!$J$16*Lookup_Lists!$D$148,0)) | AS16: =IF(OR(KOL_Database!$AN$16="",KOL_Database!$AN$16=0,KOL_Database!$AR$16=""),"",ROUND(KOL_Database!$AR$16*KOL_Database!$K$16/100*Lookup_Lists!$D$146/KOL_Database!$AN$16,2)) | AT16: 88 | AU16: 49 | AV16: None | AW16: No | AX16: No | AY16: No | AZ16: No | BA16: 46096.708 | BB16: 46253.708 | BC16: =IF(OR(KOL_Database!$J$16="",KOL_Database!$J$16=0,KOL_Database!$L$16=""),"",ROUND(KOL_Database!$L$16/KOL_Database!$J$16,3)) | BD16: =IF(OR(KOL_Database!$AP$16="",KOL_Database!$AP$16=0,Lookup_Lists!$D$149=0),"",MIN(100,ROUND(Lookup_Lists!$D$149/KOL_Database!$AP$16*100,0))) | BE16: =ROUND((IF(KOL_Database!$J$16="",0,1)+IF(KOL_Database!$K$16="",0,1)+IF(KOL_Database!$L$16="",0,1)+IF(KOL_Database!$M$16="",0,1)+IF(KOL_Database!$N$16="",0,1)+IF(KOL_Database!$O$16="",0,1)+IF(KOL_Database!$P$16="",0,1)+IF(KOL_Database!$R$16="",0,1)+IF(KOL_Database!$S$16="",0,1)+IF(KOL_Database!$AE$16="",0,1)+IF(KOL_Database!$AF$16="",0,1)+IF(KOL_Database!$AN$16="",0,1))/12*100,0) | BF16: =IF(KOL_Database!$BE$16>=Lookup_Lists!$D$159,"Live",IF(KOL_Database!$BE$16>=Lookup_Lists!$D$160,"Calculated","Estimated"))
A17: KOL-13 | B17: Kevin Halim | C17: @kevinstyleid | D17: Instagram | E17: Fashion | F17: Streetwear | G17: =IFERROR(INDEX(Lookup_Lists!$A$96:$A$100,MATCH(KOL_Database!$J$17,Lookup_Lists!$B$96:$B$100,1)),"") | H17: No | I17: Jakarta | J17: 96000 | K17: 3.4 | L17: 33575 | M17: 27597 | N17: 5.5 | O17: 16.4 | P17: 64 | Q17: 64 | R17: 86 | S17: 69 | T17: 1.76 | U17: 3.33 | V17: 81 | W17: 12 | X17: 44 | Y17: 30 | Z17: 10 | AA17: 4 | AB17: 33 | AC17: 67 | AD17: Indonesia | AE17: DKI Jakarta | AF17: Jakarta | AG17: Fashion, Shopping, Music, Entertainment, Beauty | AH17: High | AI17: Fashion, Shopping, Music | AJ17: Aesthetic | AK17: Creative | AL17: Craftsmanship, Quality, Authenticity, Fun | AM17: 85 | AN17: 5595000 | AO17: =IF(OR(KOL_Database!$AN$17="",KOL_Database!$AN$17=0,KOL_Database!$L$17="",KOL_Database!$L$17=0),"",ROUND(KOL_Database!$AN$17/KOL_Database!$L$17,2)) | AP17: =IF(OR(KOL_Database!$AN$17="",KOL_Database!$AN$17=0,KOL_Database!$L$17="",KOL_Database!$L$17=0,KOL_Database!$K$17="",KOL_Database!$K$17=0),"",ROUND(KOL_Database!$AN$17/(KOL_Database!$L$17*KOL_Database!$K$17/100),0)) | AQ17: =IF(OR(KOL_Database!$AN$17="",KOL_Database!$AN$17=0,KOL_Database!$J$17="",KOL_Database!$J$17=0),"",ROUND(KOL_Database!$AN$17/KOL_Database!$J$17*1000,0)) | AR17: =IF(OR(KOL_Database!$L$17="",KOL_Database!$J$17=""),"",ROUND(KOL_Database!$L$17*Lookup_Lists!$D$147+KOL_Database!$J$17*Lookup_Lists!$D$148,0)) | AS17: =IF(OR(KOL_Database!$AN$17="",KOL_Database!$AN$17=0,KOL_Database!$AR$17=""),"",ROUND(KOL_Database!$AR$17*KOL_Database!$K$17/100*Lookup_Lists!$D$146/KOL_Database!$AN$17,2)) | AT17: 89 | AU17: 54 | AV17: None | AW17: No | AX17: No | AY17: No | AZ17: No | BA17: 46164.708 | BB17: 46255.708 | BC17: =IF(OR(KOL_Database!$J$17="",KOL_Database!$J$17=0,KOL_Database!$L$17=""),"",ROUND(KOL_Database!$L$17/KOL_Database!$J$17,3)) | BD17: =IF(OR(KOL_Database!$AP$17="",KOL_Database!$AP$17=0,Lookup_Lists!$D$149=0),"",MIN(100,ROUND(Lookup_Lists!$D$149/KOL_Database!$AP$17*100,0))) | BE17: =ROUND((IF(KOL_Database!$J$17="",0,1)+IF(KOL_Database!$K$17="",0,1)+IF(KOL_Database!$L$17="",0,1)+IF(KOL_Database!$M$17="",0,1)+IF(KOL_Database!$N$17="",0,1)+IF(KOL_Database!$O$17="",0,1)+IF(KOL_Database!$P$17="",0,1)+IF(KOL_Database!$R$17="",0,1)+IF(KOL_Database!$S$17="",0,1)+IF(KOL_Database!$AE$17="",0,1)+IF(KOL_Database!$AF$17="",0,1)+IF(KOL_Database!$AN$17="",0,1))/12*100,0) | BF17: =IF(KOL_Database!$BE$17>=Lookup_Lists!$D$159,"Live",IF(KOL_Database!$BE$17>=Lookup_Lists!$D$160,"Calculated","Estimated"))
A18: KOL-14 | B18: Zahra Amelia | C18: @zahrahijabstyle | D18: Instagram | E18: Fashion | F18: Hijab Fashion | G18: =IFERROR(INDEX(Lookup_Lists!$A$96:$A$100,MATCH(KOL_Database!$J$18,Lookup_Lists!$B$96:$B$100,1)),"") | H18: Yes | I18: Bandung | J18: 268000 | K18: 4.7 | L18: 60835 | M18: 38966 | N18: 4.7 | O18: 13.5 | P18: 93 | Q18: 92 | R18: 62 | S18: 68 | T18: 0.6 | U18: 0.98 | V18: 49 | W18: 9 | X18: 36 | Y18: 32 | Z18: 15 | AA18: 8 | AB18: 76 | AC18: 24 | AD18: Indonesia | AE18: Jawa Barat | AF18: Bandung | AG18: Fashion, Beauty, Shopping, Skincare, Travel | AH18: High | AI18: Fashion, Beauty, Shopping | AJ18: Aesthetic | AK18: Premium | AL18: Quality, Authenticity, Craftsmanship, Trust | AM18: 63 | AN18: 9178000 | AO18: =IF(OR(KOL_Database!$AN$18="",KOL_Database!$AN$18=0,KOL_Database!$L$18="",KOL_Database!$L$18=0),"",ROUND(KOL_Database!$AN$18/KOL_Database!$L$18,2)) | AP18: =IF(OR(KOL_Database!$AN$18="",KOL_Database!$AN$18=0,KOL_Database!$L$18="",KOL_Database!$L$18=0,KOL_Database!$K$18="",KOL_Database!$K$18=0),"",ROUND(KOL_Database!$AN$18/(KOL_Database!$L$18*KOL_Database!$K$18/100),0)) | AQ18: =IF(OR(KOL_Database!$AN$18="",KOL_Database!$AN$18=0,KOL_Database!$J$18="",KOL_Database!$J$18=0),"",ROUND(KOL_Database!$AN$18/KOL_Database!$J$18*1000,0)) | AR18: =IF(OR(KOL_Database!$L$18="",KOL_Database!$J$18=""),"",ROUND(KOL_Database!$L$18*Lookup_Lists!$D$147+KOL_Database!$J$18*Lookup_Lists!$D$148,0)) | AS18: =IF(OR(KOL_Database!$AN$18="",KOL_Database!$AN$18=0,KOL_Database!$AR$18=""),"",ROUND(KOL_Database!$AR$18*KOL_Database!$K$18/100*Lookup_Lists!$D$146/KOL_Database!$AN$18,2)) | AT18: 72 | AU18: 15 | AV18: Low | AW18: No | AX18: No | AY18: No | AZ18: No | BA18: 46091.708 | BB18: 46257.708 | BC18: =IF(OR(KOL_Database!$J$18="",KOL_Database!$J$18=0,KOL_Database!$L$18=""),"",ROUND(KOL_Database!$L$18/KOL_Database!$J$18,3)) | BD18: =IF(OR(KOL_Database!$AP$18="",KOL_Database!$AP$18=0,Lookup_Lists!$D$149=0),"",MIN(100,ROUND(Lookup_Lists!$D$149/KOL_Database!$AP$18*100,0))) | BE18: =ROUND((IF(KOL_Database!$J$18="",0,1)+IF(KOL_Database!$K$18="",0,1)+IF(KOL_Database!$L$18="",0,1)+IF(KOL_Database!$M$18="",0,1)+IF(KOL_Database!$N$18="",0,1)+IF(KOL_Database!$O$18="",0,1)+IF(KOL_Database!$P$18="",0,1)+IF(KOL_Database!$R$18="",0,1)+IF(KOL_Database!$S$18="",0,1)+IF(KOL_Database!$AE$18="",0,1)+IF(KOL_Database!$AF$18="",0,1)+IF(KOL_Database!$AN$18="",0,1))/12*100,0) | BF18: =IF(KOL_Database!$BE$18>=Lookup_Lists!$D$159,"Live",IF(KOL_Database!$BE$18>=Lookup_Lists!$D$160,"Calculated","Estimated"))
A19: KOL-15 | B19: Andini Rahma | C19: @andinidaily | D19: Instagram | E19: Lifestyle | F19: Daily Vlog | G19: =IFERROR(INDEX(Lookup_Lists!$A$96:$A$100,MATCH(KOL_Database!$J$19,Lookup_Lists!$B$96:$B$100,1)),"") | H19: No | I19: Jakarta | J19: 58000 | K19: 5.8 | L19: 19817 | N19: 0.8 | O19: 2.2 | P19: 54 | Q19: 49 | R19: 79 | S19: 75 | T19: 1.78 | U19: 2.87 | V19: 77 | W19: 6 | X19: 41 | Y19: 36 | Z19: 13 | AA19: 4 | AB19: 78 | AC19: 22 | AD19: Indonesia | AE19: DKI Jakarta | AF19: Jakarta | AG19: Shopping, Food, Beauty, Travel, Fashion | AH19: High | AI19: Shopping, Food, Beauty | AJ19: Vlog | AK19: Relatable | AL19: Authenticity, Fun, Community, Affordability | AM19: 81 | AO19: =IF(OR(KOL_Database!$AN$19="",KOL_Database!$AN$19=0,KOL_Database!$L$19="",KOL_Database!$L$19=0),"",ROUND(KOL_Database!$AN$19/KOL_Database!$L$19,2)) | AP19: =IF(OR(KOL_Database!$AN$19="",KOL_Database!$AN$19=0,KOL_Database!$L$19="",KOL_Database!$L$19=0,KOL_Database!$K$19="",KOL_Database!$K$19=0),"",ROUND(KOL_Database!$AN$19/(KOL_Database!$L$19*KOL_Database!$K$19/100),0)) | AQ19: =IF(OR(KOL_Database!$AN$19="",KOL_Database!$AN$19=0,KOL_Database!$J$19="",KOL_Database!$J$19=0),"",ROUND(KOL_Database!$AN$19/KOL_Database!$J$19*1000,0)) | AR19: =IF(OR(KOL_Database!$L$19="",KOL_Database!$J$19=""),"",ROUND(KOL_Database!$L$19*Lookup_Lists!$D$147+KOL_Database!$J$19*Lookup_Lists!$D$148,0)) | AS19: =IF(OR(KOL_Database!$AN$19="",KOL_Database!$AN$19=0,KOL_Database!$AR$19=""),"",ROUND(KOL_Database!$AR$19*KOL_Database!$K$19/100*Lookup_Lists!$D$146/KOL_Database!$AN$19,2)) | AT19: 87 | AU19: 47 | AV19: None | AW19: No | AX19: No | AY19: No | AZ19: No | BA19: 46192.708 | BB19: 46241.708 | BC19: =IF(OR(KOL_Database!$J$19="",KOL_Database!$J$19=0,KOL_Database!$L$19=""),"",ROUND(KOL_Database!$L$19/KOL_Database!$J$19,3)) | BD19: =IF(OR(KOL_Database!$AP$19="",KOL_Database!$AP$19=0,Lookup_Lists!$D$149=0),"",MIN(100,ROUND(Lookup_Lists!$D$149/KOL_Database!$AP$19*100,0))) | BE19: =ROUND((IF(KOL_Database!$J$19="",0,1)+IF(KOL_Database!$K$19="",0,1)+IF(KOL_Database!$L$19="",0,1)+IF(KOL_Database!$M$19="",0,1)+IF(KOL_Database!$N$19="",0,1)+IF(KOL_Database!$O$19="",0,1)+IF(KOL_Database!$P$19="",0,1)+IF(KOL_Database!$R$19="",0,1)+IF(KOL_Database!$S$19="",0,1)+IF(KOL_Database!$AE$19="",0,1)+IF(KOL_Database!$AF$19="",0,1)+IF(KOL_Database!$AN$19="",0,1))/12*100,0) | BF19: =IF(KOL_Database!$BE$19>=Lookup_Lists!$D$159,"Live",IF(KOL_Database!$BE$19>=Lookup_Lists!$D$160,"Calculated","Estimated"))
A20: KOL-16 | B20: Yoga Pratama | C20: @yogaminimal | D20: TikTok | E20: Lifestyle | F20: Self Improvement | G20: =IFERROR(INDEX(Lookup_Lists!$A$96:$A$100,MATCH(KOL_Database!$J$20,Lookup_Lists!$B$96:$B$100,1)),"") | H20: No | I20: Yogyakarta | J20: 143000 | K20: 7.3 | L20: 128922 | M20: 93520 | N20: 1.6 | O20: 4.7 | P20: 69 | Q20: 58 | R20: 72 | S20: 75 | T20: 1.11 | U20: 1.8 | V20: 65 | W20: 10 | X20: 35 | Y20: 32 | Z20: 15 | AA20: 8 | AB20: 50 | AC20: 50 | AD20: Indonesia | AE20: DI Yogyakarta | AF20: Yogyakarta | AG20: Productivity, Education, Finance, Technology, Health | AH20: Medium | AI20: Productivity, Education, Finance | AJ20: Storytelling | AK20: Inspirational | AL20: Empowerment, Authenticity, Trust, Health | AM20: 70 | AN20: 7434000 | AO20: =IF(OR(KOL_Database!$AN$20="",KOL_Database!$AN$20=0,KOL_Database!$L$20="",KOL_Database!$L$20=0),"",ROUND(KOL_Database!$AN$20/KOL_Database!$L$20,2)) | AP20: =IF(OR(KOL_Database!$AN$20="",KOL_Database!$AN$20=0,KOL_Database!$L$20="",KOL_Database!$L$20=0,KOL_Database!$K$20="",KOL_Database!$K$20=0),"",ROUND(KOL_Database!$AN$20/(KOL_Database!$L$20*KOL_Database!$K$20/100),0)) | AQ20: =IF(OR(KOL_Database!$AN$20="",KOL_Database!$AN$20=0,KOL_Database!$J$20="",KOL_Database!$J$20=0),"",ROUND(KOL_Database!$AN$20/KOL_Database!$J$20*1000,0)) | AR20: =IF(OR(KOL_Database!$L$20="",KOL_Database!$J$20=""),"",ROUND(KOL_Database!$L$20*Lookup_Lists!$D$147+KOL_Database!$J$20*Lookup_Lists!$D$148,0)) | AS20: =IF(OR(KOL_Database!$AN$20="",KOL_Database!$AN$20=0,KOL_Database!$AR$20=""),"",ROUND(KOL_Database!$AR$20*KOL_Database!$K$20/100*Lookup_Lists!$D$146/KOL_Database!$AN$20,2)) | AT20: 80 | AU20: 27 | AV20: Low | AW20: No | AX20: No | AY20: No | AZ20: No | BA20: 46208.708 | BB20: 46258.708 | BC20: =IF(OR(KOL_Database!$J$20="",KOL_Database!$J$20=0,KOL_Database!$L$20=""),"",ROUND(KOL_Database!$L$20/KOL_Database!$J$20,3)) | BD20: =IF(OR(KOL_Database!$AP$20="",KOL_Database!$AP$20=0,Lookup_Lists!$D$149=0),"",MIN(100,ROUND(Lookup_Lists!$D$149/KOL_Database!$AP$20*100,0))) | BE20: =ROUND((IF(KOL_Database!$J$20="",0,1)+IF(KOL_Database!$K$20="",0,1)+IF(KOL_Database!$L$20="",0,1)+IF(KOL_Database!$M$20="",0,1)+IF(KOL_Database!$N$20="",0,1)+IF(KOL_Database!$O$20="",0,1)+IF(KOL_Database!$P$20="",0,1)+IF(KOL_Database!$R$20="",0,1)+IF(KOL_Database!$S$20="",0,1)+IF(KOL_Database!$AE$20="",0,1)+IF(KOL_Database!$AF$20="",0,1)+IF(KOL_Database!$AN$20="",0,1))/12*100,0) | BF20: =IF(KOL_Database!$BE$20>=Lookup_Lists!$D$159,"Live",IF(KOL_Database!$BE$20>=Lookup_Lists!$D$160,"Calculated","Estimated"))
A21: KOL-17 | B21: Sinta Maharani | C21: @sintajalanjalan | D21: Instagram | E21: Travel | F21: Domestic Travel | G21: =IFERROR(INDEX(Lookup_Lists!$A$96:$A$100,MATCH(KOL_Database!$J$21,Lookup_Lists!$B$96:$B$100,1)),"") | H21: Yes | I21: Bali | J21: 187000 | K21: 4.1 | L21: 63792 | M21: 49777 | N21: 3.8 | O21: 10.1 | P21: 60 | Q21: 55 | R21: 79 | S21: 65 | T21: 1.33 | U21: 2.67 | V21: 70 | W21: 6 | X21: 23 | Y21: 41 | Z21: 20 | AA21: 10 | AB21: 67 | AC21: 33 | AD21: Indonesia | AE21: Bali | AF21: Bali | AG21: Travel, Food, Shopping, Fashion, Entertainment | AH21: Medium | AI21: Travel, Food, Shopping | AJ21: Aesthetic | AK21: Premium | AL21: Quality, Authenticity, Fun, Community | AM21: 78 | AN21: 7207000 | AO21: =IF(OR(KOL_Database!$AN$21="",KOL_Database!$AN$21=0,KOL_Database!$L$21="",KOL_Database!$L$21=0),"",ROUND(KOL_Database!$AN$21/KOL_Database!$L$21,2)) | AP21: =IF(OR(KOL_Database!$AN$21="",KOL_Database!$AN$21=0,KOL_Database!$L$21="",KOL_Database!$L$21=0,KOL_Database!$K$21="",KOL_Database!$K$21=0),"",ROUND(KOL_Database!$AN$21/(KOL_Database!$L$21*KOL_Database!$K$21/100),0)) | AQ21: =IF(OR(KOL_Database!$AN$21="",KOL_Database!$AN$21=0,KOL_Database!$J$21="",KOL_Database!$J$21=0),"",ROUND(KOL_Database!$AN$21/KOL_Database!$J$21*1000,0)) | AR21: =IF(OR(KOL_Database!$L$21="",KOL_Database!$J$21=""),"",ROUND(KOL_Database!$L$21*Lookup_Lists!$D$147+KOL_Database!$J$21*Lookup_Lists!$D$148,0)) | AS21: =IF(OR(KOL_Database!$AN$21="",KOL_Database!$AN$21=0,KOL_Database!$AR$21=""),"",ROUND(KOL_Database!$AR$21*KOL_Database!$K$21/100*Lookup_Lists!$D$146/KOL_Database!$AN$21,2)) | AT21: 83 | AU21: 41 | AV21: None | AW21: No | AX21: No | AY21: No | AZ21: No | BA21: 46212.708 | BB21: 46254.708 | BC21: =IF(OR(KOL_Database!$J$21="",KOL_Database!$J$21=0,KOL_Database!$L$21=""),"",ROUND(KOL_Database!$L$21/KOL_Database!$J$21,3)) | BD21: =IF(OR(KOL_Database!$AP$21="",KOL_Database!$AP$21=0,Lookup_Lists!$D$149=0),"",MIN(100,ROUND(Lookup_Lists!$D$149/KOL_Database!$AP$21*100,0))) | BE21: =ROUND((IF(KOL_Database!$J$21="",0,1)+IF(KOL_Database!$K$21="",0,1)+IF(KOL_Database!$L$21="",0,1)+IF(KOL_Database!$M$21="",0,1)+IF(KOL_Database!$N$21="",0,1)+IF(KOL_Database!$O$21="",0,1)+IF(KOL_Database!$P$21="",0,1)+IF(KOL_Database!$R$21="",0,1)+IF(KOL_Database!$S$21="",0,1)+IF(KOL_Database!$AE$21="",0,1)+IF(KOL_Database!$AF$21="",0,1)+IF(KOL_Database!$AN$21="",0,1))/12*100,0) | BF21: =IF(KOL_Database!$BE$21>=Lookup_Lists!$D$159,"Live",IF(KOL_Database!$BE$21>=Lookup_Lists!$D$160,"Calculated","Estimated"))
A22: KOL-18 | B22: Reza Fadillah | C22: @rezabudgettrip | D22: TikTok | E22: Travel | F22: Budget Travel | G22: =IFERROR(INDEX(Lookup_Lists!$A$96:$A$100,MATCH(KOL_Database!$J$22,Lookup_Lists!$B$96:$B$100,1)),"") | H22: No | I22: Surabaya | J22: 72000 | K22: 6.9 | L22: 78906 | M22: 60692 | N22: 1.8 | P22: 79 | Q22: 74 | R22: 82 | S22: 75 | T22: 1.34 | U22: 3.01 | V22: 76 | W22: 8 | X22: 38 | Y22: 34 | Z22: 14 | AA22: 6 | AB22: 45 | AC22: 55 | AD22: Indonesia | AE22: Jawa Timur | AF22: Surabaya | AG22: Travel, Food, Productivity, Entertainment, Shopping | AH22: Medium | AI22: Travel, Food, Entertainment | AJ22: Vlog | AK22: Casual | AL22: Affordability, Fun, Authenticity, Community | AM22: 81 | AN22: 3178000 | AO22: =IF(OR(KOL_Database!$AN$22="",KOL_Database!$AN$22=0,KOL_Database!$L$22="",KOL_Database!$L$22=0),"",ROUND(KOL_Database!$AN$22/KOL_Database!$L$22,2)) | AP22: =IF(OR(KOL_Database!$AN$22="",KOL_Database!$AN$22=0,KOL_Database!$L$22="",KOL_Database!$L$22=0,KOL_Database!$K$22="",KOL_Database!$K$22=0),"",ROUND(KOL_Database!$AN$22/(KOL_Database!$L$22*KOL_Database!$K$22/100),0)) | AQ22: =IF(OR(KOL_Database!$AN$22="",KOL_Database!$AN$22=0,KOL_Database!$J$22="",KOL_Database!$J$22=0),"",ROUND(KOL_Database!$AN$22/KOL_Database!$J$22*1000,0)) | AR22: =IF(OR(KOL_Database!$L$22="",KOL_Database!$J$22=""),"",ROUND(KOL_Database!$L$22*Lookup_Lists!$D$147+KOL_Database!$J$22*Lookup_Lists!$D$148,0)) | AS22: =IF(OR(KOL_Database!$AN$22="",KOL_Database!$AN$22=0,KOL_Database!$AR$22=""),"",ROUND(KOL_Database!$AR$22*KOL_Database!$K$22/100*Lookup_Lists!$D$146/KOL_Database!$AN$22,2)) | AT22: 86 | AU22: 47 | AV22: None | AW22: No | AX22: No | AY22: No | AZ22: No | BA22: 46042.708 | BB22: 46262.708 | BC22: =IF(OR(KOL_Database!$J$22="",KOL_Database!$J$22=0,KOL_Database!$L$22=""),"",ROUND(KOL_Database!$L$22/KOL_Database!$J$22,3)) | BD22: =IF(OR(KOL_Database!$AP$22="",KOL_Database!$AP$22=0,Lookup_Lists!$D$149=0),"",MIN(100,ROUND(Lookup_Lists!$D$149/KOL_Database!$AP$22*100,0))) | BE22: =ROUND((IF(KOL_Database!$J$22="",0,1)+IF(KOL_Database!$K$22="",0,1)+IF(KOL_Database!$L$22="",0,1)+IF(KOL_Database!$M$22="",0,1)+IF(KOL_Database!$N$22="",0,1)+IF(KOL_Database!$O$22="",0,1)+IF(KOL_Database!$P$22="",0,1)+IF(KOL_Database!$R$22="",0,1)+IF(KOL_Database!$S$22="",0,1)+IF(KOL_Database!$AE$22="",0,1)+IF(KOL_Database!$AF$22="",0,1)+IF(KOL_Database!$AN$22="",0,1))/12*100,0) | BF22: =IF(KOL_Database!$BE$22>=Lookup_Lists!$D$159,"Live",IF(KOL_Database!$BE$22>=Lookup_Lists!$D$160,"Calculated","Estimated"))
A23: KOL-19 | B23: Putri Amanda | C23: @putrimomlife | D23: Instagram | E23: Parenting | F23: Momlife | G23: =IFERROR(INDEX(Lookup_Lists!$A$96:$A$100,MATCH(KOL_Database!$J$23,Lookup_Lists!$B$96:$B$100,1)),"") | H23: Yes | I23: Depok | J23: 134000 | K23: 4.6 | L23: 45915 | M23: 35162 | N23: 0.7 | O23: 1.5 | P23: 52 | Q23: 47 | R23: 79 | S23: 66 | T23: 1.66 | U23: 2.96 | V23: 75 | W23: 1 | X23: 24 | Y23: 48 | Z23: 20 | AA23: 7 | AB23: 75 | AC23: 25 | AD23: Indonesia | AE23: Jawa Barat | AF23: Depok | AG23: Parenting, Health, Cooking, Home Decor, Shopping | AH23: High | AI23: Parenting, Health, Cooking | AJ23: Storytelling | AK23: Relatable | AL23: Family, Health, Community, Trust | AM23: 81 | AN23: 4242000 | AO23: =IF(OR(KOL_Database!$AN$23="",KOL_Database!$AN$23=0,KOL_Database!$L$23="",KOL_Database!$L$23=0),"",ROUND(KOL_Database!$AN$23/KOL_Database!$L$23,2)) | AP23: =IF(OR(KOL_Database!$AN$23="",KOL_Database!$AN$23=0,KOL_Database!$L$23="",KOL_Database!$L$23=0,KOL_Database!$K$23="",KOL_Database!$K$23=0),"",ROUND(KOL_Database!$AN$23/(KOL_Database!$L$23*KOL_Database!$K$23/100),0)) | AQ23: =IF(OR(KOL_Database!$AN$23="",KOL_Database!$AN$23=0,KOL_Database!$J$23="",KOL_Database!$J$23=0),"",ROUND(KOL_Database!$AN$23/KOL_Database!$J$23*1000,0)) | AR23: =IF(OR(KOL_Database!$L$23="",KOL_Database!$J$23=""),"",ROUND(KOL_Database!$L$23*Lookup_Lists!$D$147+KOL_Database!$J$23*Lookup_Lists!$D$148,0)) | AS23: =IF(OR(KOL_Database!$AN$23="",KOL_Database!$AN$23=0,KOL_Database!$AR$23=""),"",ROUND(KOL_Database!$AR$23*KOL_Database!$K$23/100*Lookup_Lists!$D$146/KOL_Database!$AN$23,2)) | AT23: 86 | AU23: 48 | AV23: None | AW23: No | AX23: No | AY23: No | AZ23: No | BA23: 46079.708 | BB23: 46255.708 | BC23: =IF(OR(KOL_Database!$J$23="",KOL_Database!$J$23=0,KOL_Database!$L$23=""),"",ROUND(KOL_Database!$L$23/KOL_Database!$J$23,3)) | BD23: =IF(OR(KOL_Database!$AP$23="",KOL_Database!$AP$23=0,Lookup_Lists!$D$149=0),"",MIN(100,ROUND(Lookup_Lists!$D$149/KOL_Database!$AP$23*100,0))) | BE23: =ROUND((IF(KOL_Database!$J$23="",0,1)+IF(KOL_Database!$K$23="",0,1)+IF(KOL_Database!$L$23="",0,1)+IF(KOL_Database!$M$23="",0,1)+IF(KOL_Database!$N$23="",0,1)+IF(KOL_Database!$O$23="",0,1)+IF(KOL_Database!$P$23="",0,1)+IF(KOL_Database!$R$23="",0,1)+IF(KOL_Database!$S$23="",0,1)+IF(KOL_Database!$AE$23="",0,1)+IF(KOL_Database!$AF$23="",0,1)+IF(KOL_Database!$AN$23="",0,1))/12*100,0) | BF23: =IF(KOL_Database!$BE$23>=Lookup_Lists!$D$159,"Live",IF(KOL_Database!$BE$23>=Lookup_Lists!$D$160,"Calculated","Estimated"))
A24: KOL-20 | B24: Hendra Wijoyo | C24: @hendrakeluarga | D24: TikTok | E24: Parenting | F24: Kids & Family | G24: =IFERROR(INDEX(Lookup_Lists!$A$96:$A$100,MATCH(KOL_Database!$J$24,Lookup_Lists!$B$96:$B$100,1)),"") | H24: No | I24: Bekasi | J24: 89000 | K24: 5.4 | L24: 124509 | M24: 101100 | N24: 0.5 | O24: 1.7 | P24: 55 | Q24: 47 | R24: 85 | S24: 95 | T24: 1.74 | U24: 3.68 | V24: 86 | W24: 4 | X24: 15 | Y24: 36 | Z24: 29 | AA24: 16 | AB24: 53 | AC24: 47 | AD24: Indonesia | AE24: Jawa Barat | AF24: Bekasi | AG24: Parenting, Food, Entertainment, Home Decor, Education | AH24: Medium | AI24: Parenting, Food, Entertainment | AJ24: Entertaining | AK24: Humorous | AL24: Family, Fun, Community, Affordability | AM24: 88 | AN24: 2239000 | AO24: =IF(OR(KOL_Database!$AN$24="",KOL_Database!$AN$24=0,KOL_Database!$L$24="",KOL_Database!$L$24=0),"",ROUND(KOL_Database!$AN$24/KOL_Database!$L$24,2)) | AP24: =IF(OR(KOL_Database!$AN$24="",KOL_Database!$AN$24=0,KOL_Database!$L$24="",KOL_Database!$L$24=0,KOL_Database!$K$24="",KOL_Database!$K$24=0),"",ROUND(KOL_Database!$AN$24/(KOL_Database!$L$24*KOL_Database!$K$24/100),0)) | AQ24: =IF(OR(KOL_Database!$AN$24="",KOL_Database!$AN$24=0,KOL_Database!$J$24="",KOL_Database!$J$24=0),"",ROUND(KOL_Database!$AN$24/KOL_Database!$J$24*1000,0)) | AR24: =IF(OR(KOL_Database!$L$24="",KOL_Database!$J$24=""),"",ROUND(KOL_Database!$L$24*Lookup_Lists!$D$147+KOL_Database!$J$24*Lookup_Lists!$D$148,0)) | AS24: =IF(OR(KOL_Database!$AN$24="",KOL_Database!$AN$24=0,KOL_Database!$AR$24=""),"",ROUND(KOL_Database!$AR$24*KOL_Database!$K$24/100*Lookup_Lists!$D$146/KOL_Database!$AN$24,2)) | AT24: 92 | AU24: 58 | AV24: None | AW24: No | AX24: No | AY24: No | AZ24: No | BA24: 46166.708 | BB24: 46241.708 | BC24: =IF(OR(KOL_Database!$J$24="",KOL_Database!$J$24=0,KOL_Database!$L$24=""),"",ROUND(KOL_Database!$L$24/KOL_Database!$J$24,3)) | BD24: =IF(OR(KOL_Database!$AP$24="",KOL_Database!$AP$24=0,Lookup_Lists!$D$149=0),"",MIN(100,ROUND(Lookup_Lists!$D$149/KOL_Database!$AP$24*100,0))) | BE24: =ROUND((IF(KOL_Database!$J$24="",0,1)+IF(KOL_Database!$K$24="",0,1)+IF(KOL_Database!$L$24="",0,1)+IF(KOL_Database!$M$24="",0,1)+IF(KOL_Database!$N$24="",0,1)+IF(KOL_Database!$O$24="",0,1)+IF(KOL_Database!$P$24="",0,1)+IF(KOL_Database!$R$24="",0,1)+IF(KOL_Database!$S$24="",0,1)+IF(KOL_Database!$AE$24="",0,1)+IF(KOL_Database!$AF$24="",0,1)+IF(KOL_Database!$AN$24="",0,1))/12*100,0) | BF24: =IF(KOL_Database!$BE$24>=Lookup_Lists!$D$159,"Live",IF(KOL_Database!$BE$24>=Lookup_Lists!$D$160,"Calculated","Estimated"))
A25: KOL-21 | B25: Bagas Setiawan | C25: @bagaskomedi | D25: TikTok | E25: Entertainment | F25: Comedy | G25: =IFERROR(INDEX(Lookup_Lists!$A$96:$A$100,MATCH(KOL_Database!$J$25,Lookup_Lists!$B$96:$B$100,1)),"") | H25: Yes | I25: Jakarta | J25: 1240000 | K25: 9.2 | L25: 1287497 | M25: 977803 | N25: 2.2 | O25: 6.7 | P25: 63 | Q25: 52 | R25: 76 | S25: 83 | T25: 1.43 | U25: 2.34 | V25: 66 | W25: 12 | X25: 44 | Y25: 30 | Z25: 10 | AA25: 4 | AB25: 46 | AC25: 54 | AD25: Indonesia | AE25: Nasional | AF25: Nasional | AG25: Entertainment, Music, Food, Gaming, Shopping | AH25: Low | AI25: Entertainment, Music, Food | AJ25: Comedy | AK25: Humorous | AL25: Fun, Community, Authenticity, Affordability | AM25: 75 | AN25: 65830000 | AO25: =IF(OR(KOL_Database!$AN$25="",KOL_Database!$AN$25=0,KOL_Database!$L$25="",KOL_Database!$L$25=0),"",ROUND(KOL_Database!$AN$25/KOL_Database!$L$25,2)) | AP25: =IF(OR(KOL_Database!$AN$25="",KOL_Database!$AN$25=0,KOL_Database!$L$25="",KOL_Database!$L$25=0,KOL_Database!$K$25="",KOL_Database!$K$25=0),"",ROUND(KOL_Database!$AN$25/(KOL_Database!$L$25*KOL_Database!$K$25/100),0)) | AQ25: =IF(OR(KOL_Database!$AN$25="",KOL_Database!$AN$25=0,KOL_Database!$J$25="",KOL_Database!$J$25=0),"",ROUND(KOL_Database!$AN$25/KOL_Database!$J$25*1000,0)) | AR25: =IF(OR(KOL_Database!$L$25="",KOL_Database!$J$25=""),"",ROUND(KOL_Database!$L$25*Lookup_Lists!$D$147+KOL_Database!$J$25*Lookup_Lists!$D$148,0)) | AS25: =IF(OR(KOL_Database!$AN$25="",KOL_Database!$AN$25=0,KOL_Database!$AR$25=""),"",ROUND(KOL_Database!$AR$25*KOL_Database!$K$25/100*Lookup_Lists!$D$146/KOL_Database!$AN$25,2)) | AT25: 62 | AU25: 88 | AV25: Medium | AW25: No | AX25: No | AY25: No | AZ25: No | BA25: 46071.708 | BB25: 46236.708 | BC25: =IF(OR(KOL_Database!$J$25="",KOL_Database!$J$25=0,KOL_Database!$L$25=""),"",ROUND(KOL_Database!$L$25/KOL_Database!$J$25,3)) | BD25: =IF(OR(KOL_Database!$AP$25="",KOL_Database!$AP$25=0,Lookup_Lists!$D$149=0),"",MIN(100,ROUND(Lookup_Lists!$D$149/KOL_Database!$AP$25*100,0))) | BE25: =ROUND((IF(KOL_Database!$J$25="",0,1)+IF(KOL_Database!$K$25="",0,1)+IF(KOL_Database!$L$25="",0,1)+IF(KOL_Database!$M$25="",0,1)+IF(KOL_Database!$N$25="",0,1)+IF(KOL_Database!$O$25="",0,1)+IF(KOL_Database!$P$25="",0,1)+IF(KOL_Database!$R$25="",0,1)+IF(KOL_Database!$S$25="",0,1)+IF(KOL_Database!$AE$25="",0,1)+IF(KOL_Database!$AF$25="",0,1)+IF(KOL_Database!$AN$25="",0,1))/12*100,0) | BF25: =IF(KOL_Database!$BE$25>=Lookup_Lists!$D$159,"Live",IF(KOL_Database!$BE$25>=Lookup_Lists!$D$160,"Calculated","Estimated"))
A26: KOL-22 | B26: Nabila Kirana | C26: @nabilamusic | D26: Instagram | E26: Entertainment | F26: Music | G26: =IFERROR(INDEX(Lookup_Lists!$A$96:$A$100,MATCH(KOL_Database!$J$26,Lookup_Lists!$B$96:$B$100,1)),"") | H26: Yes | I26: Jakarta | J26: 420000 | K26: 3.6 | L26: 129874 | M26: 96335 | N26: 2.4 | O26: 5.7 | P26: 74 | Q26: 69 | R26: 75 | S26: 74 | T26: 1.14 | U26: 2.58 | V26: 72 | W26: 11 | X26: 47 | Y26: 31 | Z26: 9 | AA26: 2 | AB26: 66 | AC26: 34 | AD26: Indonesia | AE26: Nasional | AF26: Jakarta | AG26: Music, Entertainment, Fashion, Beauty, Shopping | AH26: Low | AI26: Music, Entertainment, Fashion | AJ26: Aesthetic | AK26: Creative | AL26: Fun, Craftsmanship, Authenticity, Community | AM26: 78 | AN26: 16589000 | AO26: =IF(OR(KOL_Database!$AN$26="",KOL_Database!$AN$26=0,KOL_Database!$L$26="",KOL_Database!$L$26=0),"",ROUND(KOL_Database!$AN$26/KOL_Database!$L$26,2)) | AP26: =IF(OR(KOL_Database!$AN$26="",KOL_Database!$AN$26=0,KOL_Database!$L$26="",KOL_Database!$L$26=0,KOL_Database!$K$26="",KOL_Database!$K$26=0),"",ROUND(KOL_Database!$AN$26/(KOL_Database!$L$26*KOL_Database!$K$26/100),0)) | AQ26: =IF(OR(KOL_Database!$AN$26="",KOL_Database!$AN$26=0,KOL_Database!$J$26="",KOL_Database!$J$26=0),"",ROUND(KOL_Database!$AN$26/KOL_Database!$J$26*1000,0)) | AR26: =IF(OR(KOL_Database!$L$26="",KOL_Database!$J$26=""),"",ROUND(KOL_Database!$L$26*Lookup_Lists!$D$147+KOL_Database!$J$26*Lookup_Lists!$D$148,0)) | AS26: =IF(OR(KOL_Database!$AN$26="",KOL_Database!$AN$26=0,KOL_Database!$AR$26=""),"",ROUND(KOL_Database!$AR$26*KOL_Database!$K$26/100*Lookup_Lists!$D$146/KOL_Database!$AN$26,2)) | AT26: 55 | AU26: 40 | AV26: High | AW26: No | AX26: No | AY26: No | AZ26: Yes | BA26: 46113.708 | BB26: 46271.708 | BC26: =IF(OR(KOL_Database!$J$26="",KOL_Database!$J$26=0,KOL_Database!$L$26=""),"",ROUND(KOL_Database!$L$26/KOL_Database!$J$26,3)) | BD26: =IF(OR(KOL_Database!$AP$26="",KOL_Database!$AP$26=0,Lookup_Lists!$D$149=0),"",MIN(100,ROUND(Lookup_Lists!$D$149/KOL_Database!$AP$26*100,0))) | BE26: =ROUND((IF(KOL_Database!$J$26="",0,1)+IF(KOL_Database!$K$26="",0,1)+IF(KOL_Database!$L$26="",0,1)+IF(KOL_Database!$M$26="",0,1)+IF(KOL_Database!$N$26="",0,1)+IF(KOL_Database!$O$26="",0,1)+IF(KOL_Database!$P$26="",0,1)+IF(KOL_Database!$R$26="",0,1)+IF(KOL_Database!$S$26="",0,1)+IF(KOL_Database!$AE$26="",0,1)+IF(KOL_Database!$AF$26="",0,1)+IF(KOL_Database!$AN$26="",0,1))/12*100,0) | BF26: =IF(KOL_Database!$BE$26>=Lookup_Lists!$D$159,"Live",IF(KOL_Database!$BE$26>=Lookup_Lists!$D$160,"Calculated","Estimated"))
A27: KOL-23 | B27: Arya Mahendra | C27: @aryagaming | D27: TikTok | E27: Gaming | F27: Mobile Gaming | G27: =IFERROR(INDEX(Lookup_Lists!$A$96:$A$100,MATCH(KOL_Database!$J$27,Lookup_Lists!$B$96:$B$100,1)),"") | H27: Yes | I27: Surabaya | J27: 640000 | K27: 7.8 | L27: 579030 | M27: 417940 | N27: 3.2 | O27: 8.1 | P27: 93 | Q27: 48 | R27: 73 | S27: 80 | T27: 1.25 | U27: 2.27 | V27: 67 | W27: 13 | X27: 42 | Y27: 29 | Z27: 11 | AA27: 5 | AB27: 28 | AC27: 72 | AD27: Indonesia | AE27: Nasional | AF27: Surabaya | AG27: Gaming, Technology, Entertainment, Music, Shopping | AH27: Medium | AI27: Gaming, Technology, Entertainment | AJ27: Entertaining | AK27: Entertaining | AL27: Fun, Performance, Community, Innovation | AM27: 75 | AN27: 29793000 | AO27: =IF(OR(KOL_Database!$AN$27="",KOL_Database!$AN$27=0,KOL_Database!$L$27="",KOL_Database!$L$27=0),"",ROUND(KOL_Database!$AN$27/KOL_Database!$L$27,2)) | AP27: =IF(OR(KOL_Database!$AN$27="",KOL_Database!$AN$27=0,KOL_Database!$L$27="",KOL_Database!$L$27=0,KOL_Database!$K$27="",KOL_Database!$K$27=0),"",ROUND(KOL_Database!$AN$27/(KOL_Database!$L$27*KOL_Database!$K$27/100),0)) | AQ27: =IF(OR(KOL_Database!$AN$27="",KOL_Database!$AN$27=0,KOL_Database!$J$27="",KOL_Database!$J$27=0),"",ROUND(KOL_Database!$AN$27/KOL_Database!$J$27*1000,0)) | AR27: =IF(OR(KOL_Database!$L$27="",KOL_Database!$J$27=""),"",ROUND(KOL_Database!$L$27*Lookup_Lists!$D$147+KOL_Database!$J$27*Lookup_Lists!$D$148,0)) | AS27: =IF(OR(KOL_Database!$AN$27="",KOL_Database!$AN$27=0,KOL_Database!$AR$27=""),"",ROUND(KOL_Database!$AR$27*KOL_Database!$K$27/100*Lookup_Lists!$D$146/KOL_Database!$AN$27,2)) | AT27: 82 | AU27: 35 | AV27: None | AW27: No | AX27: Yes | AY27: No | AZ27: No | BA27: 46112.708 | BB27: 46255.708 | BC27: =IF(OR(KOL_Database!$J$27="",KOL_Database!$J$27=0,KOL_Database!$L$27=""),"",ROUND(KOL_Database!$L$27/KOL_Database!$J$27,3)) | BD27: =IF(OR(KOL_Database!$AP$27="",KOL_Database!$AP$27=0,Lookup_Lists!$D$149=0),"",MIN(100,ROUND(Lookup_Lists!$D$149/KOL_Database!$AP$27*100,0))) | BE27: =ROUND((IF(KOL_Database!$J$27="",0,1)+IF(KOL_Database!$K$27="",0,1)+IF(KOL_Database!$L$27="",0,1)+IF(KOL_Database!$M$27="",0,1)+IF(KOL_Database!$N$27="",0,1)+IF(KOL_Database!$O$27="",0,1)+IF(KOL_Database!$P$27="",0,1)+IF(KOL_Database!$R$27="",0,1)+IF(KOL_Database!$S$27="",0,1)+IF(KOL_Database!$AE$27="",0,1)+IF(KOL_Database!$AF$27="",0,1)+IF(KOL_Database!$AN$27="",0,1))/12*100,0) | BF27: =IF(KOL_Database!$BE$27>=Lookup_Lists!$D$159,"Live",IF(KOL_Database!$BE$27>=Lookup_Lists!$D$160,"Calculated","Estimated"))
A28: KOL-24 | B28: Rio Saputra | C28: @riopcbuild | D28: Instagram | E28: Gaming | F28: PC & Console | G28: =IFERROR(INDEX(Lookup_Lists!$A$96:$A$100,MATCH(KOL_Database!$J$28,Lookup_Lists!$B$96:$B$100,1)),"") | H28: No | I28: Medan | J28: 51000 | K28: 4.2 | L28: 15813 | M28: 11551 | N28: 3.5 | O28: 9.2 | P28: 62 | Q28: 58 | R28: 74 | S28: 74 | T28: 1.36 | U28: 2.4 | V28: 67 | W28: 8 | X28: 38 | Y28: 34 | Z28: 14 | AA28: 6 | AB28: 29 | AC28: 71 | AD28: Indonesia | AE28: Sumatera Utara | AG28: Gaming, Technology, Productivity, Entertainment, Shopping | AH28: High | AI28: Gaming, Technology, Productivity | AJ28: Demo | AK28: Tech-savvy | AL28: Performance, Quality, Innovation, Craftsmanship | AM28: 76 | AN28: 2350000 | AO28: =IF(OR(KOL_Database!$AN$28="",KOL_Database!$AN$28=0,KOL_Database!$L$28="",KOL_Database!$L$28=0),"",ROUND(KOL_Database!$AN$28/KOL_Database!$L$28,2)) | AP28: =IF(OR(KOL_Database!$AN$28="",KOL_Database!$AN$28=0,KOL_Database!$L$28="",KOL_Database!$L$28=0,KOL_Database!$K$28="",KOL_Database!$K$28=0),"",ROUND(KOL_Database!$AN$28/(KOL_Database!$L$28*KOL_Database!$K$28/100),0)) | AQ28: =IF(OR(KOL_Database!$AN$28="",KOL_Database!$AN$28=0,KOL_Database!$J$28="",KOL_Database!$J$28=0),"",ROUND(KOL_Database!$AN$28/KOL_Database!$J$28*1000,0)) | AR28: =IF(OR(KOL_Database!$L$28="",KOL_Database!$J$28=""),"",ROUND(KOL_Database!$L$28*Lookup_Lists!$D$147+KOL_Database!$J$28*Lookup_Lists!$D$148,0)) | AS28: =IF(OR(KOL_Database!$AN$28="",KOL_Database!$AN$28=0,KOL_Database!$AR$28=""),"",ROUND(KOL_Database!$AR$28*KOL_Database!$K$28/100*Lookup_Lists!$D$146/KOL_Database!$AN$28,2)) | AT28: 82 | AU28: 38 | AV28: None | AW28: No | AX28: No | AY28: No | AZ28: No | BA28: 46169.708 | BB28: 46270.708 | BC28: =IF(OR(KOL_Database!$J$28="",KOL_Database!$J$28=0,KOL_Database!$L$28=""),"",ROUND(KOL_Database!$L$28/KOL_Database!$J$28,3)) | BD28: =IF(OR(KOL_Database!$AP$28="",KOL_Database!$AP$28=0,Lookup_Lists!$D$149=0),"",MIN(100,ROUND(Lookup_Lists!$D$149/KOL_Database!$AP$28*100,0))) | BE28: =ROUND((IF(KOL_Database!$J$28="",0,1)+IF(KOL_Database!$K$28="",0,1)+IF(KOL_Database!$L$28="",0,1)+IF(KOL_Database!$M$28="",0,1)+IF(KOL_Database!$N$28="",0,1)+IF(KOL_Database!$O$28="",0,1)+IF(KOL_Database!$P$28="",0,1)+IF(KOL_Database!$R$28="",0,1)+IF(KOL_Database!$S$28="",0,1)+IF(KOL_Database!$AE$28="",0,1)+IF(KOL_Database!$AF$28="",0,1)+IF(KOL_Database!$AN$28="",0,1))/12*100,0) | BF28: =IF(KOL_Database!$BE$28>=Lookup_Lists!$D$159,"Live",IF(KOL_Database!$BE$28>=Lookup_Lists!$D$160,"Calculated","Estimated"))
A29: KOL-25 | B29: Denny Kurniawan | C29: @dennymotovlog | D29: TikTok | E29: Automotive | F29: Motorcycle | G29: =IFERROR(INDEX(Lookup_Lists!$A$96:$A$100,MATCH(KOL_Database!$J$29,Lookup_Lists!$B$96:$B$100,1)),"") | H29: No | I29: Bekasi | J29: 228000 | K29: 5.1 | L29: 238888 | M29: 174098 | N29: 7.3 | O29: 19.6 | P29: 64 | Q29: 58 | R29: 73 | S29: 79 | T29: 0.86 | U29: 1.86 | V29: 65 | W29: 6 | X29: 40 | Y29: 37 | Z29: 13 | AA29: 4 | AB29: 22 | AC29: 78 | AD29: Indonesia | AE29: Jawa Barat | AF29: Bekasi | AG29: Automotive, Travel, Entertainment, Technology, Shopping | AH29: Medium | AI29: Automotive, Travel, Entertainment | AJ29: Vlog | AK29: Casual | AL29: Performance, Fun, Community, Affordability | AM29: 70 | AN29: 11066000 | AO29: =IF(OR(KOL_Database!$AN$29="",KOL_Database!$AN$29=0,KOL_Database!$L$29="",KOL_Database!$L$29=0),"",ROUND(KOL_Database!$AN$29/KOL_Database!$L$29,2)) | AP29: =IF(OR(KOL_Database!$AN$29="",KOL_Database!$AN$29=0,KOL_Database!$L$29="",KOL_Database!$L$29=0,KOL_Database!$K$29="",KOL_Database!$K$29=0),"",ROUND(KOL_Database!$AN$29/(KOL_Database!$L$29*KOL_Database!$K$29/100),0)) | AQ29: =IF(OR(KOL_Database!$AN$29="",KOL_Database!$AN$29=0,KOL_Database!$J$29="",KOL_Database!$J$29=0),"",ROUND(KOL_Database!$AN$29/KOL_Database!$J$29*1000,0)) | AR29: =IF(OR(KOL_Database!$L$29="",KOL_Database!$J$29=""),"",ROUND(KOL_Database!$L$29*Lookup_Lists!$D$147+KOL_Database!$J$29*Lookup_Lists!$D$148,0)) | AS29: =IF(OR(KOL_Database!$AN$29="",KOL_Database!$AN$29=0,KOL_Database!$AR$29=""),"",ROUND(KOL_Database!$AR$29*KOL_Database!$K$29/100*Lookup_Lists!$D$146/KOL_Database!$AN$29,2)) | AT29: 80 | AU29: 28 | AV29: Low | AW29: No | AX29: No | AY29: No | AZ29: No | BA29: 46192.708 | BB29: 46241.708 | BC29: =IF(OR(KOL_Database!$J$29="",KOL_Database!$J$29=0,KOL_Database!$L$29=""),"",ROUND(KOL_Database!$L$29/KOL_Database!$J$29,3)) | BD29: =IF(OR(KOL_Database!$AP$29="",KOL_Database!$AP$29=0,Lookup_Lists!$D$149=0),"",MIN(100,ROUND(Lookup_Lists!$D$149/KOL_Database!$AP$29*100,0))) | BE29: =ROUND((IF(KOL_Database!$J$29="",0,1)+IF(KOL_Database!$K$29="",0,1)+IF(KOL_Database!$L$29="",0,1)+IF(KOL_Database!$M$29="",0,1)+IF(KOL_Database!$N$29="",0,1)+IF(KOL_Database!$O$29="",0,1)+IF(KOL_Database!$P$29="",0,1)+IF(KOL_Database!$R$29="",0,1)+IF(KOL_Database!$S$29="",0,1)+IF(KOL_Database!$AE$29="",0,1)+IF(KOL_Database!$AF$29="",0,1)+IF(KOL_Database!$AN$29="",0,1))/12*100,0) | BF29: =IF(KOL_Database!$BE$29>=Lookup_Lists!$D$159,"Live",IF(KOL_Database!$BE$29>=Lookup_Lists!$D$160,"Calculated","Estimated"))
A30: KOL-26 | B30: Wisnu Adi | C30: @wisnucarreview | D30: Instagram | E30: Automotive | F30: Car Review | G30: =IFERROR(INDEX(Lookup_Lists!$A$96:$A$100,MATCH(KOL_Database!$J$30,Lookup_Lists!$B$96:$B$100,1)),"") | H30: Yes | I30: Jakarta | J30: 76000 | K30: 2.9 | L30: 16184 | M30: 10841 | N30: 3.7 | O30: 12.5 | P30: 48 | Q30: 51 | R30: 64 | S30: 74 | T30: 0.64 | U30: 0.93 | V30: 49 | W30: 1 | X30: 14 | Y30: 39 | Z30: 30 | AA30: 16 | AB30: 29 | AC30: 71 | AD30: Indonesia | AE30: DKI Jakarta | AF30: Jakarta | AG30: Automotive, Technology, Finance, Travel, Business | AH30: High | AI30: Automotive, Technology, Finance | AJ30: Review | AK30: Professional | AL30: Quality, Trust, Performance, Transparency | AM30: 62 | AN30: 1930000 | AO30: =IF(OR(KOL_Database!$AN$30="",KOL_Database!$AN$30=0,KOL_Database!$L$30="",KOL_Database!$L$30=0),"",ROUND(KOL_Database!$AN$30/KOL_Database!$L$30,2)) | AP30: =IF(OR(KOL_Database!$AN$30="",KOL_Database!$AN$30=0,KOL_Database!$L$30="",KOL_Database!$L$30=0,KOL_Database!$K$30="",KOL_Database!$K$30=0),"",ROUND(KOL_Database!$AN$30/(KOL_Database!$L$30*KOL_Database!$K$30/100),0)) | AQ30: =IF(OR(KOL_Database!$AN$30="",KOL_Database!$AN$30=0,KOL_Database!$J$30="",KOL_Database!$J$30=0),"",ROUND(KOL_Database!$AN$30/KOL_Database!$J$30*1000,0)) | AR30: =IF(OR(KOL_Database!$L$30="",KOL_Database!$J$30=""),"",ROUND(KOL_Database!$L$30*Lookup_Lists!$D$147+KOL_Database!$J$30*Lookup_Lists!$D$148,0)) | AS30: =IF(OR(KOL_Database!$AN$30="",KOL_Database!$AN$30=0,KOL_Database!$AR$30=""),"",ROUND(KOL_Database!$AR$30*KOL_Database!$K$30/100*Lookup_Lists!$D$146/KOL_Database!$AN$30,2)) | AT30: 71 | AU30: 13 | AV30: Low | AW30: No | AX30: No | AY30: No | AZ30: No | BA30: 46189.708 | BB30: 46248.708 | BC30: =IF(OR(KOL_Database!$J$30="",KOL_Database!$J$30=0,KOL_Database!$L$30=""),"",ROUND(KOL_Database!$L$30/KOL_Database!$J$30,3)) | BD30: =IF(OR(KOL_Database!$AP$30="",KOL_Database!$AP$30=0,Lookup_Lists!$D$149=0),"",MIN(100,ROUND(Lookup_Lists!$D$149/KOL_Database!$AP$30*100,0))) | BE30: =ROUND((IF(KOL_Database!$J$30="",0,1)+IF(KOL_Database!$K$30="",0,1)+IF(KOL_Database!$L$30="",0,1)+IF(KOL_Database!$M$30="",0,1)+IF(KOL_Database!$N$30="",0,1)+IF(KOL_Database!$O$30="",0,1)+IF(KOL_Database!$P$30="",0,1)+IF(KOL_Database!$R$30="",0,1)+IF(KOL_Database!$S$30="",0,1)+IF(KOL_Database!$AE$30="",0,1)+IF(KOL_Database!$AF$30="",0,1)+IF(KOL_Database!$AN$30="",0,1))/12*100,0) | BF30: =IF(KOL_Database!$BE$30>=Lookup_Lists!$D$159,"Live",IF(KOL_Database!$BE$30>=Lookup_Lists!$D$160,"Calculated","Estimated"))
A31: KOL-27 | B31: Laras Ayu | C31: @larasinterior | D31: Instagram | E31: Home & Living | F31: Interior | G31: =IFERROR(INDEX(Lookup_Lists!$A$96:$A$100,MATCH(KOL_Database!$J$31,Lookup_Lists!$B$96:$B$100,1)),"") | H31: No | I31: Bandung | J31: 46000 | K31: 4.4 | L31: 16691 | M31: 13958 | N31: 3.4 | O31: 8.9 | P31: 52 | Q31: 49 | R31: 88 | S31: 86 | T31: 1.91 | U31: 4.07 | V31: 88 | W31: 5 | X31: 23 | Y31: 42 | Z31: 20 | AA31: 10 | AB31: 74 | AC31: 26 | AD31: Indonesia | AE31: Jawa Barat | AF31: Bandung | AG31: Home Decor, Shopping, Parenting, Food, Fashion | AH31: High | AI31: Home Decor, Shopping, Parenting | AJ31: Aesthetic | AK31: Premium | AL31: Craftsmanship, Quality, Family, Sustainability | AM31: 90 | AO31: =IF(OR(KOL_Database!$AN$31="",KOL_Database!$AN$31=0,KOL_Database!$L$31="",KOL_Database!$L$31=0),"",ROUND(KOL_Database!$AN$31/KOL_Database!$L$31,2)) | AP31: =IF(OR(KOL_Database!$AN$31="",KOL_Database!$AN$31=0,KOL_Database!$L$31="",KOL_Database!$L$31=0,KOL_Database!$K$31="",KOL_Database!$K$31=0),"",ROUND(KOL_Database!$AN$31/(KOL_Database!$L$31*KOL_Database!$K$31/100),0)) | AQ31: =IF(OR(KOL_Database!$AN$31="",KOL_Database!$AN$31=0,KOL_Database!$J$31="",KOL_Database!$J$31=0),"",ROUND(KOL_Database!$AN$31/KOL_Database!$J$31*1000,0)) | AR31: =IF(OR(KOL_Database!$L$31="",KOL_Database!$J$31=""),"",ROUND(KOL_Database!$L$31*Lookup_Lists!$D$147+KOL_Database!$J$31*Lookup_Lists!$D$148,0)) | AS31: =IF(OR(KOL_Database!$AN$31="",KOL_Database!$AN$31=0,KOL_Database!$AR$31=""),"",ROUND(KOL_Database!$AR$31*KOL_Database!$K$31/100*Lookup_Lists!$D$146/KOL_Database!$AN$31,2)) | AT31: 92 | AU31: 64 | AV31: None | AW31: No | AX31: No | AY31: No | AZ31: No | BA31: 46180.708 | BB31: 46239.708 | BC31: =IF(OR(KOL_Database!$J$31="",KOL_Database!$J$31=0,KOL_Database!$L$31=""),"",ROUND(KOL_Database!$L$31/KOL_Database!$J$31,3)) | BD31: =IF(OR(KOL_Database!$AP$31="",KOL_Database!$AP$31=0,Lookup_Lists!$D$149=0),"",MIN(100,ROUND(Lookup_Lists!$D$149/KOL_Database!$AP$31*100,0))) | BE31: =ROUND((IF(KOL_Database!$J$31="",0,1)+IF(KOL_Database!$K$31="",0,1)+IF(KOL_Database!$L$31="",0,1)+IF(KOL_Database!$M$31="",0,1)+IF(KOL_Database!$N$31="",0,1)+IF(KOL_Database!$O$31="",0,1)+IF(KOL_Database!$P$31="",0,1)+IF(KOL_Database!$R$31="",0,1)+IF(KOL_Database!$S$31="",0,1)+IF(KOL_Database!$AE$31="",0,1)+IF(KOL_Database!$AF$31="",0,1)+IF(KOL_Database!$AN$31="",0,1))/12*100,0) | BF31: =IF(KOL_Database!$BE$31>=Lookup_Lists!$D$159,"Live",IF(KOL_Database!$BE$31>=Lookup_Lists!$D$160,"Calculated","Estimated"))
A32: KOL-28 | B32: Tiara Nisrina | C32: @tiararapihin | D32: TikTok | E32: Home & Living | F32: Home Organization | G32: =IFERROR(INDEX(Lookup_Lists!$A$96:$A$100,MATCH(KOL_Database!$J$32,Lookup_Lists!$B$96:$B$100,1)),"") | H32: No | I32: Jakarta | J32: 118000 | K32: 6.1 | L32: 134895 | M32: 105352 | N32: 4 | O32: 13.5 | P32: 77 | Q32: 75 | R32: 81 | S32: 75 | T32: 1.34 | U32: 2.68 | V32: 73 | W32: 8 | X32: 39 | Y32: 33 | Z32: 14 | AA32: 6 | AB32: 83 | AC32: 17 | AD32: Indonesia | AE32: DKI Jakarta | AF32: Jakarta | AG32: Home Decor, Shopping, Productivity, Parenting, Cooking | AH32: High | AI32: Home Decor, Productivity, Shopping | AJ32: Tutorial | AK32: Relatable | AL32: Quality, Affordability, Family, Community | AM32: 78 | AN32: 4594000 | AO32: =IF(OR(KOL_Database!$AN$32="",KOL_Database!$AN$32=0,KOL_Database!$L$32="",KOL_Database!$L$32=0),"",ROUND(KOL_Database!$AN$32/KOL_Database!$L$32,2)) | AP32: =IF(OR(KOL_Database!$AN$32="",KOL_Database!$AN$32=0,KOL_Database!$L$32="",KOL_Database!$L$32=0,KOL_Database!$K$32="",KOL_Database!$K$32=0),"",ROUND(KOL_Database!$AN$32/(KOL_Database!$L$32*KOL_Database!$K$32/100),0)) | AQ32: =IF(OR(KOL_Database!$AN$32="",KOL_Database!$AN$32=0,KOL_Database!$J$32="",KOL_Database!$J$32=0),"",ROUND(KOL_Database!$AN$32/KOL_Database!$J$32*1000,0)) | AR32: =IF(OR(KOL_Database!$L$32="",KOL_Database!$J$32=""),"",ROUND(KOL_Database!$L$32*Lookup_Lists!$D$147+KOL_Database!$J$32*Lookup_Lists!$D$148,0)) | AS32: =IF(OR(KOL_Database!$AN$32="",KOL_Database!$AN$32=0,KOL_Database!$AR$32=""),"",ROUND(KOL_Database!$AR$32*KOL_Database!$K$32/100*Lookup_Lists!$D$146/KOL_Database!$AN$32,2)) | AT32: 85 | AU32: 42 | AV32: None | AW32: No | AX32: No | AY32: No | AZ32: No | BA32: 46164.708 | BB32: 46255.708 | BC32: =IF(OR(KOL_Database!$J$32="",KOL_Database!$J$32=0,KOL_Database!$L$32=""),"",ROUND(KOL_Database!$L$32/KOL_Database!$J$32,3)) | BD32: =IF(OR(KOL_Database!$AP$32="",KOL_Database!$AP$32=0,Lookup_Lists!$D$149=0),"",MIN(100,ROUND(Lookup_Lists!$D$149/KOL_Database!$AP$32*100,0))) | BE32: =ROUND((IF(KOL_Database!$J$32="",0,1)+IF(KOL_Database!$K$32="",0,1)+IF(KOL_Database!$L$32="",0,1)+IF(KOL_Database!$M$32="",0,1)+IF(KOL_Database!$N$32="",0,1)+IF(KOL_Database!$O$32="",0,1)+IF(KOL_Database!$P$32="",0,1)+IF(KOL_Database!$R$32="",0,1)+IF(KOL_Database!$S$32="",0,1)+IF(KOL_Database!$AE$32="",0,1)+IF(KOL_Database!$AF$32="",0,1)+IF(KOL_Database!$AN$32="",0,1))/12*100,0) | BF32: =IF(KOL_Database!$BE$32>=Lookup_Lists!$D$159,"Live",IF(KOL_Database!$BE$32>=Lookup_Lists!$D$160,"Calculated","Estimated"))
A33: KOL-29 | B33: Sekar Ayu | C33: @sekarskincarejujur | D33: TikTok | E33: Beauty | F33: Skincare | G33: =IFERROR(INDEX(Lookup_Lists!$A$96:$A$100,MATCH(KOL_Database!$J$33,Lookup_Lists!$B$96:$B$100,1)),"") | H33: No | I33: Yogyakarta | J33: 27000 | K33: 8.9 | L33: 16833 | M33: 14812 | N33: 3.7 | O33: 9.7 | P33: 88 | Q33: 46 | R33: 91 | S33: 95 | T33: 0.32 | U33: 4.5 | V33: 92 | W33: 10 | X33: 35 | Y33: 32 | Z33: 15 | AA33: 8 | AB33: 74 | AC33: 26 | AD33: Indonesia | AE33: DI Yogyakarta | AF33: Yogyakarta | AG33: Skincare, Beauty, Health, Shopping, Makeup | AH33: High | AI33: Skincare, Beauty, Health | AJ33: Review | AK33: Relatable | AL33: Authenticity, Trust, Health, Transparency | AM33: 59 | AN33: 912000 | AO33: =IF(OR(KOL_Database!$AN$33="",KOL_Database!$AN$33=0,KOL_Database!$L$33="",KOL_Database!$L$33=0),"",ROUND(KOL_Database!$AN$33/KOL_Database!$L$33,2)) | AP33: =IF(OR(KOL_Database!$AN$33="",KOL_Database!$AN$33=0,KOL_Database!$L$33="",KOL_Database!$L$33=0,KOL_Database!$K$33="",KOL_Database!$K$33=0),"",ROUND(KOL_Database!$AN$33/(KOL_Database!$L$33*KOL_Database!$K$33/100),0)) | AQ33: =IF(OR(KOL_Database!$AN$33="",KOL_Database!$AN$33=0,KOL_Database!$J$33="",KOL_Database!$J$33=0),"",ROUND(KOL_Database!$AN$33/KOL_Database!$J$33*1000,0)) | AR33: =IF(OR(KOL_Database!$L$33="",KOL_Database!$J$33=""),"",ROUND(KOL_Database!$L$33*Lookup_Lists!$D$147+KOL_Database!$J$33*Lookup_Lists!$D$148,0)) | AS33: =IF(OR(KOL_Database!$AN$33="",KOL_Database!$AN$33=0,KOL_Database!$AR$33=""),"",ROUND(KOL_Database!$AR$33*KOL_Database!$K$33/100*Lookup_Lists!$D$146/KOL_Database!$AN$33,2)) | AT33: 94 | AU33: 12 | AV33: None | AW33: No | AX33: No | AY33: No | AZ33: No | BA33: 46144.708 | BB33: 46257.708 | BC33: =IF(OR(KOL_Database!$J$33="",KOL_Database!$J$33=0,KOL_Database!$L$33=""),"",ROUND(KOL_Database!$L$33/KOL_Database!$J$33,3)) | BD33: =IF(OR(KOL_Database!$AP$33="",KOL_Database!$AP$33=0,Lookup_Lists!$D$149=0),"",MIN(100,ROUND(Lookup_Lists!$D$149/KOL_Database!$AP$33*100,0))) | BE33: =ROUND((IF(KOL_Database!$J$33="",0,1)+IF(KOL_Database!$K$33="",0,1)+IF(KOL_Database!$L$33="",0,1)+IF(KOL_Database!$M$33="",0,1)+IF(KOL_Database!$N$33="",0,1)+IF(KOL_Database!$O$33="",0,1)+IF(KOL_Database!$P$33="",0,1)+IF(KOL_Database!$R$33="",0,1)+IF(KOL_Database!$S$33="",0,1)+IF(KOL_Database!$AE$33="",0,1)+IF(KOL_Database!$AF$33="",0,1)+IF(KOL_Database!$AN$33="",0,1))/12*100,0) | BF33: =IF(KOL_Database!$BE$33>=Lookup_Lists!$D$159,"Live",IF(KOL_Database!$BE$33>=Lookup_Lists!$D$160,"Calculated","Estimated"))
A34: KOL-30 | B34: Ibnu Faisal | C34: @ibnubisnis | D34: Instagram | E34: Finance | F34: Business | G34: =IFERROR(INDEX(Lookup_Lists!$A$96:$A$100,MATCH(KOL_Database!$J$34,Lookup_Lists!$B$96:$B$100,1)),"") | H34: Yes | I34: Jakarta | J34: 355000 | K34: 2.6 | L34: 83349 | N34: 2.1 | O34: 6.4 | P34: 53 | Q34: 88 | R34: 66 | S34: 71 | T34: 0.63 | U34: 1.3 | V34: 56 | W34: 4 | X34: 15 | Y34: 36 | Z34: 29 | AA34: 16 | AB34: 21 | AC34: 79 | AD34: Indonesia | AE34: DKI Jakarta | AF34: Jakarta | AG34: Business, Finance, Education, Technology, Productivity | AH34: Medium | AI34: Business, Finance, Education | AJ34: Talking Head | AK34: Professional | AL34: Trust, Quality, Empowerment, Transparency | AM34: 67 | AN34: 19218000 | AO34: =IF(OR(KOL_Database!$AN$34="",KOL_Database!$AN$34=0,KOL_Database!$L$34="",KOL_Database!$L$34=0),"",ROUND(KOL_Database!$AN$34/KOL_Database!$L$34,2)) | AP34: =IF(OR(KOL_Database!$AN$34="",KOL_Database!$AN$34=0,KOL_Database!$L$34="",KOL_Database!$L$34=0,KOL_Database!$K$34="",KOL_Database!$K$34=0),"",ROUND(KOL_Database!$AN$34/(KOL_Database!$L$34*KOL_Database!$K$34/100),0)) | AQ34: =IF(OR(KOL_Database!$AN$34="",KOL_Database!$AN$34=0,KOL_Database!$J$34="",KOL_Database!$J$34=0),"",ROUND(KOL_Database!$AN$34/KOL_Database!$J$34*1000,0)) | AR34: =IF(OR(KOL_Database!$L$34="",KOL_Database!$J$34=""),"",ROUND(KOL_Database!$L$34*Lookup_Lists!$D$147+KOL_Database!$J$34*Lookup_Lists!$D$148,0)) | AS34: =IF(OR(KOL_Database!$AN$34="",KOL_Database!$AN$34=0,KOL_Database!$AR$34=""),"",ROUND(KOL_Database!$AR$34*KOL_Database!$K$34/100*Lookup_Lists!$D$146/KOL_Database!$AN$34,2)) | AT34: 75 | AU34: 21 | AV34: Low | AW34: No | AX34: No | AY34: No | AZ34: No | BA34: 46179.708 | BB34: 46235.708 | BC34: =IF(OR(KOL_Database!$J$34="",KOL_Database!$J$34=0,KOL_Database!$L$34=""),"",ROUND(KOL_Database!$L$34/KOL_Database!$J$34,3)) | BD34: =IF(OR(KOL_Database!$AP$34="",KOL_Database!$AP$34=0,Lookup_Lists!$D$149=0),"",MIN(100,ROUND(Lookup_Lists!$D$149/KOL_Database!$AP$34*100,0))) | BE34: =ROUND((IF(KOL_Database!$J$34="",0,1)+IF(KOL_Database!$K$34="",0,1)+IF(KOL_Database!$L$34="",0,1)+IF(KOL_Database!$M$34="",0,1)+IF(KOL_Database!$N$34="",0,1)+IF(KOL_Database!$O$34="",0,1)+IF(KOL_Database!$P$34="",0,1)+IF(KOL_Database!$R$34="",0,1)+IF(KOL_Database!$S$34="",0,1)+IF(KOL_Database!$AE$34="",0,1)+IF(KOL_Database!$AF$34="",0,1)+IF(KOL_Database!$AN$34="",0,1))/12*100,0) | BF34: =IF(KOL_Database!$BE$34>=Lookup_Lists!$D$159,"Live",IF(KOL_Database!$BE$34>=Lookup_Lists!$D$160,"Calculated","Estimated"))

Sheet Matching_Engine
A1: MATCHING ENGINE · every creator scored against every brand
A2: Ninety rows: three brands x thirty creators. Not one score on this sheet is typed — each is a formula over Brand_Profile and KOL_Database, weighted by the constants on Lookup_Lists. Filter column A to one Brand ID to read a single brand; compare the same KOL ID across the three blocks to see that Brand Match is a function of the pair, not a ranking of creators.
A4: KEY | K4: BRAND & BUSINESS RELEVANCE — 20% | O4: TARGET AUDIENCE RELEVANCE — 30% | T4: CONTENT & CATEGORY RELEVANCE — 20% | Y4: BRAND PERSONALITY FIT — 10% | AD4: PERFORMANCE QUALITY — 10% | AK4: BRAND SAFETY — 10% | AP4: RESULT | BA4: HELPERS (intermediate lookups, kept visible on purpose)
A5: Brand ID | B5: Brand | C5: KOL ID | D5: Creator | E5: Handle | F5: Platform | G5: Category | H5: Tier | I5: Followers | J5: Engagement Rate (%) | K5: Industry Match | L5: Category Match | M5: Keyword Match | N5: Brand & Business Relevance | O5: Age Match Score | P5: Gender Match Score | Q5: Location Match Score | R5: Interest Match Score | S5: Target Audience Relevance | T5: Category Match (content) | U5: Sub Category Match | V5: Topic Match | W5: Content Style Match | X5: Content & Category Relevance | Y5: Personality Match | Z5: Tone vs Content Style | AA5: Values Match | AB5: Communication Style Match | AC5: Brand Personality Fit | AD5: Engagement Rate Score | AE5: Audience Quality Score | AF5: Consistency Score | AG5: Community Score | AH5: Average Views Score | AI5: Recent Growth Score | AJ5: Performance Quality | AK5: Brand Safety Base | AL5: Competitor Saturation | AM5: Risk Flag | AN5: Risk Multiplier | AO5: Brand Safety | AP5: Final Match Score | AQ5: Match Level | AR5: Data Completeness % | AS5: Confidence | AT5: Brand Fit Index | AU5: Opportunity Score | AV5: Hard Filter Result | AW5: Exclusion Reason | AX5: Recommendation | AY5: Final Match Score (eligible only) | AZ5: Match Key | BA5: Brand Product Parent Category | BB5: KOL Sub Parent Category | BC5: Rel: Brand Product Parent → KOL Category | BD5: Rel: Preferred Category → KOL Category | BE5: Brand Preferred Sub Parent | BF5: KOL Keyword Haystack | BG5: KOL Topic Haystack
A6: BRAND-A | B6: =Brand_Profile!$D$9 | C6: =KOL_Database!$A$5 | D6: =KOL_Database!$B$5 | E6: =KOL_Database!$C$5 | F6: =KOL_Database!$D$5 | G6: =KOL_Database!$E$5 | H6: =KOL_Database!$G$5 | I6: =KOL_Database!$J$5 | J6: =KOL_Database!$K$5 | K6: =IFERROR(INDEX(Lookup_Lists!$B$170:$O$181,MATCH(Brand_Profile!$D$10,Lookup_Lists!$A$170:$A$181,0),MATCH(KOL_Database!$E$5,Lookup_Lists!$B$169:$O$169,0)),Lookup_Lists!$D$151) | L6: =IF(KOL_Database!$F$5="",Matching_Engine!$BC$6,IF(Brand_Profile!$D$12=KOL_Database!$F$5,100,IF(Matching_Engine!$BA$6=KOL_Database!$E$5,80,IF(Matching_Engine!$BC$6>=80,60,IF(Matching_Engine!$BC$6>=60,40,Lookup_Lists!$D$151))))) | M6: =ROUND((IF(Brand_Profile!$D$62=0,Lookup_Lists!$D$150,ROUND((IF(Brand_Profile!$D$57="",0,IF(ISNUMBER(SEARCH(Brand_Profile!$D$57,Matching_Engine!$BF$6)),1,0))+IF(Brand_Profile!$D$58="",0,IF(ISNUMBER(SEARCH(Brand_Profile!$D$58,Matching_Engine!$BF$6)),1,0))+IF(Brand_Profile!$D$59="",0,IF(ISNUMBER(SEARCH(Brand_Profile!$D$59,Matching_Engine!$BF$6)),1,0))+IF(Brand_Profile!$D$60="",0,IF(ISNUMBER(SEARCH(Brand_Profile!$D$60,Matching_Engine!$BF$6)),1,0))+IF(Brand_Profile!$D$61="",0,IF(ISNUMBER(SEARCH(Brand_Profile!$D$61,Matching_Engine!$BF$6)),1,0)))/Brand_Profile!$D$62*100,0))+IF(Brand_Profile!$D$74=0,Lookup_Lists!$D$150,ROUND((IF(Brand_Profile!$D$69="",0,IF(ISNUMBER(SEARCH(Brand_Profile!$D$69,Matching_Engine!$BF$6)),1,0))+IF(Brand_Profile!$D$70="",0,IF(ISNUMBER(SEARCH(Brand_Profile!$D$70,Matching_Engine!$BF$6)),1,0))+IF(Brand_Profile!$D$71="",0,IF(ISNUMBER(SEARCH(Brand_Profile!$D$71,Matching_Engine!$BF$6)),1,0))+IF(Brand_Profile!$D$72="",0,IF(ISNUMBER(SEARCH(Brand_Profile!$D$72,Matching_Engine!$BF$6)),1,0))+IF(Brand_Profile!$D$73="",0,IF(ISNUMBER(SEARCH(Brand_Profile!$D$73,Matching_Engine!$BF$6)),1,0)))/Brand_Profile!$D$74*100,0)))/2,0) | N6: =ROUND((Matching_Engine!$K$6*Lookup_Lists!$D$110+Matching_Engine!$L$6*Lookup_Lists!$D$111+Matching_Engine!$M$6*Lookup_Lists!$D$112)/(Lookup_Lists!$D$110+Lookup_Lists!$D$111+Lookup_Lists!$D$112),0) | O6: =IF(Brand_Profile!$D$16="",Lookup_Lists!$D$150,MIN(100,ROUND((IFERROR(INDEX(KOL_Database!$W$5:KOL_Database!$AA$5,1,MATCH(Brand_Profile!$D$16,Lookup_Lists!$F$6:$F$10,0)),0)+0.5*IFERROR(INDEX(KOL_Database!$W$5:KOL_Database!$AA$5,1,MATCH(Brand_Profile!$D$17,Lookup_Lists!$F$6:$F$10,0)),0))/Lookup_Lists!$D$142*100,0))) | P6: =IF(OR(Brand_Profile!$D$18="",Brand_Profile!$D$18="Any"),100,IF(Brand_Profile!$D$18="Female",MIN(100,ROUND(KOL_Database!$AB$5/Lookup_Lists!$D$143*100,0)),IF(Brand_Profile!$D$18="Male",MIN(100,ROUND(KOL_Database!$AC$5/Lookup_Lists!$D$143*100,0)),MAX(0,ROUND(100-ABS(KOL_Database!$AB$5-50)*2,0))))) | Q6: =ROUND((IF(Brand_Profile!$D$19="",100,IF(KOL_Database!$AD$5=Brand_Profile!$D$19,100,Lookup_Lists!$D$151))*Lookup_Lists!$D$118+IF(OR(Brand_Profile!$D$20="",Brand_Profile!$D$20="Nasional"),100,IF(KOL_Database!$AE$5="",Lookup_Lists!$D$150,IF(KOL_Database!$AE$5=Brand_Profile!$D$20,100,IF(KOL_Database!$AD$5=Brand_Profile!$D$19,40,Lookup_Lists!$D$151))))*Lookup_Lists!$D$119+IF(OR(Brand_Profile!$D$21="",Brand_Profile!$D$21="Nasional"),100,IF(KOL_Database!$AF$5="",Lookup_Lists!$D$150,IF(KOL_Database!$AF$5=Brand_Profile!$D$21,100,IF(KOL_Database!$AE$5=Brand_Profile!$D$20,60,Lookup_Lists!$D$151))))*Lookup_Lists!$D$120)/(Lookup_Lists!$D$118+Lookup_Lists!$D$119+Lookup_Lists!$D$120),0) | R6: =IF(Brand_Profile!$D$68=0,Lookup_Lists!$D$150,ROUND((IF(Brand_Profile!$D$63="",0,IF(ISNUMBER(SEARCH(Brand_Profile!$D$63,KOL_Database!$AG$5)),1,0))+IF(Brand_Profile!$D$64="",0,IF(ISNUMBER(SEARCH(Brand_Profile!$D$64,KOL_Database!$AG$5)),1,0))+IF(Brand_Profile!$D$65="",0,IF(ISNUMBER(SEARCH(Brand_Profile!$D$65,KOL_Database!$AG$5)),1,0))+IF(Brand_Profile!$D$66="",0,IF(ISNUMBER(SEARCH(Brand_Profile!$D$66,KOL_Database!$AG$5)),1,0))+IF(Brand_Profile!$D$67="",0,IF(ISNUMBER(SEARCH(Brand_Profile!$D$67,KOL_Database!$AG$5)),1,0)))/Brand_Profile!$D$68*100,0)) | S6: =ROUND((Matching_Engine!$O$6*Brand_Profile!$D$96+Matching_Engine!$P$6*Brand_Profile!$D$97+Matching_Engine!$Q$6*Brand_Profile!$D$98+Matching_Engine!$R$6*Brand_Profile!$D$99)/MAX(1,Brand_Profile!$D$96+Brand_Profile!$D$97+Brand_Profile!$D$98+Brand_Profile!$D$99),0) | T6: =IF(Brand_Profile!$D$33="",Lookup_Lists!$D$150,Matching_Engine!$BD$6) | U6: =IF(Brand_Profile!$D$34="",Lookup_Lists!$D$150,IF(Brand_Profile!$D$34=KOL_Database!$F$5,100,IF(Matching_Engine!$BE$6=KOL_Database!$E$5,75,IF(Matching_Engine!$BD$6>=80,Lookup_Lists!$D$150,IF(Matching_Engine!$BD$6>=60,35,Lookup_Lists!$D$151))))) | V6: =IF(Brand_Profile!$D$86=0,Lookup_Lists!$D$150,ROUND((IF(Brand_Profile!$D$81="",0,IF(ISNUMBER(SEARCH(Brand_Profile!$D$81,Matching_Engine!$BG$6)),1,0))+IF(Brand_Profile!$D$82="",0,IF(ISNUMBER(SEARCH(Brand_Profile!$D$82,Matching_Engine!$BG$6)),1,0))+IF(Brand_Profile!$D$83="",0,IF(ISNUMBER(SEARCH(Brand_Profile!$D$83,Matching_Engine!$BG$6)),1,0))+IF(Brand_Profile!$D$84="",0,IF(ISNUMBER(SEARCH(Brand_Profile!$D$84,Matching_Engine!$BG$6)),1,0))+IF(Brand_Profile!$D$85="",0,IF(ISNUMBER(SEARCH(Brand_Profile!$D$85,Matching_Engine!$BG$6)),1,0)))/Brand_Profile!$D$86*100,0)) | W6: =IF(Brand_Profile!$D$39="",Lookup_Lists!$D$150,IFERROR(INDEX(Lookup_Lists!$B$237:$K$246,MATCH(Brand_Profile!$D$39,Lookup_Lists!$A$237:$A$246,0),MATCH(KOL_Database!$AJ$5,Lookup_Lists!$B$236:$K$236,0)),45)) | X6: =ROUND((Matching_Engine!$T$6*Lookup_Lists!$D$121+Matching_Engine!$U$6*Lookup_Lists!$D$122+Matching_Engine!$V$6*Lookup_Lists!$D$123+Matching_Engine!$W$6*Lookup_Lists!$D$124)/(Lookup_Lists!$D$121+Lookup_Lists!$D$122+Lookup_Lists!$D$123+Lookup_Lists!$D$124),0) | Y6: =MIN(100,MAX(IFERROR(INDEX(Lookup_Lists!$B$202:$M$211,MATCH(Brand_Profile!$D$25,Lookup_Lists!$A$202:$A$211,0),MATCH(KOL_Database!$AK$5,Lookup_Lists!$B$201:$M$201,0)),40),IF(KOL_Database!$AK$5=Brand_Profile!$D$41,95,0))) | Z6: =IFERROR(INDEX(Lookup_Lists!$B$215:$K$222,MATCH(Brand_Profile!$D$27,Lookup_Lists!$A$215:$A$222,0),MATCH(KOL_Database!$AJ$5,Lookup_Lists!$B$214:$K$214,0)),45) | AA6: =ROUND((IF(Brand_Profile!$D$80=0,Lookup_Lists!$D$150,ROUND((IF(Brand_Profile!$D$75="",0,IF(ISNUMBER(SEARCH(Brand_Profile!$D$75,KOL_Database!$AL$5)),1,0))+IF(Brand_Profile!$D$76="",0,IF(ISNUMBER(SEARCH(Brand_Profile!$D$76,KOL_Database!$AL$5)),1,0))+IF(Brand_Profile!$D$77="",0,IF(ISNUMBER(SEARCH(Brand_Profile!$D$77,KOL_Database!$AL$5)),1,0))+IF(Brand_Profile!$D$78="",0,IF(ISNUMBER(SEARCH(Brand_Profile!$D$78,KOL_Database!$AL$5)),1,0))+IF(Brand_Profile!$D$79="",0,IF(ISNUMBER(SEARCH(Brand_Profile!$D$79,KOL_Database!$AL$5)),1,0)))/Brand_Profile!$D$80*100,0))+IF(Brand_Profile!$D$92=0,Lookup_Lists!$D$150,ROUND((IF(Brand_Profile!$D$87="",0,IF(ISNUMBER(SEARCH(Brand_Profile!$D$87,KOL_Database!$AL$5)),1,0))+IF(Brand_Profile!$D$88="",0,IF(ISNUMBER(SEARCH(Brand_Profile!$D$88,KOL_Database!$AL$5)),1,0))+IF(Brand_Profile!$D$89="",0,IF(ISNUMBER(SEARCH(Brand_Profile!$D$89,KOL_Database!$AL$5)),1,0))+IF(Brand_Profile!$D$90="",0,IF(ISNUMBER(SEARCH(Brand_Profile!$D$90,KOL_Database!$AL$5)),1,0))+IF(Brand_Profile!$D$91="",0,IF(ISNUMBER(SEARCH(Brand_Profile!$D$91,KOL_Database!$AL$5)),1,0)))/Brand_Profile!$D$92*100,0)))/2,0) | AB6: =IFERROR(INDEX(Lookup_Lists!$B$226:$K$233,MATCH(Brand_Profile!$D$30,Lookup_Lists!$A$226:$A$233,0),MATCH(KOL_Database!$AJ$5,Lookup_Lists!$B$225:$K$225,0)),45) | AC6: =ROUND((Matching_Engine!$Y$6*Lookup_Lists!$D$125+Matching_Engine!$Z$6*Lookup_Lists!$D$126+Matching_Engine!$AA$6*Lookup_Lists!$D$127+Matching_Engine!$AB$6*Lookup_Lists!$D$128)/(Lookup_Lists!$D$125+Lookup_Lists!$D$126+Lookup_Lists!$D$127+Lookup_Lists!$D$128),0) | AD6: =IF(KOL_Database!$K$5="",0,MIN(100,ROUND(KOL_Database!$K$5/Lookup_Lists!$D$141*100,0))) | AE6: =IF(KOL_Database!$R$5="",0,MIN(100,MAX(0,KOL_Database!$R$5))) | AF6: =IF(KOL_Database!$P$5="",0,MIN(100,MAX(0,KOL_Database!$P$5))) | AG6: =IF(KOL_Database!$Q$5="",0,MIN(100,MAX(0,KOL_Database!$Q$5))) | AH6: =IF(OR(KOL_Database!$J$5="",KOL_Database!$J$5=0,KOL_Database!$L$5=""),0,MIN(100,ROUND(KOL_Database!$L$5/KOL_Database!$J$5/Lookup_Lists!$D$144*100,0))) | AI6: =IF(KOL_Database!$N$5="",0,MIN(100,MAX(0,ROUND((KOL_Database!$N$5+2)/(Lookup_Lists!$D$145+2)*100,0)))) | AJ6: =ROUND((Matching_Engine!$AD$6*Lookup_Lists!$D$129+Matching_Engine!$AE$6*Lookup_Lists!$D$130+Matching_Engine!$AF$6*Lookup_Lists!$D$131+Matching_Engine!$AG$6*Lookup_Lists!$D$132+Matching_Engine!$AH$6*Lookup_Lists!$D$133+Matching_Engine!$AI$6*Lookup_Lists!$D$134)/(Lookup_Lists!$D$129+Lookup_Lists!$D$130+Lookup_Lists!$D$131+Lookup_Lists!$D$132+Lookup_Lists!$D$133+Lookup_Lists!$D$134),0) | AK6: =IF(KOL_Database!$AT$5="",0,MIN(100,MAX(0,KOL_Database!$AT$5))) | AL6: =IF(KOL_Database!$AU$5="",0,KOL_Database!$AU$5) | AM6: =IF(KOL_Database!$AV$5="","None",KOL_Database!$AV$5) | AN6: =IF(Matching_Engine!$AM$6="High",Lookup_Lists!$D$137,IF(Matching_Engine!$AM$6="Medium",Lookup_Lists!$D$138,IF(Matching_Engine!$AM$6="Low",Lookup_Lists!$D$139,Lookup_Lists!$D$140))) | AO6: =ROUND(MIN(100,MAX(0,(Matching_Engine!$AK$6*Lookup_Lists!$D$135+(100-Matching_Engine!$AL$6)*Lookup_Lists!$D$136)/(Lookup_Lists!$D$135+Lookup_Lists!$D$136)*Matching_Engine!$AN$6)),0) | AP6: =ROUND((Matching_Engine!$N$6*Lookup_Lists!$D$104+Matching_Engine!$S$6*Lookup_Lists!$D$105+Matching_Engine!$X$6*Lookup_Lists!$D$106+Matching_Engine!$AC$6*Lookup_Lists!$D$107+Matching_Engine!$AJ$6*Lookup_Lists!$D$108+Matching_Engine!$AO$6*Lookup_Lists!$D$109)/MAX(1,(Lookup_Lists!$D$104+Lookup_Lists!$D$105+Lookup_Lists!$D$106+Lookup_Lists!$D$107+Lookup_Lists!$D$108+Lookup_Lists!$D$109)),0) | AQ6: =IF(Matching_Engine!$AP$6>=Lookup_Lists!$D$152,"Excellent Match",IF(Matching_Engine!$AP$6>=Lookup_Lists!$D$153,"Strong Match",IF(Matching_Engine!$AP$6>=Lookup_Lists!$D$154,"Good Match",IF(Matching_Engine!$AP$6>=Lookup_Lists!$D$155,"Moderate Match","Low Match")))) | AR6: =KOL_Database!$BE$5 | AS6: =IF(Matching_Engine!$AR$6>=Lookup_Lists!$D$159,"High",IF(Matching_Engine!$AR$6>=Lookup_Lists!$D$160,"Medium","Limited Data")) | AT6: =ROUND((Matching_Engine!$N$6+Matching_Engine!$X$6+Matching_Engine!$AC$6)/3,0) | AU6: =ROUND(((100-Matching_Engine!$AL$6)*Lookup_Lists!$D$162+IF(KOL_Database!$BD$5="",Lookup_Lists!$D$150,KOL_Database!$BD$5)*Lookup_Lists!$D$163+Matching_Engine!$AI$6*Lookup_Lists!$D$164+Matching_Engine!$AD$6*Lookup_Lists!$D$165)/(Lookup_Lists!$D$162+Lookup_Lists!$D$163+Lookup_Lists!$D$164+Lookup_Lists!$D$165),0) | AV6: =IF(Matching_Engine!$AW$6="","PASS","EXCLUDED") | AW6: =IF(ISERROR(SEARCH(KOL_Database!$D$5,Brand_Profile!$D$32)),"Platform not in Preferred Platform",IF(AND(Brand_Profile!$D$36>0,KOL_Database!$J$5<Brand_Profile!$D$36),"Followers below Preferred Follower Range",IF(AND(Brand_Profile!$D$37>0,KOL_Database!$J$5>Brand_Profile!$D$37),"Followers above Preferred Follower Range",IF(AND(Brand_Profile!$D$38>0,IF(KOL_Database!$K$5="",0,KOL_Database!$K$5)<Brand_Profile!$D$38),"Engagement Rate below Minimum Engagement Rate",IF(ISERROR(SEARCH(KOL_Database!$G$5,Brand_Profile!$D$35)),"Tier not in Preferred Tier",IF(AND(Brand_Profile!$D$43>0,Matching_Engine!$AE$6<Brand_Profile!$D$43),"Audience Quality below Minimum Audience Quality",IF(AND(Brand_Profile!$D$44>0,Matching_Engine!$AK$6<Brand_Profile!$D$44),"Brand Safety below Minimum Brand Safety",IF(AND(Brand_Profile!$D$47="Yes",KOL_Database!$AD$5<>Brand_Profile!$D$19),"Audience Country does not match Target Country",IF(AND(Brand_Profile!$D$46="Yes",KOL_Database!$E$5<>Brand_Profile!$D$33),"Category is not the Preferred Category",IF(AND(Brand_Profile!$D$48>0,Matching_Engine!$AL$6>Brand_Profile!$D$48),"Competitor Saturation above Max Competitor Saturation",IF(AND(Brand_Profile!$D$50="Yes",KOL_Database!$AW$5="Yes"),"Already Selected",IF(AND(Brand_Profile!$D$51="Yes",KOL_Database!$AX$5="Yes"),"Already in Cart",IF(AND(Brand_Profile!$D$52="Yes",KOL_Database!$AY$5="Yes"),"Existing Partner",IF(AND(Brand_Profile!$D$53="Yes",KOL_Database!$AZ$5="Yes"),"Excluded Creator",IF(AND(Brand_Profile!$D$49>0,Matching_Engine!$AP$6<Brand_Profile!$D$49),"Brand Match below Minimum Brand Match",""))))))))))))))) | AX6: =IF(Matching_Engine!$AV$6="EXCLUDED","Excluded",IF(Matching_Engine!$AP$6>=Lookup_Lists!$D$156,"Highly Recommended",IF(Matching_Engine!$AP$6>=Lookup_Lists!$D$157,"Recommended",IF(Matching_Engine!$AP$6>=Lookup_Lists!$D$158,"Consider","Low Priority")))) | AY6: =IF(Matching_Engine!$AV$6="PASS",Matching_Engine!$AP$6,"") | AZ6: =Matching_Engine!$A$6&"|"&Matching_Engine!$C$6 | BA6: =IFERROR(INDEX(Lookup_Lists!$B$51:$B$92,MATCH(Brand_Profile!$D$12,Lookup_Lists!$A$51:$A$92,0)),"") | BB6: =IFERROR(INDEX(Lookup_Lists!$B$51:$B$92,MATCH(KOL_Database!$F$5,Lookup_Lists!$A$51:$A$92,0)),"") | BC6: =IFERROR(INDEX(Lookup_Lists!$B$185:$O$198,MATCH(Matching_Engine!$BA$6,Lookup_Lists!$A$185:$A$198,0),MATCH(KOL_Database!$E$5,Lookup_Lists!$B$184:$O$184,0)),Lookup_Lists!$D$151) | BD6: =IFERROR(INDEX(Lookup_Lists!$B$185:$O$198,MATCH(Brand_Profile!$D$33,Lookup_Lists!$A$185:$A$198,0),MATCH(KOL_Database!$E$5,Lookup_Lists!$B$184:$O$184,0)),Lookup_Lists!$D$151) | BE6: =IFERROR(INDEX(Lookup_Lists!$B$51:$B$92,MATCH(Brand_Profile!$D$34,Lookup_Lists!$A$51:$A$92,0)),"") | BF6: =KOL_Database!$AI$5&", "&KOL_Database!$AG$5&", "&KOL_Database!$F$5&", "&KOL_Database!$E$5 | BG6: =KOL_Database!$AI$5&", "&KOL_Database!$AG$5
A7: BRAND-A | B7: =Brand_Profile!$D$9 | C7: =KOL_Database!$A$6 | D7: =KOL_Database!$B$6 | E7: =KOL_Database!$C$6 | F7: =KOL_Database!$D$6 | G7: =KOL_Database!$E$6 | H7: =KOL_Database!$G$6 | I7: =KOL_Database!$J$6 | J7: =KOL_Database!$K$6 | K7: =IFERROR(INDEX(Lookup_Lists!$B$170:$O$181,MATCH(Brand_Profile!$D$10,Lookup_Lists!$A$170:$A$181,0),MATCH(KOL_Database!$E$6,Lookup_Lists!$B$169:$O$169,0)),Lookup_Lists!$D$151) | L7: =IF(KOL_Database!$F$6="",Matching_Engine!$BC$7,IF(Brand_Profile!$D$12=KOL_Database!$F$6,100,IF(Matching_Engine!$BA$7=KOL_Database!$E$6,80,IF(Matching_Engine!$BC$7>=80,60,IF(Matching_Engine!$BC$7>=60,40,Lookup_Lists!$D$151))))) | M7: =ROUND((IF(Brand_Profile!$D$62=0,Lookup_Lists!$D$150,ROUND((IF(Brand_Profile!$D$57="",0,IF(ISNUMBER(SEARCH(Brand_Profile!$D$57,Matching_Engine!$BF$7)),1,0))+IF(Brand_Profile!$D$58="",0,IF(ISNUMBER(SEARCH(Brand_Profile!$D$58,Matching_Engine!$BF$7)),1,0))+IF(Brand_Profile!$D$59="",0,IF(ISNUMBER(SEARCH(Brand_Profile!$D$59,Matching_Engine!$BF$7)),1,0))+IF(Brand_Profile!$D$60="",0,IF(ISNUMBER(SEARCH(Brand_Profile!$D$60,Matching_Engine!$BF$7)),1,0))+IF(Brand_Profile!$D$61="",0,IF(ISNUMBER(SEARCH(Brand_Profile!$D$61,Matching_Engine!$BF$7)),1,0)))/Brand_Profile!$D$62*100,0))+IF(Brand_Profile!$D$74=0,Lookup_Lists!$D$150,ROUND((IF(Brand_Profile!$D$69="",0,IF(ISNUMBER(SEARCH(Brand_Profile!$D$69,Matching_Engine!$BF$7)),1,0))+IF(Brand_Profile!$D$70="",0,IF(ISNUMBER(SEARCH(Brand_Profile!$D$70,Matching_Engine!$BF$7)),1,0))+IF(Brand_Profile!$D$71="",0,IF(ISNUMBER(SEARCH(Brand_Profile!$D$71,Matching_Engine!$BF$7)),1,0))+IF(Brand_Profile!$D$72="",0,IF(ISNUMBER(SEARCH(Brand_Profile!$D$72,Matching_Engine!$BF$7)),1,0))+IF(Brand_Profile!$D$73="",0,IF(ISNUMBER(SEARCH(Brand_Profile!$D$73,Matching_Engine!$BF$7)),1,0)))/Brand_Profile!$D$74*100,0)))/2,0) | N7: =ROUND((Matching_Engine!$K$7*Lookup_Lists!$D$110+Matching_Engine!$L$7*Lookup_Lists!$D$111+Matching_Engine!$M$7*Lookup_Lists!$D$112)/(Lookup_Lists!$D$110+Lookup_Lists!$D$111+Lookup_Lists!$D$112),0) | O7: =IF(Brand_Profile!$D$16="",Lookup_Lists!$D$150,MIN(100,ROUND((IFERROR(INDEX(KOL_Database!$W$6:KOL_Database!$AA$6,1,MATCH(Brand_Profile!$D$16,Lookup_Lists!$F$6:$F$10,0)),0)+0.5*IFERROR(INDEX(KOL_Database!$W$6:KOL_Database!$AA$6,1,MATCH(Brand_Profile!$D$17,Lookup_Lists!$F$6:$F$10,0)),0))/Lookup_Lists!$D$142*100,0))) | P7: =IF(OR(Brand_Profile!$D$18="",Brand_Profile!$D$18="Any"),100,IF(Brand_Profile!$D$18="Female",MIN(100,ROUND(KOL_Database!$AB$6/Lookup_Lists!$D$143*100,0)),IF(Brand_Profile!$D$18="Male",MIN(100,ROUND(KOL_Database!$AC$6/Lookup_Lists!$D$143*100,0)),MAX(0,ROUND(100-ABS(KOL_Database!$AB$6-50)*2,0))))) | Q7: =ROUND((IF(Brand_Profile!$D$19="",100,IF(KOL_Database!$AD$6=Brand_Profile!$D$19,100,Lookup_Lists!$D$151))*Lookup_Lists!$D$118+IF(OR(Brand_Profile!$D$20="",Brand_Profile!$D$20="Nasional"),100,IF(KOL_Database!$AE$6="",Lookup_Lists!$D$150,IF(KOL_Database!$AE$6=Brand_Profile!$D$20,100,IF(KOL_Database!$AD$6=Brand_Profile!$D$19,40,Lookup_Lists!$D$151))))*Lookup_Lists!$D$119+IF(OR(Brand_Profile!$D$21="",Brand_Profile!$D$21="Nasional"),100,IF(KOL_Database!$AF$6="",Lookup_Lists!$D$150,IF(KOL_Database!$AF$6=Brand_Profile!$D$21,100,IF(KOL_Database!$AE$6=Brand_Profile!$D$20,60,Lookup_Lists!$D$151))))*Lookup_Lists!$D$120)/(Lookup_Lists!$D$118+Lookup_Lists!$D$119+Lookup_Lists!$D$120),0) | R7: =IF(Brand_Profile!$D$68=0,Lookup_Lists!$D$150,ROUND((IF(Brand_Profile!$D$63="",0,IF(ISNUMBER(SEARCH(Brand_Profile!$D$63,KOL_Database!$AG$6)),1,0))+IF(Brand_Profile!$D$64="",0,IF(ISNUMBER(SEARCH(Brand_Profile!$D$64,KOL_Database!$AG$6)),1,0))+IF(Brand_Profile!$D$65="",0,IF(ISNUMBER(SEARCH(Brand_Profile!$D$65,KOL_Database!$AG$6)),1,0))+IF(Brand_Profile!$D$66="",0,IF(ISNUMBER(SEARCH(Brand_Profile!$D$66,KOL_Database!$AG$6)),1,0))+IF(Brand_Profile!$D$67="",0,IF(ISNUMBER(SEARCH(Brand_Profile!$D$67,KOL_Database!$AG$6)),1,0)))/Brand_Profile!$D$68*100,0)) | S7: =ROUND((Matching_Engine!$O$7*Brand_Profile!$D$96+Matching_Engine!$P$7*Brand_Profile!$D$97+Matching_Engine!$Q$7*Brand_Profile!$D$98+Matching_Engine!$R$7*Brand_Profile!$D$99)/MAX(1,Brand_Profile!$D$96+Brand_Profile!$D$97+Brand_Profile!$D$98+Brand_Profile!$D$99),0) | T7: =IF(Brand_Profile!$D$33="",Lookup_Lists!$D$150,Matching_Engine!$BD$7) | U7: =IF(Brand_Profile!$D$34="",Lookup_Lists!$D$150,IF(Brand_Profile!$D$34=KOL_Database!$F$6,100,IF(Matching_Engine!$BE$7=KOL_Database!$E$6,75,IF(Matching_Engine!$BD$7>=80,Lookup_Lists!$D$150,IF(Matching_Engine!$BD$7>=60,35,Lookup_Lists!$D$151))))) | V7: =IF(Brand_Profile!$D$86=0,Lookup_Lists!$D$150,ROUND((IF(Brand_Profile!$D$81="",0,IF(ISNUMBER(SEARCH(Brand_Profile!$D$81,Matching_Engine!$BG$7)),1,0))+IF(Brand_Profile!$D$82="",0,IF(ISNUMBER(SEARCH(Brand_Profile!$D$82,Matching_Engine!$BG$7)),1,0))+IF(Brand_Profile!$D$83="",0,IF(ISNUMBER(SEARCH(Brand_Profile!$D$83,Matching_Engine!$BG$7)),1,0))+IF(Brand_Profile!$D$84="",0,IF(ISNUMBER(SEARCH(Brand_Profile!$D$84,Matching_Engine!$BG$7)),1,0))+IF(Brand_Profile!$D$85="",0,IF(ISNUMBER(SEARCH(Brand_Profile!$D$85,Matching_Engine!$BG$7)),1,0)))/Brand_Profile!$D$86*100,0)) | W7: =IF(Brand_Profile!$D$39="",Lookup_Lists!$D$150,IFERROR(INDEX(Lookup_Lists!$B$237:$K$246,MATCH(Brand_Profile!$D$39,Lookup_Lists!$A$237:$A$246,0),MATCH(KOL_Database!$AJ$6,Lookup_Lists!$B$236:$K$236,0)),45)) | X7: =ROUND((Matching_Engine!$T$7*Lookup_Lists!$D$121+Matching_Engine!$U$7*Lookup_Lists!$D$122+Matching_Engine!$V$7*Lookup_Lists!$D$123+Matching_Engine!$W$7*Lookup_Lists!$D$124)/(Lookup_Lists!$D$121+Lookup_Lists!$D$122+Lookup_Lists!$D$123+Lookup_Lists!$D$124),0) | Y7: =MIN(100,MAX(IFERROR(INDEX(Lookup_Lists!$B$202:$M$211,MATCH(Brand_Profile!$D$25,Lookup_Lists!$A$202:$A$211,0),MATCH(KOL_Database!$AK$6,Lookup_Lists!$B$201:$M$201,0)),40),IF(KOL_Database!$AK$6=Brand_Profile!$D$41,95,0))) | Z7: =IFERROR(INDEX(Lookup_Lists!$B$215:$K$222,MATCH(Brand_Profile!$D$27,Lookup_Lists!$A$215:$A$222,0),MATCH(KOL_Database!$AJ$6,Lookup_Lists!$B$214:$K$214,0)),45) | AA7: =ROUND((IF(Brand_Profile!$D$80=0,Lookup_Lists!$D$150,ROUND((IF(Brand_Profile!$D$75="",0,IF(ISNUMBER(SEARCH(Brand_Profile!$D$75,KOL_Database!$AL$6)),1,0))+IF(Brand_Profile!$D$76="",0,IF(ISNUMBER(SEARCH(Brand_Profile!$D$76,KOL_Database!$AL$6)),1,0))+IF(Brand_Profile!$D$77="",0,IF(ISNUMBER(SEARCH(Brand_Profile!$D$77,KOL_Database!$AL$6)),1,0))+IF(Brand_Profile!$D$78="",0,IF(ISNUMBER(SEARCH(Brand_Profile!$D$78,KOL_Database!$AL$6)),1,0))+IF(Brand_Profile!$D$79="",0,IF(ISNUMBER(SEARCH(Brand_Profile!$D$79,KOL_Database!$AL$6)),1,0)))/Brand_Profile!$D$80*100,0))+IF(Brand_Profile!$D$92=0,Lookup_Lists!$D$150,ROUND((IF(Brand_Profile!$D$87="",0,IF(ISNUMBER(SEARCH(Brand_Profile!$D$87,KOL_Database!$AL$6)),1,0))+IF(Brand_Profile!$D$88="",0,IF(ISNUMBER(SEARCH(Brand_Profile!$D$88,KOL_Database!$AL$6)),1,0))+IF(Brand_Profile!$D$89="",0,IF(ISNUMBER(SEARCH(Brand_Profile!$D$89,KOL_Database!$AL$6)),1,0))+IF(Brand_Profile!$D$90="",0,IF(ISNUMBER(SEARCH(Brand_Profile!$D$90,KOL_Database!$AL$6)),1,0))+IF(Brand_Profile!$D$91="",0,IF(ISNUMBER(SEARCH(Brand_Profile!$D$91,KOL_Database!$AL$6)),1,0)))/Brand_Profile!$D$92*100,0)))/2,0) | AB7: =IFERROR(INDEX(Lookup_Lists!$B$226:$K$233,MATCH(Brand_Profile!$D$30,Lookup_Lists!$A$226:$A$233,0),MATCH(KOL_Database!$AJ$6,Lookup_Lists!$B$225:$K$225,0)),45) | AC7: =ROUND((Matching_Engine!$Y$7*Lookup_Lists!$D$125+Matching_Engine!$Z$7*Lookup_Lists!$D$126+Matching_Engine!$AA$7*Lookup_Lists!$D$127+Matching_Engine!$AB$7*Lookup_Lists!$D$128)/(Lookup_Lists!$D$125+Lookup_Lists!$D$126+Lookup_Lists!$D$127+Lookup_Lists!$D$128),0) | AD7: =IF(KOL_Database!$K$6="",0,MIN(100,ROUND(KOL_Database!$K$6/Lookup_Lists!$D$141*100,0))) | AE7: =IF(KOL_Database!$R$6="",0,MIN(100,MAX(0,KOL_Database!$R$6))) | AF7: =IF(KOL_Database!$P$6="",0,MIN(100,MAX(0,KOL_Database!$P$6))) | AG7: =IF(KOL_Database!$Q$6="",0,MIN(100,MAX(0,KOL_Database!$Q$6))) | AH7: =IF(OR(KOL_Database!$J$6="",KOL_Database!$J$6=0,KOL_Database!$L$6=""),0,MIN(100,ROUND(KOL_Database!$L$6/KOL_Database!$J$6/Lookup_Lists!$D$144*100,0))) | AI7: =IF(KOL_Database!$N$6="",0,MIN(100,MAX(0,ROUND((KOL_Database!$N$6+2)/(Lookup_Lists!$D$145+2)*100,0)))) | AJ7: =ROUND((Matching_Engine!$AD$7*Lookup_Lists!$D$129+Matching_Engine!$AE$7*Lookup_Lists!$D$130+Matching_Engine!$AF$7*Lookup_Lists!$D$131+Matching_Engine!$AG$7*Lookup_Lists!$D$132+Matching_Engine!$AH$7*Lookup_Lists!$D$133+Matching_Engine!$AI$7*Lookup_Lists!$D$134)/(Lookup_Lists!$D$129+Lookup_Lists!$D$130+Lookup_Lists!$D$131+Lookup_Lists!$D$132+Lookup_Lists!$D$133+Lookup_Lists!$D$134),0) | AK7: =IF(KOL_Database!$AT$6="",0,MIN(100,MAX(0,KOL_Database!$AT$6))) | AL7: =IF(KOL_Database!$AU$6="",0,KOL_Database!$AU$6) | AM7: =IF(KOL_Database!$AV$6="","None",KOL_Database!$AV$6) | AN7: =IF(Matching_Engine!$AM$7="High",Lookup_Lists!$D$137,IF(Matching_Engine!$AM$7="Medium",Lookup_Lists!$D$138,IF(Matching_Engine!$AM$7="Low",Lookup_Lists!$D$139,Lookup_Lists!$D$140))) | AO7: =ROUND(MIN(100,MAX(0,(Matching_Engine!$AK$7*Lookup_Lists!$D$135+(100-Matching_Engine!$AL$7)*Lookup_Lists!$D$136)/(Lookup_Lists!$D$135+Lookup_Lists!$D$136)*Matching_Engine!$AN$7)),0) | AP7: =ROUND((Matching_Engine!$N$7*Lookup_Lists!$D$104+Matching_Engine!$S$7*Lookup_Lists!$D$105+Matching_Engine!$X$7*Lookup_Lists!$D$106+Matching_Engine!$AC$7*Lookup_Lists!$D$107+Matching_Engine!$AJ$7*Lookup_Lists!$D$108+Matching_Engine!$AO$7*Lookup_Lists!$D$109)/MAX(1,(Lookup_Lists!$D$104+Lookup_Lists!$D$105+Lookup_Lists!$D$106+Lookup_Lists!$D$107+Lookup_Lists!$D$108+Lookup_Lists!$D$109)),0) | AQ7: =IF(Matching_Engine!$AP$7>=Lookup_Lists!$D$152,"Excellent Match",IF(Matching_Engine!$AP$7>=Lookup_Lists!$D$153,"Strong Match",IF(Matching_Engine!$AP$7>=Lookup_Lists!$D$154,"Good Match",IF(Matching_Engine!$AP$7>=Lookup_Lists!$D$155,"Moderate Match","Low Match")))) | AR7: =KOL_Database!$BE$6 | AS7: =IF(Matching_Engine!$AR$7>=Lookup_Lists!$D$159,"High",IF(Matching_Engine!$AR$7>=Lookup_Lists!$D$160,"Medium","Limited Data")) | AT7: =ROUND((Matching_Engine!$N$7+Matching_Engine!$X$7+Matching_Engine!$AC$7)/3,0) | AU7: =ROUND(((100-Matching_Engine!$AL$7)*Lookup_Lists!$D$162+IF(KOL_Database!$BD$6="",Lookup_Lists!$D$150,KOL_Database!$BD$6)*Lookup_Lists!$D$163+Matching_Engine!$AI$7*Lookup_Lists!$D$164+Matching_Engine!$AD$7*Lookup_Lists!$D$165)/(Lookup_Lists!$D$162+Lookup_Lists!$D$163+Lookup_Lists!$D$164+Lookup_Lists!$D$165),0) | AV7: =IF(Matching_Engine!$AW$7="","PASS","EXCLUDED") | AW7: =IF(ISERROR(SEARCH(KOL_Database!$D$6,Brand_Profile!$D$32)),"Platform not in Preferred Platform",IF(AND(Brand_Profile!$D$36>0,KOL_Database!$J$6<Brand_Profile!$D$36),"Followers below Preferred Follower Range",IF(AND(Brand_Profile!$D$37>0,KOL_Database!$J$6>Brand_Profile!$D$37),"Followers above Preferred Follower Range",IF(AND(Brand_Profile!$D$38>0,IF(KOL_Database!$K$6="",0,KOL_Database!$K$6)<Brand_Profile!$D$38),"Engagement Rate below Minimum Engagement Rate",IF(ISERROR(SEARCH(KOL_Database!$G$6,Brand_Profile!$D$35)),"Tier not in Preferred Tier",IF(AND(Brand_Profile!$D$43>0,Matching_Engine!$AE$7<Brand_Profile!$D$43),"Audience Quality below Minimum Audience Quality",IF(AND(Brand_Profile!$D$44>0,Matching_Engine!$AK$7<Brand_Profile!$D$44),"Brand Safety below Minimum Brand Safety",IF(AND(Brand_Profile!$D$47="Yes",KOL_Database!$AD$6<>Brand_Profile!$D$19),"Audience Country does not match Target Country",IF(AND(Brand_Profile!$D$46="Yes",KOL_Database!$E$6<>Brand_Profile!$D$33),"Category is not the Preferred Category",IF(AND(Brand_Profile!$D$48>0,Matching_Engine!$AL$7>Brand_Profile!$D$48),"Competitor Saturation above Max Competitor Saturation",IF(AND(Brand_Profile!$D$50="Yes",KOL_Database!$AW$6="Yes"),"Already Selected",IF(AND(Brand_Profile!$D$51="Yes",KOL_Database!$AX$6="Yes"),"Already in Cart",IF(AND(Brand_Profile!$D$52="Yes",KOL_Database!$AY$6="Yes"),"Existing Partner",IF(AND(Brand_Profile!$D$53="Yes",KOL_Database!$AZ$6="Yes"),"Excluded Creator",IF(AND(Brand_Profile!$D$49>0,Matching_Engine!$AP$7<Brand_Profile!$D$49),"Brand Match below Minimum Brand Match",""))))))))))))))) | AX7: =IF(Matching_Engine!$AV$7="EXCLUDED","Excluded",IF(Matching_Engine!$AP$7>=Lookup_Lists!$D$156,"Highly Recommended",IF(Matching_Engine!$AP$7>=Lookup_Lists!$D$157,"Recommended",IF(Matching_Engine!$AP$7>=Lookup_Lists!$D$158,"Consider","Low Priority")))) | AY7: =IF(Matching_Engine!$AV$7="PASS",Matching_Engine!$AP$7,"") | AZ7: =Matching_Engine!$A$7&"|"&Matching_Engine!$C$7 | BA7: =IFERROR(INDEX(Lookup_Lists!$B$51:$B$92,MATCH(Brand_Profile!$D$12,Lookup_Lists!$A$51:$A$92,0)),"") | BB7: =IFERROR(INDEX(Lookup_Lists!$B$51:$B$92,MATCH(KOL_Database!$F$6,Lookup_Lists!$A$51:$A$92,0)),"") | BC7: =IFERROR(INDEX(Lookup_Lists!$B$185:$O$198,MATCH(Matching_Engine!$BA$7,Lookup_Lists!$A$185:$A$198,0),MATCH(KOL_Database!$E$6,Lookup_Lists!$B$184:$O$184,0)),Lookup_Lists!$D$151) | BD7: =IFERROR(INDEX(Lookup_Lists!$B$185:$O$198,MATCH(Brand_Profile!$D$33,Lookup_Lists!$A$185:$A$198,0),MATCH(KOL_Database!$E$6,Lookup_Lists!$B$184:$O$184,0)),Lookup_Lists!$D$151) | BE7: =IFERROR(INDEX(Lookup_Lists!$B$51:$B$92,MATCH(Brand_Profile!$D$34,Lookup_Lists!$A$51:$A$92,0)),"") | BF7: =KOL_Database!$AI$6&", "&KOL_Database!$AG$6&", "&KOL_Database!$F$6&", "&KOL_Database!$E$6 | BG7: =KOL_Database!$AI$6&", "&KOL_Database!$AG$6
A8: BRAND-A | B8: =Brand_Profile!$D$9 | C8: =KOL_Database!$A$7 | D8: =KOL_Database!$B$7 | E8: =KOL_Database!$C$7 | F8: =KOL_Database!$D$7 | G8: =KOL_Database!$E$7 | H8: =KOL_Database!$G$7 | I8: =KOL_Database!$J$7 | J8: =KOL_Database!$K$7 | K8: =IFERROR(INDEX(Lookup_Lists!$B$170:$O$181,MATCH(Brand_Profile!$D$10,Lookup_Lists!$A$170:$A$181,0),MATCH(KOL_Database!$E$7,Lookup_Lists!$B$169:$O$169,0)),Lookup_Lists!$D$151) | L8: =IF(KOL_Database!$F$7="",Matching_Engine!$BC$8,IF(Brand_Profile!$D$12=KOL_Database!$F$7,100,IF(Matching_Engine!$BA$8=KOL_Database!$E$7,80,IF(Matching_Engine!$BC$8>=80,60,IF(Matching_Engine!$BC$8>=60,40,Lookup_Lists!$D$151))))) | M8: =ROUND((IF(Brand_Profile!$D$62=0,Lookup_Lists!$D$150,ROUND((IF(Brand_Profile!$D$57="",0,IF(ISNUMBER(SEARCH(Brand_Profile!$D$57,Matching_Engine!$BF$8)),1,0))+IF(Brand_Profile!$D$58="",0,IF(ISNUMBER(SEARCH(Brand_Profile!$D$58,Matching_Engine!$BF$8)),1,0))+IF(Brand_Profile!$D$59="",0,IF(ISNUMBER(SEARCH(Brand_Profile!$D$59,Matching_Engine!$BF$8)),1,0))+IF(Brand_Profile!$D$60="",0,IF(ISNUMBER(SEARCH(Brand_Profile!$D$60,Matching_Engine!$BF$8)),1,0))+IF(Brand_Profile!$D$61="",0,IF(ISNUMBER(SEARCH(Brand_Profile!$D$61,Matching_Engine!$BF$8)),1,0)))/Brand_Profile!$D$62*100,0))+IF(Brand_Profile!$D$74=0,Lookup_Lists!$D$150,ROUND((IF(Brand_Profile!$D$69="",0,IF(ISNUMBER(SEARCH(Brand_Profile!$D$69,Matching_Engine!$BF$8)),1,0))+IF(Brand_Profile!$D$70="",0,IF(ISNUMBER(SEARCH(Brand_Profile!$D$70,Matching_Engine!$BF$8)),1,0))+IF(Brand_Profile!$D$71="",0,IF(ISNUMBER(SEARCH(Brand_Profile!$D$71,Matching_Engine!$BF$8)),1,0))+IF(Brand_Profile!$D$72="",0,IF(ISNUMBER(SEARCH(Brand_Profile!$D$72,Matching_Engine!$BF$8)),1,0))+IF(Brand_Profile!$D$73="",0,IF(ISNUMBER(SEARCH(Brand_Profile!$D$73,Matching_Engine!$BF$8)),1,0)))/Brand_Profile!$D$74*100,0)))/2,0) | N8: =ROUND((Matching_Engine!$K$8*Lookup_Lists!$D$110+Matching_Engine!$L$8*Lookup_Lists!$D$111+Matching_Engine!$M$8*Lookup_Lists!$D$112)/(Lookup_Lists!$D$110+Lookup_Lists!$D$111+Lookup_Lists!$D$112),0) | O8: =IF(Brand_Profile!$D$16="",Lookup_Lists!$D$150,MIN(100,ROUND((IFERROR(INDEX(KOL_Database!$W$7:KOL_Database!$AA$7,1,MATCH(Brand_Profile!$D$16,Lookup_Lists!$F$6:$F$10,0)),0)+0.5*IFERROR(INDEX(KOL_Database!$W$7:KOL_Database!$AA$7,1,MATCH(Brand_Profile!$D$17,Lookup_Lists!$F$6:$F$10,0)),0))/Lookup_Lists!$D$142*100,0))) | P8: =IF(OR(Brand_Profile!$D$18="",Brand_Profile!$D$18="Any"),100,IF(Brand_Profile!$D$18="Female",MIN(100,ROUND(KOL_Database!$AB$7/Lookup_Lists!$D$143*100,0)),IF(Brand_Profile!$D$18="Male",MIN(100,ROUND(KOL_Database!$AC$7/Lookup_Lists!$D$143*100,0)),MAX(0,ROUND(100-ABS(KOL_Database!$AB$7-50)*2,0))))) | Q8: =ROUND((IF(Brand_Profile!$D$19="",100,IF(KOL_Database!$AD$7=Brand_Profile!$D$19,100,Lookup_Lists!$D$151))*Lookup_Lists!$D$118+IF(OR(Brand_Profile!$D$20="",Brand_Profile!$D$20="Nasional"),100,IF(KOL_Database!$AE$7="",Lookup_Lists!$D$150,IF(KOL_Database!$AE$7=Brand_Profile!$D$20,100,IF(KOL_Database!$AD$7=Brand_Profile!$D$19,40,Lookup_Lists!$D$151))))*Lookup_Lists!$D$119+IF(OR(Brand_Profile!$D$21="",Brand_Profile!$D$21="Nasional"),100,IF(KOL_Database!$AF$7="",Lookup_Lists!$D$150,IF(KOL_Database!$AF$7=Brand_Profile!$D$21,100,IF(KOL_Database!$AE$7=Brand_Profile!$D$20,60,Lookup_Lists!$D$151))))*Lookup_Lists!$D$120)/(Lookup_Lists!$D$118+Lookup_Lists!$D$119+Lookup_Lists!$D$120),0) | R8: =IF(Brand_Profile!$D$68=0,Lookup_Lists!$D$150,ROUND((IF(Brand_Profile!$D$63="",0,IF(ISNUMBER(SEARCH(Brand_Profile!$D$63,KOL_Database!$AG$7)),1,0))+IF(Brand_Profile!$D$64="",0,IF(ISNUMBER(SEARCH(Brand_Profile!$D$64,KOL_Database!$AG$7)),1,0))+IF(Brand_Profile!$D$65="",0,IF(ISNUMBER(SEARCH(Brand_Profile!$D$65,KOL_Database!$AG$7)),1,0))+IF(Brand_Profile!$D$66="",0,IF(ISNUMBER(SEARCH(Brand_Profile!$D$66,KOL_Database!$AG$7)),1,0))+IF(Brand_Profile!$D$67="",0,IF(ISNUMBER(SEARCH(Brand_Profile!$D$67,KOL_Database!$AG$7)),1,0)))/Brand_Profile!$D$68*100,0)) | S8: =ROUND((Matching_Engine!$O$8*Brand_Profile!$D$96+Matching_Engine!$P$8*Brand_Profile!$D$97+Matching_Engine!$Q$8*Brand_Profile!$D$98+Matching_Engine!$R$8*Brand_Profile!$D$99)/MAX(1,Brand_Profile!$D$96+Brand_Profile!$D$97+Brand_Profile!$D$98+Brand_Profile!$D$99),0) | T8: =IF(Brand_Profile!$D$33="",Lookup_Lists!$D$150,Matching_Engine!$BD$8) | U8: =IF(Brand_Profile!$D$34="",Lookup_Lists!$D$150,IF(Brand_Profile!$D$34=KOL_Database!$F$7,100,IF(Matching_Engine!$BE$8=KOL_Database!$E$7,75,IF(Matching_Engine!$BD$8>=80,Lookup_Lists!$D$150,IF(Matching_Engine!$BD$8>=60,35,Lookup_Lists!$D$151))))) | V8: =IF(Brand_Profile!$D$86=0,Lookup_Lists!$D$150,ROUND((IF(Brand_Profile!$D$81="",0,IF(ISNUMBER(SEARCH(Brand_Profile!$D$81,Matching_Engine!$BG$8)),1,0))+IF(Brand_Profile!$D$82="",0,IF(ISNUMBER(SEARCH(Brand_Profile!$D$82,Matching_Engine!$BG$8)),1,0))+IF(Brand_Profile!$D$83="",0,IF(ISNUMBER(SEARCH(Brand_Profile!$D$83,Matching_Engine!$BG$8)),1,0))+IF(Brand_Profile!$D$84="",0,IF(ISNUMBER(SEARCH(Brand_Profile!$D$84,Matching_Engine!$BG$8)),1,0))+IF(Brand_Profile!$D$85="",0,IF(ISNUMBER(SEARCH(Brand_Profile!$D$85,Matching_Engine!$BG$8)),1,0)))/Brand_Profile!$D$86*100,0)) | W8: =IF(Brand_Profile!$D$39="",Lookup_Lists!$D$150,IFERROR(INDEX(Lookup_Lists!$B$237:$K$246,MATCH(Brand_Profile!$D$39,Lookup_Lists!$A$237:$A$246,0),MATCH(KOL_Database!$AJ$7,Lookup_Lists!$B$236:$K$236,0)),45)) | X8: =ROUND((Matching_Engine!$T$8*Lookup_Lists!$D$121+Matching_Engine!$U$8*Lookup_Lists!$D$122+Matching_Engine!$V$8*Lookup_Lists!$D$123+Matching_Engine!$W$8*Lookup_Lists!$D$124)/(Lookup_Lists!$D$121+Lookup_Lists!$D$122+Lookup_Lists!$D$123+Lookup_Lists!$D$124),0) | Y8: =MIN(100,MAX(IFERROR(INDEX(Lookup_Lists!$B$202:$M$211,MATCH(Brand_Profile!$D$25,Lookup_Lists!$A$202:$A$211,0),MATCH(KOL_Database!$AK$7,Lookup_Lists!$B$201:$M$201,0)),40),IF(KOL_Database!$AK$7=Brand_Profile!$D$41,95,0))) | Z8: =IFERROR(INDEX(Lookup_Lists!$B$215:$K$222,MATCH(Brand_Profile!$D$27,Lookup_Lists!$A$215:$A$222,0),MATCH(KOL_Database!$AJ$7,Lookup_Lists!$B$214:$K$214,0)),45) | AA8: =ROUND((IF(Brand_Profile!$D$80=0,Lookup_Lists!$D$150,ROUND((IF(Brand_Profile!$D$75="",0,IF(ISNUMBER(SEARCH(Brand_Profile!$D$75,KOL_Database!$AL$7)),1,0))+IF(Brand_Profile!$D$76="",0,IF(ISNUMBER(SEARCH(Brand_Profile!$D$76,KOL_Database!$AL$7)),1,0))+IF(Brand_Profile!$D$77="",0,IF(ISNUMBER(SEARCH(Brand_Profile!$D$77,KOL_Database!$AL$7)),1,0))+IF(Brand_Profile!$D$78="",0,IF(ISNUMBER(SEARCH(Brand_Profile!$D$78,KOL_Database!$AL$7)),1,0))+IF(Brand_Profile!$D$79="",0,IF(ISNUMBER(SEARCH(Brand_Profile!$D$79,KOL_Database!$AL$7)),1,0)))/Brand_Profile!$D$80*100,0))+IF(Brand_Profile!$D$92=0,Lookup_Lists!$D$150,ROUND((IF(Brand_Profile!$D$87="",0,IF(ISNUMBER(SEARCH(Brand_Profile!$D$87,KOL_Database!$AL$7)),1,0))+IF(Brand_Profile!$D$88="",0,IF(ISNUMBER(SEARCH(Brand_Profile!$D$88,KOL_Database!$AL$7)),1,0))+IF(Brand_Profile!$D$89="",0,IF(ISNUMBER(SEARCH(Brand_Profile!$D$89,KOL_Database!$AL$7)),1,0))+IF(Brand_Profile!$D$90="",0,IF(ISNUMBER(SEARCH(Brand_Profile!$D$90,KOL_Database!$AL$7)),1,0))+IF(Brand_Profile!$D$91="",0,IF(ISNUMBER(SEARCH(Brand_Profile!$D$91,KOL_Database!$AL$7)),1,0)))/Brand_Profile!$D$92*100,0)))/2,0) | AB8: =IFERROR(INDEX(Lookup_Lists!$B$226:$K$233,MATCH(Brand_Profile!$D$30,Lookup_Lists!$A$226:$A$233,0),MATCH(KOL_Database!$AJ$7,Lookup_Lists!$B$225:$K$225,0)),45) | AC8: =ROUND((Matching_Engine!$Y$8*Lookup_Lists!$D$125+Matching_Engine!$Z$8*Lookup_Lists!$D$126+Matching_Engine!$AA$8*Lookup_Lists!$D$127+Matching_Engine!$AB$8*Lookup_Lists!$D$128)/(Lookup_Lists!$D$125+Lookup_Lists!$D$126+Lookup_Lists!$D$127+Lookup_Lists!$D$128),0) | AD8: =IF(KOL_Database!$K$7="",0,MIN(100,ROUND(KOL_Database!$K$7/Lookup_Lists!$D$141*100,0))) | AE8: =IF(KOL_Database!$R$7="",0,MIN(100,MAX(0,KOL_Database!$R$7))) | AF8: =IF(KOL_Database!$P$7="",0,MIN(100,MAX(0,KOL_Database!$P$7))) | AG8: =IF(KOL_Database!$Q$7="",0,MIN(100,MAX(0,KOL_Database!$Q$7))) | AH8: =IF(OR(KOL_Database!$J$7="",KOL_Database!$J$7=0,KOL_Database!$L$7=""),0,MIN(100,ROUND(KOL_Database!$L$7/KOL_Database!$J$7/Lookup_Lists!$D$144*100,0))) | AI8: =IF(KOL_Database!$N$7="",0,MIN(100,MAX(0,ROUND((KOL_Database!$N$7+2)/(Lookup_Lists!$D$145+2)*100,0)))) | AJ8: =ROUND((Matching_Engine!$AD$8*Lookup_Lists!$D$129+Matching_Engine!$AE$8*Lookup_Lists!$D$130+Matching_Engine!$AF$8*Lookup_Lists!$D$131+Matching_Engine!$AG$8*Lookup_Lists!$D$132+Matching_Engine!$AH$8*Lookup_Lists!$D$133+Matching_Engine!$AI$8*Lookup_Lists!$D$134)/(Lookup_Lists!$D$129+Lookup_Lists!$D$130+Lookup_Lists!$D$131+Lookup_Lists!$D$132+Lookup_Lists!$D$133+Lookup_Lists!$D$134),0) | AK8: =IF(KOL_Database!$AT$7="",0,MIN(100,MAX(0,KOL_Database!$AT$7))) | AL8: =IF(KOL_Database!$AU$7="",0,KOL_Database!$AU$7) | AM8: =IF(KOL_Database!$AV$7="","None",KOL_Database!$AV$7) | AN8: =IF(Matching_Engine!$AM$8="High",Lookup_Lists!$D$137,IF(Matching_Engine!$AM$8="Medium",Lookup_Lists!$D$138,IF(Matching_Engine!$AM$8="Low",Lookup_Lists!$D$139,Lookup_Lists!$D$140))) | AO8: =ROUND(MIN(100,MAX(0,(Matching_Engine!$AK$8*Lookup_Lists!$D$135+(100-Matching_Engine!$AL$8)*Lookup_Lists!$D$136)/(Lookup_Lists!$D$135+Lookup_Lists!$D$136)*Matching_Engine!$AN$8)),0) | AP8: =ROUND((Matching_Engine!$N$8*Lookup_Lists!$D$104+Matching_Engine!$S$8*Lookup_Lists!$D$105+Matching_Engine!$X$8*Lookup_Lists!$D$106+Matching_Engine!$AC$8*Lookup_Lists!$D$107+Matching_Engine!$AJ$8*Lookup_Lists!$D$108+Matching_Engine!$AO$8*Lookup_Lists!$D$109)/MAX(1,(Lookup_Lists!$D$104+Lookup_Lists!$D$105+Lookup_Lists!$D$106+Lookup_Lists!$D$107+Lookup_Lists!$D$108+Lookup_Lists!$D$109)),0) | AQ8: =IF(Matching_Engine!$AP$8>=Lookup_Lists!$D$152,"Excellent Match",IF(Matching_Engine!$AP$8>=Lookup_Lists!$D$153,"Strong Match",IF(Matching_Engine!$AP$8>=Lookup_Lists!$D$154,"Good Match",IF(Matching_Engine!$AP$8>=Lookup_Lists!$D$155,"Moderate Match","Low Match")))) | AR8: =KOL_Database!$BE$7 | AS8: =IF(Matching_Engine!$AR$8>=Lookup_Lists!$D$159,"High",IF(Matching_Engine!$AR$8>=Lookup_Lists!$D$160,"Medium","Limited Data")) | AT8: =ROUND((Matching_Engine!$N$8+Matching_Engine!$X$8+Matching_Engine!$AC$8)/3,0) | AU8: =ROUND(((100-Matching_Engine!$AL$8)*Lookup_Lists!$D$162+IF(KOL_Database!$BD$7="",Lookup_Lists!$D$150,KOL_Database!$BD$7)*Lookup_Lists!$D$163+Matching_Engine!$AI$8*Lookup_Lists!$D$164+Matching_Engine!$AD$8*Lookup_Lists!$D$165)/(Lookup_Lists!$D$162+Lookup_Lists!$D$163+Lookup_Lists!$D$164+Lookup_Lists!$D$165),0) | AV8: =IF(Matching_Engine!$AW$8="","PASS","EXCLUDED") | AW8: =IF(ISERROR(SEARCH(KOL_Database!$D$7,Brand_Profile!$D$32)),"Platform not in Preferred Platform",IF(AND(Brand_Profile!$D$36>0,KOL_Database!$J$7<Brand_Profile!$D$36),"Followers below Preferred Follower Range",IF(AND(Brand_Profile!$D$37>0,KOL_Database!$J$7>Brand_Profile!$D$37),"Followers above Preferred Follower Range",IF(AND(Brand_Profile!$D$38>0,IF(KOL_Database!$K$7="",0,KOL_Database!$K$7)<Brand_Profile!$D$38),"Engagement Rate below Minimum Engagement Rate",IF(ISERROR(SEARCH(KOL_Database!$G$7,Brand_Profile!$D$35)),"Tier not in Preferred Tier",IF(AND(Brand_Profile!$D$43>0,Matching_Engine!$AE$8<Brand_Profile!$D$43),"Audience Quality below Minimum Audience Quality",IF(AND(Brand_Profile!$D$44>0,Matching_Engine!$AK$8<Brand_Profile!$D$44),"Brand Safety below Minimum Brand Safety",IF(AND(Brand_Profile!$D$47="Yes",KOL_Database!$AD$7<>Brand_Profile!$D$19),"Audience Country does not match Target Country",IF(AND(Brand_Profile!$D$46="Yes",KOL_Database!$E$7<>Brand_Profile!$D$33),"Category is not the Preferred Category",IF(AND(Brand_Profile!$D$48>0,Matching_Engine!$AL$8>Brand_Profile!$D$48),"Competitor Saturation above Max Competitor Saturation",IF(AND(Brand_Profile!$D$50="Yes",KOL_Database!$AW$7="Yes"),"Already Selected",IF(AND(Brand_Profile!$D$51="Yes",KOL_Database!$AX$7="Yes"),"Already in Cart",IF(AND(Brand_Profile!$D$52="Yes",KOL_Database!$AY$7="Yes"),"Existing Partner",IF(AND(Brand_Profile!$D$53="Yes",KOL_Database!$AZ$7="Yes"),"Excluded Creator",IF(AND(Brand_Profile!$D$49>0,Matching_Engine!$AP$8<Brand_Profile!$D$49),"Brand Match below Minimum Brand Match",""))))))))))))))) | AX8: =IF(Matching_Engine!$AV$8="EXCLUDED","Excluded",IF(Matching_Engine!$AP$8>=Lookup_Lists!$D$156,"Highly Recommended",IF(Matching_Engine!$AP$8>=Lookup_Lists!$D$157,"Recommended",IF(Matching_Engine!$AP$8>=Lookup_Lists!$D$158,"Consider","Low Priority")))) | AY8: =IF(Matching_Engine!$AV$8="PASS",Matching_Engine!$AP$8,"") | AZ8: =Matching_Engine!$A$8&"|"&Matching_Engine!$C$8 | BA8: =IFERROR(INDEX(Lookup_Lists!$B$51:$B$92,MATCH(Brand_Profile!$D$12,Lookup_Lists!$A$51:$A$92,0)),"") | BB8: =IFERROR(INDEX(Lookup_Lists!$B$51:$B$92,MATCH(KOL_Database!$F$7,Lookup_Lists!$A$51:$A$92,0)),"") | BC8: =IFERROR(INDEX(Lookup_Lists!$B$185:$O$198,MATCH(Matching_Engine!$BA$8,Lookup_Lists!$A$185:$A$198,0),MATCH(KOL_Database!$E$7,Lookup_Lists!$B$184:$O$184,0)),Lookup_Lists!$D$151) | BD8: =IFERROR(INDEX(Lookup_Lists!$B$185:$O$198,MATCH(Brand_Profile!$D$33,Lookup_Lists!$A$185:$A$198,0),MATCH(KOL_Database!$E$7,Lookup_Lists!$B$184:$O$184,0)),Lookup_Lists!$D$151) | BE8: =IFERROR(INDEX(Lookup_Lists!$B$51:$B$92,MATCH(Brand_Profile!$D$34,Lookup_Lists!$A$51:$A$92,0)),"") | BF8: =KOL_Database!$AI$7&", "&KOL_Database!$AG$7&", "&KOL_Database!$F$7&", "&KOL_Database!$E$7 | BG8: =KOL_Database!$AI$7&", "&KOL_Database!$AG$7
A9: BRAND-A | B9: =Brand_Profile!$D$9 | C9: =KOL_Database!$A$8 | D9: =KOL_Database!$B$8 | E9: =KOL_Database!$C$8 | F9: =KOL_Database!$D$8 | G9: =KOL_Database!$E$8 | H9: =KOL_Database!$G$8 | I9: =KOL_Database!$J$8 | J9: =KOL_Database!$K$8 | K9: =IFERROR(INDEX(Lookup_Lists!$B$170:$O$181,MATCH(Brand_Profile!$D$10,Lookup_Lists!$A$170:$A$181,0),MATCH(KOL_Database!$E$8,Lookup_Lists!$B$169:$O$169,0)),Lookup_Lists!$D$151) | L9: =IF(KOL_Database!$F$8="",Matching_Engine!$BC$9,IF(Brand_Profile!$D$12=KOL_Database!$F$8,100,IF(Matching_Engine!$BA$9=KOL_Database!$E$8,80,IF(Matching_Engine!$BC$9>=80,60,IF(Matching_Engine!$BC$9>=60,40,Lookup_Lists!$D$151))))) | M9: =ROUND((IF(Brand_Profile!$D$62=0,Lookup_Lists!$D$150,ROUND((IF(Brand_Profile!$D$57="",0,IF(ISNUMBER(SEARCH(Brand_Profile!$D$57,Matching_Engine!$BF$9)),1,0))+IF(Brand_Profile!$D$58="",0,IF(ISNUMBER(SEARCH(Brand_Profile!$D$58,Matching_Engine!$BF$9)),1,0))+IF(Brand_Profile!$D$59="",0,IF(ISNUMBER(SEARCH(Brand_Profile!$D$59,Matching_Engine!$BF$9)),1,0))+IF(Brand_Profile!$D$60="",0,IF(ISNUMBER(SEARCH(Brand_Profile!$D$60,Matching_Engine!$BF$9)),1,0))+IF(Brand_Profile!$D$61="",0,IF(ISNUMBER(SEARCH(Brand_Profile!$D$61,Matching_Engine!$BF$9)),1,0)))/Brand_Profile!$D$62*100,0))+IF(Brand_Profile!$D$74=0,Lookup_Lists!$D$150,ROUND((IF(Brand_Profile!$D$69="",0,IF(ISNUMBER(SEARCH(Brand_Profile!$D$69,Matching_Engine!$BF$9)),1,0))+IF(Brand_Profile!$D$70="",0,IF(ISNUMBER(SEARCH(Brand_Profile!$D$70,Matching_Engine!$BF$9)),1,0))+IF(Brand_Profile!$D$71="",0,IF(ISNUMBER(SEARCH(Brand_Profile!$D$71,Matching_Engine!$BF$9)),1,0))+IF(Brand_Profile!$D$72="",0,IF(ISNUMBER(SEARCH(Brand_Profile!$D$72,Matching_Engine!$BF$9)),1,0))+IF(Brand_Profile!$D$73="",0,IF(ISNUMBER(SEARCH(Brand_Profile!$D$73,Matching_Engine!$BF$9)),1,0)))/Brand_Profile!$D$74*100,0)))/2,0) | N9: =ROUND((Matching_Engine!$K$9*Lookup_Lists!$D$110+Matching_Engine!$L$9*Lookup_Lists!$D$111+Matching_Engine!$M$9*Lookup_Lists!$D$112)/(Lookup_Lists!$D$110+Lookup_Lists!$D$111+Lookup_Lists!$D$112),0) | O9: =IF(Brand_Profile!$D$16="",Lookup_Lists!$D$150,MIN(100,ROUND((IFERROR(INDEX(KOL_Database!$W$8:KOL_Database!$AA$8,1,MATCH(Brand_Profile!$D$16,Lookup_Lists!$F$6:$F$10,0)),0)+0.5*IFERROR(INDEX(KOL_Database!$W$8:KOL_Database!$AA$8,1,MATCH(Brand_Profile!$D$17,Lookup_Lists!$F$6:$F$10,0)),0))/Lookup_Lists!$D$142*100,0))) | P9: =IF(OR(Brand_Profile!$D$18="",Brand_Profile!$D$18="Any"),100,IF(Brand_Profile!$D$18="Female",MIN(100,ROUND(KOL_Database!$AB$8/Lookup_Lists!$D$143*100,0)),IF(Brand_Profile!$D$18="Male",MIN(100,ROUND(KOL_Database!$AC$8/Lookup_Lists!$D$143*100,0)),MAX(0,ROUND(100-ABS(KOL_Database!$AB$8-50)*2,0))))) | Q9: =ROUND((IF(Brand_Profile!$D$19="",100,IF(KOL_Database!$AD$8=Brand_Profile!$D$19,100,Lookup_Lists!$D$151))*Lookup_Lists!$D$118+IF(OR(Brand_Profile!$D$20="",Brand_Profile!$D$20="Nasional"),100,IF(KOL_Database!$AE$8="",Lookup_Lists!$D$150,IF(KOL_Database!$AE$8=Brand_Profile!$D$20,100,IF(KOL_Database!$AD$8=Brand_Profile!$D$19,40,Lookup_Lists!$D$151))))*Lookup_Lists!$D$119+IF(OR(Brand_Profile!$D$21="",Brand_Profile!$D$21="Nasional"),100,IF(KOL_Database!$AF$8="",Lookup_Lists!$D$150,IF(KOL_Database!$AF$8=Brand_Profile!$D$21,100,IF(KOL_Database!$AE$8=Brand_Profile!$D$20,60,Lookup_Lists!$D$151))))*Lookup_Lists!$D$120)/(Lookup_Lists!$D$118+Lookup_Lists!$D$119+Lookup_Lists!$D$120),0) | R9: =IF(Brand_Profile!$D$68=0,Lookup_Lists!$D$150,ROUND((IF(Brand_Profile!$D$63="",0,IF(ISNUMBER(SEARCH(Brand_Profile!$D$63,KOL_Database!$AG$8)),1,0))+IF(Brand_Profile!$D$64="",0,IF(ISNUMBER(SEARCH(Brand_Profile!$D$64,KOL_Database!$AG$8)),1,0))+IF(Brand_Profile!$D$65="",0,IF(ISNUMBER(SEARCH(Brand_Profile!$D$65,KOL_Database!$AG$8)),1,0))+IF(Brand_Profile!$D$66="",0,IF(ISNUMBER(SEARCH(Brand_Profile!$D$66,KOL_Database!$AG$8)),1,0))+IF(Brand_Profile!$D$67="",0,IF(ISNUMBER(SEARCH(Brand_Profile!$D$67,KOL_Database!$AG$8)),1,0)))/Brand_Profile!$D$68*100,0)) | S9: =ROUND((Matching_Engine!$O$9*Brand_Profile!$D$96+Matching_Engine!$P$9*Brand_Profile!$D$97+Matching_Engine!$Q$9*Brand_Profile!$D$98+Matching_Engine!$R$9*Brand_Profile!$D$99)/MAX(1,Brand_Profile!$D$96+Brand_Profile!$D$97+Brand_Profile!$D$98+Brand_Profile!$D$99),0) | T9: =IF(Brand_Profile!$D$33="",Lookup_Lists!$D$150,Matching_Engine!$BD$9) | U9: =IF(Brand_Profile!$D$34="",Lookup_Lists!$D$150,IF(Brand_Profile!$D$34=KOL_Database!$F$8,100,IF(Matching_Engine!$BE$9=KOL_Database!$E$8,75,IF(Matching_Engine!$BD$9>=80,Lookup_Lists!$D$150,IF(Matching_Engine!$BD$9>=60,35,Lookup_Lists!$D$151))))) | V9: =IF(Brand_Profile!$D$86=0,Lookup_Lists!$D$150,ROUND((IF(Brand_Profile!$D$81="",0,IF(ISNUMBER(SEARCH(Brand_Profile!$D$81,Matching_Engine!$BG$9)),1,0))+IF(Brand_Profile!$D$82="",0,IF(ISNUMBER(SEARCH(Brand_Profile!$D$82,Matching_Engine!$BG$9)),1,0))+IF(Brand_Profile!$D$83="",0,IF(ISNUMBER(SEARCH(Brand_Profile!$D$83,Matching_Engine!$BG$9)),1,0))+IF(Brand_Profile!$D$84="",0,IF(ISNUMBER(SEARCH(Brand_Profile!$D$84,Matching_Engine!$BG$9)),1,0))+IF(Brand_Profile!$D$85="",0,IF(ISNUMBER(SEARCH(Brand_Profile!$D$85,Matching_Engine!$BG$9)),1,0)))/Brand_Profile!$D$86*100,0)) | W9: =IF(Brand_Profile!$D$39="",Lookup_Lists!$D$150,IFERROR(INDEX(Lookup_Lists!$B$237:$K$246,MATCH(Brand_Profile!$D$39,Lookup_Lists!$A$237:$A$246,0),MATCH(KOL_Database!$AJ$8,Lookup_Lists!$B$236:$K$236,0)),45)) | X9: =ROUND((Matching_Engine!$T$9*Lookup_Lists!$D$121+Matching_Engine!$U$9*Lookup_Lists!$D$122+Matching_Engine!$V$9*Lookup_Lists!$D$123+Matching_Engine!$W$9*Lookup_Lists!$D$124)/(Lookup_Lists!$D$121+Lookup_Lists!$D$122+Lookup_Lists!$D$123+Lookup_Lists!$D$124),0) | Y9: =MIN(100,MAX(IFERROR(INDEX(Lookup_Lists!$B$202:$M$211,MATCH(Brand_Profile!$D$25,Lookup_Lists!$A$202:$A$211,0),MATCH(KOL_Database!$AK$8,Lookup_Lists!$B$201:$M$201,0)),40),IF(KOL_Database!$AK$8=Brand_Profile!$D$41,95,0))) | Z9: =IFERROR(INDEX(Lookup_Lists!$B$215:$K$222,MATCH(Brand_Profile!$D$27,Lookup_Lists!$A$215:$A$222,0),MATCH(KOL_Database!$AJ$8,Lookup_Lists!$B$214:$K$214,0)),45) | AA9: =ROUND((IF(Brand_Profile!$D$80=0,Lookup_Lists!$D$150,ROUND((IF(Brand_Profile!$D$75="",0,IF(ISNUMBER(SEARCH(Brand_Profile!$D$75,KOL_Database!$AL$8)),1,0))+IF(Brand_Profile!$D$76="",0,IF(ISNUMBER(SEARCH(Brand_Profile!$D$76,KOL_Database!$AL$8)),1,0))+IF(Brand_Profile!$D$77="",0,IF(ISNUMBER(SEARCH(Brand_Profile!$D$77,KOL_Database!$AL$8)),1,0))+IF(Brand_Profile!$D$78="",0,IF(ISNUMBER(SEARCH(Brand_Profile!$D$78,KOL_Database!$AL$8)),1,0))+IF(Brand_Profile!$D$79="",0,IF(ISNUMBER(SEARCH(Brand_Profile!$D$79,KOL_Database!$AL$8)),1,0)))/Brand_Profile!$D$80*100,0))+IF(Brand_Profile!$D$92=0,Lookup_Lists!$D$150,ROUND((IF(Brand_Profile!$D$87="",0,IF(ISNUMBER(SEARCH(Brand_Profile!$D$87,KOL_Database!$AL$8)),1,0))+IF(Brand_Profile!$D$88="",0,IF(ISNUMBER(SEARCH(Brand_Profile!$D$88,KOL_Database!$AL$8)),1,0))+IF(Brand_Profile!$D$89="",0,IF(ISNUMBER(SEARCH(Brand_Profile!$D$89,KOL_Database!$AL$8)),1,0))+IF(Brand_Profile!$D$90="",0,IF(ISNUMBER(SEARCH(Brand_Profile!$D$90,KOL_Database!$AL$8)),1,0))+IF(Brand_Profile!$D$91="",0,IF(ISNUMBER(SEARCH(Brand_Profile!$D$91,KOL_Database!$AL$8)),1,0)))/Brand_Profile!$D$92*100,0)))/2,0) | AB9: =IFERROR(INDEX(Lookup_Lists!$B$226:$K$233,MATCH(Brand_Profile!$D$30,Lookup_Lists!$A$226:$A$233,0),MATCH(KOL_Database!$AJ$8,Lookup_Lists!$B$225:$K$225,0)),45) | AC9: =ROUND((Matching_Engine!$Y$9*Lookup_Lists!$D$125+Matching_Engine!$Z$9*Lookup_Lists!$D$126+Matching_Engine!$AA$9*Lookup_Lists!$D$127+Matching_Engine!$AB$9*Lookup_Lists!$D$128)/(Lookup_Lists!$D$125+Lookup_Lists!$D$126+Lookup_Lists!$D$127+Lookup_Lists!$D$128),0) | AD9: =IF(KOL_Database!$K$8="",0,MIN(100,ROUND(KOL_Database!$K$8/Lookup_Lists!$D$141*100,0))) | AE9: =IF(KOL_Database!$R$8="",0,MIN(100,MAX(0,KOL_Database!$R$8))) | AF9: =IF(KOL_Database!$P$8="",0,MIN(100,MAX(0,KOL_Database!$P$8))) | AG9: =IF(KOL_Database!$Q$8="",0,MIN(100,MAX(0,KOL_Database!$Q$8))) | AH9: =IF(OR(KOL_Database!$J$8="",KOL_Database!$J$8=0,KOL_Database!$L$8=""),0,MIN(100,ROUND(KOL_Database!$L$8/KOL_Database!$J$8/Lookup_Lists!$D$144*100,0))) | AI9: =IF(KOL_Database!$N$8="",0,MIN(100,MAX(0,ROUND((KOL_Database!$N$8+2)/(Lookup_Lists!$D$145+2)*100,0)))) | AJ9: =ROUND((Matching_Engine!$AD$9*Lookup_Lists!$D$129+Matching_Engine!$AE$9*Lookup_Lists!$D$130+Matching_Engine!$AF$9*Lookup_Lists!$D$131+Matching_Engine!$AG$9*Lookup_Lists!$D$132+Matching_Engine!$AH$9*Lookup_Lists!$D$133+Matching_Engine!$AI$9*Lookup_Lists!$D$134)/(Lookup_Lists!$D$129+Lookup_Lists!$D$130+Lookup_Lists!$D$131+Lookup_Lists!$D$132+Lookup_Lists!$D$133+Lookup_Lists!$D$134),0) | AK9: =IF(KOL_Database!$AT$8="",0,MIN(100,MAX(0,KOL_Database!$AT$8))) | AL9: =IF(KOL_Database!$AU$8="",0,KOL_Database!$AU$8) | AM9: =IF(KOL_Database!$AV$8="","None",KOL_Database!$AV$8) | AN9: =IF(Matching_Engine!$AM$9="High",Lookup_Lists!$D$137,IF(Matching_Engine!$AM$9="Medium",Lookup_Lists!$D$138,IF(Matching_Engine!$AM$9="Low",Lookup_Lists!$D$139,Lookup_Lists!$D$140))) | AO9: =ROUND(MIN(100,MAX(0,(Matching_Engine!$AK$9*Lookup_Lists!$D$135+(100-Matching_Engine!$AL$9)*Lookup_Lists!$D$136)/(Lookup_Lists!$D$135+Lookup_Lists!$D$136)*Matching_Engine!$AN$9)),0) | AP9: =ROUND((Matching_Engine!$N$9*Lookup_Lists!$D$104+Matching_Engine!$S$9*Lookup_Lists!$D$105+Matching_Engine!$X$9*Lookup_Lists!$D$106+Matching_Engine!$AC$9*Lookup_Lists!$D$107+Matching_Engine!$AJ$9*Lookup_Lists!$D$108+Matching_Engine!$AO$9*Lookup_Lists!$D$109)/MAX(1,(Lookup_Lists!$D$104+Lookup_Lists!$D$105+Lookup_Lists!$D$106+Lookup_Lists!$D$107+Lookup_Lists!$D$108+Lookup_Lists!$D$109)),0) | AQ9: =IF(Matching_Engine!$AP$9>=Lookup_Lists!$D$152,"Excellent Match",IF(Matching_Engine!$AP$9>=Lookup_Lists!$D$153,"Strong Match",IF(Matching_Engine!$AP$9>=Lookup_Lists!$D$154,"Good Match",IF(Matching_Engine!$AP$9>=Lookup_Lists!$D$155,"Moderate Match","Low Match")))) | AR9: =KOL_Database!$BE$8 | AS9: =IF(Matching_Engine!$AR$9>=Lookup_Lists!$D$159,"High",IF(Matching_Engine!$AR$9>=Lookup_Lists!$D$160,"Medium","Limited Data")) | AT9: =ROUND((Matching_Engine!$N$9+Matching_Engine!$X$9+Matching_Engine!$AC$9)/3,0) | AU9: =ROUND(((100-Matching_Engine!$AL$9)*Lookup_Lists!$D$162+IF(KOL_Database!$BD$8="",Lookup_Lists!$D$150,KOL_Database!$BD$8)*Lookup_Lists!$D$163+Matching_Engine!$AI$9*Lookup_Lists!$D$164+Matching_Engine!$AD$9*Lookup_Lists!$D$165)/(Lookup_Lists!$D$162+Lookup_Lists!$D$163+Lookup_Lists!$D$164+Lookup_Lists!$D$165),0) | AV9: =IF(Matching_Engine!$AW$9="","PASS","EXCLUDED") | AW9: =IF(ISERROR(SEARCH(KOL_Database!$D$8,Brand_Profile!$D$32)),"Platform not in Preferred Platform",IF(AND(Brand_Profile!$D$36>0,KOL_Database!$J$8<Brand_Profile!$D$36),"Followers below Preferred Follower Range",IF(AND(Brand_Profile!$D$37>0,KOL_Database!$J$8>Brand_Profile!$D$37),"Followers above Preferred Follower Range",IF(AND(Brand_Profile!$D$38>0,IF(KOL_Database!$K$8="",0,KOL_Database!$K$8)<Brand_Profile!$D$38),"Engagement Rate below Minimum Engagement Rate",IF(ISERROR(SEARCH(KOL_Database!$G$8,Brand_Profile!$D$35)),"Tier not in Preferred Tier",IF(AND(Brand_Profile!$D$43>0,Matching_Engine!$AE$9<Brand_Profile!$D$43),"Audience Quality below Minimum Audience Quality",IF(AND(Brand_Profile!$D$44>0,Matching_Engine!$AK$9<Brand_Profile!$D$44),"Brand Safety below Minimum Brand Safety",IF(AND(Brand_Profile!$D$47="Yes",KOL_Database!$AD$8<>Brand_Profile!$D$19),"Audience Country does not match Target Country",IF(AND(Brand_Profile!$D$46="Yes",KOL_Database!$E$8<>Brand_Profile!$D$33),"Category is not the Preferred Category",IF(AND(Brand_Profile!$D$48>0,Matching_Engine!$AL$9>Brand_Profile!$D$48),"Competitor Saturation above Max Competitor Saturation",IF(AND(Brand_Profile!$D$50="Yes",KOL_Database!$AW$8="Yes"),"Already Selected",IF(AND(Brand_Profile!$D$51="Yes",KOL_Database!$AX$8="Yes"),"Already in Cart",IF(AND(Brand_Profile!$D$52="Yes",KOL_Database!$AY$8="Yes"),"Existing Partner",IF(AND(Brand_Profile!$D$53="Yes",KOL_Database!$AZ$8="Yes"),"Excluded Creator",IF(AND(Brand_Profile!$D$49>0,Matching_Engine!$AP$9<Brand_Profile!$D$49),"Brand Match below Minimum Brand Match",""))))))))))))))) | AX9: =IF(Matching_Engine!$AV$9="EXCLUDED","Excluded",IF(Matching_Engine!$AP$9>=Lookup_Lists!$D$156,"Highly Recommended",IF(Matching_Engine!$AP$9>=Lookup_Lists!$D$157,"Recommended",IF(Matching_Engine!$AP$9>=Lookup_Lists!$D$158,"Consider","Low Priority")))) | AY9: =IF(Matching_Engine!$AV$9="PASS",Matching_Engine!$AP$9,"") | AZ9: =Matching_Engine!$A$9&"|"&Matching_Engine!$C$9 | BA9: =IFERROR(INDEX(Lookup_Lists!$B$51:$B$92,MATCH(Brand_Profile!$D$12,Lookup_Lists!$A$51:$A$92,0)),"") | BB9: =IFERROR(INDEX(Lookup_Lists!$B$51:$B$92,MATCH(KOL_Database!$F$8,Lookup_Lists!$A$51:$A$92,0)),"") | BC9: =IFERROR(INDEX(Lookup_Lists!$B$185:$O$198,MATCH(Matching_Engine!$BA$9,Lookup_Lists!$A$185:$A$198,0),MATCH(KOL_Database!$E$8,Lookup_Lists!$B$184:$O$184,0)),Lookup_Lists!$D$151) | BD9: =IFERROR(INDEX(Lookup_Lists!$B$185:$O$198,MATCH(Brand_Profile!$D$33,Lookup_Lists!$A$185:$A$198,0),MATCH(KOL_Database!$E$8,Lookup_Lists!$B$184:$O$184,0)),Lookup_Lists!$D$151) | BE9: =IFERROR(INDEX(Lookup_Lists!$B$51:$B$92,MATCH(Brand_Profile!$D$34,Lookup_Lists!$A$51:$A$92,0)),"") | BF9: =KOL_Database!$AI$8&", "&KOL_Database!$AG$8&", "&KOL_Database!$F$8&", "&KOL_Database!$E$8 | BG9: =KOL_Database!$AI$8&", "&KOL_Database!$AG$8
A10: BRAND-A | B10: =Brand_Profile!$D$9 | C10: =KOL_Database!$A$9 | D10: =KOL_Database!$B$9 | E10: =KOL_Database!$C$9 | F10: =KOL_Database!$D$9 | G10: =KOL_Database!$E$9 | H10: =KOL_Database!$G$9 | I10: =KOL_Database!$J$9 | J10: =KOL_Database!$K$9 | K10: =IFERROR(INDEX(Lookup_Lists!$B$170:$O$181,MATCH(Brand_Profile!$D$10,Lookup_Lists!$A$170:$A$181,0),MATCH(KOL_Database!$E$9,Lookup_Lists!$B$169:$O$169,0)),Lookup_Lists!$D$151) | L10: =IF(KOL_Database!$F$9="",Matching_Engine!$BC$10,IF(Brand_Profile!$D$12=KOL_Database!$F$9,100,IF(Matching_Engine!$BA$10=KOL_Database!$E$9,80,IF(Matching_Engine!$BC$10>=80,60,IF(Matching_Engine!$BC$10>=60,40,Lookup_Lists!$D$151))))) | M10: =ROUND((IF(Brand_Profile!$D$62=0,Lookup_Lists!$D$150,ROUND((IF(Brand_Profile!$D$57="",0,IF(ISNUMBER(SEARCH(Brand_Profile!$D$57,Matching_Engine!$BF$10)),1,0))+IF(Brand_Profile!$D$58="",0,IF(ISNUMBER(SEARCH(Brand_Profile!$D$58,Matching_Engine!$BF$10)),1,0))+IF(Brand_Profile!$D$59="",0,IF(ISNUMBER(SEARCH(Brand_Profile!$D$59,Matching_Engine!$BF$10)),1,0))+IF(Brand_Profile!$D$60="",0,IF(ISNUMBER(SEARCH(Brand_Profile!$D$60,Matching_Engine!$BF$10)),1,0))+IF(Brand_Profile!$D$61="",0,IF(ISNUMBER(SEARCH(Brand_Profile!$D$61,Matching_Engine!$BF$10)),1,0)))/Brand_Profile!$D$62*100,0))+IF(Brand_Profile!$D$74=0,Lookup_Lists!$D$150,ROUND((IF(Brand_Profile!$D$69="",0,IF(ISNUMBER(SEARCH(Brand_Profile!$D$69,Matching_Engine!$BF$10)),1,0))+IF(Brand_Profile!$D$70="",0,IF(ISNUMBER(SEARCH(Brand_Profile!$D$70,Matching_Engine!$BF$10)),1,0))+IF(Brand_Profile!$D$71="",0,IF(ISNUMBER(SEARCH(Brand_Profile!$D$71,Matching_Engine!$BF$10)),1,0))+IF(Brand_Profile!$D$72="",0,IF(ISNUMBER(SEARCH(Brand_Profile!$D$72,Matching_Engine!$BF$10)),1,0))+IF(Brand_Profile!$D$73="",0,IF(ISNUMBER(SEARCH(Brand_Profile!$D$73,Matching_Engine!$BF$10)),1,0)))/Brand_Profile!$D$74*100,0)))/2,0) | N10: =ROUND((Matching_Engine!$K$10*Lookup_Lists!$D$110+Matching_Engine!$L$10*Lookup_Lists!$D$111+Matching_Engine!$M$10*Lookup_Lists!$D$112)/(Lookup_Lists!$D$110+Lookup_Lists!$D$111+Lookup_Lists!$D$112),0) | O10: =IF(Brand_Profile!$D$16="",Lookup_Lists!$D$150,MIN(100,ROUND((IFERROR(INDEX(KOL_Database!$W$9:KOL_Database!$AA$9,1,MATCH(Brand_Profile!$D$16,Lookup_Lists!$F$6:$F$10,0)),0)+0.5*IFERROR(INDEX(KOL_Database!$W$9:KOL_Database!$AA$9,1,MATCH(Brand_Profile!$D$17,Lookup_Lists!$F$6:$F$10,0)),0))/Lookup_Lists!$D$142*100,0))) | P10: =IF(OR(Brand_Profile!$D$18="",Brand_Profile!$D$18="Any"),100,IF(Brand_Profile!$D$18="Female",MIN(100,ROUND(KOL_Database!$AB$9/Lookup_Lists!$D$143*100,0)),IF(Brand_Profile!$D$18="Male",MIN(100,ROUND(KOL_Database!$AC$9/Lookup_Lists!$D$143*100,0)),MAX(0,ROUND(100-ABS(KOL_Database!$AB$9-50)*2,0))))) | Q10: =ROUND((IF(Brand_Profile!$D$19="",100,IF(KOL_Database!$AD$9=Brand_Profile!$D$19,100,Lookup_Lists!$D$151))*Lookup_Lists!$D$118+IF(OR(Brand_Profile!$D$20="",Brand_Profile!$D$20="Nasional"),100,IF(KOL_Database!$AE$9="",Lookup_Lists!$D$150,IF(KOL_Database!$AE$9=Brand_Profile!$D$20,100,IF(KOL_Database!$AD$9=Brand_Profile!$D$19,40,Lookup_Lists!$D$151))))*Lookup_Lists!$D$119+IF(OR(Brand_Profile!$D$21="",Brand_Profile!$D$21="Nasional"),100,IF(KOL_Database!$AF$9="",Lookup_Lists!$D$150,IF(KOL_Database!$AF$9=Brand_Profile!$D$21,100,IF(KOL_Database!$AE$9=Brand_Profile!$D$20,60,Lookup_Lists!$D$151))))*Lookup_Lists!$D$120)/(Lookup_Lists!$D$118+Lookup_Lists!$D$119+Lookup_Lists!$D$120),0) | R10: =IF(Brand_Profile!$D$68=0,Lookup_Lists!$D$150,ROUND((IF(Brand_Profile!$D$63="",0,IF(ISNUMBER(SEARCH(Brand_Profile!$D$63,KOL_Database!$AG$9)),1,0))+IF(Brand_Profile!$D$64="",0,IF(ISNUMBER(SEARCH(Brand_Profile!$D$64,KOL_Database!$AG$9)),1,0))+IF(Brand_Profile!$D$65="",0,IF(ISNUMBER(SEARCH(Brand_Profile!$D$65,KOL_Database!$AG$9)),1,0))+IF(Brand_Profile!$D$66="",0,IF(ISNUMBER(SEARCH(Brand_Profile!$D$66,KOL_Database!$AG$9)),1,0))+IF(Brand_Profile!$D$67="",0,IF(ISNUMBER(SEARCH(Brand_Profile!$D$67,KOL_Database!$AG$9)),1,0)))/Brand_Profile!$D$68*100,0)) | S10: =ROUND((Matching_Engine!$O$10*Brand_Profile!$D$96+Matching_Engine!$P$10*Brand_Profile!$D$97+Matching_Engine!$Q$10*Brand_Profile!$D$98+Matching_Engine!$R$10*Brand_Profile!$D$99)/MAX(1,Brand_Profile!$D$96+Brand_Profile!$D$97+Brand_Profile!$D$98+Brand_Profile!$D$99),0) | T10: =IF(Brand_Profile!$D$33="",Lookup_Lists!$D$150,Matching_Engine!$BD$10) | U10: =IF(Brand_Profile!$D$34="",Lookup_Lists!$D$150,IF(Brand_Profile!$D$34=KOL_Database!$F$9,100,IF(Matching_Engine!$BE$10=KOL_Database!$E$9,75,IF(Matching_Engine!$BD$10>=80,Lookup_Lists!$D$150,IF(Matching_Engine!$BD$10>=60,35,Lookup_Lists!$D$151))))) | V10: =IF(Brand_Profile!$D$86=0,Lookup_Lists!$D$150,ROUND((IF(Brand_Profile!$D$81="",0,IF(ISNUMBER(SEARCH(Brand_Profile!$D$81,Matching_Engine!$BG$10)),1,0))+IF(Brand_Profile!$D$82="",0,IF(ISNUMBER(SEARCH(Brand_Profile!$D$82,Matching_Engine!$BG$10)),1,0))+IF(Brand_Profile!$D$83="",0,IF(ISNUMBER(SEARCH(Brand_Profile!$D$83,Matching_Engine!$BG$10)),1,0))+IF(Brand_Profile!$D$84="",0,IF(ISNUMBER(SEARCH(Brand_Profile!$D$84,Matching_Engine!$BG$10)),1,0))+IF(Brand_Profile!$D$85="",0,IF(ISNUMBER(SEARCH(Brand_Profile!$D$85,Matching_Engine!$BG$10)),1,0)))/Brand_Profile!$D$86*100,0)) | W10: =IF(Brand_Profile!$D$39="",Lookup_Lists!$D$150,IFERROR(INDEX(Lookup_Lists!$B$237:$K$246,MATCH(Brand_Profile!$D$39,Lookup_Lists!$A$237:$A$246,0),MATCH(KOL_Database!$AJ$9,Lookup_Lists!$B$236:$K$236,0)),45)) | X10: =ROUND((Matching_Engine!$T$10*Lookup_Lists!$D$121+Matching_Engine!$U$10*Lookup_Lists!$D$122+Matching_Engine!$V$10*Lookup_Lists!$D$123+Matching_Engine!$W$10*Lookup_Lists!$D$124)/(Lookup_Lists!$D$121+Lookup_Lists!$D$122+Lookup_Lists!$D$123+Lookup_Lists!$D$124),0) | Y10: =MIN(100,MAX(IFERROR(INDEX(Lookup_Lists!$B$202:$M$211,MATCH(Brand_Profile!$D$25,Lookup_Lists!$A$202:$A$211,0),MATCH(KOL_Database!$AK$9,Lookup_Lists!$B$201:$M$201,0)),40),IF(KOL_Database!$AK$9=Brand_Profile!$D$41,95,0))) | Z10: =IFERROR(INDEX(Lookup_Lists!$B$215:$K$222,MATCH(Brand_Profile!$D$27,Lookup_Lists!$A$215:$A$222,0),MATCH(KOL_Database!$AJ$9,Lookup_Lists!$B$214:$K$214,0)),45) | AA10: =ROUND((IF(Brand_Profile!$D$80=0,Lookup_Lists!$D$150,ROUND((IF(Brand_Profile!$D$75="",0,IF(ISNUMBER(SEARCH(Brand_Profile!$D$75,KOL_Database!$AL$9)),1,0))+IF(Brand_Profile!$D$76="",0,IF(ISNUMBER(SEARCH(Brand_Profile!$D$76,KOL_Database!$AL$9)),1,0))+IF(Brand_Profile!$D$77="",0,IF(ISNUMBER(SEARCH(Brand_Profile!$D$77,KOL_Database!$AL$9)),1,0))+IF(Brand_Profile!$D$78="",0,IF(ISNUMBER(SEARCH(Brand_Profile!$D$78,KOL_Database!$AL$9)),1,0))+IF(Brand_Profile!$D$79="",0,IF(ISNUMBER(SEARCH(Brand_Profile!$D$79,KOL_Database!$AL$9)),1,0)))/Brand_Profile!$D$80*100,0))+IF(Brand_Profile!$D$92=0,Lookup_Lists!$D$150,ROUND((IF(Brand_Profile!$D$87="",0,IF(ISNUMBER(SEARCH(Brand_Profile!$D$87,KOL_Database!$AL$9)),1,0))+IF(Brand_Profile!$D$88="",0,IF(ISNUMBER(SEARCH(Brand_Profile!$D$88,KOL_Database!$AL$9)),1,0))+IF(Brand_Profile!$D$89="",0,IF(ISNUMBER(SEARCH(Brand_Profile!$D$89,KOL_Database!$AL$9)),1,0))+IF(Brand_Profile!$D$90="",0,IF(ISNUMBER(SEARCH(Brand_Profile!$D$90,KOL_Database!$AL$9)),1,0))+IF(Brand_Profile!$D$91="",0,IF(ISNUMBER(SEARCH(Brand_Profile!$D$91,KOL_Database!$AL$9)),1,0)))/Brand_Profile!$D$92*100,0)))/2,0) | AB10: =IFERROR(INDEX(Lookup_Lists!$B$226:$K$233,MATCH(Brand_Profile!$D$30,Lookup_Lists!$A$226:$A$233,0),MATCH(KOL_Database!$AJ$9,Lookup_Lists!$B$225:$K$225,0)),45) | AC10: =ROUND((Matching_Engine!$Y$10*Lookup_Lists!$D$125+Matching_Engine!$Z$10*Lookup_Lists!$D$126+Matching_Engine!$AA$10*Lookup_Lists!$D$127+Matching_Engine!$AB$10*Lookup_Lists!$D$128)/(Lookup_Lists!$D$125+Lookup_Lists!$D$126+Lookup_Lists!$D$127+Lookup_Lists!$D$128),0) | AD10: =IF(KOL_Database!$K$9="",0,MIN(100,ROUND(KOL_Database!$K$9/Lookup_Lists!$D$141*100,0))) | AE10: =IF(KOL_Database!$R$9="",0,MIN(100,MAX(0,KOL_Database!$R$9))) | AF10: =IF(KOL_Database!$P$9="",0,MIN(100,MAX(0,KOL_Database!$P$9))) | AG10: =IF(KOL_Database!$Q$9="",0,MIN(100,MAX(0,KOL_Database!$Q$9))) | AH10: =IF(OR(KOL_Database!$J$9="",KOL_Database!$J$9=0,KOL_Database!$L$9=""),0,MIN(100,ROUND(KOL_Database!$L$9/KOL_Database!$J$9/Lookup_Lists!$D$144*100,0))) | AI10: =IF(KOL_Database!$N$9="",0,MIN(100,MAX(0,ROUND((KOL_Database!$N$9+2)/(Lookup_Lists!$D$145+2)*100,0)))) | AJ10: =ROUND((Matching_Engine!$AD$10*Lookup_Lists!$D$129+Matching_Engine!$AE$10*Lookup_Lists!$D$130+Matching_Engine!$AF$10*Lookup_Lists!$D$131+Matching_Engine!$AG$10*Lookup_Lists!$D$132+Matching_Engine!$AH$10*Lookup_Lists!$D$133+Matching_Engine!$AI$10*Lookup_Lists!$D$134)/(Lookup_Lists!$D$129+Lookup_Lists!$D$130+Lookup_Lists!$D$131+Lookup_Lists!$D$132+Lookup_Lists!$D$133+Lookup_Lists!$D$134),0) | AK10: =IF(KOL_Database!$AT$9="",0,MIN(100,MAX(0,KOL_Database!$AT$9))) | AL10: =IF(KOL_Database!$AU$9="",0,KOL_Database!$AU$9) | AM10: =IF(KOL_Database!$AV$9="","None",KOL_Database!$AV$9) | AN10: =IF(Matching_Engine!$AM$10="High",Lookup_Lists!$D$137,IF(Matching_Engine!$AM$10="Medium",Lookup_Lists!$D$138,IF(Matching_Engine!$AM$10="Low",Lookup_Lists!$D$139,Lookup_Lists!$D$140))) | AO10: =ROUND(MIN(100,MAX(0,(Matching_Engine!$AK$10*Lookup_Lists!$D$135+(100-Matching_Engine!$AL$10)*Lookup_Lists!$D$136)/(Lookup_Lists!$D$135+Lookup_Lists!$D$136)*Matching_Engine!$AN$10)),0) | AP10: =ROUND((Matching_Engine!$N$10*Lookup_Lists!$D$104+Matching_Engine!$S$10*Lookup_Lists!$D$105+Matching_Engine!$X$10*Lookup_Lists!$D$106+Matching_Engine!$AC$10*Lookup_Lists!$D$107+Matching_Engine!$AJ$10*Lookup_Lists!$D$108+Matching_Engine!$AO$10*Lookup_Lists!$D$109)/MAX(1,(Lookup_Lists!$D$104+Lookup_Lists!$D$105+Lookup_Lists!$D$106+Lookup_Lists!$D$107+Lookup_Lists!$D$108+Lookup_Lists!$D$109)),0) | AQ10: =IF(Matching_Engine!$AP$10>=Lookup_Lists!$D$152,"Excellent Match",IF(Matching_Engine!$AP$10>=Lookup_Lists!$D$153,"Strong Match",IF(Matching_Engine!$AP$10>=Lookup_Lists!$D$154,"Good Match",IF(Matching_Engine!$AP$10>=Lookup_Lists!$D$155,"Moderate Match","Low Match")))) | AR10: =KOL_Database!$BE$9 | AS10: =IF(Matching_Engine!$AR$10>=Lookup_Lists!$D$159,"High",IF(Matching_Engine!$AR$10>=Lookup_Lists!$D$160,"Medium","Limited Data")) | AT10: =ROUND((Matching_Engine!$N$10+Matching_Engine!$X$10+Matching_Engine!$AC$10)/3,0) | AU10: =ROUND(((100-Matching_Engine!$AL$10)*Lookup_Lists!$D$162+IF(KOL_Database!$BD$9="",Lookup_Lists!$D$150,KOL_Database!$BD$9)*Lookup_Lists!$D$163+Matching_Engine!$AI$10*Lookup_Lists!$D$164+Matching_Engine!$AD$10*Lookup_Lists!$D$165)/(Lookup_Lists!$D$162+Lookup_Lists!$D$163+Lookup_Lists!$D$164+Lookup_Lists!$D$165),0) | AV10: =IF(Matching_Engine!$AW$10="","PASS","EXCLUDED") | AW10: =IF(ISERROR(SEARCH(KOL_Database!$D$9,Brand_Profile!$D$32)),"Platform not in Preferred Platform",IF(AND(Brand_Profile!$D$36>0,KOL_Database!$J$9<Brand_Profile!$D$36),"Followers below Preferred Follower Range",IF(AND(Brand_Profile!$D$37>0,KOL_Database!$J$9>Brand_Profile!$D$37),"Followers above Preferred Follower Range",IF(AND(Brand_Profile!$D$38>0,IF(KOL_Database!$K$9="",0,KOL_Database!$K$9)<Brand_Profile!$D$38),"Engagement Rate below Minimum Engagement Rate",IF(ISERROR(SEARCH(KOL_Database!$G$9,Brand_Profile!$D$35)),"Tier not in Preferred Tier",IF(AND(Brand_Profile!$D$43>0,Matching_Engine!$AE$10<Brand_Profile!$D$43),"Audience Quality below Minimum Audience Quality",IF(AND(Brand_Profile!$D$44>0,Matching_Engine!$AK$10<Brand_Profile!$D$44),"Brand Safety below Minimum Brand Safety",IF(AND(Brand_Profile!$D$47="Yes",KOL_Database!$AD$9<>Brand_Profile!$D$19),"Audience Country does not match Target Country",IF(AND(Brand_Profile!$D$46="Yes",KOL_Database!$E$9<>Brand_Profile!$D$33),"Category is not the Preferred Category",IF(AND(Brand_Profile!$D$48>0,Matching_Engine!$AL$10>Brand_Profile!$D$48),"Competitor Saturation above Max Competitor Saturation",IF(AND(Brand_Profile!$D$50="Yes",KOL_Database!$AW$9="Yes"),"Already Selected",IF(AND(Brand_Profile!$D$51="Yes",KOL_Database!$AX$9="Yes"),"Already in Cart",IF(AND(Brand_Profile!$D$52="Yes",KOL_Database!$AY$9="Yes"),"Existing Partner",IF(AND(Brand_Profile!$D$53="Yes",KOL_Database!$AZ$9="Yes"),"Excluded Creator",IF(AND(Brand_Profile!$D$49>0,Matching_Engine!$AP$10<Brand_Profile!$D$49),"Brand Match below Minimum Brand Match",""))))))))))))))) | AX10: =IF(Matching_Engine!$AV$10="EXCLUDED","Excluded",IF(Matching_Engine!$AP$10>=Lookup_Lists!$D$156,"Highly Recommended",IF(Matching_Engine!$AP$10>=Lookup_Lists!$D$157,"Recommended",IF(Matching_Engine!$AP$10>=Lookup_Lists!$D$158,"Consider","Low Priority")))) | AY10: =IF(Matching_Engine!$AV$10="PASS",Matching_Engine!$AP$10,"") | AZ10: =Matching_Engine!$A$10&"|"&Matching_Engine!$C$10 | BA10: =IFERROR(INDEX(Lookup_Lists!$B$51:$B$92,MATCH(Brand_Profile!$D$12,Lookup_Lists!$A$51:$A$92,0)),"") | BB10: =IFERROR(INDEX(Lookup_Lists!$B$51:$B$92,MATCH(KOL_Database!$F$9,Lookup_Lists!$A$51:$A$92,0)),"") | BC10: =IFERROR(INDEX(Lookup_Lists!$B$185:$O$198,MATCH(Matching_Engine!$BA$10,Lookup_Lists!$A$185:$A$198,0),MATCH(KOL_Database!$E$9,Lookup_Lists!$B$184:$O$184,0)),Lookup_Lists!$D$151) | BD10: =IFERROR(INDEX(Lookup_Lists!$B$185:$O$198,MATCH(Brand_Profile!$D$33,Lookup_Lists!$A$185:$A$198,0),MATCH(KOL_Database!$E$9,Lookup_Lists!$B$184:$O$184,0)),Lookup_Lists!$D$151) | BE10: =IFERROR(INDEX(Lookup_Lists!$B$51:$B$92,MATCH(Brand_Profile!$D$34,Lookup_Lists!$A$51:$A$92,0)),"") | BF10: =KOL_Database!$AI$9&", "&KOL_Database!$AG$9&", "&KOL_Database!$F$9&", "&KOL_Database!$E$9 | BG10: =KOL_Database!$AI$9&", "&KOL_Database!$AG$9
A11: BRAND-A | B11: =Brand_Profile!$D$9 | C11: =KOL_Database!$A$10 | D11: =KOL_Database!$B$10 | E11: =KOL_Database!$C$10 | F11: =KOL_Database!$D$10 | G11: =KOL_Database!$E$10 | H11: =KOL_Database!$G$10 | I11: =KOL_Database!$J$10 | J11: =KOL_Database!$K$10 | K11: =IFERROR(INDEX(Lookup_Lists!$B$170:$O$181,MATCH(Brand_Profile!$D$10,Lookup_Lists!$A$170:$A$181,0),MATCH(KOL_Database!$E$10,Lookup_Lists!$B$169:$O$169,0)),Lookup_Lists!$D$151) | L11: =IF(KOL_Database!$F$10="",Matching_Engine!$BC$11,IF(Brand_Profile!$D$12=KOL_Database!$F$10,100,IF(Matching_Engine!$BA$11=KOL_Database!$E$10,80,IF(Matching_Engine!$BC$11>=80,60,IF(Matching_Engine!$BC$11>=60,40,Lookup_Lists!$D$151))))) | M11: =ROUND((IF(Brand_Profile!$D$62=0,Lookup_Lists!$D$150,ROUND((IF(Brand_Profile!$D$57="",0,IF(ISNUMBER(SEARCH(Brand_Profile!$D$57,Matching_Engine!$BF$11)),1,0))+IF(Brand_Profile!$D$58="",0,IF(ISNUMBER(SEARCH(Brand_Profile!$D$58,Matching_Engine!$BF$11)),1,0))+IF(Brand_Profile!$D$59="",0,IF(ISNUMBER(SEARCH(Brand_Profile!$D$59,Matching_Engine!$BF$11)),1,0))+IF(Brand_Profile!$D$60="",0,IF(ISNUMBER(SEARCH(Brand_Profile!$D$60,Matching_Engine!$BF$11)),1,0))+IF(Brand_Profile!$D$61="",0,IF(ISNUMBER(SEARCH(Brand_Profile!$D$61,Matching_Engine!$BF$11)),1,0)))/Brand_Profile!$D$62*100,0))+IF(Brand_Profile!$D$74=0,Lookup_Lists!$D$150,ROUND((IF(Brand_Profile!$D$69="",0,IF(ISNUMBER(SEARCH(Brand_Profile!$D$69,Matching_Engine!$BF$11)),1,0))+IF(Brand_Profile!$D$70="",0,IF(ISNUMBER(SEARCH(Brand_Profile!$D$70,Matching_Engine!$BF$11)),1,0))+IF(Brand_Profile!$D$71="",0,IF(ISNUMBER(SEARCH(Brand_Profile!$D$71,Matching_Engine!$BF$11)),1,0))+IF(Brand_Profile!$D$72="",0,IF(ISNUMBER(SEARCH(Brand_Profile!$D$72,Matching_Engine!$BF$11)),1,0))+IF(Brand_Profile!$D$73="",0,IF(ISNUMBER(SEARCH(Brand_Profile!$D$73,Matching_Engine!$BF$11)),1,0)))/Brand_Profile!$D$74*100,0)))/2,0) | N11: =ROUND((Matching_Engine!$K$11*Lookup_Lists!$D$110+Matching_Engine!$L$11*Lookup_Lists!$D$111+Matching_Engine!$M$11*Lookup_Lists!$D$112)/(Lookup_Lists!$D$110+Lookup_Lists!$D$111+Lookup_Lists!$D$112),0) | O11: =IF(Brand_Profile!$D$16="",Lookup_Lists!$D$150,MIN(100,ROUND((IFERROR(INDEX(KOL_Database!$W$10:KOL_Database!$AA$10,1,MATCH(Brand_Profile!$D$16,Lookup_Lists!$F$6:$F$10,0)),0)+0.5*IFERROR(INDEX(KOL_Database!$W$10:KOL_Database!$AA$10,1,MATCH(Brand_Profile!$D$17,Lookup_Lists!$F$6:$F$10,0)),0))/Lookup_Lists!$D$142*100,0))) | P11: =IF(OR(Brand_Profile!$D$18="",Brand_Profile!$D$18="Any"),100,IF(Brand_Profile!$D$18="Female",MIN(100,ROUND(KOL_Database!$AB$10/Lookup_Lists!$D$143*100,0)),IF(Brand_Profile!$D$18="Male",MIN(100,ROUND(KOL_Database!$AC$10/Lookup_Lists!$D$143*100,0)),MAX(0,ROUND(100-ABS(KOL_Database!$AB$10-50)*2,0))))) | Q11: =ROUND((IF(Brand_Profile!$D$19="",100,IF(KOL_Database!$AD$10=Brand_Profile!$D$19,100,Lookup_Lists!$D$151))*Lookup_Lists!$D$118+IF(OR(Brand_Profile!$D$20="",Brand_Profile!$D$20="Nasional"),100,IF(KOL_Database!$AE$10="",Lookup_Lists!$D$150,IF(KOL_Database!$AE$10=Brand_Profile!$D$20,100,IF(KOL_Database!$AD$10=Brand_Profile!$D$19,40,Lookup_Lists!$D$151))))*Lookup_Lists!$D$119+IF(OR(Brand_Profile!$D$21="",Brand_Profile!$D$21="Nasional"),100,IF(KOL_Database!$AF$10="",Lookup_Lists!$D$150,IF(KOL_Database!$AF$10=Brand_Profile!$D$21,100,IF(KOL_Database!$AE$10=Brand_Profile!$D$20,60,Lookup_Lists!$D$151))))*Lookup_Lists!$D$120)/(Lookup_Lists!$D$118+Lookup_Lists!$D$119+Lookup_Lists!$D$120),0) | R11: =IF(Brand_Profile!$D$68=0,Lookup_Lists!$D$150,ROUND((IF(Brand_Profile!$D$63="",0,IF(ISNUMBER(SEARCH(Brand_Profile!$D$63,KOL_Database!$AG$10)),1,0))+IF(Brand_Profile!$D$64="",0,IF(ISNUMBER(SEARCH(Brand_Profile!$D$64,KOL_Database!$AG$10)),1,0))+IF(Brand_Profile!$D$65="",0,IF(ISNUMBER(SEARCH(Brand_Profile!$D$65,KOL_Database!$AG$10)),1,0))+IF(Brand_Profile!$D$66="",0,IF(ISNUMBER(SEARCH(Brand_Profile!$D$66,KOL_Database!$AG$10)),1,0))+IF(Brand_Profile!$D$67="",0,IF(ISNUMBER(SEARCH(Brand_Profile!$D$67,KOL_Database!$AG$10)),1,0)))/Brand_Profile!$D$68*100,0)) | S11: =ROUND((Matching_Engine!$O$11*Brand_Profile!$D$96+Matching_Engine!$P$11*Brand_Profile!$D$97+Matching_Engine!$Q$11*Brand_Profile!$D$98+Matching_Engine!$R$11*Brand_Profile!$D$99)/MAX(1,Brand_Profile!$D$96+Brand_Profile!$D$97+Brand_Profile!$D$98+Brand_Profile!$D$99),0) | T11: =IF(Brand_Profile!$D$33="",Lookup_Lists!$D$150,Matching_Engine!$BD$11) | U11: =IF(Brand_Profile!$D$34="",Lookup_Lists!$D$150,IF(Brand_Profile!$D$34=KOL_Database!$F$10,100,IF(Matching_Engine!$BE$11=KOL_Database!$E$10,75,IF(Matching_Engine!$BD$11>=80,Lookup_Lists!$D$150,IF(Matching_Engine!$BD$11>=60,35,Lookup_Lists!$D$151))))) | V11: =IF(Brand_Profile!$D$86=0,Lookup_Lists!$D$150,ROUND((IF(Brand_Profile!$D$81="",0,IF(ISNUMBER(SEARCH(Brand_Profile!$D$81,Matching_Engine!$BG$11)),1,0))+IF(Brand_Profile!$D$82="",0,IF(ISNUMBER(SEARCH(Brand_Profile!$D$82,Matching_Engine!$BG$11)),1,0))+IF(Brand_Profile!$D$83="",0,IF(ISNUMBER(SEARCH(Brand_Profile!$D$83,Matching_Engine!$BG$11)),1,0))+IF(Brand_Profile!$D$84="",0,IF(ISNUMBER(SEARCH(Brand_Profile!$D$84,Matching_Engine!$BG$11)),1,0))+IF(Brand_Profile!$D$85="",0,IF(ISNUMBER(SEARCH(Brand_Profile!$D$85,Matching_Engine!$BG$11)),1,0)))/Brand_Profile!$D$86*100,0)) | W11: =IF(Brand_Profile!$D$39="",Lookup_Lists!$D$150,IFERROR(INDEX(Lookup_Lists!$B$237:$K$246,MATCH(Brand_Profile!$D$39,Lookup_Lists!$A$237:$A$246,0),MATCH(KOL_Database!$AJ$10,Lookup_Lists!$B$236:$K$236,0)),45)) | X11: =ROUND((Matching_Engine!$T$11*Lookup_Lists!$D$121+Matching_Engine!$U$11*Lookup_Lists!$D$122+Matching_Engine!$V$11*Lookup_Lists!$D$123+Matching_Engine!$W$11*Lookup_Lists!$D$124)/(Lookup_Lists!$D$121+Lookup_Lists!$D$122+Lookup_Lists!$D$123+Lookup_Lists!$D$124),0) | Y11: =MIN(100,MAX(IFERROR(INDEX(Lookup_Lists!$B$202:$M$211,MATCH(Brand_Profile!$D$25,Lookup_Lists!$A$202:$A$211,0),MATCH(KOL_Database!$AK$10,Lookup_Lists!$B$201:$M$201,0)),40),IF(KOL_Database!$AK$10=Brand_Profile!$D$41,95,0))) | Z11: =IFERROR(INDEX(Lookup_Lists!$B$215:$K$222,MATCH(Brand_Profile!$D$27,Lookup_Lists!$A$215:$A$222,0),MATCH(KOL_Database!$AJ$10,Lookup_Lists!$B$214:$K$214,0)),45) | AA11: =ROUND((IF(Brand_Profile!$D$80=0,Lookup_Lists!$D$150,ROUND((IF(Brand_Profile!$D$75="",0,IF(ISNUMBER(SEARCH(Brand_Profile!$D$75,KOL_Database!$AL$10)),1,0))+IF(Brand_Profile!$D$76="",0,IF(ISNUMBER(SEARCH(Brand_Profile!$D$76,KOL_Database!$AL$10)),1,0))+IF(Brand_Profile!$D$77="",0,IF(ISNUMBER(SEARCH(Brand_Profile!$D$77,KOL_Database!$AL$10)),1,0))+IF(Brand_Profile!$D$78="",0,IF(ISNUMBER(SEARCH(Brand_Profile!$D$78,KOL_Database!$AL$10)),1,0))+IF(Brand_Profile!$D$79="",0,IF(ISNUMBER(SEARCH(Brand_Profile!$D$79,KOL_Database!$AL$10)),1,0)))/Brand_Profile!$D$80*100,0))+IF(Brand_Profile!$D$92=0,Lookup_Lists!$D$150,ROUND((IF(Brand_Profile!$D$87="",0,IF(ISNUMBER(SEARCH(Brand_Profile!$D$87,KOL_Database!$AL$10)),1,0))+IF(Brand_Profile!$D$88="",0,IF(ISNUMBER(SEARCH(Brand_Profile!$D$88,KOL_Database!$AL$10)),1,0))+IF(Brand_Profile!$D$89="",0,IF(ISNUMBER(SEARCH(Brand_Profile!$D$89,KOL_Database!$AL$10)),1,0))+IF(Brand_Profile!$D$90="",0,IF(ISNUMBER(SEARCH(Brand_Profile!$D$90,KOL_Database!$AL$10)),1,0))+IF(Brand_Profile!$D$91="",0,IF(ISNUMBER(SEARCH(Brand_Profile!$D$91,KOL_Database!$AL$10)),1,0)))/Brand_Profile!$D$92*100,0)))/2,0) | AB11: =IFERROR(INDEX(Lookup_Lists!$B$226:$K$233,MATCH(Brand_Profile!$D$30,Lookup_Lists!$A$226:$A$233,0),MATCH(KOL_Database!$AJ$10,Lookup_Lists!$B$225:$K$225,0)),45) | AC11: =ROUND((Matching_Engine!$Y$11*Lookup_Lists!$D$125+Matching_Engine!$Z$11*Lookup_Lists!$D$126+Matching_Engine!$AA$11*Lookup_Lists!$D$127+Matching_Engine!$AB$11*Lookup_Lists!$D$128)/(Lookup_Lists!$D$125+Lookup_Lists!$D$126+Lookup_Lists!$D$127+Lookup_Lists!$D$128),0) | AD11: =IF(KOL_Database!$K$10="",0,MIN(100,ROUND(KOL_Database!$K$10/Lookup_Lists!$D$141*100,0))) | AE11: =IF(KOL_Database!$R$10="",0,MIN(100,MAX(0,KOL_Database!$R$10))) | AF11: =IF(KOL_Database!$P$10="",0,MIN(100,MAX(0,KOL_Database!$P$10))) | AG11: =IF(KOL_Database!$Q$10="",0,MIN(100,MAX(0,KOL_Database!$Q$10))) | AH11: =IF(OR(KOL_Database!$J$10="",KOL_Database!$J$10=0,KOL_Database!$L$10=""),0,MIN(100,ROUND(KOL_Database!$L$10/KOL_Database!$J$10/Lookup_Lists!$D$144*100,0))) | AI11: =IF(KOL_Database!$N$10="",0,MIN(100,MAX(0,ROUND((KOL_Database!$N$10+2)/(Lookup_Lists!$D$145+2)*100,0)))) | AJ11: =ROUND((Matching_Engine!$AD$11*Lookup_Lists!$D$129+Matching_Engine!$AE$11*Lookup_Lists!$D$130+Matching_Engine!$AF$11*Lookup_Lists!$D$131+Matching_Engine!$AG$11*Lookup_Lists!$D$132+Matching_Engine!$AH$11*Lookup_Lists!$D$133+Matching_Engine!$AI$11*Lookup_Lists!$D$134)/(Lookup_Lists!$D$129+Lookup_Lists!$D$130+Lookup_Lists!$D$131+Lookup_Lists!$D$132+Lookup_Lists!$D$133+Lookup_Lists!$D$134),0) | AK11: =IF(KOL_Database!$AT$10="",0,MIN(100,MAX(0,KOL_Database!$AT$10))) | AL11: =IF(KOL_Database!$AU$10="",0,KOL_Database!$AU$10) | AM11: =IF(KOL_Database!$AV$10="","None",KOL_Database!$AV$10) | AN11: =IF(Matching_Engine!$AM$11="High",Lookup_Lists!$D$137,IF(Matching_Engine!$AM$11="Medium",Lookup_Lists!$D$138,IF(Matching_Engine!$AM$11="Low",Lookup_Lists!$D$139,Lookup_Lists!$D$140))) | AO11: =ROUND(MIN(100,MAX(0,(Matching_Engine!$AK$11*Lookup_Lists!$D$135+(100-Matching_Engine!$AL$11)*Lookup_Lists!$D$136)/(Lookup_Lists!$D$135+Lookup_Lists!$D$136)*Matching_Engine!$AN$11)),0) | AP11: =ROUND((Matching_Engine!$N$11*Lookup_Lists!$D$104+Matching_Engine!$S$11*Lookup_Lists!$D$105+Matching_Engine!$X$11*Lookup_Lists!$D$106+Matching_Engine!$AC$11*Lookup_Lists!$D$107+Matching_Engine!$AJ$11*Lookup_Lists!$D$108+Matching_Engine!$AO$11*Lookup_Lists!$D$109)/MAX(1,(Lookup_Lists!$D$104+Lookup_Lists!$D$105+Lookup_Lists!$D$106+Lookup_Lists!$D$107+Lookup_Lists!$D$108+Lookup_Lists!$D$109)),0) | AQ11: =IF(Matching_Engine!$AP$11>=Lookup_Lists!$D$152,"Excellent Match",IF(Matching_Engine!$AP$11>=Lookup_Lists!$D$153,"Strong Match",IF(Matching_Engine!$AP$11>=Lookup_Lists!$D$154,"Good Match",IF(Matching_Engine!$AP$11>=Lookup_Lists!$D$155,"Moderate Match","Low Match")))) | AR11: =KOL_Database!$BE$10 | AS11: =IF(Matching_Engine!$AR$11>=Lookup_Lists!$D$159,"High",IF(Matching_Engine!$AR$11>=Lookup_Lists!$D$160,"Medium","Limited Data")) | AT11: =ROUND((Matching_Engine!$N$11+Matching_Engine!$X$11+Matching_Engine!$AC$11)/3,0) | AU11: =ROUND(((100-Matching_Engine!$AL$11)*Lookup_Lists!$D$162+IF(KOL_Database!$BD$10="",Lookup_Lists!$D$150,KOL_Database!$BD$10)*Lookup_Lists!$D$163+Matching_Engine!$AI$11*Lookup_Lists!$D$164+Matching_Engine!$AD$11*Lookup_Lists!$D$165)/(Lookup_Lists!$D$162+Lookup_Lists!$D$163+Lookup_Lists!$D$164+Lookup_Lists!$D$165),0) | AV11: =IF(Matching_Engine!$AW$11="","PASS","EXCLUDED") | AW11: =IF(ISERROR(SEARCH(KOL_Database!$D$10,Brand_Profile!$D$32)),"Platform not in Preferred Platform",IF(AND(Brand_Profile!$D$36>0,KOL_Database!$J$10<Brand_Profile!$D$36),"Followers below Preferred Follower Range",IF(AND(Brand_Profile!$D$37>0,KOL_Database!$J$10>Brand_Profile!$D$37),"Followers above Preferred Follower Range",IF(AND(Brand_Profile!$D$38>0,IF(KOL_Database!$K$10="",0,KOL_Database!$K$10)<Brand_Profile!$D$38),"Engagement Rate below Minimum Engagement Rate",IF(ISERROR(SEARCH(KOL_Database!$G$10,Brand_Profile!$D$35)),"Tier not in Preferred Tier",IF(AND(Brand_Profile!$D$43>0,Matching_Engine!$AE$11<Brand_Profile!$D$43),"Audience Quality below Minimum Audience Quality",IF(AND(Brand_Profile!$D$44>0,Matching_Engine!$AK$11<Brand_Profile!$D$44),"Brand Safety below Minimum Brand Safety",IF(AND(Brand_Profile!$D$47="Yes",KOL_Database!$AD$10<>Brand_Profile!$D$19),"Audience Country does not match Target Country",IF(AND(Brand_Profile!$D$46="Yes",KOL_Database!$E$10<>Brand_Profile!$D$33),"Category is not the Preferred Category",IF(AND(Brand_Profile!$D$48>0,Matching_Engine!$AL$11>Brand_Profile!$D$48),"Competitor Saturation above Max Competitor Saturation",IF(AND(Brand_Profile!$D$50="Yes",KOL_Database!$AW$10="Yes"),"Already Selected",IF(AND(Brand_Profile!$D$51="Yes",KOL_Database!$AX$10="Yes"),"Already in Cart",IF(AND(Brand_Profile!$D$52="Yes",KOL_Database!$AY$10="Yes"),"Existing Partner",IF(AND(Brand_Profile!$D$53="Yes",KOL_Database!$AZ$10="Yes"),"Excluded Creator",IF(AND(Brand_Profile!$D$49>0,Matching_Engine!$AP$11<Brand_Profile!$D$49),"Brand Match below Minimum Brand Match",""))))))))))))))) | AX11: =IF(Matching_Engine!$AV$11="EXCLUDED","Excluded",IF(Matching_Engine!$AP$11>=Lookup_Lists!$D$156,"Highly Recommended",IF(Matching_Engine!$AP$11>=Lookup_Lists!$D$157,"Recommended",IF(Matching_Engine!$AP$11>=Lookup_Lists!$D$158,"Consider","Low Priority")))) | AY11: =IF(Matching_Engine!$AV$11="PASS",Matching_Engine!$AP$11,"") | AZ11: =Matching_Engine!$A$11&"|"&Matching_Engine!$C$11 | BA11: =IFERROR(INDEX(Lookup_Lists!$B$51:$B$92,MATCH(Brand_Profile!$D$12,Lookup_Lists!$A$51:$A$92,0)),"") | BB11: =IFERROR(INDEX(Lookup_Lists!$B$51:$B$92,MATCH(KOL_Database!$F$10,Lookup_Lists!$A$51:$A$92,0)),"") | BC11: =IFERROR(INDEX(Lookup_Lists!$B$185:$O$198,MATCH(Matching_Engine!$BA$11,Lookup_Lists!$A$185:$A$198,0),MATCH(KOL_Database!$E$10,Lookup_Lists!$B$184:$O$184,0)),Lookup_Lists!$D$151) | BD11: =IFERROR(INDEX(Lookup_Lists!$B$185:$O$198,MATCH(Brand_Profile!$D$33,Lookup_Lists!$A$185:$A$198,0),MATCH(KOL_Database!$E$10,Lookup_Lists!$B$184:$O$184,0)),Lookup_Lists!$D$151) | BE11: =IFERROR(INDEX(Lookup_Lists!$B$51:$B$92,MATCH(Brand_Profile!$D$34,Lookup_Lists!$A$51:$A$92,0)),"") | BF11: =KOL_Database!$AI$10&", "&KOL_Database!$AG$10&", "&KOL_Database!$F$10&", "&KOL_Database!$E$10 | BG11: =KOL_Database!$AI$10&", "&KOL_Database!$AG$10
