Workbook

Sheet README
A1: AUTOMETRIC — BRAND MATCH COMPARISON
A2: 24 creators read from the KOL server, scored against 5 brands, 120 matching records. Roster measured 2026-09-10 04:48 UTC from 10.100.14.216/kol.
A4: 1. WHAT THIS WORKBOOK IS
A5: Purpose | B5: To show that Brand Match is a contextual score — a function of (brand, creator) — rather than a permanent rating attached to a creator. The same 24 creators are scored against 5 deliberately different brands, and the resulting orders differ. Brand_Comparison is where that is easiest to see: one row per creator, one column per brand, and a Spread column that would read 0 if the model were secretly ranking creators rather than pairs.
A6: Source of data | B6: Every creator field comes from the KOL server (10.100.14.216/kol) via scripts/brand-match/roster-fetch.mjs, read-only. Nothing on KOL_Source_Data is invented, estimated to fill a gap, or carried over from the engine workbook's sample roster. Tables read: public.kol_directory, public.kol_social_account, public.kol_categories, feature.ig/tt_audience_analysis, feature.ig_engagement_analysis, l2_gold.kol_profile_card, l2_gold.audience_interest_daily, l2_gold.audience_geo_daily, l2_gold.audience_demographics_daily, l1_silver.unified_post.
A7: Relationship to the engine workbook | B7: Autometric_Brand_Match_Engine.xlsx is the specification of the logic and runs on a hand-built sample roster. This workbook runs the same logic on real rows: the same six components, the same weights, the same relevance matrices, all read from the same Lookup_Lists code (scripts/brand-match/build.mjs) and the same taxonomy (taxonomy.mjs). There is one model, not two.
A8: 2. THE 24 CREATORS
A9: Selection | B9: The 24 handles were given. They were not chosen by the model, and no creator outside the list appears anywhere in this workbook. 24 resolved to an active row in public.kol_directory. None had to be reported NOT FOUND.
A10: Two spellings were corrected | B10: Two requested handles do not exist on the server and each has a neighbour one transposition away that does: @erickapinedao9 → @erickapineda09, @shabiraaluaadnan → @shabiraalulaadnan. Both spellings are printed on KOL_Source_Data and on Validation. This is the only place a requested handle and a scored handle differ.
A11: Four handles existed twice | B11: Four creators hold a row on both Instagram and TikTok. The brief asks for 24 accounts, so one row per handle survives — the row carrying the most measured signal, not the most followers. Every dropped row is listed on Validation with the follower count it had, because a dropped row nobody can see is indistinguishable from a row that was never there.
A12: 3. THE FIVE BRANDS · every category taken from the database
A13: The categories are the database’s, not the workbook’s | B13: public.kol_categories holds 28 category names, and its taxonomy_key column already says which of them are the same thing — Foodies, Food and Cooking all carry Food; Sports, Gym Enthusiast, Cyclist and Fitness all carry Fitness. That column yields nine canonical values: Beauty · Entertainment · Fashion · Fitness · Food · Gen Z · Lifestyle · Moms · Tech. Lookup_Lists section 11a prints all 28 rows with their counts and their key. Both halves of every comparison resolve through that one column, so neither half authored the vocabulary it is scored on.
A14: The five brands | B14: NovaTech → Tech · LumiSkin → Beauty · DailyBite → Food · MoveFit → Fitness · UrbanMuse → Fashion. Five different canonical categories, different audience genders, different interest sets — five brands wanting the same creator profile would rank identically and demonstrate nothing. Brand_Profile carries a Source column naming the database column behind every field, and the record shape follows public.brand: name, category, brand_keywords, brand_hashtags.
A15: Audience interests are the database’s keys too | B15: The interest rows on Brand_Profile hold l2_gold.audience_interest_daily.interest_key values, spelled exactly as the server spells them — lower case, and 'sports' kept separate from 'fitness' because the database keeps them separate, which is why MoveFit targets both. A brand cannot target an interest the database does not have: the build asserts it and stops.
A16: There is no Industry field, because there is no industry column | B16: An earlier draft of this workbook carried brand Industry, Product Category, Sub Category, Brand Niche, Brand Personality, Tone, Communication Style and Positioning, scored against a 14-label taxonomy written for the engine workbook. None of those exist as creator columns on this server, and the taxonomy was a second vocabulary that disagreed with the database in two places — it filed Moms under Parenting and dropped Gen Z, when kol_categories assigns both a key of their own. They are gone. What remains either maps to a database column or is marked on Brand_Profile as scoring nothing.
A17: Hard filters left permissive | B17: The brief asks how 24 named creators compare across 5 brands. A minimum-follower or minimum-ER gate would answer a different question by deleting rows from the comparison. Sheet Hard_vs_Soft_Filter documents every gate that exists and counts what each would remove from this roster if it were switched on.
A18: 4. THE MODEL
A19: Final Match Score | B19: Final = (Business x 20 + Audience x 30 + Content x 20 + Personality x 10 + Performance x 10 + Safety x 10) / 100, on a 0-100 scale. The six weights live in editable cells on Lookup_Lists section 4 and CHECK_WEIGHT_TOTAL asserts they sum to 100. No score anywhere in this workbook is a typed number: every one is a formula over KOL_Source_Data and Brand_Profile.
A20: Sub-weights | B20: Target Audience = Age 25 / Gender 15 / Location 30 / Interest 30 (the brief’s own split). Brand & Business = Category 60 / Keyword 25 / Hashtag 15. Content & Category = Content Category 60 / Topic 40. Performance = ER 35 / Audience Quality 20 / Consistency 20 / Community 10 / Average Views 10 / Recent Growth 5. Brand Safety = Authenticity 40 / Follower Quality 30 / Verification 15 / Paid Ratio 15. The first two are not even splits, and Lookup_Lists section 11 says why: measured on this roster, Category Match takes 8 distinct values across the 120 pairs while Keyword Match takes 3 and Hashtag Match 2. Letting the two sparse signals carry 60% of a component would make it mostly measure whether a celebrity writes marketing copy in their captions, which none of them does.
A21: Missing inputs renormalise; they never become zero | B21: This is the one mechanism this workbook adds to the engine's. Where the server has no reading, the cell reads N/A and drops out of its weighted mean, so the remaining weights renormalise to 100 by themselves. A component with no inputs at all is N/A and drops out of the Final Match Score; the Available Weight column reports how much of the nominal 100 each row could be scored on. Zero is a measurement — "we looked, and there was none". Using it for "nobody looked" would rank an unmeasured creator below a bad one.
A22: Score interpretation | B22: Excellent Match 90-100 · Strong Match 80-89 · Good Match 70-79 · Moderate Match 60-69 · Low Match below 60. The bands are the brief's and live in editable cells (BAND_EXCELLENT and below). Scores on this roster sit low relative to those bands, and that is a finding rather than a bug: see section 6.
A23: 5. HARD FILTER vs SOFT MATCH
A24: The distinction | B24: A hard filter answers yes or no and removes creators from the result set: platform, minimum followers, mandatory location, tier, minimum ER, category requirement, connected-only. A soft match returns 0-100 and reorders them: brand match, audience relevance, content relevance, personality, performance, brand safety. Confusing the two is how a filter can be marked DONE while returning zero creators for every value.
A25: 6. LIMITATIONS · read this before quoting a number
A26: Six inputs do not exist on this server | B26: Audience age (no rows anywhere), sub category (no column), creator personality/tone/values/content style (no column — this empties Brand Personality Fit entirely), community (no column), comment sentiment and toxicity (0 rows), rate card (0 rows). Validation lists each one with where it would live, how it was verified and what it does to the score.
A27: Absolute scores are low against the bands — read them as a ranking, not a percentage | B27: Final scores on this roster run roughly 20 to 71, so almost every row lands in Low Match and a handful reach Moderate or Good. That is a property of the data, not of the creators. Brand Personality Fit contributes nothing at all (10 points of the 100 gone); audience interest and geography are known for only 10-20% of each sampled audience; and Keyword and Topic Match are near-empty for the reasons below. The bands are the brief's and they assume a complete creator record. USE THIS WORKBOOK TO COMPARE — creators within one brand, and one creator across the five brands. Do not read 52/100 as "52% fit".
A28: Engagement rate is scored against the creator's own tier | B28: Section 11b of Lookup_Lists sets the ER that scores 100 per tier, from 8% at Nano down to 2% at Mega. All 24 of these accounts are Mega. The shared CAL_ER_TARGET of 6% is calibrated for micro creators and would have scored @cristiano's 2.21% — the best engagement on the roster by some distance — as 37 out of 100. Engagement rate falls with reach as a matter of arithmetic, so the question the tier targets ask is "well engaged for an account this size", which is the only version a brand can act on.
A29: Audience shares are shares of the KNOWN portion | B29: l2_gold.audience_interest_daily is dominated by the key 'unknown' — often 80-89% of a creator's sample. Interest and country shares here are computed over the known remainder, and Interest Known % / Country Known % on KOL_Source_Data report how large that remainder was. A 100 on Interest Score off a 12% known sample is a much weaker claim than the same 100 off a 60% one.
A30: Categories are three different kinds of thing | B30: 12 creators carry a category from public.kol_categories (basis: live). 3 were classified from their own captions and hashtags by the taxonomy's keyword rules (basis: calculated or estimated), and the evidence that produced each one is printed beside it on KOL_Source_Data so it can be overruled. 9 carry none at all. A classified category ranks; it never gates.
A31: 9 creators have no category, and it moves their score | B31: Category Match and Content Category Match fall back to CAL_NEUTRAL for them — not to N/A, and not to CAL_UNRELATED. This has a consequence worth stating plainly: a creator nobody has categorised can outscore one who is known to be a poor fit. That is correct. Knowing @cristiano makes fitness content is real evidence against a SaaS brief; knowing nothing about @leomessi is not evidence either way. Category Basis and Confidence are the columns that tell the two apart, and their ranking says more about their audience than about their content.
A32: Keyword Match and Topic Match are close to empty, and honestly so | B32: Across all 120 pairs, Keyword Match averages under 2 and Topic Match under 4. Three reasons, none of them a bug: kol_directory.bio is ~12% filled; the brand keyword lists are Indonesian while several of these creators caption in English or Spanish, so @leomessi and @cristiano can never hit an Indonesian term whatever they post about; and these are celebrity and entertainment accounts that genuinely do not write about SaaS, skincare formulation or sportswear. The consequence is that Brand & Business Relevance rests mostly on Industry and Category (70% of it) and Content Relevance rests mostly on category, since Topic is half of what is left after sub-category and style drop out. A per-language keyword set would fix the second reason; nothing in the data fixes the third.
A33: 7. SHEETS
A34: Sheet | B34: What it holds
A35: README | B35: This sheet.
A36: KOL_Source_Data | B36: The 24 accounts as the server has them, with a Data Note per row saying what was missing.
A37: Brand_Profile | B37: The 5 brands, one column each, keyed for the engine.
A38: Matching_Engine | B38: 120 rows. Every score a formula. The only sheet that computes anything.
A39: Score_Breakdown | B39: The same rows, sub-scores first. A pure view.
A40: Match_Explanation | B40: 120 written reasons, each assembled from its own row's scores.
A41: Brand_Comparison | B41: One row per creator, one column per brand, plus Best Brand and Spread.
A42: Brand_Ranking | B42: 5 blocks of 24, ordered by the engine's Rank Key.
A43: Top_Matches | B43: Top 5 and bottom 5 for each brand, with reason, strength and concern.
A44: Hard_vs_Soft_Filter | B44: Every filter in the catalogue, split by kind, with its measured effect on this roster.
A45: Validation | B45: 15 checks, each computed in the workbook, plus the handle resolutions and the data gaps.
A46: Lookup_Lists | B46: Every weight, band, matrix and calibration constant. Edit here and the workbook moves.
A47: 8. REGENERATING
A48: Commands | B48: npm run brandmatch:fetch (office VPN required — re-reads the 24 accounts and rewrites scripts/brand-match/roster.json) · npm run brandmatch:comparison (rebuilds this file) · npm run brandmatch:comparison:verify (reads the built file back and checks the roster, the row counts, the formulas and the contextual-score claim).

Sheet KOL_Source_Data
A1: KOL SOURCE DATA · the 24 requested accounts, read from the KOL server
A2: Nothing on this sheet is invented, estimated to fill a gap, or carried over from the engine workbook's sample roster. A cell reading N/A means the column exists and is empty, or the column does not exist at all — the Data Note says which. Every one of the five age columns is N/A for every creator: there is no age signal anywhere on this server.
A4: IDENTITY | J4: CATEGORY & CONTENT | V4: AUDIENCE | BG4: PERFORMANCE | BS4: INTEGRITY | BW4: COVERAGE
A5: KOL ID | B5: Requested Handle | C5: Handle | D5: Creator Name | E5: Platform | F5: Found In Database | G5: Followers | H5: Tier | I5: Verified | J5: Directory Category (raw) | K5: Category | L5: Category Basis | M5: Category From Captions | N5: Content Topics | O5: Classification Evidence | P5: Sub Category | Q5: Content Style | R5: Creator City | S5: Bio | T5: Caption Digest | U5: Hashtag Digest | V5: Audience Age 13-17 % | W5: Audience Age 18-24 % | X5: Audience Age 25-34 % | Y5: Audience Age 35-44 % | Z5: Audience Age 45+ % | AA5: Female % | AB5: Male % | AC5: Gender Known % | AD5: Audience Country | AE5: Country Share % | AF5: Country Known % | AG5: Audience City 1 | AH5: City 1 Share % | AI5: Audience City 2 | AJ5: City 2 Share % | AK5: Audience City 3 | AL5: City 3 Share % | AM5: City Known % | AN5: Interest Known % | AO5: Interest: art % | AP5: Interest: automotive % | AQ5: Interest: beauty % | AR5: Interest: business % | AS5: Interest: education % | AT5: Interest: entertainment % | AU5: Interest: fashion % | AV5: Interest: fitness % | AW5: Interest: food % | AX5: Interest: gaming % | AY5: Interest: music % | AZ5: Interest: parenting % | BA5: Interest: pets % | BB5: Interest: photography % | BC5: Interest: religion % | BD5: Interest: sports % | BE5: Interest: technology % | BF5: Interest: travel % | BG5: Engagement Rate (%) | BH5: Engagement Rate Source | BI5: Average Views | BJ5: Median Views | BK5: View-to-Follower Ratio | BL5: Posts Analyzed | BM5: Posts / Month | BN5: Observation Days | BO5: Cadence Usable | BP5: Followers Growth % | BQ5: Paid Ratio % | BR5: Community Score | BS5: Audience Quality | BT5: Authenticity | BU5: Follower Quality | BV5: Content Risk | BW5: Data Completeness % | BX5: Confidence | BY5: Data Note
A6: KOL-01 | B6: @instagram | C6: @instagram | D6: instagram | E6: Instagram | F6: FOUND | G6: 685896635 | H6: =IFERROR(INDEX(Lookup_Lists!$A$96:$A$100,MATCH(KOL_Source_Data!$G$6,Lookup_Lists!$B$96:$B$100,1)),"N/A") | I6: Yes | J6: Lifestyle | Moms | K6: Lifestyle | L6: live | M6: N/A | N6: Music | O6: Entertainment 2pt [music (caption)] | P6: N/A | Q6: N/A | R6: N/A | S6: Discover what's new on Instagram 🔎✨ | T6: The precision in this trick 🤯 @leonmbz is a freestyle footballer who collabs with athletes across different sports. Here, he’s teaming up with spinning top world champion @jun_spintop_s. “I’ve always been trying to push the boundaries of what’s possible.” Video by @leonmbz and @jun_spintop_s Music by @_zynyx | U6: N/A | V6: N/A | W6: N/A | X6: N/A | Y6: N/A | Z6: N/A | AA6: N/A | AB6: N/A | AC6: N/A | AD6: N/A | AE6: N/A | AF6: N/A | AG6: N/A | AH6: N/A | AI6: N/A | AJ6: N/A | AK6: N/A | AL6: N/A | AM6: N/A | AN6: N/A | AO6: N/A | AP6: N/A | AQ6: N/A | AR6: N/A | AS6: N/A | AT6: N/A | AU6: N/A | AV6: N/A | AW6: N/A | AX6: N/A | AY6: N/A | AZ6: N/A | BA6: N/A | BB6: N/A | BC6: N/A | BD6: N/A | BE6: N/A | BF6: N/A | BG6: 0.07 | BH6: kol_directory.engagement_rate | BI6: 136309208 | BJ6: 136309208 | BK6: 19.8731 | BL6: 1 | BM6: N/A | BN6: 0 | BO6: N/A | BP6: N/A | BQ6: 0 | BR6: N/A | BS6: N/A | BT6: N/A | BU6: N/A | BV6: N/A | BW6: =ROUND((IF(ISNUMBER(KOL_Source_Data!$K$6),1,IF(AND(ISTEXT(KOL_Source_Data!$K$6),KOL_Source_Data!$K$6<>"N/A"),1,0))+IF(ISNUMBER(KOL_Source_Data!$BG$6),1,IF(AND(ISTEXT(KOL_Source_Data!$BG$6),KOL_Source_Data!$BG$6<>"N/A"),1,0))+IF(ISNUMBER(KOL_Source_Data!$BI$6),1,IF(AND(ISTEXT(KOL_Source_Data!$BI$6),KOL_Source_Data!$BI$6<>"N/A"),1,0))+IF(ISNUMBER(KOL_Source_Data!$BK$6),1,IF(AND(ISTEXT(KOL_Source_Data!$BK$6),KOL_Source_Data!$BK$6<>"N/A"),1,0))+IF(ISNUMBER(KOL_Source_Data!$AA$6),1,IF(AND(ISTEXT(KOL_Source_Data!$AA$6),KOL_Source_Data!$AA$6<>"N/A"),1,0))+IF(ISNUMBER(KOL_Source_Data!$AE$6),1,IF(AND(ISTEXT(KOL_Source_Data!$AE$6),KOL_Source_Data!$AE$6<>"N/A"),1,0))+IF(ISNUMBER(KOL_Source_Data!$AH$6),1,IF(AND(ISTEXT(KOL_Source_Data!$AH$6),KOL_Source_Data!$AH$6<>"N/A"),1,0))+IF(ISNUMBER(KOL_Source_Data!$AN$6),1,IF(AND(ISTEXT(KOL_Source_Data!$AN$6),KOL_Source_Data!$AN$6<>"N/A"),1,0))+IF(ISNUMBER(KOL_Source_Data!$BS$6),1,IF(AND(ISTEXT(KOL_Source_Data!$BS$6),KOL_Source_Data!$BS$6<>"N/A"),1,0))+IF(ISNUMBER(KOL_Source_Data!$BT$6),1,IF(AND(ISTEXT(KOL_Source_Data!$BT$6),KOL_Source_Data!$BT$6<>"N/A"),1,0))+IF(ISNUMBER(KOL_Source_Data!$BU$6),1,IF(AND(ISTEXT(KOL_Source_Data!$BU$6),KOL_Source_Data!$BU$6<>"N/A"),1,0))+IF(ISNUMBER(KOL_Source_Data!$BM$6),1,IF(AND(ISTEXT(KOL_Source_Data!$BM$6),KOL_Source_Data!$BM$6<>"N/A"),1,0)))/12*100,0) | BX6: =IF(KOL_Source_Data!$BW$6>=Lookup_Lists!$D$159,"High",IF(KOL_Source_Data!$BW$6>=Lookup_Lists!$D$160,"Medium","Limited Data")) | BY6: no audience analysis row · no audience interest rows · cadence unusable: null/month extrapolated from 0 observed day(s)
A7: KOL-02 | B7: @cristiano | C7: @cristiano | D7: cristiano | E7: Instagram | F7: FOUND | G7: 679264838 | H7: =IFERROR(INDEX(Lookup_Lists!$A$96:$A$100,MATCH(KOL_Source_Data!$G$7,Lookup_Lists!$B$96:$B$100,1)),"N/A") | I7: Yes | J7: Fitness | K7: Fitness | L7: live | M7: Tech | N7: Esports, Makeup | O7: Gaming 3pt [game (caption); esports (caption)] · Beauty 2pt [makeup (caption)] | P7: N/A | Q7: N/A | R7: N/A | S7: N/A | T7: @Cristiano Ronaldo and Georgina Rodríguez (@georginagio) are married! For weeks, the internet was awash with speculation—about the date, the location, the guest list. (The rumored celebrity attendees included everyone from Rio Ferdinand to Rihanna.) In the end, the couple’s wedding took place on a symbolic date: August 11, the 10th anniversary of the day they first met at a Gucci store in Madrid. Instead of a blowout celebration, the couple, who have over 750 million Instagram followers between them, got married in their living room, wearing @gucci by Demna. “It was exactly as I’d imagined it,” says Georgina. For Vogue’s Summer digital cover, Gaby Wood spoke to Cris y Gio, as they are known to friends and family, about their intimate wedding day in Portugal. Tap the link in our bio for an exclusive look inside the ceremony. Photographed by @juergentellerstudio, makeup by @fermartinezlab, hair by @torrentfernando, with special thanks to @angelsproject, Vogue, Summer Digital Cover 2026. · Back 🟡🔵 · C❤️G · My toys 🚀 · Not yet 🤷🏽‍♂️😅 · Cuando te vuelves hacia la luz del sol, las sombras caen detrás de ti. 🌅 · Try my Game Day Blast recipe. Stay sharp. Stay ready. #FuelLikeRonaldo · Pai feliz ❤️ · Greatness takes many forms 💪 Esports World Cup is live in Paris with over 2000 players putting in the work to be the champion. @ewc_en · Football, art and passion. Proud to be part of Knight of Najd – Chapter II with @alnassr and @vhils. 100 moments from my journey, carved into on | U7: #fuellikeronaldo #alnassr #vhils #cr7 #knightofnajd | V7: N/A | W7: N/A | X7: N/A | Y7: N/A | Z7: N/A | AA7: 18.18 | AB7: 81.82 | AC7: 22 | AD7: N/A | AE7: N/A | AF7: 6 | AG7: N/A | AH7: N/A | AI7: N/A | AJ7: N/A | AK7: N/A | AL7: N/A | AM7: N/A | AN7: 16.7 | AO7: N/A | AP7: N/A | AQ7: N/A | AR7: 5.9 | AS7: 5.9 | AT7: 11.8 | AU7: N/A | AV7: N/A | AW7: 5.9 | AX7: 5.9 | AY7: N/A | AZ7: N/A | BA7: N/A | BB7: N/A | BC7: 29.4 | BD7: 29.4 | BE7: 5.9 | BF7: N/A | BG7: 2.21 | BH7: kol_directory.engagement_rate | BI7: 80305356 | BJ7: 80305356 | BK7: N/A | BL7: 8 | BM7: 10 | BN7: 24 | BO7: Yes | BP7: 0.0637 | BQ7: 12.5 | BR7: N/A | BS7: 68 | BT7: 69 | BU7: 68 | BV7: N/A | BW7: =ROUND((IF(ISNUMBER(KOL_Source_Data!$K$7),1,IF(AND(ISTEXT(KOL_Source_Data!$K$7),KOL_Source_Data!$K$7<>"N/A"),1,0))+IF(ISNUMBER(KOL_Source_Data!$BG$7),1,IF(AND(ISTEXT(KOL_Source_Data!$BG$7),KOL_Source_Data!$BG$7<>"N/A"),1,0))+IF(ISNUMBER(KOL_Source_Data!$BI$7),1,IF(AND(ISTEXT(KOL_Source_Data!$BI$7),KOL_Source_Data!$BI$7<>"N/A"),1,0))+IF(ISNUMBER(KOL_Source_Data!$BK$7),1,IF(AND(ISTEXT(KOL_Source_Data!$BK$7),KOL_Source_Data!$BK$7<>"N/A"),1,0))+IF(ISNUMBER(KOL_Source_Data!$AA$7),1,IF(AND(ISTEXT(KOL_Source_Data!$AA$7),KOL_Source_Data!$AA$7<>"N/A"),1,0))+IF(ISNUMBER(KOL_Source_Data!$AE$7),1,IF(AND(ISTEXT(KOL_Source_Data!$AE$7),KOL_Source_Data!$AE$7<>"N/A"),1,0))+IF(ISNUMBER(KOL_Source_Data!$AH$7),1,IF(AND(ISTEXT(KOL_Source_Data!$AH$7),KOL_Source_Data!$AH$7<>"N/A"),1,0))+IF(ISNUMBER(KOL_Source_Data!$AN$7),1,IF(AND(ISTEXT(KOL_Source_Data!$AN$7),KOL_Source_Data!$AN$7<>"N/A"),1,0))+IF(ISNUMBER(KOL_Source_Data!$BS$7),1,IF(AND(ISTEXT(KOL_Source_Data!$BS$7),KOL_Source_Data!$BS$7<>"N/A"),1,0))+IF(ISNUMBER(KOL_Source_Data!$BT$7),1,IF(AND(ISTEXT(KOL_Source_Data!$BT$7),KOL_Source_Data!$BT$7<>"N/A"),1,0))+IF(ISNUMBER(KOL_Source_Data!$BU$7),1,IF(AND(ISTEXT(KOL_Source_Data!$BU$7),KOL_Source_Data!$BU$7<>"N/A"),1,0))+IF(ISNUMBER(KOL_Source_Data!$BM$7),1,IF(AND(ISTEXT(KOL_Source_Data!$BM$7),KOL_Source_Data!$BM$7<>"N/A"),1,0)))/12*100,0) | BX7: =IF(KOL_Source_Data!$BW$7>=Lookup_Lists!$D$159,"High",IF(KOL_Source_Data!$BW$7>=Lookup_Lists!$D$160,"Medium","Limited Data")) | BY7: complete on every tracked field
A8: KOL-03 | B8: @leomessi | C8: @leomessi | D8: leomessi | E8: Instagram | F8: FOUND | G8: 516185245 | H8: =IFERROR(INDEX(Lookup_Lists!$A$96:$A$100,MATCH(KOL_Source_Data!$G$8,Lookup_Lists!$B$96:$B$100,1)),"N/A") | I8: Yes | J8: Animal Lovers | K8: N/A | L8: N/A | M8: N/A | N8: N/A | O8: N/A | P8: N/A | Q8: N/A | R8: N/A | S8: Bienvenidos a la cuenta oficial de Instagram de Leo Messi / Welcome to the official Leo Messi Instagram account | T8: Te amo, pa. ❤️ · Germany 2006. South Africa 2010. Brazil 2014. Russia 2018. Qatar 2022. Canada, Mexico and United States 2026. Six FIFA World Cups. Relive the journey with my official FIFA World Cup™ signed collection - available only at Icons.com Alemania 2006. Sudáfrica 2010. Brasil 2014. Rusia 2018. Qatar 2022. Canadá, México y Estados Unidos 2026. Seis Copas del Mundo. Reviví todo el camino con mi colección oficial firmada de la Copa Mundial de la FIFA™. Disponible exclusivamente en Icons.com · Thanks world, we’ll take it from here. 🌎 MLS & Leagues Cup are back in a big way. · golden memories. ✨ the new Leo Messi x Originals collection, available tomorrow. · Introducing the new Leo Messi x Originals collection, available tomorrow. Certified gold. 🏅 Descubrí la nueva colección Leo Messi x Originals. Disponible desde mañana. Puro oro. 🏅 · El dolor es muy grande y va a costar que cierre esta herida. Pero también me quedo con todo lo bueno… Con los partidos que dimos vuelta dejando todo y que quedarán para siempre en la memoria, con el apoyo de un país entero que junto con el trabajo y el esfuerzo de este grupo nos llevó a volver a estar, una vez más, entre los mejores del mundo. Hoy cuesta valorar lo que hicimos, pero este grupo llegó a dos finales consecutivas de la Copa del Mundo. Muchas gracias de corazón por cada saludo y por cada mensaje. Una vez más logramos unirnos como país y estar todos juntos, compartiendo el inmenso orgullo de ser argentinos. También quiero fel | U8: N/A | V8: N/A | W8: N/A | X8: N/A | Y8: N/A | Z8: N/A | AA8: 20 | AB8: 80 | AC8: 25 | AD8: N/A | AE8: N/A | AF8: 3 | AG8: N/A | AH8: N/A | AI8: N/A | AJ8: N/A | AK8: N/A | AL8: N/A | AM8: N/A | AN8: 18.3 | AO8: 5.3 | AP8: 5.3 | AQ8: N/A | AR8: 10.5 | AS8: N/A | AT8: 5.3 | AU8: N/A | AV8: 5.3 | AW8: N/A | AX8: 10.5 | AY8: 10.5 | AZ8: 10.5 | BA8: N/A | BB8: N/A | BC8: 21.1 | BD8: 15.8 | BE8: N/A | BF8: N/A | BG8: 2.66 | BH8: kol_directory.engagement_rate | BI8: 44938781 | BJ8: 44938781 | BK8: N/A | BL8: 8 | BM8: 0.87 | BN8: 275 | BO8: Yes | BP8: 0.0191 | BQ8: 25 | BR8: N/A | BS8: 65 | BT8: 67 | BU8: 63 | BV8: N/A | BW8: =ROUND((IF(ISNUMBER(KOL_Source_Data!$K$8),1,IF(AND(ISTEXT(KOL_Source_Data!$K$8),KOL_Source_Data!$K$8<>"N/A"),1,0))+IF(ISNUMBER(KOL_Source_Data!$BG$8),1,IF(AND(ISTEXT(KOL_Source_Data!$BG$8),KOL_Source_Data!$BG$8<>"N/A"),1,0))+IF(ISNUMBER(KOL_Source_Data!$BI$8),1,IF(AND(ISTEXT(KOL_Source_Data!$BI$8),KOL_Source_Data!$BI$8<>"N/A"),1,0))+IF(ISNUMBER(KOL_Source_Data!$BK$8),1,IF(AND(ISTEXT(KOL_Source_Data!$BK$8),KOL_Source_Data!$BK$8<>"N/A"),1,0))+IF(ISNUMBER(KOL_Source_Data!$AA$8),1,IF(AND(ISTEXT(KOL_Source_Data!$AA$8),KOL_Source_Data!$AA$8<>"N/A"),1,0))+IF(ISNUMBER(KOL_Source_Data!$AE$8),1,IF(AND(ISTEXT(KOL_Source_Data!$AE$8),KOL_Source_Data!$AE$8<>"N/A"),1,0))+IF(ISNUMBER(KOL_Source_Data!$AH$8),1,IF(AND(ISTEXT(KOL_Source_Data!$AH$8),KOL_Source_Data!$AH$8<>"N/A"),1,0))+IF(ISNUMBER(KOL_Source_Data!$AN$8),1,IF(AND(ISTEXT(KOL_Source_Data!$AN$8),KOL_Source_Data!$AN$8<>"N/A"),1,0))+IF(ISNUMBER(KOL_Source_Data!$BS$8),1,IF(AND(ISTEXT(KOL_Source_Data!$BS$8),KOL_Source_Data!$BS$8<>"N/A"),1,0))+IF(ISNUMBER(KOL_Source_Data!$BT$8),1,IF(AND(ISTEXT(KOL_Source_Data!$BT$8),KOL_Source_Data!$BT$8<>"N/A"),1,0))+IF(ISNUMBER(KOL_Source_Data!$BU$8),1,IF(AND(ISTEXT(KOL_Source_Data!$BU$8),KOL_Source_Data!$BU$8<>"N/A"),1,0))+IF(ISNUMBER(KOL_Source_Data!$BM$8),1,IF(AND(ISTEXT(KOL_Source_Data!$BM$8),KOL_Source_Data!$BM$8<>"N/A"),1,0)))/12*100,0) | BX8: =IF(KOL_Source_Data!$BW$8>=Lookup_Lists!$D$159,"High",IF(KOL_Source_Data!$BW$8>=Lookup_Lists!$D$160,"Medium","Limited Data")) | BY8: no category: kol_categories carries none and caption evidence did not reach the threshold
A9: KOL-04 | B9: @raffinagita1717 | C9: @raffinagita1717 | D9: raffinagita1717 | E9: Instagram | F9: FOUND | G9: 75052814 | H9: =IFERROR(INDEX(Lookup_Lists!$A$96:$A$100,MATCH(KOL_Source_Data!$G$9,Lookup_Lists!$B$96:$B$100,1)),"N/A") | I9: Yes | J9: N/A | K9: Lifestyle | L9: calculated | M9: Lifestyle | N9: Domestic Travel, Business, City & Culture | O9: Travel 9pt [jalan-jalan (caption); wisata (caption); wisata lokal (caption)] · Finance 5pt [umkm (caption)] | P9: N/A | Q9: N/A | R9: N/A | S9: Single terbaru "Bersyukurlah" ⬇️⬇️ | T9: Dari Indonesia, menuju lebih dekat ke Asia. 🌏🏠 Di press conference D’MASIV Asia Home Run, Nagita Slavina berbagi harapannya untuk membawa pengalaman D’MASIV lebih dekat dengan para pendengar di berbagai negara Asia—dengan skala yang lebih besar dan tentunya pengalaman yang nggak terlupakan. Siap ikut merasakan perjalanan D’MASIV Asia Home Run? 🏃‍♂️💨 🎟️ Dapatkan tiketmu: dmasivtour.com · Perjalanan The Duda’s-1 belum selesai. Setelah berkeliling Indonesia dan sempat membawa cerita sampai ke Amerika, kali ini rasa penasaran itu membawa kita menjelajahi Asia. Bukan cuma datang ke tempat baru, tapi mengenal lebih dekat budaya, kebiasaan, makanan, musik, dan cerita orang-orangnya. Melihat apa yang membuat setiap negara berbeda, sekaligus menemukan banyak hal yang ternyata terasa dekat dengan Indonesia. The Duda’s-1 Goes to Asia. Satu benua, banyak cerita. Kira-kira negara mana yang bakal mereka datangi pertama? · The Dudas-1, yang beranggotakan Raffi Ahmad, Ariel NOAH, Gading Marten, dan Desta, bersiap melebarkan sayap mereka ke kancah internasional lewat tur Asia. Setelah hampir tiga tahun aktif berkeliling Indonesia untuk mempromosikan destinasi wisata lokal serta mendongkrak UMKM, keempat sahabat ini memutuskan untuk menjajal tantangan baru di luar negeri. Ariel NOAH menjelaskan bahwa pemilihan kawasan Asia bertujuan untuk mempelajari cara negara-negara tetangga mempromosikan pariwisata mereka ke tingkat dunia, sehingga hasilnya dapat menjadi bahan pembelajaran yang berman | U9: #thedudasminusone #ransentertainment #dmasiv #nagitaslavina #utusankhususpresiden #pembinaangenerasimuda #pekerjaseni | V9: N/A | W9: N/A | X9: N/A | Y9: N/A | Z9: N/A | AA9: 50 | AB9: 50 | AC9: 30 | AD9: Indonesia | AE9: 60 | AF9: 5 | AG9: N/A | AH9: N/A | AI9: N/A | AJ9: N/A | AK9: N/A | AL9: N/A | AM9: N/A | AN9: 8.7 | AO9: N/A | AP9: N/A | AQ9: 11.1 | AR9: 22.2 | AS9: 22.2 | AT9: 11.1 | AU9: N/A | AV9: N/A | AW9: N/A | AX9: N/A | AY9: 11.1 | AZ9: 11.1 | BA9: N/A | BB9: N/A | BC9: N/A | BD9: N/A | BE9: 11.1 | BF9: N/A | BG9: 0.52 | BH9: kol_directory.engagement_rate | BI9: 1148129 | BJ9: 1148129 | BK9: 1.5298 | BL9: 6 | BM9: 0.27 | BN9: 666 | BO9: Yes | BP9: -0.0261 | BQ9: 0 | BR9: N/A | BS9: 58 | BT9: 29 | BU9: 86 | BV9: N/A | BW9: =ROUND((IF(ISNUMBER(KOL_Source_Data!$K$9),1,IF(AND(ISTEXT(KOL_Source_Data!$K$9),KOL_Source_Data!$K$9<>"N/A"),1,0))+IF(ISNUMBER(KOL_Source_Data!$BG$9),1,IF(AND(ISTEXT(KOL_Source_Data!$BG$9),KOL_Source_Data!$BG$9<>"N/A"),1,0))+IF(ISNUMBER(KOL_Source_Data!$BI$9),1,IF(AND(ISTEXT(KOL_Source_Data!$BI$9),KOL_Source_Data!$BI$9<>"N/A"),1,0))+IF(ISNUMBER(KOL_Source_Data!$BK$9),1,IF(AND(ISTEXT(KOL_Source_Data!$BK$9),KOL_Source_Data!$BK$9<>"N/A"),1,0))+IF(ISNUMBER(KOL_Source_Data!$AA$9),1,IF(AND(ISTEXT(KOL_Source_Data!$AA$9),KOL_Source_Data!$AA$9<>"N/A"),1,0))+IF(ISNUMBER(KOL_Source_Data!$AE$9),1,IF(AND(ISTEXT(KOL_Source_Data!$AE$9),KOL_Source_Data!$AE$9<>"N/A"),1,0))+IF(ISNUMBER(KOL_Source_Data!$AH$9),1,IF(AND(ISTEXT(KOL_Source_Data!$AH$9),KOL_Source_Data!$AH$9<>"N/A"),1,0))+IF(ISNUMBER(KOL_Source_Data!$AN$9),1,IF(AND(ISTEXT(KOL_Source_Data!$AN$9),KOL_Source_Data!$AN$9<>"N/A"),1,0))+IF(ISNUMBER(KOL_Source_Data!$BS$9),1,IF(AND(ISTEXT(KOL_Source_Data!$BS$9),KOL_Source_Data!$BS$9<>"N/A"),1,0))+IF(ISNUMBER(KOL_Source_Data!$BT$9),1,IF(AND(ISTEXT(KOL_Source_Data!$BT$9),KOL_Source_Data!$BT$9<>"N/A"),1,0))+IF(ISNUMBER(KOL_Source_Data!$BU$9),1,IF(AND(ISTEXT(KOL_Source_Data!$BU$9),KOL_Source_Data!$BU$9<>"N/A"),1,0))+IF(ISNUMBER(KOL_Source_Data!$BM$9),1,IF(AND(ISTEXT(KOL_Source_Data!$BM$9),KOL_Source_Data!$BM$9<>"N/A"),1,0)))/12*100,0) | BX9: =IF(KOL_Source_Data!$BW$9>=Lookup_Lists!$D$159,"High",IF(KOL_Source_Data!$BW$9>=Lookup_Lists!$D$160,"Medium","Limited Data")) | BY9: category calculated from captions, not from kol_categories
A10: KOL-05 | B10: @lunamaya | C10: @lunamaya | D10: lunamaya | E10: Instagram | F10: FOUND | G10: 37961844 | H10: =IFERROR(INDEX(Lookup_Lists!$A$96:$A$100,MATCH(KOL_Source_Data!$G$10,Lookup_Lists!$B$96:$B$100,1)),"N/A") | I10: Yes | J10: Beauty | K10: Beauty | L10: live | M10: N/A | N10: Career, Job Hunting & CV, Domestic Travel | O10: Education 5pt [interview (caption)] · Fashion 4pt [fashion (caption); gaya (caption); outfit (caption)] | P10: N/A | Q10: N/A | R10: N/A | S10: @namabeauty.co @tsmediaid @roleentertainment @yayasan_lunamayanawasena lunamaya@role-entertainment.com BA @zappremiere @rrfx.indonesia | T10: POV: the jewels changed everything! @bvlgari✨️ More from this special cover story over at @bazaarindonesia 🫶 · A glimpse behind the sparkle✨️ @bvlgari · Dalam gerak, kilau, dan siluet yang tegas, @lunamaya mewarnai Harper’s Bazaar Indonesia edisi Agustus 2026. Dipotret di Singapura dalam balutan @bvlgari High Jewelry, kamera menangkap sisi Luna yang modern, powerful, dan penuh karakter. ✨ Portofolio ini: Keseluruhan Perhiasan & Jam tangan: @bvlgari High Jewelry Director: @hilariusjason Video Editor: @fajrids Editor Fashion: @yudithnk Busana: @blancstudio.official @dibbaofficial, Didit Hediprasetyo, @heaven_tanudiredja @_peau @yosafat_k Makeup: @zhouaiyimua Hair: @tressandcurvy (@colinyeohair @dorenelowhair @sitosthair @janebokhair) Asst. Stylist: @nau.kamillaa Lokasi: The Clifford Pier Alfresco Deck and La Brasserie’s Private Dining Room at @fullertonbayhotelsg · A very Cinta birthday! @claurakiehl 🥳🫶 · Here’s to a brighter Indonesia🇮🇩🫶 · Dressed up for a day that means so much✨️🇮🇩 Dirgahayu ke-81, Indonesiaku. Semoga negeri ini selalu menjadi rumah yang kita banggakan❤️🤍 -- Outfit: @saptodjojokartiko | Stylist: @hagaipakan | Bag: @bvlgari | Make Up: @kunsoomakeupartist | Hair Do: @iwanetaufik_hair | Broch: @epajewel | Suntiang: @hummingbirdroad · Didn’t expect anything to survive HYROX hahaha but my makeup did tho. complexion, bibir, semuanya masih cakeppp💋 · Untuk edisi Agustus 2026, @lunamaya kembali menghiasi cover Harper’s Bazaar Indonesia. Dipotret di Singapur | U10: #withgalaxy #teamgalaxy #galaxys26ultra #circletosearchwithgoogle #circleitthatsall #mexico66golf #onitsukatiger #onitsukatigerid | V10: N/A | W10: N/A | X10: N/A | Y10: N/A | Z10: N/A | AA10: 51.52 | AB10: 48.48 | AC10: 33 | AD10: Indonesia | AE10: 85 | AF10: 20 | AG10: Bali | AH10: 25 | AI10: Bandung | AJ10: 25 | AK10: Jakarta | AL10: 16.7 | AM10: 100 | AN10: 25.2 | AO10: N/A | AP10: 3.6 | AQ10: 3.6 | AR10: 28.6 | AS10: 7.1 | AT10: 7.1 | AU10: 10.7 | AV10: N/A | AW10: 3.6 | AX10: N/A | AY10: N/A | AZ10: 3.6 | BA10: N/A | BB10: 3.6 | BC10: 10.7 | BD10: 3.6 | BE10: 10.7 | BF10: 3.6 | BG10: 0.03 | BH10: kol_directory.engagement_rate | BI10: 383646 | BJ10: 205306 | BK10: 1.0106 | BL10: 6 | BM10: 45 | BN10: 4 | BO10: No | BP10: -0.0301 | BQ10: 0 | BR10: N/A | BS10: 72 | BT10: 73 | BU10: 71 | BV10: N/A | BW10: =ROUND((IF(ISNUMBER(KOL_Source_Data!$K$10),1,IF(AND(ISTEXT(KOL_Source_Data!$K$10),KOL_Source_Data!$K$10<>"N/A"),1,0))+IF(ISNUMBER(KOL_Source_Data!$BG$10),1,IF(AND(ISTEXT(KOL_Source_Data!$BG$10),KOL_Source_Data!$BG$10<>"N/A"),1,0))+IF(ISNUMBER(KOL_Source_Data!$BI$10),1,IF(AND(ISTEXT(KOL_Source_Data!$BI$10),KOL_Source_Data!$BI$10<>"N/A"),1,0))+IF(ISNUMBER(KOL_Source_Data!$BK$10),1,IF(AND(ISTEXT(KOL_Source_Data!$BK$10),KOL_Source_Data!$BK$10<>"N/A"),1,0))+IF(ISNUMBER(KOL_Source_Data!$AA$10),1,IF(AND(ISTEXT(KOL_Source_Data!$AA$10),KOL_Source_Data!$AA$10<>"N/A"),1,0))+IF(ISNUMBER(KOL_Source_Data!$AE$10),1,IF(AND(ISTEXT(KOL_Source_Data!$AE$10),KOL_Source_Data!$AE$10<>"N/A"),1,0))+IF(ISNUMBER(KOL_Source_Data!$AH$10),1,IF(AND(ISTEXT(KOL_Source_Data!$AH$10),KOL_Source_Data!$AH$10<>"N/A"),1,0))+IF(ISNUMBER(KOL_Source_Data!$AN$10),1,IF(AND(ISTEXT(KOL_Source_Data!$AN$10),KOL_Source_Data!$AN$10<>"N/A"),1,0))+IF(ISNUMBER(KOL_Source_Data!$BS$10),1,IF(AND(ISTEXT(KOL_Source_Data!$BS$10),KOL_Source_Data!$BS$10<>"N/A"),1,0))+IF(ISNUMBER(KOL_Source_Data!$BT$10),1,IF(AND(ISTEXT(KOL_Source_Data!$BT$10),KOL_Source_Data!$BT$10<>"N/A"),1,0))+IF(ISNUMBER(KOL_Source_Data!$BU$10),1,IF(AND(ISTEXT(KOL_Source_Data!$BU$10),KOL_Source_Data!$BU$10<>"N/A"),1,0))+IF(ISNUMBER(KOL_Source_Data!$BM$10),1,IF(AND(ISTEXT(KOL_Source_Data!$BM$10),KOL_Source_Data!$BM$10<>"N/A"),1,0)))/12*100,0) | BX10: =IF(KOL_Source_Data!$BW$10>=Lookup_Lists!$D$159,"High",IF(KOL_Source_Data!$BW$10>=Lookup_Lists!$D$160,"Medium","Limited Data")) | BY10: cadence unusable: 45/month extrapolated from 4 observed day(s)
A11: KOL-06 | B11: @ibnuwardani | C11: @ibnuwardani | D11: ibnuwardani | E11: TikTok | F11: FOUND | G11: 26200000 | H11: =IFERROR(INDEX(Lookup_Lists!$A$96:$A$100,MATCH(KOL_Source_Data!$G$11,Lookup_Lists!$B$96:$B$100,1)),"N/A") | I11: Yes | J11: N/A | K11: N/A | L11: N/A | M11: N/A | N11: N/A | O11: Home & Living 1pt [rumah (caption)] | P11: N/A | Q11: N/A | R11: N/A | S11: N/A | T11: Setuju ga kalau kita keliling Indonesia? @Lita🐣 @Alvarazka Antarsukha Wardani · 🙏🏻🤣🙏🏻 @Lita🐣 @Alvarazka Antarsukha Wardani · Spiderman😍 @Lita🐣 @Alvarazka Antarsukha Wardani · STICH VIDEO INI‼️ Ultah Agustus mana JJ-nya🤣‼️ @Lita🐣 @Alvarazka Antarsukha Wardani · Kok malah rebahan😭🙏🏻 @Lita🐣 @Alvarazka Antarsukha Wardani · ULANGTAHUN AGUSTUS?! @Lita🐣 @Alvarazka Antarsukha Wardani · BIKIN NGILER! Sekali di TF 1 video jutaan, inimah puluhan ratusan juta gampang bgt🙏🏻😭 @tokoclippers · 🙏🏻🤣 @Lita🐣 @Alvarazka Antarsukha Wardani · BTS konten🤣 @Lita🐣 @Alvarazka Antarsukha Wardani · Rumah Impian ini untukmu, dan hanya untukmu, selamanya kamu akan jadi orang yang paling aku sayang🩵 @Lita🐣 @Alvarazka Antarsukha Wardani @Sibambo Studio @Satrio Ananda #rumahibnulita · #rumahibnulita | U11: #rumahibnulita | V11: N/A | W11: N/A | X11: N/A | Y11: N/A | Z11: N/A | AA11: 51.72 | AB11: 48.28 | AC11: 29 | AD11: Indonesia | AE11: 66.7 | AF11: 9 | AG11: N/A | AH11: N/A | AI11: N/A | AJ11: N/A | AK11: N/A | AL11: N/A | AM11: N/A | AN11: 11.8 | AO11: N/A | AP11: N/A | AQ11: 16.7 | AR11: 16.7 | AS11: N/A | AT11: 8.3 | AU11: N/A | AV11: N/A | AW11: 8.3 | AX11: N/A | AY11: 16.7 | AZ11: 16.7 | BA11: N/A | BB11: N/A | BC11: 8.3 | BD11: 8.3 | BE11: N/A | BF11: N/A | BG11: 0.33 | BH11: l2_gold.kol_profile_card.monitoring_er_pct | BI11: 2762680 | BJ11: 308650 | BK11: 5.5438 | BL11: N/A | BM11: 1.65 | BN11: 182 | BO11: Yes | BP11: 0.2857 | BQ11: 10 | BR11: N/A | BS11: 76 | BT11: 61 | BU11: 92 | BV11: N/A | BW11: =ROUND((IF(ISNUMBER(KOL_Source_Data!$K$11),1,IF(AND(ISTEXT(KOL_Source_Data!$K$11),KOL_Source_Data!$K$11<>"N/A"),1,0))+IF(ISNUMBER(KOL_Source_Data!$BG$11),1,IF(AND(ISTEXT(KOL_Source_Data!$BG$11),KOL_Source_Data!$BG$11<>"N/A"),1,0))+IF(ISNUMBER(KOL_Source_Data!$BI$11),1,IF(AND(ISTEXT(KOL_Source_Data!$BI$11),KOL_Source_Data!$BI$11<>"N/A"),1,0))+IF(ISNUMBER(KOL_Source_Data!$BK$11),1,IF(AND(ISTEXT(KOL_Source_Data!$BK$11),KOL_Source_Data!$BK$11<>"N/A"),1,0))+IF(ISNUMBER(KOL_Source_Data!$AA$11),1,IF(AND(ISTEXT(KOL_Source_Data!$AA$11),KOL_Source_Data!$AA$11<>"N/A"),1,0))+IF(ISNUMBER(KOL_Source_Data!$AE$11),1,IF(AND(ISTEXT(KOL_Source_Data!$AE$11),KOL_Source_Data!$AE$11<>"N/A"),1,0))+IF(ISNUMBER(KOL_Source_Data!$AH$11),1,IF(AND(ISTEXT(KOL_Source_Data!$AH$11),KOL_Source_Data!$AH$11<>"N/A"),1,0))+IF(ISNUMBER(KOL_Source_Data!$AN$11),1,IF(AND(ISTEXT(KOL_Source_Data!$AN$11),KOL_Source_Data!$AN$11<>"N/A"),1,0))+IF(ISNUMBER(KOL_Source_Data!$BS$11),1,IF(AND(ISTEXT(KOL_Source_Data!$BS$11),KOL_Source_Data!$BS$11<>"N/A"),1,0))+IF(ISNUMBER(KOL_Source_Data!$BT$11),1,IF(AND(ISTEXT(KOL_Source_Data!$BT$11),KOL_Source_Data!$BT$11<>"N/A"),1,0))+IF(ISNUMBER(KOL_Source_Data!$BU$11),1,IF(AND(ISTEXT(KOL_Source_Data!$BU$11),KOL_Source_Data!$BU$11<>"N/A"),1,0))+IF(ISNUMBER(KOL_Source_Data!$BM$11),1,IF(AND(ISTEXT(KOL_Source_Data!$BM$11),KOL_Source_Data!$BM$11<>"N/A"),1,0)))/12*100,0) | BX11: =IF(KOL_Source_Data!$BW$11>=Lookup_Lists!$D$159,"High",IF(KOL_Source_Data!$BW$11>=Lookup_Lists!$D$160,"Medium","Limited Data")) | BY11: no category: kol_categories carries none and caption evidence did not reach the threshold
A12: KOL-07 | B12: @iben_ma | C12: @iben_ma | D12: iben_ma | E12: Instagram | F12: FOUND | G12: 3997609 | H12: =IFERROR(INDEX(Lookup_Lists!$A$96:$A$100,MATCH(KOL_Source_Data!$G$12,Lookup_Lists!$B$96:$B$100,1)),"N/A") | I12: Yes | J12: Entertainment | K12: Entertainment | L12: live | M12: N/A | N12: N/A | O12: N/A | P12: N/A | Q12: N/A | R12: N/A | S12: living life to the fullest of capacity 💯🚀 #LLTTFOC @sambalbakar 🔥 @jualemasidn 🥇 @fuelworld_ 💨 CP: 0811-1479-279 (Nonie) | T12: Awas lu Habibi, harus gantian lah!! · Jujur! Kalau lu bakal bawain nya apa?? 😁🙏🏻 · The real ngebut Pak Vincent, merdeka! 🇮🇩😁 · Maaf, tapi semua tindakan harus ada balasannya. 🙏🏻 · finallyyyyyy joining this trend, lots of prewedding content coming soon❤️ pre-wedding content creator @momentsmatter.id · Kadang semuanya udah masuk akal, masuk logika. Tapi tetep aja, perlu that final push of “I trust u” buat ngejalaninnya bener-bener maksimal dan pede. Thank you baby @natashabigeyl sudah percaya dengan decision-decision aku yang kadang terlalu roller coaster 😁❤️ Penghargaan ini ditujukan untuk kalian semua pecinta Eatsambel, dan yang pasti untuk team yang udah selalu support Eatsambel 24/7. LET’S GO KITA BAWA SAMBEL MENDUNIA!!!! 🔥🔥🔥🤤🤤🤤 · Wah harus JELAS nih. @sambalbakar · A one minute teaser of our pre-wedding session in our favorite city of all time. You know I’m the happiest when the gummy smile is out🤪❤️ baru teaser aja jujur udh mellow nontonnya hahaha gak sabar next week for the full video, tungguin yaaa!!!🥹❤️ video by @retromagis · Kita tunggu bareng nih di akunnya…😁🤩 📍Jual Emas Indonesia Cipinang · Astaga Habibi, udah gua bilang kan.. 🤣😁 | U12: N/A | V12: N/A | W12: N/A | X12: N/A | Y12: N/A | Z12: N/A | AA12: 39.47 | AB12: 60.53 | AC12: 38 | AD12: Indonesia | AE12: 85.7 | AF12: 14 | AG12: Bali | AH12: 33.3 | AI12: Kediri | AJ12: 16.7 | AK12: Lampung | AL12: 16.7 | AM12: 100 | AN12: 15.2 | AO12: N/A | AP12: 6.3 | AQ12: 6.3 | AR12: 6.3 | AS12: 12.5 | AT12: 6.3 | AU12: N/A | AV12: N/A | AW12: 6.3 | AX12: N/A | AY12: 12.5 | AZ12: 12.5 | BA12: N/A | BB12: N/A | BC12: 18.8 | BD12: 12.5 | BE12: N/A | BF12: N/A | BG12: 1.46 | BH12: kol_directory.engagement_rate | BI12: 1608002.1 | BJ12: 1110744 | BK12: 50.0887 | BL12: 8 | BM12: 34.29 | BN12: 7 | BO12: No | BP12: 0.2351 | BQ12: 0 | BR12: N/A | BS12: 63 | BT12: 77 | BU12: 49 | BV12: N/A | BW12: =ROUND((IF(ISNUMBER(KOL_Source_Data!$K$12),1,IF(AND(ISTEXT(KOL_Source_Data!$K$12),KOL_Source_Data!$K$12<>"N/A"),1,0))+IF(ISNUMBER(KOL_Source_Data!$BG$12),1,IF(AND(ISTEXT(KOL_Source_Data!$BG$12),KOL_Source_Data!$BG$12<>"N/A"),1,0))+IF(ISNUMBER(KOL_Source_Data!$BI$12),1,IF(AND(ISTEXT(KOL_Source_Data!$BI$12),KOL_Source_Data!$BI$12<>"N/A"),1,0))+IF(ISNUMBER(KOL_Source_Data!$BK$12),1,IF(AND(ISTEXT(KOL_Source_Data!$BK$12),KOL_Source_Data!$BK$12<>"N/A"),1,0))+IF(ISNUMBER(KOL_Source_Data!$AA$12),1,IF(AND(ISTEXT(KOL_Source_Data!$AA$12),KOL_Source_Data!$AA$12<>"N/A"),1,0))+IF(ISNUMBER(KOL_Source_Data!$AE$12),1,IF(AND(ISTEXT(KOL_Source_Data!$AE$12),KOL_Source_Data!$AE$12<>"N/A"),1,0))+IF(ISNUMBER(KOL_Source_Data!$AH$12),1,IF(AND(ISTEXT(KOL_Source_Data!$AH$12),KOL_Source_Data!$AH$12<>"N/A"),1,0))+IF(ISNUMBER(KOL_Source_Data!$AN$12),1,IF(AND(ISTEXT(KOL_Source_Data!$AN$12),KOL_Source_Data!$AN$12<>"N/A"),1,0))+IF(ISNUMBER(KOL_Source_Data!$BS$12),1,IF(AND(ISTEXT(KOL_Source_Data!$BS$12),KOL_Source_Data!$BS$12<>"N/A"),1,0))+IF(ISNUMBER(KOL_Source_Data!$BT$12),1,IF(AND(ISTEXT(KOL_Source_Data!$BT$12),KOL_Source_Data!$BT$12<>"N/A"),1,0))+IF(ISNUMBER(KOL_Source_Data!$BU$12),1,IF(AND(ISTEXT(KOL_Source_Data!$BU$12),KOL_Source_Data!$BU$12<>"N/A"),1,0))+IF(ISNUMBER(KOL_Source_Data!$BM$12),1,IF(AND(ISTEXT(KOL_Source_Data!$BM$12),KOL_Source_Data!$BM$12<>"N/A"),1,0)))/12*100,0) | BX12: =IF(KOL_Source_Data!$BW$12>=Lookup_Lists!$D$159,"High",IF(KOL_Source_Data!$BW$12>=Lookup_Lists!$D$160,"Medium","Limited Data")) | BY12: cadence unusable: 34.29/month extrapolated from 7 observed day(s)
A13: KOL-08 | B13: @inul.d | C13: @inul.d | D13: inul.d | E13: Instagram | F13: FOUND | G13: 20046665 | H13: =IFERROR(INDEX(Lookup_Lists!$A$96:$A$100,MATCH(KOL_Source_Data!$G$13,Lookup_Lists!$B$96:$B$100,1)),"N/A") | I13: Yes | J13: N/A | K13: Food | L13: calculated | M13: Food | N13: Coffee & Beverage, Baking & Dessert, Budget Travel | O13: Food 10pt [dessert (caption); minuman (caption); cafe (caption)] · Travel 4pt [travel (caption); promo (caption)] | P13: N/A | Q13: N/A | R13: N/A | S13: ✨BA @sunco_id @brightgas @miburungdara @purinaindonesia INUL INFO 👇 | T13: sexy 💋 designer 👉 @jaka_raja @jaka_raja2 💋 shoes Bali 👉 @niluhdjelantik 💋 DMD Panggung Rezeki @officialmnctv · REVEAL! ✨ Scent Your Song — Paket Karaoke + Parfum Favoritmu! 🎤✨ Yang kemarin masih coming soon, sekarang waktunya di-reveal! 👀 Nikmati serunya karaoke sambil bawa pulang parfum pilihanmu dalam Scent Your Song dari Inul Vizta. 🎶💐 MEDIUM PACKAGE — Rp315.000 2 Jam Room + 1 Appetizer + 1 Dessert + 1 Pitcher Minuman + 1 Parfum LARGE PACKAGE — Rp510.000 2 Jam Room + 2 Appetizer + 2 Dessert + 2 Pitcher Minuman + 1 Parfum DELUXE PACKAGE — Rp750.000 2 Jam Room + 3 Appetizer + 3 Dessert + 3 Pitcher Minuman + 1 Parfum 🍴 Appetizer: Cheese Sticks / Mac N’ Cheese / Tteokbokki Cheese 🍰 Dessert: Double Choux 🥤 Beverage: Lychee Tea / Lemon Tea / Orange Juice / Coca-Cola / Fanta 🎁 BONUS PROMO PARFUM Tebus parfum hanya Rp75.000 dengan minimal belanja Rp1.000.000. Harga paket sudah termasuk tax & service. Harga tebus parfum Rp75.000 belum termasuk tax & service. 📍 Tersedia di outlet: DKI Jakarta • Inul Vizta Buaran • Inul Vizta Kramat Jati • Inul Vizta Kota Kasablanka • Inul Vizta Melawai • Inul Vizta Pejaten Jawa Barat • Inul Vizta Summarecon Bekasi • Inul Vizta Harapan Indah • Inul Vizta Blu Plaza • Inul Vizta TSM Cibubur • Inul Vizta Cileungsi • Inul Rumah Bernyanyi • Inul Vizta Festive Walk • Inul Vizta Sukabumi • Inul Vizta Paskal Bandung Banten • Inul Vizta Tangerang City • Inul Vizta Balekota Jambi • Inul Vizta Jambi 🎤 Sing your song, complete your scent! Saatnya | U13: #inulvizta #daraparfum #promokaraoke #scentyoursong #keinvizaja #inulviztakaraoke #karaokekeluarga #17agustus #dmdpanggungrezeki #mnctvrumahnyadangdut #hutri81 | V13: N/A | W13: N/A | X13: N/A | Y13: N/A | Z13: N/A | AA13: 57.5 | AB13: 42.5 | AC13: 40 | AD13: Indonesia | AE13: 86.7 | AF13: 15 | AG13: Bandung | AH13: 18.2 | AI13: Bali | AJ13: 9.1 | AK13: Jakarta | AL13: 9.1 | AM13: 100 | AN13: 17.1 | AO13: 5.6 | AP13: N/A | AQ13: N/A | AR13: 27.8 | AS13: 5.6 | AT13: 5.6 | AU13: N/A | AV13: 5.6 | AW13: 11.1 | AX13: N/A | AY13: N/A | AZ13: 22.2 | BA13: N/A | BB13: N/A | BC13: 16.7 | BD13: N/A | BE13: N/A | BF13: N/A | BG13: 0.01 | BH13: kol_directory.engagement_rate | BI13: 226692.67 | BJ13: 80192 | BK13: 1.1308 | BL13: 7 | BM13: 105 | BN13: 2 | BO13: No | BP13: -0.0202 | BQ13: 0 | BR13: N/A | BS13: 62 | BT13: 55 | BU13: 70 | BV13: N/A | BW13: =ROUND((IF(ISNUMBER(KOL_Source_Data!$K$13),1,IF(AND(ISTEXT(KOL_Source_Data!$K$13),KOL_Source_Data!$K$13<>"N/A"),1,0))+IF(ISNUMBER(KOL_Source_Data!$BG$13),1,IF(AND(ISTEXT(KOL_Source_Data!$BG$13),KOL_Source_Data!$BG$13<>"N/A"),1,0))+IF(ISNUMBER(KOL_Source_Data!$BI$13),1,IF(AND(ISTEXT(KOL_Source_Data!$BI$13),KOL_Source_Data!$BI$13<>"N/A"),1,0))+IF(ISNUMBER(KOL_Source_Data!$BK$13),1,IF(AND(ISTEXT(KOL_Source_Data!$BK$13),KOL_Source_Data!$BK$13<>"N/A"),1,0))+IF(ISNUMBER(KOL_Source_Data!$AA$13),1,IF(AND(ISTEXT(KOL_Source_Data!$AA$13),KOL_Source_Data!$AA$13<>"N/A"),1,0))+IF(ISNUMBER(KOL_Source_Data!$AE$13),1,IF(AND(ISTEXT(KOL_Source_Data!$AE$13),KOL_Source_Data!$AE$13<>"N/A"),1,0))+IF(ISNUMBER(KOL_Source_Data!$AH$13),1,IF(AND(ISTEXT(KOL_Source_Data!$AH$13),KOL_Source_Data!$AH$13<>"N/A"),1,0))+IF(ISNUMBER(KOL_Source_Data!$AN$13),1,IF(AND(ISTEXT(KOL_Source_Data!$AN$13),KOL_Source_Data!$AN$13<>"N/A"),1,0))+IF(ISNUMBER(KOL_Source_Data!$BS$13),1,IF(AND(ISTEXT(KOL_Source_Data!$BS$13),KOL_Source_Data!$BS$13<>"N/A"),1,0))+IF(ISNUMBER(KOL_Source_Data!$BT$13),1,IF(AND(ISTEXT(KOL_Source_Data!$BT$13),KOL_Source_Data!$BT$13<>"N/A"),1,0))+IF(ISNUMBER(KOL_Source_Data!$BU$13),1,IF(AND(ISTEXT(KOL_Source_Data!$BU$13),KOL_Source_Data!$BU$13<>"N/A"),1,0))+IF(ISNUMBER(KOL_Source_Data!$BM$13),1,IF(AND(ISTEXT(KOL_Source_Data!$BM$13),KOL_Source_Data!$BM$13<>"N/A"),1,0)))/12*100,0) | BX13: =IF(KOL_Source_Data!$BW$13>=Lookup_Lists!$D$159,"High",IF(KOL_Source_Data!$BW$13>=Lookup_Lists!$D$160,"Medium","Limited Data")) | BY13: category calculated from captions, not from kol_categories · cadence unusable: 105/month extrapolated from 2 observed day(s)
A14: KOL-09 | B14: @bbrightvc | C14: @bbrightvc | D14: bbrightvc | E14: Instagram | F14: FOUND | G14: 18018065 | H14: =IFERROR(INDEX(Lookup_Lists!$A$96:$A$100,MATCH(KOL_Source_Data!$G$14,Lookup_Lists!$B$96:$B$100,1)),"N/A") | I14: No | J14: Fashion | K14: Fashion | L14: live | M14: N/A | N14: N/A | O14: N/A | P14: N/A | Q14: N/A | R14: N/A | S14: N/A | T14: N/A | U14: N/A | V14: N/A | W14: N/A | X14: N/A | Y14: N/A | Z14: N/A | AA14: N/A | AB14: N/A | AC14: N/A | AD14: N/A | AE14: N/A | AF14: N/A | AG14: N/A | AH14: N/A | AI14: N/A | AJ14: N/A | AK14: N/A | AL14: N/A | AM14: N/A | AN14: N/A | AO14: N/A | AP14: N/A | AQ14: N/A | AR14: N/A | AS14: N/A | AT14: N/A | AU14: N/A | AV14: N/A | AW14: N/A | AX14: N/A | AY14: N/A | AZ14: N/A | BA14: N/A | BB14: N/A | BC14: N/A | BD14: N/A | BE14: N/A | BF14: N/A | BG14: N/A | BH14: N/A | BI14: N/A | BJ14: N/A | BK14: N/A | BL14: N/A | BM14: N/A | BN14: N/A | BO14: N/A | BP14: N/A | BQ14: N/A | BR14: N/A | BS14: N/A | BT14: N/A | BU14: N/A | BV14: N/A | BW14: =ROUND((IF(ISNUMBER(KOL_Source_Data!$K$14),1,IF(AND(ISTEXT(KOL_Source_Data!$K$14),KOL_Source_Data!$K$14<>"N/A"),1,0))+IF(ISNUMBER(KOL_Source_Data!$BG$14),1,IF(AND(ISTEXT(KOL_Source_Data!$BG$14),KOL_Source_Data!$BG$14<>"N/A"),1,0))+IF(ISNUMBER(KOL_Source_Data!$BI$14),1,IF(AND(ISTEXT(KOL_Source_Data!$BI$14),KOL_Source_Data!$BI$14<>"N/A"),1,0))+IF(ISNUMBER(KOL_Source_Data!$BK$14),1,IF(AND(ISTEXT(KOL_Source_Data!$BK$14),KOL_Source_Data!$BK$14<>"N/A"),1,0))+IF(ISNUMBER(KOL_Source_Data!$AA$14),1,IF(AND(ISTEXT(KOL_Source_Data!$AA$14),KOL_Source_Data!$AA$14<>"N/A"),1,0))+IF(ISNUMBER(KOL_Source_Data!$AE$14),1,IF(AND(ISTEXT(KOL_Source_Data!$AE$14),KOL_Source_Data!$AE$14<>"N/A"),1,0))+IF(ISNUMBER(KOL_Source_Data!$AH$14),1,IF(AND(ISTEXT(KOL_Source_Data!$AH$14),KOL_Source_Data!$AH$14<>"N/A"),1,0))+IF(ISNUMBER(KOL_Source_Data!$AN$14),1,IF(AND(ISTEXT(KOL_Source_Data!$AN$14),KOL_Source_Data!$AN$14<>"N/A"),1,0))+IF(ISNUMBER(KOL_Source_Data!$BS$14),1,IF(AND(ISTEXT(KOL_Source_Data!$BS$14),KOL_Source_Data!$BS$14<>"N/A"),1,0))+IF(ISNUMBER(KOL_Source_Data!$BT$14),1,IF(AND(ISTEXT(KOL_Source_Data!$BT$14),KOL_Source_Data!$BT$14<>"N/A"),1,0))+IF(ISNUMBER(KOL_Source_Data!$BU$14),1,IF(AND(ISTEXT(KOL_Source_Data!$BU$14),KOL_Source_Data!$BU$14<>"N/A"),1,0))+IF(ISNUMBER(KOL_Source_Data!$BM$14),1,IF(AND(ISTEXT(KOL_Source_Data!$BM$14),KOL_Source_Data!$BM$14<>"N/A"),1,0)))/12*100,0) | BX14: =IF(KOL_Source_Data!$BW$14>=Lookup_Lists!$D$159,"High",IF(KOL_Source_Data!$BW$14>=Lookup_Lists!$D$160,"Medium","Limited Data")) | BY14: no engagement rate on any of the three sources · no audience analysis row · no audience interest rows
A15: KOL-10 | B15: @pevpearce | C15: @pevpearce | D15: pevpearce | E15: Instagram | F15: FOUND | G15: 17452714 | H15: =IFERROR(INDEX(Lookup_Lists!$A$96:$A$100,MATCH(KOL_Source_Data!$G$15,Lookup_Lists!$B$96:$B$100,1)),"N/A") | I15: Yes | J15: Lifestyle | K15: Lifestyle | L15: live | M15: N/A | N15: Race & Event, Running, Investing | O15: Fitness 3pt [race (caption)] · Beauty 2pt [makeup (caption)] | P15: N/A | Q15: N/A | R15: N/A | S15: N/A | T15: A reminder, dreams do come true ✨🏎️ · Monza, we finally meet and even more 🏁 Nggak ada yang ngalahin feeling balik ke race week setelah summer break apalagi ngerasainnya langsung dari salah satu circuit paling legendaris di dunia. Plus, sempat shooting bareng Lewis & Charles juga… kebayang kan serunya kaya apa ✨ Can't wait to show you more... stay tuned! 🏎️ · Next coba apa lagi ya? Spill ✨️ · Date night · Once upon a time di 2019 pas lagi medical check up di Kuala Lumpur dikenalin ke Mirzan dan fast forward sekarang ngerayain hari ulang tahunnya as husband & wife. Life is so funny. They say the best stories are the ones you don’t see coming. Meeting you was mine. Thank you for being you, My Love. Happy birthday to my fave person. · Off the grid for a few days · My July cover for Harper's Bazaar Indonesia is out! Sharing stories of dedication and my creative path, all while in beautiful @louisvuitton. So much love for this feature Fotografi: @mr_hendra Fashion Editor: @sophisticadit Makeup: @evalovira Hair: @picaleva Asisten Stylist: @nau.kamillaa Wardrobe & Accessories: @louisvuitton Teks: sadini Layout Cover: @somadvladislav · Bagi @pevpearce, apa yang terwujud hari ini mungkin pernah bermula dari sesuatu yang sederhana, yakni sebuah bayangan tentang apa yang ingin ia ciptakan. Membuka edisi Juli 2026 Harper’s Bazaar Indonesia, Pevita Pearce hadir dalam balutan @louisvuitton dan berbagi cerita tentang karya, manifestasi, serta dedikasi yang membawanya sampai pada titik in | U15: N/A | V15: N/A | W15: N/A | X15: N/A | Y15: N/A | Z15: N/A | AA15: 28.21 | AB15: 71.79 | AC15: 39 | AD15: Indonesia | AE15: 56.3 | AF15: 16 | AG15: Jakarta | AH15: 25 | AI15: Bandung | AJ15: 12.5 | AK15: Jawa | AL15: 12.5 | AM15: 100 | AN15: 22.2 | AO15: N/A | AP15: N/A | AQ15: N/A | AR15: 16.7 | AS15: N/A | AT15: 4.2 | AU15: N/A | AV15: 4.2 | AW15: 12.5 | AX15: 4.2 | AY15: 8.3 | AZ15: 4.2 | BA15: N/A | BB15: 12.5 | BC15: 20.8 | BD15: 4.2 | BE15: 4.2 | BF15: 4.2 | BG15: 0.28 | BH15: kol_directory.engagement_rate | BI15: 577655.67 | BJ15: 557850 | BK15: 0.996 | BL15: 9 | BM15: 5.74 | BN15: 47 | BO15: Yes | BP15: -0.022 | BQ15: 0 | BR15: N/A | BS15: 54 | BT15: 51 | BU15: 56 | BV15: N/A | BW15: =ROUND((IF(ISNUMBER(KOL_Source_Data!$K$15),1,IF(AND(ISTEXT(KOL_Source_Data!$K$15),KOL_Source_Data!$K$15<>"N/A"),1,0))+IF(ISNUMBER(KOL_Source_Data!$BG$15),1,IF(AND(ISTEXT(KOL_Source_Data!$BG$15),KOL_Source_Data!$BG$15<>"N/A"),1,0))+IF(ISNUMBER(KOL_Source_Data!$BI$15),1,IF(AND(ISTEXT(KOL_Source_Data!$BI$15),KOL_Source_Data!$BI$15<>"N/A"),1,0))+IF(ISNUMBER(KOL_Source_Data!$BK$15),1,IF(AND(ISTEXT(KOL_Source_Data!$BK$15),KOL_Source_Data!$BK$15<>"N/A"),1,0))+IF(ISNUMBER(KOL_Source_Data!$AA$15),1,IF(AND(ISTEXT(KOL_Source_Data!$AA$15),KOL_Source_Data!$AA$15<>"N/A"),1,0))+IF(ISNUMBER(KOL_Source_Data!$AE$15),1,IF(AND(ISTEXT(KOL_Source_Data!$AE$15),KOL_Source_Data!$AE$15<>"N/A"),1,0))+IF(ISNUMBER(KOL_Source_Data!$AH$15),1,IF(AND(ISTEXT(KOL_Source_Data!$AH$15),KOL_Source_Data!$AH$15<>"N/A"),1,0))+IF(ISNUMBER(KOL_Source_Data!$AN$15),1,IF(AND(ISTEXT(KOL_Source_Data!$AN$15),KOL_Source_Data!$AN$15<>"N/A"),1,0))+IF(ISNUMBER(KOL_Source_Data!$BS$15),1,IF(AND(ISTEXT(KOL_Source_Data!$BS$15),KOL_Source_Data!$BS$15<>"N/A"),1,0))+IF(ISNUMBER(KOL_Source_Data!$BT$15),1,IF(AND(ISTEXT(KOL_Source_Data!$BT$15),KOL_Source_Data!$BT$15<>"N/A"),1,0))+IF(ISNUMBER(KOL_Source_Data!$BU$15),1,IF(AND(ISTEXT(KOL_Source_Data!$BU$15),KOL_Source_Data!$BU$15<>"N/A"),1,0))+IF(ISNUMBER(KOL_Source_Data!$BM$15),1,IF(AND(ISTEXT(KOL_Source_Data!$BM$15),KOL_Source_Data!$BM$15<>"N/A"),1,0)))/12*100,0) | BX15: =IF(KOL_Source_Data!$BW$15>=Lookup_Lists!$D$159,"High",IF(KOL_Source_Data!$BW$15>=Lookup_Lists!$D$160,"Medium","Limited Data")) | BY15: complete on every tracked field
A16: KOL-11 | B16: @irwansyah_15 | C16: @irwansyah_15 | D16: irwansyah_15 | E16: Instagram | F16: FOUND | G16: 14916540 | H16: =IFERROR(INDEX(Lookup_Lists!$A$96:$A$100,MATCH(KOL_Source_Data!$G$16,Lookup_Lists!$B$96:$B$100,1)),"N/A") | I16: Yes | J16: N/A | K16: N/A | L16: N/A | M16: N/A | N16: Coffee & Beverage, Kids & Family | O16: Parenting 3pt [keluarga (caption)] · Food 2pt [kopi (caption)] | P16: N/A | Q16: N/A | R16: N/A | S16: Indonesian • @15interior_official • @jannahtravel • @umroqutravel • @swizgroup Cp +6285176781115 Ov (work only) | T16: Dirgahayu Indonesiaku! 81 tahun Indonesia merdeka, Indonesia berdaulat adil dan makmur 🇮🇩 · Semoga kelak Anak2 bisa lebih baik dari kami , semoga Allah jaga mereka آمِيْن اللّهُمَّ آمِيْن Barakallahufiikum anak2 shaleh dan shalehah ku syg · Gawat Ada King @mister.aloy di hari Minggu ❤️ Sehat" semuanyaa guys 🙏 · MasyaAllah Tabarakallah ❤️ semoga Allah jaga anak2ku syg · Ternyata ini isi tasnya @irwansyah_15 ❤️👀 ide challenge apa ya berikutnya? #pakaiautannyamukpamitan · kirain ada maling nggak taunya...🤣🦟 #PakaiAutanNyamukPamitan · caption nya apa ya? 😎 · Kamu team roma + kopi ? Atau roma + teh ? #Pastiromakelapa 🤤😍 @roma.biskuitkelapa · Alhamdulillah Senangnya bisa bergabung di keluarga @barakat_id 😍 siapa yang udah coba @barakat_id ? Ada yang mau dikirimin parcel barakat? Cungg👆🏻 · Satu lagi dari @mayoraofficial , @le_mineraleid 😉 · #pakaiautannyamukpamitan · #PakaiAutanNyamukPamitan · #Pastiromakelapa | U16: #pakaiautannyamukpamitan #pastiromakelapa | V16: N/A | W16: N/A | X16: N/A | Y16: N/A | Z16: N/A | AA16: 71.79 | AB16: 28.21 | AC16: 39 | AD16: Indonesia | AE16: 70 | AF16: 10 | AG16: Lampung | AH16: 16.7 | AI16: Madiun | AJ16: 16.7 | AK16: Palu | AL16: 16.7 | AM16: 100 | AN16: 21.7 | AO16: 4.3 | AP16: 4.3 | AQ16: 4.3 | AR16: 21.7 | AS16: 4.3 | AT16: 4.3 | AU16: N/A | AV16: 4.3 | AW16: 4.3 | AX16: N/A | AY16: 4.3 | AZ16: 8.7 | BA16: N/A | BB16: 4.3 | BC16: 17.4 | BD16: 4.3 | BE16: 8.7 | BF16: N/A | BG16: 0.25 | BH16: kol_directory.engagement_rate | BI16: N/A | BJ16: N/A | BK16: N/A | BL16: 0 | BM16: N/A | BN16: N/A | BO16: N/A | BP16: -0.0281 | BQ16: N/A | BR16: N/A | BS16: 62 | BT16: 42 | BU16: 81 | BV16: N/A | BW16: =ROUND((IF(ISNUMBER(KOL_Source_Data!$K$16),1,IF(AND(ISTEXT(KOL_Source_Data!$K$16),KOL_Source_Data!$K$16<>"N/A"),1,0))+IF(ISNUMBER(KOL_Source_Data!$BG$16),1,IF(AND(ISTEXT(KOL_Source_Data!$BG$16),KOL_Source_Data!$BG$16<>"N/A"),1,0))+IF(ISNUMBER(KOL_Source_Data!$BI$16),1,IF(AND(ISTEXT(KOL_Source_Data!$BI$16),KOL_Source_Data!$BI$16<>"N/A"),1,0))+IF(ISNUMBER(KOL_Source_Data!$BK$16),1,IF(AND(ISTEXT(KOL_Source_Data!$BK$16),KOL_Source_Data!$BK$16<>"N/A"),1,0))+IF(ISNUMBER(KOL_Source_Data!$AA$16),1,IF(AND(ISTEXT(KOL_Source_Data!$AA$16),KOL_Source_Data!$AA$16<>"N/A"),1,0))+IF(ISNUMBER(KOL_Source_Data!$AE$16),1,IF(AND(ISTEXT(KOL_Source_Data!$AE$16),KOL_Source_Data!$AE$16<>"N/A"),1,0))+IF(ISNUMBER(KOL_Source_Data!$AH$16),1,IF(AND(ISTEXT(KOL_Source_Data!$AH$16),KOL_Source_Data!$AH$16<>"N/A"),1,0))+IF(ISNUMBER(KOL_Source_Data!$AN$16),1,IF(AND(ISTEXT(KOL_Source_Data!$AN$16),KOL_Source_Data!$AN$16<>"N/A"),1,0))+IF(ISNUMBER(KOL_Source_Data!$BS$16),1,IF(AND(ISTEXT(KOL_Source_Data!$BS$16),KOL_Source_Data!$BS$16<>"N/A"),1,0))+IF(ISNUMBER(KOL_Source_Data!$BT$16),1,IF(AND(ISTEXT(KOL_Source_Data!$BT$16),KOL_Source_Data!$BT$16<>"N/A"),1,0))+IF(ISNUMBER(KOL_Source_Data!$BU$16),1,IF(AND(ISTEXT(KOL_Source_Data!$BU$16),KOL_Source_Data!$BU$16<>"N/A"),1,0))+IF(ISNUMBER(KOL_Source_Data!$BM$16),1,IF(AND(ISTEXT(KOL_Source_Data!$BM$16),KOL_Source_Data!$BM$16<>"N/A"),1,0)))/12*100,0) | BX16: =IF(KOL_Source_Data!$BW$16>=Lookup_Lists!$D$159,"High",IF(KOL_Source_Data!$BW$16>=Lookup_Lists!$D$160,"Medium","Limited Data")) | BY16: no category: kol_categories carries none and caption evidence did not reach the threshold
A17: KOL-12 | B17: @fadiljaidi | C17: @fadiljaidi | D17: fadiljaidi | E17: Instagram | F17: FOUND | G17: 14398391 | H17: =IFERROR(INDEX(Lookup_Lists!$A$96:$A$100,MATCH(KOL_Source_Data!$G$17,Lookup_Lists!$B$96:$B$100,1)),"N/A") | I17: Yes | J17: N/A | K17: N/A | L17: N/A | M17: N/A | N17: Makeup, Product Swatch & Review | O17: Beauty 3pt [shade (caption)] · Fashion 1pt [gaya (caption)] | P17: N/A | Q17: N/A | R17: N/A | S17: BA @maricafe.id Endorsement WA : 081295223083(Admin 1) 085282606565(Admin 2) | T17: Ini gaya tos nya udah dari kita kecil serius 🙏🏻😭 #Juanneve #jasthr #Fadiljaidi · Udah akrab aja jasthr sama om ini @fadiljaidi 😭 #Juanneve · GIMANA KALO KITA KASIH LANGSUNG DAN LIAT REAKSINYA ?🙄 Jual Emas Indonesia baru buka nihh di JEI Pondok Indah yaaa berikut alamatnya : 📍 Jl. Sultan Iskandar Muda No.8, Kec. Kebayoran Lama, Kota Jakarta Selatan. · Mau review shade, tapi shadenya MOP Arena wkwk seruuuuu bareng @fadiljaidi @keanuagl Nippon Paint, Best in Class!! #NipponPaint #NPBestinClass · Final Match Piala Dunia seru banget!! Terima kasih @rexonamenid udah selalu setia setiap saat bikin papa happy di Piala dunia kali ini #SetiaSetiapSaat · Laporan Kesehatan Papa · Ada orang Ganteng + Wangi · Mood hari ini · 😂❤️😂 · kamu punya paket? langsung aja kirim, dijamin harganya lebih fair #TolakBayarAngin · #Juanneve · #jasthr · #Fadiljaidi · #Juanneve · #NipponPaint · #NPBestinClass · #SetiaSetiapSaat · #TolakBayarAngin | U17: #juanneve #jasthr #fadiljaidi #nipponpaint #npbestinclass #setiasetiapsaat #tolakbayarangin | V17: N/A | W17: N/A | X17: N/A | Y17: N/A | Z17: N/A | AA17: 71.43 | AB17: 28.57 | AC17: 21 | AD17: Indonesia | AE17: 80 | AF17: 5 | AG17: Magelang | AH17: 50 | AI17: Pontianak | AJ17: 50 | AK17: N/A | AL17: N/A | AM17: 100 | AN17: 10.8 | AO17: N/A | AP17: N/A | AQ17: 9.1 | AR17: 18.2 | AS17: 9.1 | AT17: N/A | AU17: N/A | AV17: N/A | AW17: 18.2 | AX17: N/A | AY17: N/A | AZ17: N/A | BA17: N/A | BB17: N/A | BC17: 18.2 | BD17: 18.2 | BE17: N/A | BF17: 9.1 | BG17: 3.07 | BH17: kol_directory.engagement_rate | BI17: 10433740 | BJ17: 7989419 | BK17: N/A | BL17: 6 | BM17: 6.67 | BN17: 27 | BO17: Yes | BP17: 0.0038 | BQ17: 0 | BR17: N/A | BS17: 58 | BT17: 64 | BU17: 53 | BV17: N/A | BW17: =ROUND((IF(ISNUMBER(KOL_Source_Data!$K$17),1,IF(AND(ISTEXT(KOL_Source_Data!$K$17),KOL_Source_Data!$K$17<>"N/A"),1,0))+IF(ISNUMBER(KOL_Source_Data!$BG$17),1,IF(AND(ISTEXT(KOL_Source_Data!$BG$17),KOL_Source_Data!$BG$17<>"N/A"),1,0))+IF(ISNUMBER(KOL_Source_Data!$BI$17),1,IF(AND(ISTEXT(KOL_Source_Data!$BI$17),KOL_Source_Data!$BI$17<>"N/A"),1,0))+IF(ISNUMBER(KOL_Source_Data!$BK$17),1,IF(AND(ISTEXT(KOL_Source_Data!$BK$17),KOL_Source_Data!$BK$17<>"N/A"),1,0))+IF(ISNUMBER(KOL_Source_Data!$AA$17),1,IF(AND(ISTEXT(KOL_Source_Data!$AA$17),KOL_Source_Data!$AA$17<>"N/A"),1,0))+IF(ISNUMBER(KOL_Source_Data!$AE$17),1,IF(AND(ISTEXT(KOL_Source_Data!$AE$17),KOL_Source_Data!$AE$17<>"N/A"),1,0))+IF(ISNUMBER(KOL_Source_Data!$AH$17),1,IF(AND(ISTEXT(KOL_Source_Data!$AH$17),KOL_Source_Data!$AH$17<>"N/A"),1,0))+IF(ISNUMBER(KOL_Source_Data!$AN$17),1,IF(AND(ISTEXT(KOL_Source_Data!$AN$17),KOL_Source_Data!$AN$17<>"N/A"),1,0))+IF(ISNUMBER(KOL_Source_Data!$BS$17),1,IF(AND(ISTEXT(KOL_Source_Data!$BS$17),KOL_Source_Data!$BS$17<>"N/A"),1,0))+IF(ISNUMBER(KOL_Source_Data!$BT$17),1,IF(AND(ISTEXT(KOL_Source_Data!$BT$17),KOL_Source_Data!$BT$17<>"N/A"),1,0))+IF(ISNUMBER(KOL_Source_Data!$BU$17),1,IF(AND(ISTEXT(KOL_Source_Data!$BU$17),KOL_Source_Data!$BU$17<>"N/A"),1,0))+IF(ISNUMBER(KOL_Source_Data!$BM$17),1,IF(AND(ISTEXT(KOL_Source_Data!$BM$17),KOL_Source_Data!$BM$17<>"N/A"),1,0)))/12*100,0) | BX17: =IF(KOL_Source_Data!$BW$17>=Lookup_Lists!$D$159,"High",IF(KOL_Source_Data!$BW$17>=Lookup_Lists!$D$160,"Medium","Limited Data")) | BY17: no category: kol_categories carries none and caption evidence did not reach the threshold
A18: KOL-13 | B18: @saalhaerid | C18: @saalhaerid | D18: saalhaerid | E18: Instagram | F18: FOUND | G18: 2249679 | H18: =IFERROR(INDEX(Lookup_Lists!$A$96:$A$100,MATCH(KOL_Source_Data!$G$18,Lookup_Lists!$B$96:$B$100,1)),"N/A") | I18: Yes | J18: N/A | K18: N/A | L18: N/A | M18: N/A | N18: N/A | O18: N/A | P18: N/A | Q18: N/A | R18: N/A | S18: PP/ENDORSE @prabmanagement Campaign/Kerjasama DM @adminabadi @pentolplatkt @tofu_brutal @gorenganpokgeboy | T18: 🤣🤣🤣 #sadin · kesayanganku😍 #sadin · 🤣🤣🤣 #sadin · langsung ketar ketir😭 #sadin · baru kepikiran🤭🤣 #sadin · 😭😭😭 #sadin · Dua hati, satu janji, dan seumur hidup untuk dijalani. Untuk cinta, tawa, dan awal selamanya kita yang dimulai hari ini. · jika tujuannya sama, perasaanya sama, sebesar apapun rintangan dan cobaanya pasti akan sampai juga. #sadin · a new chapter begins. #sadin · #sadin · #sadin · #sadin · #sadin · #sadin · #sadin · #sadin · #sadin | U18: #sadin | V18: N/A | W18: N/A | X18: N/A | Y18: N/A | Z18: N/A | AA18: 20 | AB18: 80 | AC18: 30 | AD18: Indonesia | AE18: 55.6 | AF18: 9 | AG18: N/A | AH18: N/A | AI18: N/A | AJ18: N/A | AK18: N/A | AL18: N/A | AM18: N/A | AN18: 7 | AO18: N/A | AP18: N/A | AQ18: N/A | AR18: N/A | AS18: 14.3 | AT18: N/A | AU18: N/A | AV18: N/A | AW18: N/A | AX18: N/A | AY18: 14.3 | AZ18: 14.3 | BA18: N/A | BB18: N/A | BC18: 42.9 | BD18: 14.3 | BE18: N/A | BF18: N/A | BG18: 0.72 | BH18: kol_directory.engagement_rate | BI18: 501299.75 | BJ18: 335177.5 | BK18: 24.1573 | BL18: 8 | BM18: 1.03 | BN18: 233 | BO18: Yes | BP18: 0 | BQ18: 0 | BR18: N/A | BS18: 59 | BT18: 48 | BU18: 70 | BV18: N/A | BW18: =ROUND((IF(ISNUMBER(KOL_Source_Data!$K$18),1,IF(AND(ISTEXT(KOL_Source_Data!$K$18),KOL_Source_Data!$K$18<>"N/A"),1,0))+IF(ISNUMBER(KOL_Source_Data!$BG$18),1,IF(AND(ISTEXT(KOL_Source_Data!$BG$18),KOL_Source_Data!$BG$18<>"N/A"),1,0))+IF(ISNUMBER(KOL_Source_Data!$BI$18),1,IF(AND(ISTEXT(KOL_Source_Data!$BI$18),KOL_Source_Data!$BI$18<>"N/A"),1,0))+IF(ISNUMBER(KOL_Source_Data!$BK$18),1,IF(AND(ISTEXT(KOL_Source_Data!$BK$18),KOL_Source_Data!$BK$18<>"N/A"),1,0))+IF(ISNUMBER(KOL_Source_Data!$AA$18),1,IF(AND(ISTEXT(KOL_Source_Data!$AA$18),KOL_Source_Data!$AA$18<>"N/A"),1,0))+IF(ISNUMBER(KOL_Source_Data!$AE$18),1,IF(AND(ISTEXT(KOL_Source_Data!$AE$18),KOL_Source_Data!$AE$18<>"N/A"),1,0))+IF(ISNUMBER(KOL_Source_Data!$AH$18),1,IF(AND(ISTEXT(KOL_Source_Data!$AH$18),KOL_Source_Data!$AH$18<>"N/A"),1,0))+IF(ISNUMBER(KOL_Source_Data!$AN$18),1,IF(AND(ISTEXT(KOL_Source_Data!$AN$18),KOL_Source_Data!$AN$18<>"N/A"),1,0))+IF(ISNUMBER(KOL_Source_Data!$BS$18),1,IF(AND(ISTEXT(KOL_Source_Data!$BS$18),KOL_Source_Data!$BS$18<>"N/A"),1,0))+IF(ISNUMBER(KOL_Source_Data!$BT$18),1,IF(AND(ISTEXT(KOL_Source_Data!$BT$18),KOL_Source_Data!$BT$18<>"N/A"),1,0))+IF(ISNUMBER(KOL_Source_Data!$BU$18),1,IF(AND(ISTEXT(KOL_Source_Data!$BU$18),KOL_Source_Data!$BU$18<>"N/A"),1,0))+IF(ISNUMBER(KOL_Source_Data!$BM$18),1,IF(AND(ISTEXT(KOL_Source_Data!$BM$18),KOL_Source_Data!$BM$18<>"N/A"),1,0)))/12*100,0) | BX18: =IF(KOL_Source_Data!$BW$18>=Lookup_Lists!$D$159,"High",IF(KOL_Source_Data!$BW$18>=Lookup_Lists!$D$160,"Medium","Limited Data")) | BY18: no category: kol_categories carries none and caption evidence did not reach the threshold
A19: KOL-14 | B19: @jharnabhagwani | C19: @jharnabhagwani | D19: jharnabhagwani | E19: TikTok | F19: FOUND | G19: 13200000 | H19: =IFERROR(INDEX(Lookup_Lists!$A$96:$A$100,MATCH(KOL_Source_Data!$G$19,Lookup_Lists!$B$96:$B$100,1)),"N/A") | I19: Yes | J19: N/A | K19: N/A | L19: N/A | M19: N/A | N19: Makeup, City & Culture, Domestic Travel | O19: Beauty 4pt [makeup (caption); makeup (hashtag)] · Travel 3pt [budaya (caption)] | P19: N/A | Q19: N/A | R19: N/A | S19: N/A | T19: Last one! 🕷️❣️ #spiderman · Dirgahayu Republik Indonesia 🇮🇩❤️ Indonesia yang penuh warna, budaya, dan cerita. Merdeka! 🇮🇩✨ · REBIRTH 🕷️🕸️ #spidermanbrandnewday #makeup #transition · Spider woman 🕷️❣️ #spidermanbrandnewday #spiderman #makeup #trend · Thank you @Urban Decay Indonesia having me at The Baddest Party of the Year! Always a blast celebrating bold looks with the best team. #urbandecayid #UDbaddies · Mommy 🕷️ and Baby Spidey 🕸️ #spiderman #makeup #transition · The Odyssey 👁️ #odyssey #makeup #transition · Devdas Makeup Transition 🪔 Paro’s pov ✨ • #devdas #indianmakeup #transition #bollywood · Cleopatra x The Mummy 🪲⚰️ One of the most requests I’ve ever received on a trend!! Better late than never right? 🫣 I tried to putting my own twist on it, and learned so many new things along the way 🥹💛 Hope you enjoyed watching! Trend setter: @ _marianazambrano Shout out to all the amazing content creators who did this trend! And Thank you for tagging and waiting for me to join in ✨ · Here’s my version of the #Asoka trend! 🫣♥️ Hope you guys like it 🥰 #jharnabhagwani #makeuptransition · #spiderman · #spidermanbrandnewday · #makeup · #transition · #spidermanbrandnewday · #spiderman · #makeup · #trend · #urbandecayid · #udbaddies · #spiderman · #makeup · #transition · #odyssey · #makeup · #transition · #devdas · #indianmakeup · #transition · #bollywood · #asoka · #jharnabhagwani · #makeuptransition | U19: #spiderman #spidermanbrandnewday #makeup #transition #trend #urbandecayid #udbaddies #odyssey #devdas #indianmakeup #bollywood #asoka #jharnabhagwani #makeuptransition | V19: N/A | W19: N/A | X19: N/A | Y19: N/A | Z19: N/A | AA19: 69.23 | AB19: 30.77 | AC19: 26 | AD19: Indonesia | AE19: 40 | AF19: 10 | AG19: Tulungagung | AH19: 100 | AI19: N/A | AJ19: N/A | AK19: N/A | AL19: N/A | AM19: 100 | AN19: 18.3 | AO19: 15.8 | AP19: N/A | AQ19: 21.1 | AR19: N/A | AS19: N/A | AT19: N/A | AU19: 10.5 | AV19: N/A | AW19: N/A | AX19: 15.8 | AY19: 5.3 | AZ19: 10.5 | BA19: N/A | BB19: 5.3 | BC19: 10.5 | BD19: N/A | BE19: 5.3 | BF19: N/A | BG19: 0.19 | BH19: l2_gold.kol_profile_card.monitoring_er_pct | BI19: 47997390 | BJ19: 354300 | BK19: 1.7595 | BL19: N/A | BM19: 0.35 | BN19: 851 | BO19: Yes | BP19: 0 | BQ19: 10 | BR19: N/A | BS19: 67 | BT19: 56 | BU19: 78 | BV19: N/A | BW19: =ROUND((IF(ISNUMBER(KOL_Source_Data!$K$19),1,IF(AND(ISTEXT(KOL_Source_Data!$K$19),KOL_Source_Data!$K$19<>"N/A"),1,0))+IF(ISNUMBER(KOL_Source_Data!$BG$19),1,IF(AND(ISTEXT(KOL_Source_Data!$BG$19),KOL_Source_Data!$BG$19<>"N/A"),1,0))+IF(ISNUMBER(KOL_Source_Data!$BI$19),1,IF(AND(ISTEXT(KOL_Source_Data!$BI$19),KOL_Source_Data!$BI$19<>"N/A"),1,0))+IF(ISNUMBER(KOL_Source_Data!$BK$19),1,IF(AND(ISTEXT(KOL_Source_Data!$BK$19),KOL_Source_Data!$BK$19<>"N/A"),1,0))+IF(ISNUMBER(KOL_Source_Data!$AA$19),1,IF(AND(ISTEXT(KOL_Source_Data!$AA$19),KOL_Source_Data!$AA$19<>"N/A"),1,0))+IF(ISNUMBER(KOL_Source_Data!$AE$19),1,IF(AND(ISTEXT(KOL_Source_Data!$AE$19),KOL_Source_Data!$AE$19<>"N/A"),1,0))+IF(ISNUMBER(KOL_Source_Data!$AH$19),1,IF(AND(ISTEXT(KOL_Source_Data!$AH$19),KOL_Source_Data!$AH$19<>"N/A"),1,0))+IF(ISNUMBER(KOL_Source_Data!$AN$19),1,IF(AND(ISTEXT(KOL_Source_Data!$AN$19),KOL_Source_Data!$AN$19<>"N/A"),1,0))+IF(ISNUMBER(KOL_Source_Data!$BS$19),1,IF(AND(ISTEXT(KOL_Source_Data!$BS$19),KOL_Source_Data!$BS$19<>"N/A"),1,0))+IF(ISNUMBER(KOL_Source_Data!$BT$19),1,IF(AND(ISTEXT(KOL_Source_Data!$BT$19),KOL_Source_Data!$BT$19<>"N/A"),1,0))+IF(ISNUMBER(KOL_Source_Data!$BU$19),1,IF(AND(ISTEXT(KOL_Source_Data!$BU$19),KOL_Source_Data!$BU$19<>"N/A"),1,0))+IF(ISNUMBER(KOL_Source_Data!$BM$19),1,IF(AND(ISTEXT(KOL_Source_Data!$BM$19),KOL_Source_Data!$BM$19<>"N/A"),1,0)))/12*100,0) | BX19: =IF(KOL_Source_Data!$BW$19>=Lookup_Lists!$D$159,"High",IF(KOL_Source_Data!$BW$19>=Lookup_Lists!$D$160,"Medium","Limited Data")) | BY19: no category: kol_categories carries none and caption evidence did not reach the threshold
A20: KOL-15 | B20: @sptrakori_ | C20: @sptrakori_ | D20: sptrakori_ | E20: TikTok | F20: FOUND | G20: 13100000 | H20: =IFERROR(INDEX(Lookup_Lists!$A$96:$A$100,MATCH(KOL_Source_Data!$G$20,Lookup_Lists!$B$96:$B$100,1)),"N/A") | I20: Yes | J20: Entertainment | K20: Entertainment | L20: live | M20: N/A | N20: Kids & Family | O20: Parenting 3pt [anak (caption)] | P20: N/A | Q20: N/A | R20: N/A | S20: N/A | T20: uncle sama enduw jalan jalan di Bali Farm🥰 #sptrakori_ #enduw #korizen · snack ini emang untuk perempuan di seluruh muka bumi de kayaknya🥲#snackterserah · kalo di culik tapi ditidurinnya diatas @TURU sih mau yaaa😗 #sptrakori_ #korizen · anak kecil belom boleh pacaran yah😛 #sptrakori_ #korizen · pertama kali enduw berenang dirumah uncle😍 #sptrakori_ #enduw · ga pernah se-terharu ini🥹😭❤️ makasi banyak semuanyaa🫶🏻 #sptrakori_ · PAPAPA ULALALA😛 · Kalo sampe crush kalian kayak gini mau ges?@Garnier Indonesia #MomenPalingNyerah #HelloMochiSkin #GarnierDryTouchCream #skin · maapin ya vlognya panjang, biar puas nontonnya hahaha😆 #sptrakori_ #korizen · ASMR acara Melaspas dan Birthday, 13.08.2026 #sptrakori_ #korizen · #sptrakori_ · #enduw · #korizen · #snackterserah · #sptrakori_ · #korizen · #sptrakori_ · #korizen · #sptrakori_ · #enduw · #sptrakori_ · #momenpalingnyerah · #hellomochiskin · #garnierdrytouchcream · #skin · #sptrakori_ · #korizen · #sptrakori_ · #korizen | U20: #sptrakori_ #enduw #korizen #snackterserah #momenpalingnyerah #hellomochiskin #garnierdrytouchcream #skin | V20: N/A | W20: N/A | X20: N/A | Y20: N/A | Z20: N/A | AA20: 80.65 | AB20: 19.35 | AC20: 31 | AD20: Indonesia | AE20: 81.3 | AF20: 16 | AG20: Garut | AH20: 33.3 | AI20: Palembang | AJ20: 33.3 | AK20: Tangerang | AL20: 33.3 | AM20: 100 | AN20: 13.9 | AO20: N/A | AP20: N/A | AQ20: N/A | AR20: 14.3 | AS20: 14.3 | AT20: N/A | AU20: N/A | AV20: N/A | AW20: N/A | AX20: 14.3 | AY20: N/A | AZ20: 21.4 | BA20: 14.3 | BB20: N/A | BC20: 14.3 | BD20: N/A | BE20: N/A | BF20: 7.1 | BG20: 0.6 | BH20: l2_gold.kol_profile_card.monitoring_er_pct | BI20: 843860 | BJ20: 495650 | BK20: 4.1775 | BL20: N/A | BM20: 50 | BN20: 6 | BO20: No | BP20: 0 | BQ20: 10 | BR20: N/A | BS20: 76 | BT20: 59 | BU20: 93 | BV20: N/A | BW20: =ROUND((IF(ISNUMBER(KOL_Source_Data!$K$20),1,IF(AND(ISTEXT(KOL_Source_Data!$K$20),KOL_Source_Data!$K$20<>"N/A"),1,0))+IF(ISNUMBER(KOL_Source_Data!$BG$20),1,IF(AND(ISTEXT(KOL_Source_Data!$BG$20),KOL_Source_Data!$BG$20<>"N/A"),1,0))+IF(ISNUMBER(KOL_Source_Data!$BI$20),1,IF(AND(ISTEXT(KOL_Source_Data!$BI$20),KOL_Source_Data!$BI$20<>"N/A"),1,0))+IF(ISNUMBER(KOL_Source_Data!$BK$20),1,IF(AND(ISTEXT(KOL_Source_Data!$BK$20),KOL_Source_Data!$BK$20<>"N/A"),1,0))+IF(ISNUMBER(KOL_Source_Data!$AA$20),1,IF(AND(ISTEXT(KOL_Source_Data!$AA$20),KOL_Source_Data!$AA$20<>"N/A"),1,0))+IF(ISNUMBER(KOL_Source_Data!$AE$20),1,IF(AND(ISTEXT(KOL_Source_Data!$AE$20),KOL_Source_Data!$AE$20<>"N/A"),1,0))+IF(ISNUMBER(KOL_Source_Data!$AH$20),1,IF(AND(ISTEXT(KOL_Source_Data!$AH$20),KOL_Source_Data!$AH$20<>"N/A"),1,0))+IF(ISNUMBER(KOL_Source_Data!$AN$20),1,IF(AND(ISTEXT(KOL_Source_Data!$AN$20),KOL_Source_Data!$AN$20<>"N/A"),1,0))+IF(ISNUMBER(KOL_Source_Data!$BS$20),1,IF(AND(ISTEXT(KOL_Source_Data!$BS$20),KOL_Source_Data!$BS$20<>"N/A"),1,0))+IF(ISNUMBER(KOL_Source_Data!$BT$20),1,IF(AND(ISTEXT(KOL_Source_Data!$BT$20),KOL_Source_Data!$BT$20<>"N/A"),1,0))+IF(ISNUMBER(KOL_Source_Data!$BU$20),1,IF(AND(ISTEXT(KOL_Source_Data!$BU$20),KOL_Source_Data!$BU$20<>"N/A"),1,0))+IF(ISNUMBER(KOL_Source_Data!$BM$20),1,IF(AND(ISTEXT(KOL_Source_Data!$BM$20),KOL_Source_Data!$BM$20<>"N/A"),1,0)))/12*100,0) | BX20: =IF(KOL_Source_Data!$BW$20>=Lookup_Lists!$D$159,"High",IF(KOL_Source_Data!$BW$20>=Lookup_Lists!$D$160,"Medium","Limited Data")) | BY20: cadence unusable: 50/month extrapolated from 6 observed day(s)
A21: KOL-16 | B21: @lalitahutami | C21: @lalitahutami | D21: lalitahutami | E21: TikTok | F21: FOUND | G21: 12700000 | H21: =IFERROR(INDEX(Lookup_Lists!$A$96:$A$100,MATCH(KOL_Source_Data!$G$21,Lookup_Lists!$B$96:$B$100,1)),"N/A") | I21: Yes | J21: N/A | K21: N/A | L21: N/A | M21: N/A | N21: N/A | O21: Education 1pt [belajar (caption)] · Lifestyle 1pt [daily (caption)] | P21: N/A | Q21: N/A | R21: N/A | S21: N/A | T21: ashoyyy 🤙🏼 @Ibnu Wardani · CAPEK BGT NGETAWAIN MASNU 😭 @Ibnu Wardani · Lift Trend💖 @Ibnu Wardani @Alvarazka Antarsukha Wardani · Pengen sedikit cerita sama kalian 🥹 hampir mau nyerah, tapi untung ada @Garnier Indonesia ✨ #MomenPalingNyerah #HelloMochiSkin #GarnierDryTouchCream #Skin · Zuzurrr bgt ganyangka sampe abis segini🤣 untung aja sekarang pake @ulike.indonesia 😋🫶🏻 #Ulike #Ulikeid #UlikeIPL · Hubungan saling effort😊👊❤️ @Ibnu Wardani @Alvarazka Antarsukha Wardani @Ibnu Lita daily · hasil belajar 5menit ☺️🫶🏻 · Hmm jadi percaya siapa yaa?🙄 @iniristamoritaa @Ibnu Wardani #MertuaMenantuShow · Cuma mau liatin video doang loh😭 @Ibnu Wardani @Alvarazka Antarsukha Wardani · 🫶🏻🥲 @Ibnu Wardani @Alvarazka Antarsukha Wardani · #momenpalingnyerah · #hellomochiskin · #garnierdrytouchcream · #skin · #ulike · #ulikeid · #ulikeipl · #mertuamenantushow | U21: #momenpalingnyerah #hellomochiskin #garnierdrytouchcream #skin #ulike #ulikeid #ulikeipl #mertuamenantushow | V21: N/A | W21: N/A | X21: N/A | Y21: N/A | Z21: N/A | AA21: 66.67 | AB21: 33.33 | AC21: 21 | AD21: Indonesia | AE21: 70 | AF21: 10 | AG21: Ende | AH21: 50 | AI21: Sulawesi Selatan | AJ21: 50 | AK21: N/A | AL21: N/A | AM21: 100 | AN21: 12.7 | AO21: N/A | AP21: N/A | AQ21: 7.7 | AR21: 7.7 | AS21: N/A | AT21: 7.7 | AU21: 7.7 | AV21: N/A | AW21: N/A | AX21: 15.4 | AY21: 7.7 | AZ21: 23.1 | BA21: N/A | BB21: N/A | BC21: 23.1 | BD21: N/A | BE21: N/A | BF21: N/A | BG21: 0.06 | BH21: l2_gold.kol_profile_card.monitoring_er_pct | BI21: 392440 | BJ21: 286800 | BK21: 0.7763 | BL21: N/A | BM21: 5.36 | BN21: 56 | BO21: Yes | BP21: 0 | BQ21: 20 | BR21: N/A | BS21: 78 | BT21: 65 | BU21: 90 | BV21: N/A | BW21: =ROUND((IF(ISNUMBER(KOL_Source_Data!$K$21),1,IF(AND(ISTEXT(KOL_Source_Data!$K$21),KOL_Source_Data!$K$21<>"N/A"),1,0))+IF(ISNUMBER(KOL_Source_Data!$BG$21),1,IF(AND(ISTEXT(KOL_Source_Data!$BG$21),KOL_Source_Data!$BG$21<>"N/A"),1,0))+IF(ISNUMBER(KOL_Source_Data!$BI$21),1,IF(AND(ISTEXT(KOL_Source_Data!$BI$21),KOL_Source_Data!$BI$21<>"N/A"),1,0))+IF(ISNUMBER(KOL_Source_Data!$BK$21),1,IF(AND(ISTEXT(KOL_Source_Data!$BK$21),KOL_Source_Data!$BK$21<>"N/A"),1,0))+IF(ISNUMBER(KOL_Source_Data!$AA$21),1,IF(AND(ISTEXT(KOL_Source_Data!$AA$21),KOL_Source_Data!$AA$21<>"N/A"),1,0))+IF(ISNUMBER(KOL_Source_Data!$AE$21),1,IF(AND(ISTEXT(KOL_Source_Data!$AE$21),KOL_Source_Data!$AE$21<>"N/A"),1,0))+IF(ISNUMBER(KOL_Source_Data!$AH$21),1,IF(AND(ISTEXT(KOL_Source_Data!$AH$21),KOL_Source_Data!$AH$21<>"N/A"),1,0))+IF(ISNUMBER(KOL_Source_Data!$AN$21),1,IF(AND(ISTEXT(KOL_Source_Data!$AN$21),KOL_Source_Data!$AN$21<>"N/A"),1,0))+IF(ISNUMBER(KOL_Source_Data!$BS$21),1,IF(AND(ISTEXT(KOL_Source_Data!$BS$21),KOL_Source_Data!$BS$21<>"N/A"),1,0))+IF(ISNUMBER(KOL_Source_Data!$BT$21),1,IF(AND(ISTEXT(KOL_Source_Data!$BT$21),KOL_Source_Data!$BT$21<>"N/A"),1,0))+IF(ISNUMBER(KOL_Source_Data!$BU$21),1,IF(AND(ISTEXT(KOL_Source_Data!$BU$21),KOL_Source_Data!$BU$21<>"N/A"),1,0))+IF(ISNUMBER(KOL_Source_Data!$BM$21),1,IF(AND(ISTEXT(KOL_Source_Data!$BM$21),KOL_Source_Data!$BM$21<>"N/A"),1,0)))/12*100,0) | BX21: =IF(KOL_Source_Data!$BW$21>=Lookup_Lists!$D$159,"High",IF(KOL_Source_Data!$BW$21>=Lookup_Lists!$D$160,"Medium","Limited Data")) | BY21: no category: kol_categories carries none and caption evidence did not reach the threshold
A22: KOL-17 | B22: @isyanasarasvati | C22: @isyanasarasvati | D22: isyanasarasvati | E22: Instagram | F22: FOUND | G22: 12292815 | H22: =IFERROR(INDEX(Lookup_Lists!$A$96:$A$100,MATCH(KOL_Source_Data!$G$22,Lookup_Lists!$B$96:$B$100,1)),"N/A") | I22: Yes | J22: Fashion | K22: Fashion | L22: live | M22: N/A | N22: Music | O22: Entertainment 2pt [music (caption)] | P22: N/A | Q22: N/A | R22: N/A | S22: @sarasvatistage @redrose.records | T22: MANILA, WE’RE COMING! 🇵🇭 Isyana Sarasvati’s ASIA TOUR SET is making its way to @lalalafestmanila See youuuu! ❤️‍🔥🤘🏻 · seru-seruan pake menu spesial 😋 · Kangenku terobati piuu kemarin, thank youu energi isanesenna Inyooo @isyanation_ 🥹❤️‍🔥✨ #ISYANAEKLEKTIKO · The ICON Season 1 has finally come to an end! It’s been an incredible journey being one of the judges for this pilot season. Thank you @theiconindonesia_sctv for trusting me. Such an honor to witness so many incredible talents and watch them grow stronger EVERY single day. Congratulationsss to @theicon_felicia , @theicon_vedra , and all the contestants. You GUYS ARE ONE OF A KIND! Thank you for bringing such a breath of fresh air to the music scene. I’m officially a fan of you both. Welcome to the club! 🖤🫶🏻✨🤘🏻🎤🎵 photos by @lukasandre0306 · Honored to be performing at the Yamaha Gala Concert 2026 in Tokyo! 🇯🇵🫶🏻✨ As a yamaha music school alumna, it means so much to return and celebrate music alongside incredible musicians. Grateful to represent Indonesia w/ @kenanloui as the only two artists joining from overseas. See you in Tokyo!! · KOREAAAA! YESTERDAY WAS UNREAL! YOUR ENERGY WAS OUT OF THIS WORLD! One of the best crowds I’ve had this year! KAMSAMNIDA, YOROBUNNN!! @pentaportrf 🤘🏻✨🇰🇷 It was my second time performing in Korea, and once again, it felt so unreal to see how much you appreciated my music. I truly hope I can come back again someday! #IsyanaSarasvatiAsiaTour2026 Photos by team @pentaportrf | U22: #isyanaeklektiko #isyanasarasvatiasiatour2026 #isyanasarasvati #sarasvatistage #eklektikoisyana #isyana5thalbum | V22: N/A | W22: N/A | X22: N/A | Y22: N/A | Z22: N/A | AA22: 38.46 | AB22: 61.54 | AC22: 26 | AD22: Indonesia | AE22: 16.7 | AF22: 6 | AG22: N/A | AH22: N/A | AI22: N/A | AJ22: N/A | AK22: N/A | AL22: N/A | AM22: N/A | AN22: 16.3 | AO22: N/A | AP22: 5.9 | AQ22: N/A | AR22: 11.8 | AS22: 5.9 | AT22: 5.9 | AU22: N/A | AV22: 5.9 | AW22: N/A | AX22: N/A | AY22: 11.8 | AZ22: 11.8 | BA22: 11.8 | BB22: 5.9 | BC22: 5.9 | BD22: N/A | BE22: 11.8 | BF22: 5.9 | BG22: 0.12 | BH22: kol_directory.engagement_rate | BI22: N/A | BJ22: N/A | BK22: N/A | BL22: 0 | BM22: N/A | BN22: N/A | BO22: N/A | BP22: -0.051 | BQ22: N/A | BR22: N/A | BS22: 59 | BT22: 52 | BU22: 66 | BV22: N/A | BW22: =ROUND((IF(ISNUMBER(KOL_Source_Data!$K$22),1,IF(AND(ISTEXT(KOL_Source_Data!$K$22),KOL_Source_Data!$K$22<>"N/A"),1,0))+IF(ISNUMBER(KOL_Source_Data!$BG$22),1,IF(AND(ISTEXT(KOL_Source_Data!$BG$22),KOL_Source_Data!$BG$22<>"N/A"),1,0))+IF(ISNUMBER(KOL_Source_Data!$BI$22),1,IF(AND(ISTEXT(KOL_Source_Data!$BI$22),KOL_Source_Data!$BI$22<>"N/A"),1,0))+IF(ISNUMBER(KOL_Source_Data!$BK$22),1,IF(AND(ISTEXT(KOL_Source_Data!$BK$22),KOL_Source_Data!$BK$22<>"N/A"),1,0))+IF(ISNUMBER(KOL_Source_Data!$AA$22),1,IF(AND(ISTEXT(KOL_Source_Data!$AA$22),KOL_Source_Data!$AA$22<>"N/A"),1,0))+IF(ISNUMBER(KOL_Source_Data!$AE$22),1,IF(AND(ISTEXT(KOL_Source_Data!$AE$22),KOL_Source_Data!$AE$22<>"N/A"),1,0))+IF(ISNUMBER(KOL_Source_Data!$AH$22),1,IF(AND(ISTEXT(KOL_Source_Data!$AH$22),KOL_Source_Data!$AH$22<>"N/A"),1,0))+IF(ISNUMBER(KOL_Source_Data!$AN$22),1,IF(AND(ISTEXT(KOL_Source_Data!$AN$22),KOL_Source_Data!$AN$22<>"N/A"),1,0))+IF(ISNUMBER(KOL_Source_Data!$BS$22),1,IF(AND(ISTEXT(KOL_Source_Data!$BS$22),KOL_Source_Data!$BS$22<>"N/A"),1,0))+IF(ISNUMBER(KOL_Source_Data!$BT$22),1,IF(AND(ISTEXT(KOL_Source_Data!$BT$22),KOL_Source_Data!$BT$22<>"N/A"),1,0))+IF(ISNUMBER(KOL_Source_Data!$BU$22),1,IF(AND(ISTEXT(KOL_Source_Data!$BU$22),KOL_Source_Data!$BU$22<>"N/A"),1,0))+IF(ISNUMBER(KOL_Source_Data!$BM$22),1,IF(AND(ISTEXT(KOL_Source_Data!$BM$22),KOL_Source_Data!$BM$22<>"N/A"),1,0)))/12*100,0) | BX22: =IF(KOL_Source_Data!$BW$22>=Lookup_Lists!$D$159,"High",IF(KOL_Source_Data!$BW$22>=Lookup_Lists!$D$160,"Medium","Limited Data")) | BY22: complete on every tracked field
A23: KOL-18 | B23: @lambe_turah | C23: @lambe_turah | D23: lambe_turah | E23: Instagram | F23: FOUND | G23: 12163586 | H23: =IFERROR(INDEX(Lookup_Lists!$A$96:$A$100,MATCH(KOL_Source_Data!$G$23,Lookup_Lists!$B$96:$B$100,1)),"N/A") | I23: Yes | J23: Entertainment | K23: Entertainment | L23: live | M23: N/A | N23: N/A | O23: N/A | P23: N/A | Q23: N/A | R23: N/A | S23: GOSIP ADALAH FAKTA YANG TERTUNDA DM NO PICT = HOAX SPAM = BLOCK | T23: Bisa sekalian hiling nehhh... · Lagi banyak kejadian di laut.. · Pake sabun.... · Ka kanwil pajak lhoooo..... · What happen aya naon?🤔🤔 · Pray For NTT 🙏🙏 · Klean desil berapa nderr??? · Siappp grak.... · Semangat kakak 💪💪 · Klean desil berapa nderr??? | U23: N/A | V23: N/A | W23: N/A | X23: N/A | Y23: N/A | Z23: N/A | AA23: 45 | AB23: 55 | AC23: 20 | AD23: Indonesia | AE23: 90 | AF23: 10 | AG23: Padang | AH23: 33.3 | AI23: Palu | AJ23: 33.3 | AK23: Samarinda | AL23: 33.3 | AM23: 100 | AN23: 15.5 | AO23: N/A | AP23: N/A | AQ23: 6.3 | AR23: 31.3 | AS23: 6.3 | AT23: N/A | AU23: 6.3 | AV23: N/A | AW23: N/A | AX23: 6.3 | AY23: 6.3 | AZ23: 12.5 | BA23: 6.3 | BB23: N/A | BC23: 12.5 | BD23: N/A | BE23: 6.3 | BF23: N/A | BG23: 0.08 | BH23: kol_directory.engagement_rate | BI23: N/A | BJ23: N/A | BK23: N/A | BL23: 10 | BM23: 300 | BN23: 1 | BO23: No | BP23: 0.0343 | BQ23: 0 | BR23: N/A | BS23: 63 | BT23: 52 | BU23: 74 | BV23: N/A | BW23: =ROUND((IF(ISNUMBER(KOL_Source_Data!$K$23),1,IF(AND(ISTEXT(KOL_Source_Data!$K$23),KOL_Source_Data!$K$23<>"N/A"),1,0))+IF(ISNUMBER(KOL_Source_Data!$BG$23),1,IF(AND(ISTEXT(KOL_Source_Data!$BG$23),KOL_Source_Data!$BG$23<>"N/A"),1,0))+IF(ISNUMBER(KOL_Source_Data!$BI$23),1,IF(AND(ISTEXT(KOL_Source_Data!$BI$23),KOL_Source_Data!$BI$23<>"N/A"),1,0))+IF(ISNUMBER(KOL_Source_Data!$BK$23),1,IF(AND(ISTEXT(KOL_Source_Data!$BK$23),KOL_Source_Data!$BK$23<>"N/A"),1,0))+IF(ISNUMBER(KOL_Source_Data!$AA$23),1,IF(AND(ISTEXT(KOL_Source_Data!$AA$23),KOL_Source_Data!$AA$23<>"N/A"),1,0))+IF(ISNUMBER(KOL_Source_Data!$AE$23),1,IF(AND(ISTEXT(KOL_Source_Data!$AE$23),KOL_Source_Data!$AE$23<>"N/A"),1,0))+IF(ISNUMBER(KOL_Source_Data!$AH$23),1,IF(AND(ISTEXT(KOL_Source_Data!$AH$23),KOL_Source_Data!$AH$23<>"N/A"),1,0))+IF(ISNUMBER(KOL_Source_Data!$AN$23),1,IF(AND(ISTEXT(KOL_Source_Data!$AN$23),KOL_Source_Data!$AN$23<>"N/A"),1,0))+IF(ISNUMBER(KOL_Source_Data!$BS$23),1,IF(AND(ISTEXT(KOL_Source_Data!$BS$23),KOL_Source_Data!$BS$23<>"N/A"),1,0))+IF(ISNUMBER(KOL_Source_Data!$BT$23),1,IF(AND(ISTEXT(KOL_Source_Data!$BT$23),KOL_Source_Data!$BT$23<>"N/A"),1,0))+IF(ISNUMBER(KOL_Source_Data!$BU$23),1,IF(AND(ISTEXT(KOL_Source_Data!$BU$23),KOL_Source_Data!$BU$23<>"N/A"),1,0))+IF(ISNUMBER(KOL_Source_Data!$BM$23),1,IF(AND(ISTEXT(KOL_Source_Data!$BM$23),KOL_Source_Data!$BM$23<>"N/A"),1,0)))/12*100,0) | BX23: =IF(KOL_Source_Data!$BW$23>=Lookup_Lists!$D$159,"High",IF(KOL_Source_Data!$BW$23>=Lookup_Lists!$D$160,"Medium","Limited Data")) | BY23: cadence unusable: 300/month extrapolated from 1 observed day(s)
A24: KOL-19 | B24: @ditanganu | C24: @ditanganu | D24: ditanganu | E24: TikTok | F24: FOUND | G24: 12100000 | H24: =IFERROR(INDEX(Lookup_Lists!$A$96:$A$100,MATCH(KOL_Source_Data!$G$24,Lookup_Lists!$B$96:$B$100,1)),"N/A") | I24: Yes | J24: N/A | K24: N/A | L24: N/A | M24: N/A | N24: N/A | O24: Finance 1pt [uang (caption)] · Food 1pt [makanan (caption)] | P24: N/A | Q24: N/A | R24: N/A | S24: N/A | T24: TUTUP GORDEN LANJUT TIDUR · HARUS PUNYA INI DI RUMAH · COCOK BUAT KALIAN YANG SUKA FOTO · KANGEN BANGET MASA ITU · KALAU KE MAKANAN UANG SELALU ADA · BANGGA DENGAN PENCAPAIANKU · BISA DI PINDAHIN KEMANAPUN · YAUDAH AKU MINTA MAAF · SIAP JALAN JALAN · NYESEL MAKAN DI LUAR | U24: N/A | V24: N/A | W24: N/A | X24: N/A | Y24: N/A | Z24: N/A | AA24: 65.62 | AB24: 34.38 | AC24: 32 | AD24: Indonesia | AE24: 58.3 | AF24: 12 | AG24: N/A | AH24: N/A | AI24: N/A | AJ24: N/A | AK24: N/A | AL24: N/A | AM24: N/A | AN24: 7 | AO24: N/A | AP24: N/A | AQ24: N/A | AR24: N/A | AS24: N/A | AT24: N/A | AU24: N/A | AV24: N/A | AW24: 28.6 | AX24: N/A | AY24: N/A | AZ24: 14.3 | BA24: N/A | BB24: 14.3 | BC24: 42.9 | BD24: N/A | BE24: N/A | BF24: N/A | BG24: 0.06 | BH24: l2_gold.kol_profile_card.monitoring_er_pct | BI24: 96298.4 | BJ24: 66800 | BK24: 0.6463 | BL24: N/A | BM24: 150 | BN24: 2 | BO24: No | BP24: 0 | BQ24: 20 | BR24: N/A | BS24: 70 | BT24: 57 | BU24: 82 | BV24: N/A | BW24: =ROUND((IF(ISNUMBER(KOL_Source_Data!$K$24),1,IF(AND(ISTEXT(KOL_Source_Data!$K$24),KOL_Source_Data!$K$24<>"N/A"),1,0))+IF(ISNUMBER(KOL_Source_Data!$BG$24),1,IF(AND(ISTEXT(KOL_Source_Data!$BG$24),KOL_Source_Data!$BG$24<>"N/A"),1,0))+IF(ISNUMBER(KOL_Source_Data!$BI$24),1,IF(AND(ISTEXT(KOL_Source_Data!$BI$24),KOL_Source_Data!$BI$24<>"N/A"),1,0))+IF(ISNUMBER(KOL_Source_Data!$BK$24),1,IF(AND(ISTEXT(KOL_Source_Data!$BK$24),KOL_Source_Data!$BK$24<>"N/A"),1,0))+IF(ISNUMBER(KOL_Source_Data!$AA$24),1,IF(AND(ISTEXT(KOL_Source_Data!$AA$24),KOL_Source_Data!$AA$24<>"N/A"),1,0))+IF(ISNUMBER(KOL_Source_Data!$AE$24),1,IF(AND(ISTEXT(KOL_Source_Data!$AE$24),KOL_Source_Data!$AE$24<>"N/A"),1,0))+IF(ISNUMBER(KOL_Source_Data!$AH$24),1,IF(AND(ISTEXT(KOL_Source_Data!$AH$24),KOL_Source_Data!$AH$24<>"N/A"),1,0))+IF(ISNUMBER(KOL_Source_Data!$AN$24),1,IF(AND(ISTEXT(KOL_Source_Data!$AN$24),KOL_Source_Data!$AN$24<>"N/A"),1,0))+IF(ISNUMBER(KOL_Source_Data!$BS$24),1,IF(AND(ISTEXT(KOL_Source_Data!$BS$24),KOL_Source_Data!$BS$24<>"N/A"),1,0))+IF(ISNUMBER(KOL_Source_Data!$BT$24),1,IF(AND(ISTEXT(KOL_Source_Data!$BT$24),KOL_Source_Data!$BT$24<>"N/A"),1,0))+IF(ISNUMBER(KOL_Source_Data!$BU$24),1,IF(AND(ISTEXT(KOL_Source_Data!$BU$24),KOL_Source_Data!$BU$24<>"N/A"),1,0))+IF(ISNUMBER(KOL_Source_Data!$BM$24),1,IF(AND(ISTEXT(KOL_Source_Data!$BM$24),KOL_Source_Data!$BM$24<>"N/A"),1,0)))/12*100,0) | BX24: =IF(KOL_Source_Data!$BW$24>=Lookup_Lists!$D$159,"High",IF(KOL_Source_Data!$BW$24>=Lookup_Lists!$D$160,"Medium","Limited Data")) | BY24: no category: kol_categories carries none and caption evidence did not reach the threshold · cadence unusable: 150/month extrapolated from 2 observed day(s)
A25: KOL-20 | B25: @hesfinatia | C25: @hesfinatia | D25: hesfinatia | E25: TikTok | F25: FOUND | G25: 12000000 | H25: =IFERROR(INDEX(Lookup_Lists!$A$96:$A$100,MATCH(KOL_Source_Data!$G$25,Lookup_Lists!$B$96:$B$100,1)),"N/A") | I25: No | J25: Entertainment | K25: Entertainment | L25: live | M25: N/A | N25: N/A | O25: N/A | P25: N/A | Q25: N/A | R25: N/A | S25: N/A | T25: Reaksi orang” pada ngakak😭🫵🏻 #fyp · Ternyata dia gatau kopdes jadi maunya indromarets🥲🙏🏻 · bisa” nya dia baru bilang😭 #fyp · Ini hasilnya🥹🙏🏻 #fyp · Drama banget😭🙏🏻 #fakebodyy⚠️ #fakesituation⚠️️ · lah ko dia doyan😭 · Plis takut banget😭🫵🏻 #fyp · Jadi pengen nikah lagi deh😭🙏🏻 #fyp · Bridesmaid nya @Gelia Linda 🤍✨ · Banyak ngelamun gini😭 #fyp · #fyp · #fyp · #fyp · #fakebodyy⚠️ · #fakesituation⚠️️ · #fyp · #fyp · #fyp | U25: #fyp #fakebodyy⚠️ #fakesituation⚠️️ | V25: N/A | W25: N/A | X25: N/A | Y25: N/A | Z25: N/A | AA25: 90 | AB25: 10 | AC25: 20 | AD25: Indonesia | AE25: 55.6 | AF25: 9 | AG25: N/A | AH25: N/A | AI25: N/A | AJ25: N/A | AK25: N/A | AL25: N/A | AM25: N/A | AN25: 11 | AO25: N/A | AP25: N/A | AQ25: N/A | AR25: N/A | AS25: N/A | AT25: N/A | AU25: N/A | AV25: N/A | AW25: 18.2 | AX25: 9.1 | AY25: 18.2 | AZ25: 27.3 | BA25: 9.1 | BB25: N/A | BC25: 9.1 | BD25: N/A | BE25: 9.1 | BF25: N/A | BG25: 1.81 | BH25: l2_gold.kol_profile_card.monitoring_er_pct | BI25: 2383810 | BJ25: 1700000 | BK25: 16.1074 | BL25: N/A | BM25: 42.86 | BN25: 7 | BO25: No | BP25: 0.6711 | BQ25: 0 | BR25: N/A | BS25: 75 | BT25: 67 | BU25: 83 | BV25: N/A | BW25: =ROUND((IF(ISNUMBER(KOL_Source_Data!$K$25),1,IF(AND(ISTEXT(KOL_Source_Data!$K$25),KOL_Source_Data!$K$25<>"N/A"),1,0))+IF(ISNUMBER(KOL_Source_Data!$BG$25),1,IF(AND(ISTEXT(KOL_Source_Data!$BG$25),KOL_Source_Data!$BG$25<>"N/A"),1,0))+IF(ISNUMBER(KOL_Source_Data!$BI$25),1,IF(AND(ISTEXT(KOL_Source_Data!$BI$25),KOL_Source_Data!$BI$25<>"N/A"),1,0))+IF(ISNUMBER(KOL_Source_Data!$BK$25),1,IF(AND(ISTEXT(KOL_Source_Data!$BK$25),KOL_Source_Data!$BK$25<>"N/A"),1,0))+IF(ISNUMBER(KOL_Source_Data!$AA$25),1,IF(AND(ISTEXT(KOL_Source_Data!$AA$25),KOL_Source_Data!$AA$25<>"N/A"),1,0))+IF(ISNUMBER(KOL_Source_Data!$AE$25),1,IF(AND(ISTEXT(KOL_Source_Data!$AE$25),KOL_Source_Data!$AE$25<>"N/A"),1,0))+IF(ISNUMBER(KOL_Source_Data!$AH$25),1,IF(AND(ISTEXT(KOL_Source_Data!$AH$25),KOL_Source_Data!$AH$25<>"N/A"),1,0))+IF(ISNUMBER(KOL_Source_Data!$AN$25),1,IF(AND(ISTEXT(KOL_Source_Data!$AN$25),KOL_Source_Data!$AN$25<>"N/A"),1,0))+IF(ISNUMBER(KOL_Source_Data!$BS$25),1,IF(AND(ISTEXT(KOL_Source_Data!$BS$25),KOL_Source_Data!$BS$25<>"N/A"),1,0))+IF(ISNUMBER(KOL_Source_Data!$BT$25),1,IF(AND(ISTEXT(KOL_Source_Data!$BT$25),KOL_Source_Data!$BT$25<>"N/A"),1,0))+IF(ISNUMBER(KOL_Source_Data!$BU$25),1,IF(AND(ISTEXT(KOL_Source_Data!$BU$25),KOL_Source_Data!$BU$25<>"N/A"),1,0))+IF(ISNUMBER(KOL_Source_Data!$BM$25),1,IF(AND(ISTEXT(KOL_Source_Data!$BM$25),KOL_Source_Data!$BM$25<>"N/A"),1,0)))/12*100,0) | BX25: =IF(KOL_Source_Data!$BW$25>=Lookup_Lists!$D$159,"High",IF(KOL_Source_Data!$BW$25>=Lookup_Lists!$D$160,"Medium","Limited Data")) | BY25: cadence unusable: 42.86/month extrapolated from 7 observed day(s)
A26: KOL-21 | B26: @erickapinedao9 | C26: @erickapineda09 | D26: erickapineda09 | E26: TikTok | F26: FOUND (alias) | G26: 11800000 | H26: =IFERROR(INDEX(Lookup_Lists!$A$96:$A$100,MATCH(KOL_Source_Data!$G$26,Lookup_Lists!$B$96:$B$100,1)),"N/A") | I26: Yes | J26: Beauty | K26: Beauty | L26: live | M26: N/A | N26: N/A | O26: N/A | P26: N/A | Q26: N/A | R26: N/A | S26: N/A | T26: N/A | U26: N/A | V26: N/A | W26: N/A | X26: N/A | Y26: N/A | Z26: N/A | AA26: N/A | AB26: N/A | AC26: N/A | AD26: N/A | AE26: N/A | AF26: N/A | AG26: N/A | AH26: N/A | AI26: N/A | AJ26: N/A | AK26: N/A | AL26: N/A | AM26: N/A | AN26: N/A | AO26: N/A | AP26: N/A | AQ26: N/A | AR26: N/A | AS26: N/A | AT26: N/A | AU26: N/A | AV26: N/A | AW26: N/A | AX26: N/A | AY26: N/A | AZ26: N/A | BA26: N/A | BB26: N/A | BC26: N/A | BD26: N/A | BE26: N/A | BF26: N/A | BG26: N/A | BH26: N/A | BI26: N/A | BJ26: N/A | BK26: N/A | BL26: N/A | BM26: N/A | BN26: N/A | BO26: N/A | BP26: N/A | BQ26: N/A | BR26: N/A | BS26: N/A | BT26: N/A | BU26: N/A | BV26: N/A | BW26: =ROUND((IF(ISNUMBER(KOL_Source_Data!$K$26),1,IF(AND(ISTEXT(KOL_Source_Data!$K$26),KOL_Source_Data!$K$26<>"N/A"),1,0))+IF(ISNUMBER(KOL_Source_Data!$BG$26),1,IF(AND(ISTEXT(KOL_Source_Data!$BG$26),KOL_Source_Data!$BG$26<>"N/A"),1,0))+IF(ISNUMBER(KOL_Source_Data!$BI$26),1,IF(AND(ISTEXT(KOL_Source_Data!$BI$26),KOL_Source_Data!$BI$26<>"N/A"),1,0))+IF(ISNUMBER(KOL_Source_Data!$BK$26),1,IF(AND(ISTEXT(KOL_Source_Data!$BK$26),KOL_Source_Data!$BK$26<>"N/A"),1,0))+IF(ISNUMBER(KOL_Source_Data!$AA$26),1,IF(AND(ISTEXT(KOL_Source_Data!$AA$26),KOL_Source_Data!$AA$26<>"N/A"),1,0))+IF(ISNUMBER(KOL_Source_Data!$AE$26),1,IF(AND(ISTEXT(KOL_Source_Data!$AE$26),KOL_Source_Data!$AE$26<>"N/A"),1,0))+IF(ISNUMBER(KOL_Source_Data!$AH$26),1,IF(AND(ISTEXT(KOL_Source_Data!$AH$26),KOL_Source_Data!$AH$26<>"N/A"),1,0))+IF(ISNUMBER(KOL_Source_Data!$AN$26),1,IF(AND(ISTEXT(KOL_Source_Data!$AN$26),KOL_Source_Data!$AN$26<>"N/A"),1,0))+IF(ISNUMBER(KOL_Source_Data!$BS$26),1,IF(AND(ISTEXT(KOL_Source_Data!$BS$26),KOL_Source_Data!$BS$26<>"N/A"),1,0))+IF(ISNUMBER(KOL_Source_Data!$BT$26),1,IF(AND(ISTEXT(KOL_Source_Data!$BT$26),KOL_Source_Data!$BT$26<>"N/A"),1,0))+IF(ISNUMBER(KOL_Source_Data!$BU$26),1,IF(AND(ISTEXT(KOL_Source_Data!$BU$26),KOL_Source_Data!$BU$26<>"N/A"),1,0))+IF(ISNUMBER(KOL_Source_Data!$BM$26),1,IF(AND(ISTEXT(KOL_Source_Data!$BM$26),KOL_Source_Data!$BM$26<>"N/A"),1,0)))/12*100,0) | BX26: =IF(KOL_Source_Data!$BW$26>=Lookup_Lists!$D$159,"High",IF(KOL_Source_Data!$BW$26>=Lookup_Lists!$D$160,"Medium","Limited Data")) | BY26: requested @erickapinedao9; resolved to @erickapineda09 · no engagement rate on any of the three sources · no audience analysis row · no audience interest rows
A27: KOL-22 | B27: @anyageraldine | C27: @anyageraldine | D27: anyageraldine | E27: Instagram | F27: FOUND | G27: 11208273 | H27: =IFERROR(INDEX(Lookup_Lists!$A$96:$A$100,MATCH(KOL_Source_Data!$G$27,Lookup_Lists!$B$96:$B$100,1)),"N/A") | I27: Yes | J27: Lifestyle | K27: Lifestyle | L27: live | M27: N/A | N27: Career, Film & Series, Job Hunting & CV | O27: Education 5pt [interview (caption)] · Entertainment 4pt [film (caption); bioskop (caption)] | P27: N/A | Q27: N/A | R27: N/A | S27: 🇮🇩 Business inquiries: +62 811 191 8959 (ochi) Whatsapp. | T27: reminiscing 🇯🇵🥢 · Kemanapun dan kapanpun, aku gak pernah lepas dari Joiway i1 ini! Selain harganya yang affordable banget, Joiway i1 udah jadi salah satu barang essential aku yang harus selalu aku bawa😆 @joiway_id #JOIWAYi1 #JoiwayEveryday #BestDevice2026 · dululululu one-sided love story 💓🤓🫰🏻🌈🫂🦋 (doain ya ges) · Karena banyak pilihan warna, Joiway i1 bisa aku bawa untuk semua aktivitas aku! Termasuk interview kali ini, yang sampai bikin salfok🫣 #JOIWAYi1 #JoiwayEveryday #BestDevice2026 · her ego needed some fresh air 🧘🏼‍♀️🏞️🥂💅🏼✨ · #obsession 💘💘💘 · The little details make all the difference. ✨ Mulai dari apa yang kudengar dengan #OPPOEncoClip2 hingga momen yang kuabadikan dengan #OPPOFindX9s, setiap detail punya ceritanya sendiri. #EffortlessInStyle · Official Poster #Shutter 📸🧟‍♀️ Tayang 30 Oktober di Bioskop @vinogbastian__ @nikenanjanii @anyageraldine @donnyalamsyah @andrimashadi @rangganattra @dewigita01 @rukmanrosadi_ @chellibobs @nugietrilogy @iangdarmawan @nonangie @aphang_alimsudio @herwinnovianto @er1ca · Masa lalu yang kelam membuat luka yang begitu dalam di hati. Namun, Aris kembali. Kinan, Lydia... Siapa yang tersakiti kali ini? Film Layangan Putus SEGERA di bioskop! 🪁 #LayanganPutus #MDEntertainment #MDPictures · Emangnya GAMPANG cari CUAN? Adik kakak selalu punya sifat, kelakukan, tempramen, dan ambisi beda-beda. Tapi pas ada momen, harus kerja bareng melawan realita yang lebih sering bikin nangis daripada manis. Apapun itu, yang penting | U27: #joiwayi1 #joiwayeveryday #bestdevice2026 #obsession #oppoencoclip2 #oppofindx9s, #effortlessinstyle #shutter #layanganputus #mdentertainment #mdpictures #gampangcuanfilm | V27: N/A | W27: N/A | X27: N/A | Y27: N/A | Z27: N/A | AA27: 25.64 | AB27: 74.36 | AC27: 39 | AD27: Indonesia | AE27: 100 | AF27: 10 | AG27: Bali | AH27: 12.5 | AI27: Bandung | AJ27: 12.5 | AK27: Bogor | AL27: 12.5 | AM27: 100 | AN27: 24.5 | AO27: 3.8 | AP27: N/A | AQ27: 3.8 | AR27: 23.1 | AS27: N/A | AT27: N/A | AU27: 7.7 | AV27: N/A | AW27: 7.7 | AX27: N/A | AY27: 7.7 | AZ27: 7.7 | BA27: N/A | BB27: N/A | BC27: 38.5 | BD27: N/A | BE27: N/A | BF27: N/A | BG27: 0.6 | BH27: kol_directory.engagement_rate | BI27: 230981.5 | BJ27: 230981.5 | BK27: 1.5523 | BL27: 7 | BM27: 3.44 | BN27: 61 | BO27: Yes | BP27: -0.0271 | BQ27: 0 | BR27: N/A | BS27: 59 | BT27: 61 | BU27: 57 | BV27: N/A | BW27: =ROUND((IF(ISNUMBER(KOL_Source_Data!$K$27),1,IF(AND(ISTEXT(KOL_Source_Data!$K$27),KOL_Source_Data!$K$27<>"N/A"),1,0))+IF(ISNUMBER(KOL_Source_Data!$BG$27),1,IF(AND(ISTEXT(KOL_Source_Data!$BG$27),KOL_Source_Data!$BG$27<>"N/A"),1,0))+IF(ISNUMBER(KOL_Source_Data!$BI$27),1,IF(AND(ISTEXT(KOL_Source_Data!$BI$27),KOL_Source_Data!$BI$27<>"N/A"),1,0))+IF(ISNUMBER(KOL_Source_Data!$BK$27),1,IF(AND(ISTEXT(KOL_Source_Data!$BK$27),KOL_Source_Data!$BK$27<>"N/A"),1,0))+IF(ISNUMBER(KOL_Source_Data!$AA$27),1,IF(AND(ISTEXT(KOL_Source_Data!$AA$27),KOL_Source_Data!$AA$27<>"N/A"),1,0))+IF(ISNUMBER(KOL_Source_Data!$AE$27),1,IF(AND(ISTEXT(KOL_Source_Data!$AE$27),KOL_Source_Data!$AE$27<>"N/A"),1,0))+IF(ISNUMBER(KOL_Source_Data!$AH$27),1,IF(AND(ISTEXT(KOL_Source_Data!$AH$27),KOL_Source_Data!$AH$27<>"N/A"),1,0))+IF(ISNUMBER(KOL_Source_Data!$AN$27),1,IF(AND(ISTEXT(KOL_Source_Data!$AN$27),KOL_Source_Data!$AN$27<>"N/A"),1,0))+IF(ISNUMBER(KOL_Source_Data!$BS$27),1,IF(AND(ISTEXT(KOL_Source_Data!$BS$27),KOL_Source_Data!$BS$27<>"N/A"),1,0))+IF(ISNUMBER(KOL_Source_Data!$BT$27),1,IF(AND(ISTEXT(KOL_Source_Data!$BT$27),KOL_Source_Data!$BT$27<>"N/A"),1,0))+IF(ISNUMBER(KOL_Source_Data!$BU$27),1,IF(AND(ISTEXT(KOL_Source_Data!$BU$27),KOL_Source_Data!$BU$27<>"N/A"),1,0))+IF(ISNUMBER(KOL_Source_Data!$BM$27),1,IF(AND(ISTEXT(KOL_Source_Data!$BM$27),KOL_Source_Data!$BM$27<>"N/A"),1,0)))/12*100,0) | BX27: =IF(KOL_Source_Data!$BW$27>=Lookup_Lists!$D$159,"High",IF(KOL_Source_Data!$BW$27>=Lookup_Lists!$D$160,"Medium","Limited Data")) | BY27: complete on every tracked field
A28: KOL-23 | B28: @shabiraaluaadnan | C28: @shabiraalulaadnan | D28: shabiraalulaadnan | E28: TikTok | F28: FOUND (alias) | G28: 10664778 | H28: =IFERROR(INDEX(Lookup_Lists!$A$96:$A$100,MATCH(KOL_Source_Data!$G$28,Lookup_Lists!$B$96:$B$100,1)),"N/A") | I28: No | J28: N/A | K28: N/A | L28: N/A | M28: N/A | N28: N/A | O28: N/A | P28: N/A | Q28: N/A | R28: N/A | S28: N/A | T28: N/A | U28: N/A | V28: N/A | W28: N/A | X28: N/A | Y28: N/A | Z28: N/A | AA28: N/A | AB28: N/A | AC28: N/A | AD28: N/A | AE28: N/A | AF28: N/A | AG28: N/A | AH28: N/A | AI28: N/A | AJ28: N/A | AK28: N/A | AL28: N/A | AM28: N/A | AN28: N/A | AO28: N/A | AP28: N/A | AQ28: N/A | AR28: N/A | AS28: N/A | AT28: N/A | AU28: N/A | AV28: N/A | AW28: N/A | AX28: N/A | AY28: N/A | AZ28: N/A | BA28: N/A | BB28: N/A | BC28: N/A | BD28: N/A | BE28: N/A | BF28: N/A | BG28: N/A | BH28: N/A | BI28: N/A | BJ28: N/A | BK28: N/A | BL28: N/A | BM28: N/A | BN28: N/A | BO28: N/A | BP28: N/A | BQ28: N/A | BR28: N/A | BS28: N/A | BT28: N/A | BU28: N/A | BV28: N/A | BW28: =ROUND((IF(ISNUMBER(KOL_Source_Data!$K$28),1,IF(AND(ISTEXT(KOL_Source_Data!$K$28),KOL_Source_Data!$K$28<>"N/A"),1,0))+IF(ISNUMBER(KOL_Source_Data!$BG$28),1,IF(AND(ISTEXT(KOL_Source_Data!$BG$28),KOL_Source_Data!$BG$28<>"N/A"),1,0))+IF(ISNUMBER(KOL_Source_Data!$BI$28),1,IF(AND(ISTEXT(KOL_Source_Data!$BI$28),KOL_Source_Data!$BI$28<>"N/A"),1,0))+IF(ISNUMBER(KOL_Source_Data!$BK$28),1,IF(AND(ISTEXT(KOL_Source_Data!$BK$28),KOL_Source_Data!$BK$28<>"N/A"),1,0))+IF(ISNUMBER(KOL_Source_Data!$AA$28),1,IF(AND(ISTEXT(KOL_Source_Data!$AA$28),KOL_Source_Data!$AA$28<>"N/A"),1,0))+IF(ISNUMBER(KOL_Source_Data!$AE$28),1,IF(AND(ISTEXT(KOL_Source_Data!$AE$28),KOL_Source_Data!$AE$28<>"N/A"),1,0))+IF(ISNUMBER(KOL_Source_Data!$AH$28),1,IF(AND(ISTEXT(KOL_Source_Data!$AH$28),KOL_Source_Data!$AH$28<>"N/A"),1,0))+IF(ISNUMBER(KOL_Source_Data!$AN$28),1,IF(AND(ISTEXT(KOL_Source_Data!$AN$28),KOL_Source_Data!$AN$28<>"N/A"),1,0))+IF(ISNUMBER(KOL_Source_Data!$BS$28),1,IF(AND(ISTEXT(KOL_Source_Data!$BS$28),KOL_Source_Data!$BS$28<>"N/A"),1,0))+IF(ISNUMBER(KOL_Source_Data!$BT$28),1,IF(AND(ISTEXT(KOL_Source_Data!$BT$28),KOL_Source_Data!$BT$28<>"N/A"),1,0))+IF(ISNUMBER(KOL_Source_Data!$BU$28),1,IF(AND(ISTEXT(KOL_Source_Data!$BU$28),KOL_Source_Data!$BU$28<>"N/A"),1,0))+IF(ISNUMBER(KOL_Source_Data!$BM$28),1,IF(AND(ISTEXT(KOL_Source_Data!$BM$28),KOL_Source_Data!$BM$28<>"N/A"),1,0)))/12*100,0) | BX28: =IF(KOL_Source_Data!$BW$28>=Lookup_Lists!$D$159,"High",IF(KOL_Source_Data!$BW$28>=Lookup_Lists!$D$160,"Medium","Limited Data")) | BY28: requested @shabiraaluaadnan; resolved to @shabiraalulaadnan · no category: kol_categories carries none and caption evidence did not reach the threshold · no engagement rate on any of the three sources · no audience analysis row · no audience interest rows
A29: KOL-24 | B29: @pojoksatu.id | C29: @pojoksatu.id | D29: pojoksatu.id | E29: TikTok | F29: FOUND | G29: 10500000 | H29: =IFERROR(INDEX(Lookup_Lists!$A$96:$A$100,MATCH(KOL_Source_Data!$G$29,Lookup_Lists!$B$96:$B$100,1)),"N/A") | I29: Yes | J29: N/A | K29: Lifestyle | L29: calculated | M29: Lifestyle | N29: Domestic Travel, Nature & Outdoor, Audio & Wearable | O29: Travel 10pt [pantai (caption); gunung (caption)] · Tech 6pt [headphone (caption); api (caption)] | P29: N/A | Q29: N/A | R29: N/A | S29: N/A | T29: Kasus hukum yang menyangkut PT Toba Pulp Lestari kembali jadi sorotan. Bagaimana tidak, kini ada 3 kasus hukum sekaligus. Terbaru Kejagung mengungkap dugaan korupsi transfer pricing yang menyeret nama perusahaan. Usai viral, PT Toba Pulp Lestari Tbk (INRU) buka suara. Direktur sekaligus Corporate Secretary INRU, Anwar Lawden, mengaku telah menerima informasi tersebut. Saat ini, perseroan masih melakukan pendalaman dan verifikasi atas informasi tersebut. "Perseroan akan menyampaikan informasi lebih lanjut kepada BEI dan publik sesuai dengan ketentuan peraturan perundang-undangan yang berlaku apabila telah tersedia informasi yang material, relevan, dan dapat diverifikasi," tulis Anwar, Kamis (20/8/2026). #pojoksatu · Aksi seorang pengendara motor di Jalan Lebak Bulus mendadak bikin warganet mengelus dada dan emosi jiwa. Bagaimana tidak, di saat ambulans sedang melaju kencang membawa pasien dalam kondisi kritis menuju RS Fatmawati, pemotor ini justru terkesan enggan memberi ruang jalan meski sirine sudah meraung-raung. Bukannya langsung menepi demi menyelamatkan nyawa orang, situasi di jalanan malah makin memanas setelah sang pemotor justru terlibat cekcok dengan sopir ambulans. Aksi egois yang lebih mementingkan gengsi ketimbang keselamatan pasien kritis ini jelas memicu amarah publik. Bikin heran, kok ya sempat-sempatnya diajak debat di saat nyawa orang lain sedang dipertaruhkan? · Momen seorang penumpang kereta api menjadi perhatian setelah memutar musik dengan volume keras t | U29: #pojoksatu #wuwacreator #wutheringwaves | V29: N/A | W29: N/A | X29: N/A | Y29: N/A | Z29: N/A | AA29: 26.67 | AB29: 73.33 | AC29: 15 | AD29: Indonesia | AE29: 76.9 | AF29: 13 | AG29: Jakarta | AH29: 25 | AI29: Lampung | AJ29: 25 | AK29: Sulawesi | AL29: 25 | AM29: 100 | AN29: 12.7 | AO29: N/A | AP29: 7.7 | AQ29: N/A | AR29: N/A | AS29: N/A | AT29: N/A | AU29: N/A | AV29: N/A | AW29: 23.1 | AX29: 15.4 | AY29: N/A | AZ29: 15.4 | BA29: 7.7 | BB29: N/A | BC29: 15.4 | BD29: N/A | BE29: N/A | BF29: 15.4 | BG29: 0.01 | BH29: kol_directory.engagement_rate | BI29: 59235.9 | BJ29: 46550 | BK29: 0.5434 | BL29: N/A | BM29: N/A | BN29: 0 | BO29: N/A | BP29: 0.9174 | BQ29: 0 | BR29: N/A | BS29: 80 | BT29: 75 | BU29: 84 | BV29: N/A | BW29: =ROUND((IF(ISNUMBER(KOL_Source_Data!$K$29),1,IF(AND(ISTEXT(KOL_Source_Data!$K$29),KOL_Source_Data!$K$29<>"N/A"),1,0))+IF(ISNUMBER(KOL_Source_Data!$BG$29),1,IF(AND(ISTEXT(KOL_Source_Data!$BG$29),KOL_Source_Data!$BG$29<>"N/A"),1,0))+IF(ISNUMBER(KOL_Source_Data!$BI$29),1,IF(AND(ISTEXT(KOL_Source_Data!$BI$29),KOL_Source_Data!$BI$29<>"N/A"),1,0))+IF(ISNUMBER(KOL_Source_Data!$BK$29),1,IF(AND(ISTEXT(KOL_Source_Data!$BK$29),KOL_Source_Data!$BK$29<>"N/A"),1,0))+IF(ISNUMBER(KOL_Source_Data!$AA$29),1,IF(AND(ISTEXT(KOL_Source_Data!$AA$29),KOL_Source_Data!$AA$29<>"N/A"),1,0))+IF(ISNUMBER(KOL_Source_Data!$AE$29),1,IF(AND(ISTEXT(KOL_Source_Data!$AE$29),KOL_Source_Data!$AE$29<>"N/A"),1,0))+IF(ISNUMBER(KOL_Source_Data!$AH$29),1,IF(AND(ISTEXT(KOL_Source_Data!$AH$29),KOL_Source_Data!$AH$29<>"N/A"),1,0))+IF(ISNUMBER(KOL_Source_Data!$AN$29),1,IF(AND(ISTEXT(KOL_Source_Data!$AN$29),KOL_Source_Data!$AN$29<>"N/A"),1,0))+IF(ISNUMBER(KOL_Source_Data!$BS$29),1,IF(AND(ISTEXT(KOL_Source_Data!$BS$29),KOL_Source_Data!$BS$29<>"N/A"),1,0))+IF(ISNUMBER(KOL_Source_Data!$BT$29),1,IF(AND(ISTEXT(KOL_Source_Data!$BT$29),KOL_Source_Data!$BT$29<>"N/A"),1,0))+IF(ISNUMBER(KOL_Source_Data!$BU$29),1,IF(AND(ISTEXT(KOL_Source_Data!$BU$29),KOL_Source_Data!$BU$29<>"N/A"),1,0))+IF(ISNUMBER(KOL_Source_Data!$BM$29),1,IF(AND(ISTEXT(KOL_Source_Data!$BM$29),KOL_Source_Data!$BM$29<>"N/A"),1,0)))/12*100,0) | BX29: =IF(KOL_Source_Data!$BW$29>=Lookup_Lists!$D$159,"High",IF(KOL_Source_Data!$BW$29>=Lookup_Lists!$D$160,"Medium","Limited Data")) | BY29: category calculated from captions, not from kol_categories · cadence unusable: null/month extrapolated from 0 observed day(s)

Sheet Brand_Profile
A1: BRAND PROFILE · five brands, every category taken from the KOL database
A2: One column per brand. The Category row holds a kol_categories.taxonomy_key value — Tech, Beauty, Food, Fitness, Fashion — and the Audience Interests rows hold audience_interest_daily.interest_key values, both exactly as the database spells them. The Source column says which database column each field speaks to, or states that none does; the three fields where none does score nothing.
A4: Section | B4: Brand Field | C4: Key | D4: Source in the database | E4: NovaTech | F4: LumiSkin | G4: DailyBite | H4: MoveFit | I4: UrbanMuse
A5: A. BRAND RECORD · public.brand | B5: Brand ID | C5: brand_id | D5: — workbook key | E5: BR-01 | F5: BR-02 | G5: BR-03 | H5: BR-04 | I5: BR-05
B6: Brand Name | C6: brand_name | D6: public.brand.name | E6: NovaTech | F6: LumiSkin | G6: DailyBite | H6: MoveFit | I6: UrbanMuse
B7: Category (canonical) | C7: category | D7: public.kol_categories.taxonomy_key — one of the 9 canonical values | E7: Tech | F7: Beauty | G7: Food | H7: Fitness | I7: Fashion
B8: Product / Service | C8: product | D8: — descriptive, scores nothing | E8: Productivity & Business Software | F8: Skincare / Beauty | G8: Food / Beverage | H8: Sportswear / Fitness Product | I8: Fashion / Apparel
B9: Brand Keywords | C9: brand_keywords | D9: public.brand.brand_keywords | E9: teknologi, software, aplikasi, produktivitas, bisnis, digital | F9: skincare, perawatan kulit, kecantikan, glowing, serum, sunscreen | G9: makanan, minuman, kuliner, resto, cafe, jajan | H9: fitness, olahraga, gym, lari, kebugaran, sehat | I9: fashion, outfit, ootd, gaya, koleksi, style
B10: Brand Hashtags | C10: brand_hashtags | D10: public.brand.brand_hashtags | E10: tech, gadget, startup, produktivitas, aplikasi | F10: skincare, beauty, glowing, makeup, bpom | G10: kuliner, food, makanan, foodie, jajan | H10: fitness, workout, gym, olahraga, sport | I10: ootd, fashion, style, outfit, lookbook
A11: B. TARGET AUDIENCE | B11: Primary Age Range | C11: primary_age_range | D11: NO COLUMN — audience_demographics_daily holds gender only; scores nothing | E11: 25-34 | F11: 18-24 | G11: 18-24 | H11: 18-24 | I11: 18-24
B12: Secondary Age Range | C12: secondary_age_range | D12: NO COLUMN — as above | E12: 18-24 | F12: 25-34 | G12: 25-34 | H12: 25-34 | I12: 25-34
B13: Gender Majority | C13: gender_majority | D13: audience_demographics_daily (audience_type='gender') + feature.*_audience_analysis.female_pct | E13: Balanced | F13: Female | G13: Balanced | H13: Balanced | I13: Female
B14: Target Country | C14: target_country | D14: audience_geo_daily (geo_level='country') | E14: Indonesia | F14: Indonesia | G14: Indonesia | H14: Indonesia | I14: Indonesia
B15: Target City | C15: target_city | D15: audience_geo_daily (geo_level='city') | E15: Jakarta | F15: Jakarta | G15: Jakarta | H15: Jakarta | I15: Jakarta
B16: Audience Interests | C16: interests | D16: l2_gold.audience_interest_daily.interest_key — exact keys only | E16: technology, business, education, gaming | F16: beauty, fashion, entertainment | G16: food, entertainment, parenting, travel | H16: fitness, sports, food | I16: fashion, beauty, travel, music, photography
B17: · art | C17: interest_art | D17: interest_key = 'art' | E17: 0 | F17: 0 | G17: 0 | H17: 0 | I17: 0
B18: · automotive | C18: interest_automotive | D18: interest_key = 'automotive' | E18: 0 | F18: 0 | G18: 0 | H18: 0 | I18: 0
B19: · beauty | C19: interest_beauty | D19: interest_key = 'beauty' | E19: 0 | F19: 1 | G19: 0 | H19: 0 | I19: 1
B20: · business | C20: interest_business | D20: interest_key = 'business' | E20: 1 | F20: 0 | G20: 0 | H20: 0 | I20: 0
B21: · education | C21: interest_education | D21: interest_key = 'education' | E21: 1 | F21: 0 | G21: 0 | H21: 0 | I21: 0
B22: · entertainment | C22: interest_entertainment | D22: interest_key = 'entertainment' | E22: 0 | F22: 1 | G22: 1 | H22: 0 | I22: 0
B23: · fashion | C23: interest_fashion | D23: interest_key = 'fashion' | E23: 0 | F23: 1 | G23: 0 | H23: 0 | I23: 1
B24: · fitness | C24: interest_fitness | D24: interest_key = 'fitness' | E24: 0 | F24: 0 | G24: 0 | H24: 1 | I24: 0
B25: · food | C25: interest_food | D25: interest_key = 'food' | E25: 0 | F25: 0 | G25: 1 | H25: 1 | I25: 0
B26: · gaming | C26: interest_gaming | D26: interest_key = 'gaming' | E26: 1 | F26: 0 | G26: 0 | H26: 0 | I26: 0
B27: · music | C27: interest_music | D27: interest_key = 'music' | E27: 0 | F27: 0 | G27: 0 | H27: 0 | I27: 1
B28: · parenting | C28: interest_parenting | D28: interest_key = 'parenting' | E28: 0 | F28: 0 | G28: 1 | H28: 0 | I28: 0
... B34: · travel | C34: interest_travel | D34: interest_key = 'travel' | E34: 0 | F34: 0 | G34: 1 | H34: 0 | I34: 1
A35: C. CONTENT EVIDENCE | B35: Caption Search Terms | C35: caption_terms | D35: searched in l1_silver.unified_post.caption — NOT a taxonomy; post_analysis.content_category is NULL in all 212 rows | E35: teknologi, aplikasi, digital, bisnis, edukasi, gadget | F35: skincare, kecantikan, makeup, glowing, perawatan, cantik | G35: kuliner, makanan, minuman, resto, enak, keluarga | H35: olahraga, fitness, lari, gym, sehat, latihan | I35: fashion, outfit, gaya, style, koleksi, travel
A36: D. BRIEFED, NOT SCORED | B36: Brand Personality | C36: personality_brief | D36: NO CREATOR COLUMN — no personality, tone, values or content-style field exists anywhere; Brand Personality Fit is N/A on all 120 rows | E36: Professional · Innovative · Modern · Educational | F36: Elegant · Friendly · Modern · Trustworthy | G36: Friendly · Fun · Casual · Relatable | H36: Energetic · Motivational · Active · Bold | I36: Modern · Stylish · Creative · Premium
B37: Ideal Creator | C37: ideal_creator | D37: — descriptive, states which kol_categories rows feed this brand's canonical key | E37: Creators carrying the Tech category — kol_categories "Technology and gadgets" or "Gaming" — with a business or education audience. | F37: Creators carrying the Beauty category, with a majority-female audience. | G37: Creators carrying the Food category — kol_categories "Foodies", "Food" or "Cooking" — or an entertainment audience that indexes on food. | H37: Creators carrying the Fitness category — kol_categories "Fitness", "Sports", "Gym Enthusiast" or "Cyclist". | I37: Creators carrying the Fashion category, with a majority-female audience.
A39: TOKEN SLOTS · each term on its own row, because the match tests them one at a time
A40: Token set | B40: Slot | C40: Key | D40: Searched in | E40: NovaTech | F40: LumiSkin | G40: DailyBite | H40: MoveFit | I40: UrbanMuse
A41: brand_keywords | B41: slot 1 | C41: brand_keywords_1 | D41: creator bio + captions + category names | E41: teknologi | F41: skincare | G41: makanan | H41: fitness | I41: fashion
B42: slot 2 | C42: brand_keywords_2 | E42: software | F42: perawatan kulit | G42: minuman | H42: olahraga | I42: outfit
B43: slot 3 | C43: brand_keywords_3 | E43: aplikasi | F43: kecantikan | G43: kuliner | H43: gym | I43: ootd
B44: slot 4 | C44: brand_keywords_4 | E44: produktivitas | F44: glowing | G44: resto | H44: lari | I44: gaya
B45: slot 5 | C45: brand_keywords_5 | E45: bisnis | F45: serum | G45: cafe | H45: kebugaran | I45: koleksi
B46: slot 6 | C46: brand_keywords_6 | E46: digital | F46: sunscreen | G46: jajan | H46: sehat | I46: style
B47: terms filled | C47: brand_keywords_count | E47: =COUNTIF(E41:E46,"<>") | F47: =COUNTIF(F41:F46,"<>") | G47: =COUNTIF(G41:G46,"<>") | H47: =COUNTIF(H41:H46,"<>") | I47: =COUNTIF(I41:I46,"<>")
A48: brand_hashtags | B48: slot 1 | C48: brand_hashtags_1 | D48: the creator's own hashtags (l1_silver.unified_post.hashtags) | E48: tech | F48: skincare | G48: kuliner | H48: fitness | I48: ootd
B49: slot 2 | C49: brand_hashtags_2 | E49: gadget | F49: beauty | G49: food | H49: workout | I49: fashion
B50: slot 3 | C50: brand_hashtags_3 | E50: startup | F50: glowing | G50: makanan | H50: gym | I50: style
B51: slot 4 | C51: brand_hashtags_4 | E51: produktivitas | F51: makeup | G51: foodie | H51: olahraga | I51: outfit
B52: slot 5 | C52: brand_hashtags_5 | E52: aplikasi | F52: bpom | G52: jajan | H52: sport | I52: lookbook
B53: terms filled | C53: brand_hashtags_count | E53: =COUNTIF(E48:E52,"<>") | F53: =COUNTIF(F48:F52,"<>") | G53: =COUNTIF(G48:G52,"<>") | H53: =COUNTIF(H48:H52,"<>") | I53: =COUNTIF(I48:I52,"<>")
A54: caption_terms | B54: slot 1 | C54: caption_terms_1 | D54: l1_silver.unified_post.caption | E54: teknologi | F54: skincare | G54: kuliner | H54: olahraga | I54: fashion
B55: slot 2 | C55: caption_terms_2 | E55: aplikasi | F55: kecantikan | G55: makanan | H55: fitness | I55: outfit
B56: slot 3 | C56: caption_terms_3 | E56: digital | F56: makeup | G56: minuman | H56: lari | I56: gaya
B57: slot 4 | C57: caption_terms_4 | E57: bisnis | F57: glowing | G57: resto | H57: gym | I57: style
B58: slot 5 | C58: caption_terms_5 | E58: edukasi | F58: perawatan | G58: enak | H58: sehat | I58: koleksi
B59: slot 6 | C59: caption_terms_6 | E59: gadget | F59: cantik | G59: keluarga | H59: latihan | I59: travel
B60: terms filled | C60: caption_terms_count | E60: =COUNTIF(E54:E59,"<>") | F60: =COUNTIF(F54:F59,"<>") | G60: =COUNTIF(G54:G59,"<>") | H60: =COUNTIF(H54:H59,"<>") | I60: =COUNTIF(I54:I59,"<>")

Sheet Matching_Engine
A1: MATCHING ENGINE · every creator scored against every brand
A2: 120 rows: 5 brands x 24 creators. Not one score here is typed — each is a formula over KOL_Source_Data and Brand_Profile, weighted by the constants on Lookup_Lists. Filter column A to one Brand ID to read a single brand; compare one KOL ID down the five blocks to see that the score is a function of the pair, not a ranking of creators.
A4: KEY | J4: BRAND & BUSINESS RELEVANCE — 20% | O4: TARGET AUDIENCE RELEVANCE — 30% | U4: CONTENT & CATEGORY RELEVANCE — 20% | AA4: BRAND PERSONALITY FIT — 10% | AG4: PERFORMANCE QUALITY — 10% | AO4: BRAND SAFETY — 10% | AX4: RESULT | BD4: HELPERS (intermediate lookups, kept visible on purpose)
A5: Brand ID | B5: Brand | C5: KOL ID | D5: KOL | E5: Creator | F5: Platform | G5: Category | H5: Followers | I5: Engagement Rate (%) | J5: Category Match | K5: Keyword Match | L5: Hashtag Match | M5: Business Score | N5: Business Available | O5: Age Score | P5: Gender Score | Q5: Location Score | R5: Interest Score | S5: Audience Score | T5: Audience Available | U5: Content Category Match | V5: Sub Category Match | W5: Topic Match | X5: Content Style Match | Y5: Content Score | Z5: Content Available | AA5: Personality Match | AB5: Tone Match | AC5: Values Match | AD5: Communication Match | AE5: Personality Score | AF5: Personality Available | AG5: ER Score | AH5: Audience Quality Score | AI5: Consistency Score | AJ5: Community Score | AK5: Average Views Score | AL5: Recent Growth Score | AM5: Performance Score | AN5: Performance Available | AO5: Authenticity Score | AP5: Follower Quality Score | AQ5: Verification Score | AR5: Paid Ratio Score | AS5: Content Risk Score | AT5: Safety Score | AU5: Safety Available | AV5: Safety Level | AW5: Risk Note | AX5: Available Weight | AY5: Final Match Score | AZ5: Match Level | BA5: Data Completeness % | BB5: Confidence | BC5: Rank Key | BD5: Keyword Haystack | BE5: Topic Haystack | BF5: Hashtag Haystack | BG5: Match Key
A6: BR-01 | B6: =Brand_Profile!$E$6 | C6: =KOL_Source_Data!$A$6 | D6: =KOL_Source_Data!$C$6 | E6: =KOL_Source_Data!$D$6 | F6: =KOL_Source_Data!$E$6 | G6: =KOL_Source_Data!$K$6 | H6: =KOL_Source_Data!$G$6 | I6: =KOL_Source_Data!$BG$6 | J6: =IF(NOT(AND(ISTEXT(KOL_Source_Data!$K$6),KOL_Source_Data!$K$6<>"N/A")),Lookup_Lists!$D$150,IF(Brand_Profile!$E$7=KOL_Source_Data!$K$6,100,IFERROR(INDEX(Lookup_Lists!$B$349:$J$357,MATCH(Brand_Profile!$E$7,Lookup_Lists!$A$349:$A$357,0),MATCH(KOL_Source_Data!$K$6,Lookup_Lists!$B$348:$J$348,0)),Lookup_Lists!$D$151))) | K6: =IF(LEN(TRIM(SUBSTITUTE(Matching_Engine!$BD$6,"|","")))=0,"N/A",IF(Brand_Profile!$E$47=0,Lookup_Lists!$D$150,ROUND((IF(Brand_Profile!$E$41="",0,IF(ISNUMBER(SEARCH(Brand_Profile!$E$41,Matching_Engine!$BD$6)),1,0))+IF(Brand_Profile!$E$42="",0,IF(ISNUMBER(SEARCH(Brand_Profile!$E$42,Matching_Engine!$BD$6)),1,0))+IF(Brand_Profile!$E$43="",0,IF(ISNUMBER(SEARCH(Brand_Profile!$E$43,Matching_Engine!$BD$6)),1,0))+IF(Brand_Profile!$E$44="",0,IF(ISNUMBER(SEARCH(Brand_Profile!$E$44,Matching_Engine!$BD$6)),1,0))+IF(Brand_Profile!$E$45="",0,IF(ISNUMBER(SEARCH(Brand_Profile!$E$45,Matching_Engine!$BD$6)),1,0))+IF(Brand_Profile!$E$46="",0,IF(ISNUMBER(SEARCH(Brand_Profile!$E$46,Matching_Engine!$BD$6)),1,0)))/Brand_Profile!$E$47*100,0))) | L6: =IF(NOT(AND(ISTEXT(KOL_Source_Data!$U$6),KOL_Source_Data!$U$6<>"N/A")),"N/A",IF(Brand_Profile!$E$53=0,Lookup_Lists!$D$150,ROUND((IF(Brand_Profile!$E$48="",0,IF(ISNUMBER(SEARCH(Brand_Profile!$E$48,Matching_Engine!$BF$6)),1,0))+IF(Brand_Profile!$E$49="",0,IF(ISNUMBER(SEARCH(Brand_Profile!$E$49,Matching_Engine!$BF$6)),1,0))+IF(Brand_Profile!$E$50="",0,IF(ISNUMBER(SEARCH(Brand_Profile!$E$50,Matching_Engine!$BF$6)),1,0))+IF(Brand_Profile!$E$51="",0,IF(ISNUMBER(SEARCH(Brand_Profile!$E$51,Matching_Engine!$BF$6)),1,0))+IF(Brand_Profile!$E$52="",0,IF(ISNUMBER(SEARCH(Brand_Profile!$E$52,Matching_Engine!$BF$6)),1,0)))/Brand_Profile!$E$53*100,0))) | M6: =IF((IF(ISNUMBER(Matching_Engine!$J$6),Lookup_Lists!$D$332,0)+IF(ISNUMBER(Matching_Engine!$K$6),Lookup_Lists!$D$333,0)+IF(ISNUMBER(Matching_Engine!$L$6),Lookup_Lists!$D$334,0))=0,"N/A",ROUND((IF(ISNUMBER(Matching_Engine!$J$6),Matching_Engine!$J$6*Lookup_Lists!$D$332,0)+IF(ISNUMBER(Matching_Engine!$K$6),Matching_Engine!$K$6*Lookup_Lists!$D$333,0)+IF(ISNUMBER(Matching_Engine!$L$6),Matching_Engine!$L$6*Lookup_Lists!$D$334,0))/(IF(ISNUMBER(Matching_Engine!$J$6),Lookup_Lists!$D$332,0)+IF(ISNUMBER(Matching_Engine!$K$6),Lookup_Lists!$D$333,0)+IF(ISNUMBER(Matching_Engine!$L$6),Lookup_Lists!$D$334,0)),0)) | N6: =IF(ISNUMBER(Matching_Engine!$M$6),1,0) | O6: =IF(NOT(ISNUMBER(IFERROR(INDEX(KOL_Source_Data!$V$6:KOL_Source_Data!$Z$6,1,MATCH(Brand_Profile!$E$11,Lookup_Lists!$F$6:$F$10,0)),""))),"N/A",MIN(100,ROUND((IFERROR(INDEX(KOL_Source_Data!$V$6:KOL_Source_Data!$Z$6,1,MATCH(Brand_Profile!$E$11,Lookup_Lists!$F$6:$F$10,0)),"")+0.5*IF(ISNUMBER(IFERROR(INDEX(KOL_Source_Data!$V$6:KOL_Source_Data!$Z$6,1,MATCH(Brand_Profile!$E$12,Lookup_Lists!$F$6:$F$10,0)),"")),IFERROR(INDEX(KOL_Source_Data!$V$6:KOL_Source_Data!$Z$6,1,MATCH(Brand_Profile!$E$12,Lookup_Lists!$F$6:$F$10,0)),""),0))/Lookup_Lists!$D$142*100,0))) | P6: =IF(Brand_Profile!$E$13="Any",100,IF(NOT(ISNUMBER(KOL_Source_Data!$AA$6)),"N/A",IF(Brand_Profile!$E$13="Female",MIN(100,ROUND(KOL_Source_Data!$AA$6/Lookup_Lists!$D$143*100,0)),IF(Brand_Profile!$E$13="Male",MIN(100,ROUND(IF(ISNUMBER(KOL_Source_Data!$AB$6),KOL_Source_Data!$AB$6,100-KOL_Source_Data!$AA$6)/Lookup_Lists!$D$143*100,0)),MAX(0,ROUND(100-ABS(KOL_Source_Data!$AA$6-50)*2,0)))))) | Q6: =IF((IF(ISNUMBER(IF(NOT(ISNUMBER(KOL_Source_Data!$AE$6)),"N/A",IF(KOL_Source_Data!$AD$6<>Brand_Profile!$E$14,Lookup_Lists!$D$151,MIN(100,ROUND(KOL_Source_Data!$AE$6/Lookup_Lists!$D$316*100,0))))),Lookup_Lists!$D$118,0)+IF(ISNUMBER(IF(NOT(ISNUMBER(KOL_Source_Data!$AM$6)),"N/A",MIN(100,ROUND((IF(KOL_Source_Data!$AG$6=Brand_Profile!$E$15,IF(ISNUMBER(KOL_Source_Data!$AH$6),KOL_Source_Data!$AH$6,0),0)+IF(KOL_Source_Data!$AI$6=Brand_Profile!$E$15,IF(ISNUMBER(KOL_Source_Data!$AJ$6),KOL_Source_Data!$AJ$6,0),0)+IF(KOL_Source_Data!$AK$6=Brand_Profile!$E$15,IF(ISNUMBER(KOL_Source_Data!$AL$6),KOL_Source_Data!$AL$6,0),0))/Lookup_Lists!$D$317*100,0)))),Lookup_Lists!$D$120,0))=0,"N/A",ROUND((IF(ISNUMBER(IF(NOT(ISNUMBER(KOL_Source_Data!$AE$6)),"N/A",IF(KOL_Source_Data!$AD$6<>Brand_Profile!$E$14,Lookup_Lists!$D$151,MIN(100,ROUND(KOL_Source_Data!$AE$6/Lookup_Lists!$D$316*100,0))))),IF(NOT(ISNUMBER(KOL_Source_Data!$AE$6)),"N/A",IF(KOL_Source_Data!$AD$6<>Brand_Profile!$E$14,Lookup_Lists!$D$151,MIN(100,ROUND(KOL_Source_Data!$AE$6/Lookup_Lists!$D$316*100,0))))*Lookup_Lists!$D$118,0)+IF(ISNUMBER(IF(NOT(ISNUMBER(KOL_Source_Data!$AM$6)),"N/A",MIN(100,ROUND((IF(KOL_Source_Data!$AG$6=Brand_Profile!$E$15,IF(ISNUMBER(KOL_Source_Data!$AH$6),KOL_Source_Data!$AH$6,0),0)+IF(KOL_Source_Data!$AI$6=Brand_Profile!$E$15,IF(ISNUMBER(KOL_Source_Data!$AJ$6),KOL_Source_Data!$AJ$6,0),0)+IF(KOL_Source_Data!$AK$6=Brand_Profile!$E$15,IF(ISNUMBER(KOL_Source_Data!$AL$6),KOL_Source_Data!$AL$6,0),0))/Lookup_Lists!$D$317*100,0)))),IF(NOT(ISNUMBER(KOL_Source_Data!$AM$6)),"N/A",MIN(100,ROUND((IF(KOL_Source_Data!$AG$6=Brand_Profile!$E$15,IF(ISNUMBER(KOL_Source_Data!$AH$6),KOL_Source_Data!$AH$6,0),0)+IF(KOL_Source_Data!$AI$6=Brand_Profile!$E$15,IF(ISNUMBER(KOL_Source_Data!$AJ$6),KOL_Source_Data!$AJ$6,0),0)+IF(KOL_Source_Data!$AK$6=Brand_Profile!$E$15,IF(ISNUMBER(KOL_Source_Data!$AL$6),KOL_Source_Data!$AL$6,0),0))/Lookup_Lists!$D$317*100,0)))*Lookup_Lists!$D$120,0))/(IF(ISNUMBER(IF(NOT(ISNUMBER(KOL_Source_Data!$AE$6)),"N/A",IF(KOL_Source_Data!$AD$6<>Brand_Profile!$E$14,Lookup_Lists!$D$151,MIN(100,ROUND(KOL_Source_Data!$AE$6/Lookup_Lists!$D$316*100,0))))),Lookup_Lists!$D$118,0)+IF(ISNUMBER(IF(NOT(ISNUMBER(KOL_Source_Data!$AM$6)),"N/A",MIN(100,ROUND((IF(KOL_Source_Data!$AG$6=Brand_Profile!$E$15,IF(ISNUMBER(KOL_Source_Data!$AH$6),KOL_Source_Data!$AH$6,0),0)+IF(KOL_Source_Data!$AI$6=Brand_Profile!$E$15,IF(ISNUMBER(KOL_Source_Data!$AJ$6),KOL_Source_Data!$AJ$6,0),0)+IF(KOL_Source_Data!$AK$6=Brand_Profile!$E$15,IF(ISNUMBER(KOL_Source_Data!$AL$6),KOL_Source_Data!$AL$6,0),0))/Lookup_Lists!$D$317*100,0)))),Lookup_Lists!$D$120,0)),0)) | R6: =IF(NOT(ISNUMBER(KOL_Source_Data!$AN$6)),"N/A",MIN(100,ROUND((IF(ISNUMBER(KOL_Source_Data!$AO$6),KOL_Source_Data!$AO$6*Brand_Profile!$E$17,0)+IF(ISNUMBER(KOL_Source_Data!$AP$6),KOL_Source_Data!$AP$6*Brand_Profile!$E$18,0)+IF(ISNUMBER(KOL_Source_Data!$AQ$6),KOL_Source_Data!$AQ$6*Brand_Profile!$E$19,0)+IF(ISNUMBER(KOL_Source_Data!$AR$6),KOL_Source_Data!$AR$6*Brand_Profile!$E$20,0)+IF(ISNUMBER(KOL_Source_Data!$AS$6),KOL_Source_Data!$AS$6*Brand_Profile!$E$21,0)+IF(ISNUMBER(KOL_Source_Data!$AT$6),KOL_Source_Data!$AT$6*Brand_Profile!$E$22,0)+IF(ISNUMBER(KOL_Source_Data!$AU$6),KOL_Source_Data!$AU$6*Brand_Profile!$E$23,0)+IF(ISNUMBER(KOL_Source_Data!$AV$6),KOL_Source_Data!$AV$6*Brand_Profile!$E$24,0)+IF(ISNUMBER(KOL_Source_Data!$AW$6),KOL_Source_Data!$AW$6*Brand_Profile!$E$25,0)+IF(ISNUMBER(KOL_Source_Data!$AX$6),KOL_Source_Data!$AX$6*Brand_Profile!$E$26,0)+IF(ISNUMBER(KOL_Source_Data!$AY$6),KOL_Source_Data!$AY$6*Brand_Profile!$E$27,0)+IF(ISNUMBER(KOL_Source_Data!$AZ$6),KOL_Source_Data!$AZ$6*Brand_Profile!$E$28,0)+IF(ISNUMBER(KOL_Source_Data!$BA$6),KOL_Source_Data!$BA$6*Brand_Profile!$E$29,0)+IF(ISNUMBER(KOL_Source_Data!$BB$6),KOL_Source_Data!$BB$6*Brand_Profile!$E$30,0)+IF(ISNUMBER(KOL_Source_Data!$BC$6),KOL_Source_Data!$BC$6*Brand_Profile!$E$31,0)+IF(ISNUMBER(KOL_Source_Data!$BD$6),KOL_Source_Data!$BD$6*Brand_Profile!$E$32,0)+IF(ISNUMBER(KOL_Source_Data!$BE$6),KOL_Source_Data!$BE$6*Brand_Profile!$E$33,0)+IF(ISNUMBER(KOL_Source_Data!$BF$6),KOL_Source_Data!$BF$6*Brand_Profile!$E$34,0))/Lookup_Lists!$D$318*100,0))) | S6: =IF((IF(ISNUMBER(Matching_Engine!$O$6),Lookup_Lists!$D$113,0)+IF(ISNUMBER(Matching_Engine!$P$6),Lookup_Lists!$D$114,0)+IF(ISNUMBER(Matching_Engine!$Q$6),Lookup_Lists!$D$115,0)+IF(ISNUMBER(Matching_Engine!$R$6),Lookup_Lists!$D$116,0))=0,"N/A",ROUND((IF(ISNUMBER(Matching_Engine!$O$6),Matching_Engine!$O$6*Lookup_Lists!$D$113,0)+IF(ISNUMBER(Matching_Engine!$P$6),Matching_Engine!$P$6*Lookup_Lists!$D$114,0)+IF(ISNUMBER(Matching_Engine!$Q$6),Matching_Engine!$Q$6*Lookup_Lists!$D$115,0)+IF(ISNUMBER(Matching_Engine!$R$6),Matching_Engine!$R$6*Lookup_Lists!$D$116,0))/(IF(ISNUMBER(Matching_Engine!$O$6),Lookup_Lists!$D$113,0)+IF(ISNUMBER(Matching_Engine!$P$6),Lookup_Lists!$D$114,0)+IF(ISNUMBER(Matching_Engine!$Q$6),Lookup_Lists!$D$115,0)+IF(ISNUMBER(Matching_Engine!$R$6),Lookup_Lists!$D$116,0)),0)) | T6: =IF(ISNUMBER(Matching_Engine!$S$6),1,0) | U6: =IF(NOT(AND(ISTEXT(KOL_Source_Data!$M$6),KOL_Source_Data!$M$6<>"N/A")),Lookup_Lists!$D$150,IF(Brand_Profile!$E$7=KOL_Source_Data!$M$6,100,IFERROR(INDEX(Lookup_Lists!$B$349:$J$357,MATCH(Brand_Profile!$E$7,Lookup_Lists!$A$349:$A$357,0),MATCH(KOL_Source_Data!$M$6,Lookup_Lists!$B$348:$J$348,0)),Lookup_Lists!$D$151))) | V6: =IF(NOT(AND(ISTEXT(KOL_Source_Data!$P$6),KOL_Source_Data!$P$6<>"N/A")),"N/A",IFERROR(INDEX(Lookup_Lists!$B$349:$J$357,MATCH(Brand_Profile!$E$7,Lookup_Lists!$A$349:$A$357,0),MATCH(KOL_Source_Data!$P$6,Lookup_Lists!$B$348:$J$348,0)),Lookup_Lists!$D$151)) | W6: =IF(LEN(TRIM(SUBSTITUTE(Matching_Engine!$BE$6,"|","")))=0,"N/A",IF(Brand_Profile!$E$60=0,Lookup_Lists!$D$150,ROUND((IF(Brand_Profile!$E$54="",0,IF(ISNUMBER(SEARCH(Brand_Profile!$E$54,Matching_Engine!$BE$6)),1,0))+IF(Brand_Profile!$E$55="",0,IF(ISNUMBER(SEARCH(Brand_Profile!$E$55,Matching_Engine!$BE$6)),1,0))+IF(Brand_Profile!$E$56="",0,IF(ISNUMBER(SEARCH(Brand_Profile!$E$56,Matching_Engine!$BE$6)),1,0))+IF(Brand_Profile!$E$57="",0,IF(ISNUMBER(SEARCH(Brand_Profile!$E$57,Matching_Engine!$BE$6)),1,0))+IF(Brand_Profile!$E$58="",0,IF(ISNUMBER(SEARCH(Brand_Profile!$E$58,Matching_Engine!$BE$6)),1,0))+IF(Brand_Profile!$E$59="",0,IF(ISNUMBER(SEARCH(Brand_Profile!$E$59,Matching_Engine!$BE$6)),1,0)))/Brand_Profile!$E$60*100,0))) | X6: =IF(NOT(AND(ISTEXT(KOL_Source_Data!$Q$6),KOL_Source_Data!$Q$6<>"N/A")),"N/A",Lookup_Lists!$D$150) | Y6: =IF((IF(ISNUMBER(Matching_Engine!$U$6),Lookup_Lists!$D$335,0)+IF(ISNUMBER(Matching_Engine!$V$6),Lookup_Lists!$D$122,0)+IF(ISNUMBER(Matching_Engine!$W$6),Lookup_Lists!$D$336,0)+IF(ISNUMBER(Matching_Engine!$X$6),Lookup_Lists!$D$124,0))=0,"N/A",ROUND((IF(ISNUMBER(Matching_Engine!$U$6),Matching_Engine!$U$6*Lookup_Lists!$D$335,0)+IF(ISNUMBER(Matching_Engine!$V$6),Matching_Engine!$V$6*Lookup_Lists!$D$122,0)+IF(ISNUMBER(Matching_Engine!$W$6),Matching_Engine!$W$6*Lookup_Lists!$D$336,0)+IF(ISNUMBER(Matching_Engine!$X$6),Matching_Engine!$X$6*Lookup_Lists!$D$124,0))/(IF(ISNUMBER(Matching_Engine!$U$6),Lookup_Lists!$D$335,0)+IF(ISNUMBER(Matching_Engine!$V$6),Lookup_Lists!$D$122,0)+IF(ISNUMBER(Matching_Engine!$W$6),Lookup_Lists!$D$336,0)+IF(ISNUMBER(Matching_Engine!$X$6),Lookup_Lists!$D$124,0)),0)) | Z6: =IF(ISNUMBER(Matching_Engine!$Y$6),1,0) | AA6: =IF(NOT(AND(ISTEXT(KOL_Source_Data!$Q$6),KOL_Source_Data!$Q$6<>"N/A")),"N/A",Lookup_Lists!$D$150) | AB6: =IF(NOT(AND(ISTEXT(KOL_Source_Data!$Q$6),KOL_Source_Data!$Q$6<>"N/A")),"N/A",Lookup_Lists!$D$150) | AC6: ="N/A" | AD6: =IF(NOT(AND(ISTEXT(KOL_Source_Data!$Q$6),KOL_Source_Data!$Q$6<>"N/A")),"N/A",Lookup_Lists!$D$150) | AE6: =IF((IF(ISNUMBER(Matching_Engine!$AA$6),Lookup_Lists!$D$125,0)+IF(ISNUMBER(Matching_Engine!$AB$6),Lookup_Lists!$D$126,0)+IF(ISNUMBER(Matching_Engine!$AC$6),Lookup_Lists!$D$127,0)+IF(ISNUMBER(Matching_Engine!$AD$6),Lookup_Lists!$D$128,0))=0,"N/A",ROUND((IF(ISNUMBER(Matching_Engine!$AA$6),Matching_Engine!$AA$6*Lookup_Lists!$D$125,0)+IF(ISNUMBER(Matching_Engine!$AB$6),Matching_Engine!$AB$6*Lookup_Lists!$D$126,0)+IF(ISNUMBER(Matching_Engine!$AC$6),Matching_Engine!$AC$6*Lookup_Lists!$D$127,0)+IF(ISNUMBER(Matching_Engine!$AD$6),Matching_Engine!$AD$6*Lookup_Lists!$D$128,0))/(IF(ISNUMBER(Matching_Engine!$AA$6),Lookup_Lists!$D$125,0)+IF(ISNUMBER(Matching_Engine!$AB$6),Lookup_Lists!$D$126,0)+IF(ISNUMBER(Matching_Engine!$AC$6),Lookup_Lists!$D$127,0)+IF(ISNUMBER(Matching_Engine!$AD$6),Lookup_Lists!$D$128,0)),0)) | AF6: =IF(ISNUMBER(Matching_Engine!$AE$6),1,0) | AG6: =IF(NOT(ISNUMBER(KOL_Source_Data!$BG$6)),"N/A",MIN(100,ROUND(KOL_Source_Data!$BG$6/IFERROR(INDEX(Lookup_Lists!$B$340:$B$344,MATCH(KOL_Source_Data!$H$6,Lookup_Lists!$A$340:$A$344,0)),Lookup_Lists!$D$141)*100,0))) | AH6: =IF(NOT(ISNUMBER(KOL_Source_Data!$BS$6)),"N/A",MIN(100,MAX(0,KOL_Source_Data!$BS$6))) | AI6: =IF(OR(NOT(ISNUMBER(KOL_Source_Data!$BM$6)),NOT(ISNUMBER(KOL_Source_Data!$BN$6)),KOL_Source_Data!$BN$6<Lookup_Lists!$D$320),"N/A",MIN(100,ROUND(KOL_Source_Data!$BM$6/Lookup_Lists!$D$319*100,0))) | AJ6: =IF(NOT(ISNUMBER(KOL_Source_Data!$BR$6)),"N/A",KOL_Source_Data!$BR$6) | AK6: =IF(NOT(ISNUMBER(KOL_Source_Data!$BK$6)),"N/A",MIN(100,ROUND(KOL_Source_Data!$BK$6/Lookup_Lists!$D$321*100,0))) | AL6: =IF(NOT(ISNUMBER(KOL_Source_Data!$BP$6)),"N/A",MIN(100,MAX(0,ROUND((KOL_Source_Data!$BP$6+2)/(Lookup_Lists!$D$145+2)*100,0)))) | AM6: =IF((IF(ISNUMBER(Matching_Engine!$AG$6),Lookup_Lists!$D$129,0)+IF(ISNUMBER(Matching_Engine!$AH$6),Lookup_Lists!$D$130,0)+IF(ISNUMBER(Matching_Engine!$AI$6),Lookup_Lists!$D$131,0)+IF(ISNUMBER(Matching_Engine!$AJ$6),Lookup_Lists!$D$132,0)+IF(ISNUMBER(Matching_Engine!$AK$6),Lookup_Lists!$D$133,0)+IF(ISNUMBER(Matching_Engine!$AL$6),Lookup_Lists!$D$134,0))=0,"N/A",ROUND((IF(ISNUMBER(Matching_Engine!$AG$6),Matching_Engine!$AG$6*Lookup_Lists!$D$129,0)+IF(ISNUMBER(Matching_Engine!$AH$6),Matching_Engine!$AH$6*Lookup_Lists!$D$130,0)+IF(ISNUMBER(Matching_Engine!$AI$6),Matching_Engine!$AI$6*Lookup_Lists!$D$131,0)+IF(ISNUMBER(Matching_Engine!$AJ$6),Matching_Engine!$AJ$6*Lookup_Lists!$D$132,0)+IF(ISNUMBER(Matching_Engine!$AK$6),Matching_Engine!$AK$6*Lookup_Lists!$D$133,0)+IF(ISNUMBER(Matching_Engine!$AL$6),Matching_Engine!$AL$6*Lookup_Lists!$D$134,0))/(IF(ISNUMBER(Matching_Engine!$AG$6),Lookup_Lists!$D$129,0)+IF(ISNUMBER(Matching_Engine!$AH$6),Lookup_Lists!$D$130,0)+IF(ISNUMBER(Matching_Engine!$AI$6),Lookup_Lists!$D$131,0)+IF(ISNUMBER(Matching_Engine!$AJ$6),Lookup_Lists!$D$132,0)+IF(ISNUMBER(Matching_Engine!$AK$6),Lookup_Lists!$D$133,0)+IF(ISNUMBER(Matching_Engine!$AL$6),Lookup_Lists!$D$134,0)),0)) | AN6: =IF(ISNUMBER(Matching_Engine!$AM$6),1,0) | AO6: =IF(NOT(ISNUMBER(KOL_Source_Data!$BT$6)),"N/A",MIN(100,MAX(0,KOL_Source_Data!$BT$6))) | AP6: =IF(NOT(ISNUMBER(KOL_Source_Data!$BU$6)),"N/A",MIN(100,MAX(0,KOL_Source_Data!$BU$6))) | AQ6: =IF(KOL_Source_Data!$I$6="Yes",Lookup_Lists!$D$326,IF(KOL_Source_Data!$I$6="No",Lookup_Lists!$D$327,"N/A")) | AR6: =IF(NOT(ISNUMBER(KOL_Source_Data!$BQ$6)),"N/A",MAX(0,ROUND(100-KOL_Source_Data!$BQ$6/Lookup_Lists!$D$328*100,0))) | AS6: =IF(NOT(AND(ISTEXT(KOL_Source_Data!$BV$6),KOL_Source_Data!$BV$6<>"N/A")),"N/A",KOL_Source_Data!$BV$6) | AT6: =IF((IF(ISNUMBER(Matching_Engine!$AO$6),Lookup_Lists!$D$322,0)+IF(ISNUMBER(Matching_Engine!$AP$6),Lookup_Lists!$D$323,0)+IF(ISNUMBER(Matching_Engine!$AQ$6),Lookup_Lists!$D$324,0)+IF(ISNUMBER(Matching_Engine!$AR$6),Lookup_Lists!$D$325,0))=0,"N/A",ROUND((IF(ISNUMBER(Matching_Engine!$AO$6),Matching_Engine!$AO$6*Lookup_Lists!$D$322,0)+IF(ISNUMBER(Matching_Engine!$AP$6),Matching_Engine!$AP$6*Lookup_Lists!$D$323,0)+IF(ISNUMBER(Matching_Engine!$AQ$6),Matching_Engine!$AQ$6*Lookup_Lists!$D$324,0)+IF(ISNUMBER(Matching_Engine!$AR$6),Matching_Engine!$AR$6*Lookup_Lists!$D$325,0))/(IF(ISNUMBER(Matching_Engine!$AO$6),Lookup_Lists!$D$322,0)+IF(ISNUMBER(Matching_Engine!$AP$6),Lookup_Lists!$D$323,0)+IF(ISNUMBER(Matching_Engine!$AQ$6),Lookup_Lists!$D$324,0)+IF(ISNUMBER(Matching_Engine!$AR$6),Lookup_Lists!$D$325,0)),0)) | AU6: =IF(ISNUMBER(Matching_Engine!$AT$6),1,0) | AV6: =IF(NOT(ISNUMBER(Matching_Engine!$AT$6)),"Not Screened",IF(Matching_Engine!$AT$6>=Lookup_Lists!$D$329,"Low Risk",IF(Matching_Engine!$AT$6>=Lookup_Lists!$D$330,"Moderate Risk",IF(Matching_Engine!$AT$6>=Lookup_Lists!$D$331,"Elevated Risk","High Risk")))) | AW6: =IF(NOT(ISNUMBER(Matching_Engine!$AT$6)),"No integrity signal: no audience-analysis row for this account.","Integrity screen only — no content-risk reading exists (comments_analysis: 0 rows). "&IF(ISNUMBER(Matching_Engine!$AO$6),"Authenticity "&Matching_Engine!$AO$6&". ","Authenticity N/A. ")&IF(ISNUMBER(Matching_Engine!$AP$6),"Follower quality "&Matching_Engine!$AP$6&". ","Follower quality N/A. ")&IF(KOL_Source_Data!$I$6="Yes","Platform-verified.","Not platform-verified.")) | AX6: =Matching_Engine!$N$6*Lookup_Lists!$D$104+Matching_Engine!$T$6*Lookup_Lists!$D$105+Matching_Engine!$Z$6*Lookup_Lists!$D$106+Matching_Engine!$AF$6*Lookup_Lists!$D$107+Matching_Engine!$AN$6*Lookup_Lists!$D$108+Matching_Engine!$AU$6*Lookup_Lists!$D$109 | AY6: =IF(Matching_Engine!$AX$6=0,"N/A",ROUND((IF(Matching_Engine!$N$6=1,Matching_Engine!$M$6*Lookup_Lists!$D$104,0)+IF(Matching_Engine!$T$6=1,Matching_Engine!$S$6*Lookup_Lists!$D$105,0)+IF(Matching_Engine!$Z$6=1,Matching_Engine!$Y$6*Lookup_Lists!$D$106,0)+IF(Matching_Engine!$AF$6=1,Matching_Engine!$AE$6*Lookup_Lists!$D$107,0)+IF(Matching_Engine!$AN$6=1,Matching_Engine!$AM$6*Lookup_Lists!$D$108,0)+IF(Matching_Engine!$AU$6=1,Matching_Engine!$AT$6*Lookup_Lists!$D$109,0))/Matching_Engine!$AX$6,0)) | AZ6: =IF(NOT(ISNUMBER(Matching_Engine!$AY$6)),"Not Scored",IF(Matching_Engine!$AY$6>=Lookup_Lists!$D$152,"Excellent Match",IF(Matching_Engine!$AY$6>=Lookup_Lists!$D$153,"Strong Match",IF(Matching_Engine!$AY$6>=Lookup_Lists!$D$154,"Good Match",IF(Matching_Engine!$AY$6>=Lookup_Lists!$D$155,"Moderate Match","Low Match"))))) | BA6: =KOL_Source_Data!$BW$6 | BB6: =KOL_Source_Data!$BX$6 | BC6: =IF(NOT(ISNUMBER(Matching_Engine!$AY$6)),-1,Matching_Engine!$AY$6*1000+24) | BD6: =IF(AND(ISTEXT(KOL_Source_Data!$S$6),KOL_Source_Data!$S$6<>"N/A"),KOL_Source_Data!$S$6,"")&" | "&IF(AND(ISTEXT(KOL_Source_Data!$T$6),KOL_Source_Data!$T$6<>"N/A"),KOL_Source_Data!$T$6,"")&" | "&IF(AND(ISTEXT(KOL_Source_Data!$N$6),KOL_Source_Data!$N$6<>"N/A"),KOL_Source_Data!$N$6,"")&" | "&IF(AND(ISTEXT(KOL_Source_Data!$K$6),KOL_Source_Data!$K$6<>"N/A"),KOL_Source_Data!$K$6,"")&" | "&IF(AND(ISTEXT(KOL_Source_Data!$J$6),KOL_Source_Data!$J$6<>"N/A"),KOL_Source_Data!$J$6,"") | BE6: =IF(AND(ISTEXT(KOL_Source_Data!$T$6),KOL_Source_Data!$T$6<>"N/A"),KOL_Source_Data!$T$6,"")&" | "&IF(AND(ISTEXT(KOL_Source_Data!$N$6),KOL_Source_Data!$N$6<>"N/A"),KOL_Source_Data!$N$6,"")&" | "&IF(AND(ISTEXT(KOL_Source_Data!$O$6),KOL_Source_Data!$O$6<>"N/A"),KOL_Source_Data!$O$6,"")&" | "&IF(AND(ISTEXT(KOL_Source_Data!$S$6),KOL_Source_Data!$S$6<>"N/A"),KOL_Source_Data!$S$6,"") | BF6: =IF(AND(ISTEXT(KOL_Source_Data!$U$6),KOL_Source_Data!$U$6<>"N/A"),KOL_Source_Data!$U$6,"") | BG6: =Matching_Engine!$A$6&"|"&Matching_Engine!$C$6
A7: BR-01 | B7: =Brand_Profile!$E$6 | C7: =KOL_Source_Data!$A$7 | D7: =KOL_Source_Data!$C$7 | E7: =KOL_Source_Data!$D$7 | F7: =KOL_Source_Data!$E$7 | G7: =KOL_Source_Data!$K$7 | H7: =KOL_Source_Data!$G$7 | I7: =KOL_Source_Data!$BG$7 | J7: =IF(NOT(AND(ISTEXT(KOL_Source_Data!$K$7),KOL_Source_Data!$K$7<>"N/A")),Lookup_Lists!$D$150,IF(Brand_Profile!$E$7=KOL_Source_Data!$K$7,100,IFERROR(INDEX(Lookup_Lists!$B$349:$J$357,MATCH(Brand_Profile!$E$7,Lookup_Lists!$A$349:$A$357,0),MATCH(KOL_Source_Data!$K$7,Lookup_Lists!$B$348:$J$348,0)),Lookup_Lists!$D$151))) | K7: =IF(LEN(TRIM(SUBSTITUTE(Matching_Engine!$BD$7,"|","")))=0,"N/A",IF(Brand_Profile!$E$47=0,Lookup_Lists!$D$150,ROUND((IF(Brand_Profile!$E$41="",0,IF(ISNUMBER(SEARCH(Brand_Profile!$E$41,Matching_Engine!$BD$7)),1,0))+IF(Brand_Profile!$E$42="",0,IF(ISNUMBER(SEARCH(Brand_Profile!$E$42,Matching_Engine!$BD$7)),1,0))+IF(Brand_Profile!$E$43="",0,IF(ISNUMBER(SEARCH(Brand_Profile!$E$43,Matching_Engine!$BD$7)),1,0))+IF(Brand_Profile!$E$44="",0,IF(ISNUMBER(SEARCH(Brand_Profile!$E$44,Matching_Engine!$BD$7)),1,0))+IF(Brand_Profile!$E$45="",0,IF(ISNUMBER(SEARCH(Brand_Profile!$E$45,Matching_Engine!$BD$7)),1,0))+IF(Brand_Profile!$E$46="",0,IF(ISNUMBER(SEARCH(Brand_Profile!$E$46,Matching_Engine!$BD$7)),1,0)))/Brand_Profile!$E$47*100,0))) | L7: =IF(NOT(AND(ISTEXT(KOL_Source_Data!$U$7),KOL_Source_Data!$U$7<>"N/A")),"N/A",IF(Brand_Profile!$E$53=0,Lookup_Lists!$D$150,ROUND((IF(Brand_Profile!$E$48="",0,IF(ISNUMBER(SEARCH(Brand_Profile!$E$48,Matching_Engine!$BF$7)),1,0))+IF(Brand_Profile!$E$49="",0,IF(ISNUMBER(SEARCH(Brand_Profile!$E$49,Matching_Engine!$BF$7)),1,0))+IF(Brand_Profile!$E$50="",0,IF(ISNUMBER(SEARCH(Brand_Profile!$E$50,Matching_Engine!$BF$7)),1,0))+IF(Brand_Profile!$E$51="",0,IF(ISNUMBER(SEARCH(Brand_Profile!$E$51,Matching_Engine!$BF$7)),1,0))+IF(Brand_Profile!$E$52="",0,IF(ISNUMBER(SEARCH(Brand_Profile!$E$52,Matching_Engine!$BF$7)),1,0)))/Brand_Profile!$E$53*100,0))) | M7: =IF((IF(ISNUMBER(Matching_Engine!$J$7),Lookup_Lists!$D$332,0)+IF(ISNUMBER(Matching_Engine!$K$7),Lookup_Lists!$D$333,0)+IF(ISNUMBER(Matching_Engine!$L$7),Lookup_Lists!$D$334,0))=0,"N/A",ROUND((IF(ISNUMBER(Matching_Engine!$J$7),Matching_Engine!$J$7*Lookup_Lists!$D$332,0)+IF(ISNUMBER(Matching_Engine!$K$7),Matching_Engine!$K$7*Lookup_Lists!$D$333,0)+IF(ISNUMBER(Matching_Engine!$L$7),Matching_Engine!$L$7*Lookup_Lists!$D$334,0))/(IF(ISNUMBER(Matching_Engine!$J$7),Lookup_Lists!$D$332,0)+IF(ISNUMBER(Matching_Engine!$K$7),Lookup_Lists!$D$333,0)+IF(ISNUMBER(Matching_Engine!$L$7),Lookup_Lists!$D$334,0)),0)) | N7: =IF(ISNUMBER(Matching_Engine!$M$7),1,0) | O7: =IF(NOT(ISNUMBER(IFERROR(INDEX(KOL_Source_Data!$V$7:KOL_Source_Data!$Z$7,1,MATCH(Brand_Profile!$E$11,Lookup_Lists!$F$6:$F$10,0)),""))),"N/A",MIN(100,ROUND((IFERROR(INDEX(KOL_Source_Data!$V$7:KOL_Source_Data!$Z$7,1,MATCH(Brand_Profile!$E$11,Lookup_Lists!$F$6:$F$10,0)),"")+0.5*IF(ISNUMBER(IFERROR(INDEX(KOL_Source_Data!$V$7:KOL_Source_Data!$Z$7,1,MATCH(Brand_Profile!$E$12,Lookup_Lists!$F$6:$F$10,0)),"")),IFERROR(INDEX(KOL_Source_Data!$V$7:KOL_Source_Data!$Z$7,1,MATCH(Brand_Profile!$E$12,Lookup_Lists!$F$6:$F$10,0)),""),0))/Lookup_Lists!$D$142*100,0))) | P7: =IF(Brand_Profile!$E$13="Any",100,IF(NOT(ISNUMBER(KOL_Source_Data!$AA$7)),"N/A",IF(Brand_Profile!$E$13="Female",MIN(100,ROUND(KOL_Source_Data!$AA$7/Lookup_Lists!$D$143*100,0)),IF(Brand_Profile!$E$13="Male",MIN(100,ROUND(IF(ISNUMBER(KOL_Source_Data!$AB$7),KOL_Source_Data!$AB$7,100-KOL_Source_Data!$AA$7)/Lookup_Lists!$D$143*100,0)),MAX(0,ROUND(100-ABS(KOL_Source_Data!$AA$7-50)*2,0)))))) | Q7: =IF((IF(ISNUMBER(IF(NOT(ISNUMBER(KOL_Source_Data!$AE$7)),"N/A",IF(KOL_Source_Data!$AD$7<>Brand_Profile!$E$14,Lookup_Lists!$D$151,MIN(100,ROUND(KOL_Source_Data!$AE$7/Lookup_Lists!$D$316*100,0))))),Lookup_Lists!$D$118,0)+IF(ISNUMBER(IF(NOT(ISNUMBER(KOL_Source_Data!$AM$7)),"N/A",MIN(100,ROUND((IF(KOL_Source_Data!$AG$7=Brand_Profile!$E$15,IF(ISNUMBER(KOL_Source_Data!$AH$7),KOL_Source_Data!$AH$7,0),0)+IF(KOL_Source_Data!$AI$7=Brand_Profile!$E$15,IF(ISNUMBER(KOL_Source_Data!$AJ$7),KOL_Source_Data!$AJ$7,0),0)+IF(KOL_Source_Data!$AK$7=Brand_Profile!$E$15,IF(ISNUMBER(KOL_Source_Data!$AL$7),KOL_Source_Data!$AL$7,0),0))/Lookup_Lists!$D$317*100,0)))),Lookup_Lists!$D$120,0))=0,"N/A",ROUND((IF(ISNUMBER(IF(NOT(ISNUMBER(KOL_Source_Data!$AE$7)),"N/A",IF(KOL_Source_Data!$AD$7<>Brand_Profile!$E$14,Lookup_Lists!$D$151,MIN(100,ROUND(KOL_Source_Data!$AE$7/Lookup_Lists!$D$316*100,0))))),IF(NOT(ISNUMBER(KOL_Source_Data!$AE$7)),"N/A",IF(KOL_Source_Data!$AD$7<>Brand_Profile!$E$14,Lookup_Lists!$D$151,MIN(100,ROUND(KOL_Source_Data!$AE$7/Lookup_Lists!$D$316*100,0))))*Lookup_Lists!$D$118,0)+IF(ISNUMBER(IF(NOT(ISNUMBER(KOL_Source_Data!$AM$7)),"N/A",MIN(100,ROUND((IF(KOL_Source_Data!$AG$7=Brand_Profile!$E$15,IF(ISNUMBER(KOL_Source_Data!$AH$7),KOL_Source_Data!$AH$7,0),0)+IF(KOL_Source_Data!$AI$7=Brand_Profile!$E$15,IF(ISNUMBER(KOL_Source_Data!$AJ$7),KOL_Source_Data!$AJ$7,0),0)+IF(KOL_Source_Data!$AK$7=Brand_Profile!$E$15,IF(ISNUMBER(KOL_Source_Data!$AL$7),KOL_Source_Data!$AL$7,0),0))/Lookup_Lists!$D$317*100,0)))),IF(NOT(ISNUMBER(KOL_Source_Data!$AM$7)),"N/A",MIN(100,ROUND((IF(KOL_Source_Data!$AG$7=Brand_Profile!$E$15,IF(ISNUMBER(KOL_Source_Data!$AH$7),KOL_Source_Data!$AH$7,0),0)+IF(KOL_Source_Data!$AI$7=Brand_Profile!$E$15,IF(ISNUMBER(KOL_Source_Data!$AJ$7),KOL_Source_Data!$AJ$7,0),0)+IF(KOL_Source_Data!$AK$7=Brand_Profile!$E$15,IF(ISNUMBER(KOL_Source_Data!$AL$7),KOL_Source_Data!$AL$7,0),0))/Lookup_Lists!$D$317*100,0)))*Lookup_Lists!$D$120,0))/(IF(ISNUMBER(IF(NOT(ISNUMBER(KOL_Source_Data!$AE$7)),"N/A",IF(KOL_Source_Data!$AD$7<>Brand_Profile!$E$14,Lookup_Lists!$D$151,MIN(100,ROUND(KOL_Source_Data!$AE$7/Lookup_Lists!$D$316*100,0))))),Lookup_Lists!$D$118,0)+IF(ISNUMBER(IF(NOT(ISNUMBER(KOL_Source_Data!$AM$7)),"N/A",MIN(100,ROUND((IF(KOL_Source_Data!$AG$7=Brand_Profile!$E$15,IF(ISNUMBER(KOL_Source_Data!$AH$7),KOL_Source_Data!$AH$7,0),0)+IF(KOL_Source_Data!$AI$7=Brand_Profile!$E$15,IF(ISNUMBER(KOL_Source_Data!$AJ$7),KOL_Source_Data!$AJ$7,0),0)+IF(KOL_Source_Data!$AK$7=Brand_Profile!$E$15,IF(ISNUMBER(KOL_Source_Data!$AL$7),KOL_Source_Data!$AL$7,0),0))/Lookup_Lists!$D$317*100,0)))),Lookup_Lists!$D$120,0)),0)) | R7: =IF(NOT(ISNUMBER(KOL_Source_Data!$AN$7)),"N/A",MIN(100,ROUND((IF(ISNUMBER(KOL_Source_Data!$AO$7),KOL_Source_Data!$AO$7*Brand_Profile!$E$17,0)+IF(ISNUMBER(KOL_Source_Data!$AP$7),KOL_Source_Data!$AP$7*Brand_Profile!$E$18,0)+IF(ISNUMBER(KOL_Source_Data!$AQ$7),KOL_Source_Data!$AQ$7*Brand_Profile!$E$19,0)+IF(ISNUMBER(KOL_Source_Data!$AR$7),KOL_Source_Data!$AR$7*Brand_Profile!$E$20,0)+IF(ISNUMBER(KOL_Source_Data!$AS$7),KOL_Source_Data!$AS$7*Brand_Profile!$E$21,0)+IF(ISNUMBER(KOL_Source_Data!$AT$7),KOL_Source_Data!$AT$7*Brand_Profile!$E$22,0)+IF(ISNUMBER(KOL_Source_Data!$AU$7),KOL_Source_Data!$AU$7*Brand_Profile!$E$23,0)+IF(ISNUMBER(KOL_Source_Data!$AV$7),KOL_Source_Data!$AV$7*Brand_Profile!$E$24,0)+IF(ISNUMBER(KOL_Source_Data!$AW$7),KOL_Source_Data!$AW$7*Brand_Profile!$E$25,0)+IF(ISNUMBER(KOL_Source_Data!$AX$7),KOL_Source_Data!$AX$7*Brand_Profile!$E$26,0)+IF(ISNUMBER(KOL_Source_Data!$AY$7),KOL_Source_Data!$AY$7*Brand_Profile!$E$27,0)+IF(ISNUMBER(KOL_Source_Data!$AZ$7),KOL_Source_Data!$AZ$7*Brand_Profile!$E$28,0)+IF(ISNUMBER(KOL_Source_Data!$BA$7),KOL_Source_Data!$BA$7*Brand_Profile!$E$29,0)+IF(ISNUMBER(KOL_Source_Data!$BB$7),KOL_Source_Data!$BB$7*Brand_Profile!$E$30,0)+IF(ISNUMBER(KOL_Source_Data!$BC$7),KOL_Source_Data!$BC$7*Brand_Profile!$E$31,0)+IF(ISNUMBER(KOL_Source_Data!$BD$7),KOL_Source_Data!$BD$7*Brand_Profile!$E$32,0)+IF(ISNUMBER(KOL_Source_Data!$BE$7),KOL_Source_Data!$BE$7*Brand_Profile!$E$33,0)+IF(ISNUMBER(KOL_Source_Data!$BF$7),KOL_Source_Data!$BF$7*Brand_Profile!$E$34,0))/Lookup_Lists!$D$318*100,0))) | S7: =IF((IF(ISNUMBER(Matching_Engine!$O$7),Lookup_Lists!$D$113,0)+IF(ISNUMBER(Matching_Engine!$P$7),Lookup_Lists!$D$114,0)+IF(ISNUMBER(Matching_Engine!$Q$7),Lookup_Lists!$D$115,0)+IF(ISNUMBER(Matching_Engine!$R$7),Lookup_Lists!$D$116,0))=0,"N/A",ROUND((IF(ISNUMBER(Matching_Engine!$O$7),Matching_Engine!$O$7*Lookup_Lists!$D$113,0)+IF(ISNUMBER(Matching_Engine!$P$7),Matching_Engine!$P$7*Lookup_Lists!$D$114,0)+IF(ISNUMBER(Matching_Engine!$Q$7),Matching_Engine!$Q$7*Lookup_Lists!$D$115,0)+IF(ISNUMBER(Matching_Engine!$R$7),Matching_Engine!$R$7*Lookup_Lists!$D$116,0))/(IF(ISNUMBER(Matching_Engine!$O$7),Lookup_Lists!$D$113,0)+IF(ISNUMBER(Matching_Engine!$P$7),Lookup_Lists!$D$114,0)+IF(ISNUMBER(Matching_Engine!$Q$7),Lookup_Lists!$D$115,0)+IF(ISNUMBER(Matching_Engine!$R$7),Lookup_Lists!$D$116,0)),0)) | T7: =IF(ISNUMBER(Matching_Engine!$S$7),1,0) | U7: =IF(NOT(AND(ISTEXT(KOL_Source_Data!$M$7),KOL_Source_Data!$M$7<>"N/A")),Lookup_Lists!$D$150,IF(Brand_Profile!$E$7=KOL_Source_Data!$M$7,100,IFERROR(INDEX(Lookup_Lists!$B$349:$J$357,MATCH(Brand_Profile!$E$7,Lookup_Lists!$A$349:$A$357,0),MATCH(KOL_Source_Data!$M$7,Lookup_Lists!$B$348:$J$348,0)),Lookup_Lists!$D$151))) | V7: =IF(NOT(AND(ISTEXT(KOL_Source_Data!$P$7),KOL_Source_Data!$P$7<>"N/A")),"N/A",IFERROR(INDEX(Lookup_Lists!$B$349:$J$357,MATCH(Brand_Profile!$E$7,Lookup_Lists!$A$349:$A$357,0),MATCH(KOL_Source_Data!$P$7,Lookup_Lists!$B$348:$J$348,0)),Lookup_Lists!$D$151)) | W7: =IF(LEN(TRIM(SUBSTITUTE(Matching_Engine!$BE$7,"|","")))=0,"N/A",IF(Brand_Profile!$E$60=0,Lookup_Lists!$D$150,ROUND((IF(Brand_Profile!$E$54="",0,IF(ISNUMBER(SEARCH(Brand_Profile!$E$54,Matching_Engine!$BE$7)),1,0))+IF(Brand_Profile!$E$55="",0,IF(ISNUMBER(SEARCH(Brand_Profile!$E$55,Matching_Engine!$BE$7)),1,0))+IF(Brand_Profile!$E$56="",0,IF(ISNUMBER(SEARCH(Brand_Profile!$E$56,Matching_Engine!$BE$7)),1,0))+IF(Brand_Profile!$E$57="",0,IF(ISNUMBER(SEARCH(Brand_Profile!$E$57,Matching_Engine!$BE$7)),1,0))+IF(Brand_Profile!$E$58="",0,IF(ISNUMBER(SEARCH(Brand_Profile!$E$58,Matching_Engine!$BE$7)),1,0))+IF(Brand_Profile!$E$59="",0,IF(ISNUMBER(SEARCH(Brand_Profile!$E$59,Matching_Engine!$BE$7)),1,0)))/Brand_Profile!$E$60*100,0))) | X7: =IF(NOT(AND(ISTEXT(KOL_Source_Data!$Q$7),KOL_Source_Data!$Q$7<>"N/A")),"N/A",Lookup_Lists!$D$150) | Y7: =IF((IF(ISNUMBER(Matching_Engine!$U$7),Lookup_Lists!$D$335,0)+IF(ISNUMBER(Matching_Engine!$V$7),Lookup_Lists!$D$122,0)+IF(ISNUMBER(Matching_Engine!$W$7),Lookup_Lists!$D$336,0)+IF(ISNUMBER(Matching_Engine!$X$7),Lookup_Lists!$D$124,0))=0,"N/A",ROUND((IF(ISNUMBER(Matching_Engine!$U$7),Matching_Engine!$U$7*Lookup_Lists!$D$335,0)+IF(ISNUMBER(Matching_Engine!$V$7),Matching_Engine!$V$7*Lookup_Lists!$D$122,0)+IF(ISNUMBER(Matching_Engine!$W$7),Matching_Engine!$W$7*Lookup_Lists!$D$336,0)+IF(ISNUMBER(Matching_Engine!$X$7),Matching_Engine!$X$7*Lookup_Lists!$D$124,0))/(IF(ISNUMBER(Matching_Engine!$U$7),Lookup_Lists!$D$335,0)+IF(ISNUMBER(Matching_Engine!$V$7),Lookup_Lists!$D$122,0)+IF(ISNUMBER(Matching_Engine!$W$7),Lookup_Lists!$D$336,0)+IF(ISNUMBER(Matching_Engine!$X$7),Lookup_Lists!$D$124,0)),0)) | Z7: =IF(ISNUMBER(Matching_Engine!$Y$7),1,0) | AA7: =IF(NOT(AND(ISTEXT(KOL_Source_Data!$Q$7),KOL_Source_Data!$Q$7<>"N/A")),"N/A",Lookup_Lists!$D$150) | AB7: =IF(NOT(AND(ISTEXT(KOL_Source_Data!$Q$7),KOL_Source_Data!$Q$7<>"N/A")),"N/A",Lookup_Lists!$D$150) | AC7: ="N/A" | AD7: =IF(NOT(AND(ISTEXT(KOL_Source_Data!$Q$7),KOL_Source_Data!$Q$7<>"N/A")),"N/A",Lookup_Lists!$D$150) | AE7: =IF((IF(ISNUMBER(Matching_Engine!$AA$7),Lookup_Lists!$D$125,0)+IF(ISNUMBER(Matching_Engine!$AB$7),Lookup_Lists!$D$126,0)+IF(ISNUMBER(Matching_Engine!$AC$7),Lookup_Lists!$D$127,0)+IF(ISNUMBER(Matching_Engine!$AD$7),Lookup_Lists!$D$128,0))=0,"N/A",ROUND((IF(ISNUMBER(Matching_Engine!$AA$7),Matching_Engine!$AA$7*Lookup_Lists!$D$125,0)+IF(ISNUMBER(Matching_Engine!$AB$7),Matching_Engine!$AB$7*Lookup_Lists!$D$126,0)+IF(ISNUMBER(Matching_Engine!$AC$7),Matching_Engine!$AC$7*Lookup_Lists!$D$127,0)+IF(ISNUMBER(Matching_Engine!$AD$7),Matching_Engine!$AD$7*Lookup_Lists!$D$128,0))/(IF(ISNUMBER(Matching_Engine!$AA$7),Lookup_Lists!$D$125,0)+IF(ISNUMBER(Matching_Engine!$AB$7),Lookup_Lists!$D$126,0)+IF(ISNUMBER(Matching_Engine!$AC$7),Lookup_Lists!$D$127,0)+IF(ISNUMBER(Matching_Engine!$AD$7),Lookup_Lists!$D$128,0)),0)) | AF7: =IF(ISNUMBER(Matching_Engine!$AE$7),1,0) | AG7: =IF(NOT(ISNUMBER(KOL_Source_Data!$BG$7)),"N/A",MIN(100,ROUND(KOL_Source_Data!$BG$7/IFERROR(INDEX(Lookup_Lists!$B$340:$B$344,MATCH(KOL_Source_Data!$H$7,Lookup_Lists!$A$340:$A$344,0)),Lookup_Lists!$D$141)*100,0))) | AH7: =IF(NOT(ISNUMBER(KOL_Source_Data!$BS$7)),"N/A",MIN(100,MAX(0,KOL_Source_Data!$BS$7))) | AI7: =IF(OR(NOT(ISNUMBER(KOL_Source_Data!$BM$7)),NOT(ISNUMBER(KOL_Source_Data!$BN$7)),KOL_Source_Data!$BN$7<Lookup_Lists!$D$320),"N/A",MIN(100,ROUND(KOL_Source_Data!$BM$7/Lookup_Lists!$D$319*100,0))) | AJ7: =IF(NOT(ISNUMBER(KOL_Source_Data!$BR$7)),"N/A",KOL_Source_Data!$BR$7) | AK7: =IF(NOT(ISNUMBER(KOL_Source_Data!$BK$7)),"N/A",MIN(100,ROUND(KOL_Source_Data!$BK$7/Lookup_Lists!$D$321*100,0))) | AL7: =IF(NOT(ISNUMBER(KOL_Source_Data!$BP$7)),"N/A",MIN(100,MAX(0,ROUND((KOL_Source_Data!$BP$7+2)/(Lookup_Lists!$D$145+2)*100,0)))) | AM7: =IF((IF(ISNUMBER(Matching_Engine!$AG$7),Lookup_Lists!$D$129,0)+IF(ISNUMBER(Matching_Engine!$AH$7),Lookup_Lists!$D$130,0)+IF(ISNUMBER(Matching_Engine!$AI$7),Lookup_Lists!$D$131,0)+IF(ISNUMBER(Matching_Engine!$AJ$7),Lookup_Lists!$D$132,0)+IF(ISNUMBER(Matching_Engine!$AK$7),Lookup_Lists!$D$133,0)+IF(ISNUMBER(Matching_Engine!$AL$7),Lookup_Lists!$D$134,0))=0,"N/A",ROUND((IF(ISNUMBER(Matching_Engine!$AG$7),Matching_Engine!$AG$7*Lookup_Lists!$D$129,0)+IF(ISNUMBER(Matching_Engine!$AH$7),Matching_Engine!$AH$7*Lookup_Lists!$D$130,0)+IF(ISNUMBER(Matching_Engine!$AI$7),Matching_Engine!$AI$7*Lookup_Lists!$D$131,0)+IF(ISNUMBER(Matching_Engine!$AJ$7),Matching_Engine!$AJ$7*Lookup_Lists!$D$132,0)+IF(ISNUMBER(Matching_Engine!$AK$7),Matching_Engine!$AK$7*Lookup_Lists!$D$133,0)+IF(ISNUMBER(Matching_Engine!$AL$7),Matching_Engine!$AL$7*Lookup_Lists!$D$134,0))/(IF(ISNUMBER(Matching_Engine!$AG$7),Lookup_Lists!$D$129,0)+IF(ISNUMBER(Matching_Engine!$AH$7),Lookup_Lists!$D$130,0)+IF(ISNUMBER(Matching_Engine!$AI$7),Lookup_Lists!$D$131,0)+IF(ISNUMBER(Matching_Engine!$AJ$7),Lookup_Lists!$D$132,0)+IF(ISNUMBER(Matching_Engine!$AK$7),Lookup_Lists!$D$133,0)+IF(ISNUMBER(Matching_Engine!$AL$7),Lookup_Lists!$D$134,0)),0)) | AN7: =IF(ISNUMBER(Matching_Engine!$AM$7),1,0) | AO7: =IF(NOT(ISNUMBER(KOL_Source_Data!$BT$7)),"N/A",MIN(100,MAX(0,KOL_Source_Data!$BT$7))) | AP7: =IF(NOT(ISNUMBER(KOL_Source_Data!$BU$7)),"N/A",MIN(100,MAX(0,KOL_Source_Data!$BU$7))) | AQ7: =IF(KOL_Source_Data!$I$7="Yes",Lookup_Lists!$D$326,IF(KOL_Source_Data!$I$7="No",Lookup_Lists!$D$327,"N/A")) | AR7: =IF(NOT(ISNUMBER(KOL_Source_Data!$BQ$7)),"N/A",MAX(0,ROUND(100-KOL_Source_Data!$BQ$7/Lookup_Lists!$D$328*100,0))) | AS7: =IF(NOT(AND(ISTEXT(KOL_Source_Data!$BV$7),KOL_Source_Data!$BV$7<>"N/A")),"N/A",KOL_Source_Data!$BV$7) | AT7: =IF((IF(ISNUMBER(Matching_Engine!$AO$7),Lookup_Lists!$D$322,0)+IF(ISNUMBER(Matching_Engine!$AP$7),Lookup_Lists!$D$323,0)+IF(ISNUMBER(Matching_Engine!$AQ$7),Lookup_Lists!$D$324,0)+IF(ISNUMBER(Matching_Engine!$AR$7),Lookup_Lists!$D$325,0))=0,"N/A",ROUND((IF(ISNUMBER(Matching_Engine!$AO$7),Matching_Engine!$AO$7*Lookup_Lists!$D$322,0)+IF(ISNUMBER(Matching_Engine!$AP$7),Matching_Engine!$AP$7*Lookup_Lists!$D$323,0)+IF(ISNUMBER(Matching_Engine!$AQ$7),Matching_Engine!$AQ$7*Lookup_Lists!$D$324,0)+IF(ISNUMBER(Matching_Engine!$AR$7),Matching_Engine!$AR$7*Lookup_Lists!$D$325,0))/(IF(ISNUMBER(Matching_Engine!$AO$7),Lookup_Lists!$D$322,0)+IF(ISNUMBER(Matching_Engine!$AP$7),Lookup_Lists!$D$323,0)+IF(ISNUMBER(Matching_Engine!$AQ$7),Lookup_Lists!$D$324,0)+IF(ISNUMBER(Matching_Engine!$AR$7),Lookup_Lists!$D$325,0)),0)) | AU7: =IF(ISNUMBER(Matching_Engine!$AT$7),1,0) | AV7: =IF(NOT(ISNUMBER(Matching_Engine!$AT$7)),"Not Screened",IF(Matching_Engine!$AT$7>=Lookup_Lists!$D$329,"Low Risk",IF(Matching_Engine!$AT$7>=Lookup_Lists!$D$330,"Moderate Risk",IF(Matching_Engine!$AT$7>=Lookup_Lists!$D$331,"Elevated Risk","High Risk")))) | AW7: =IF(NOT(ISNUMBER(Matching_Engine!$AT$7)),"No integrity signal: no audience-analysis row for this account.","Integrity screen only — no content-risk reading exists (comments_analysis: 0 rows). "&IF(ISNUMBER(Matching_Engine!$AO$7),"Authenticity "&Matching_Engine!$AO$7&". ","Authenticity N/A. ")&IF(ISNUMBER(Matching_Engine!$AP$7),"Follower quality "&Matching_Engine!$AP$7&". ","Follower quality N/A. ")&IF(KOL_Source_Data!$I$7="Yes","Platform-verified.","Not platform-verified.")) | AX7: =Matching_Engine!$N$7*Lookup_Lists!$D$104+Matching_Engine!$T$7*Lookup_Lists!$D$105+Matching_Engine!$Z$7*Lookup_Lists!$D$106+Matching_Engine!$AF$7*Lookup_Lists!$D$107+Matching_Engine!$AN$7*Lookup_Lists!$D$108+Matching_Engine!$AU$7*Lookup_Lists!$D$109 | AY7: =IF(Matching_Engine!$AX$7=0,"N/A",ROUND((IF(Matching_Engine!$N$7=1,Matching_Engine!$M$7*Lookup_Lists!$D$104,0)+IF(Matching_Engine!$T$7=1,Matching_Engine!$S$7*Lookup_Lists!$D$105,0)+IF(Matching_Engine!$Z$7=1,Matching_Engine!$Y$7*Lookup_Lists!$D$106,0)+IF(Matching_Engine!$AF$7=1,Matching_Engine!$AE$7*Lookup_Lists!$D$107,0)+IF(Matching_Engine!$AN$7=1,Matching_Engine!$AM$7*Lookup_Lists!$D$108,0)+IF(Matching_Engine!$AU$7=1,Matching_Engine!$AT$7*Lookup_Lists!$D$109,0))/Matching_Engine!$AX$7,0)) | AZ7: =IF(NOT(ISNUMBER(Matching_Engine!$AY$7)),"Not Scored",IF(Matching_Engine!$AY$7>=Lookup_Lists!$D$152,"Excellent Match",IF(Matching_Engine!$AY$7>=Lookup_Lists!$D$153,"Strong Match",IF(Matching_Engine!$AY$7>=Lookup_Lists!$D$154,"Good Match",IF(Matching_Engine!$AY$7>=Lookup_Lists!$D$155,"Moderate Match","Low Match"))))) | BA7: =KOL_Source_Data!$BW$7 | BB7: =KOL_Source_Data!$BX$7 | BC7: =IF(NOT(ISNUMBER(Matching_Engine!$AY$7)),-1,Matching_Engine!$AY$7*1000+23) | BD7: =IF(AND(ISTEXT(KOL_Source_Data!$S$7),KOL_Source_Data!$S$7<>"N/A"),KOL_Source_Data!$S$7,"")&" | "&IF(AND(ISTEXT(KOL_Source_Data!$T$7),KOL_Source_Data!$T$7<>"N/A"),KOL_Source_Data!$T$7,"")&" | "&IF(AND(ISTEXT(KOL_Source_Data!$N$7),KOL_Source_Data!$N$7<>"N/A"),KOL_Source_Data!$N$7,"")&" | "&IF(AND(ISTEXT(KOL_Source_Data!$K$7),KOL_Source_Data!$K$7<>"N/A"),KOL_Source_Data!$K$7,"")&" | "&IF(AND(ISTEXT(KOL_Source_Data!$J$7),KOL_Source_Data!$J$7<>"N/A"),KOL_Source_Data!$J$7,"") | BE7: =IF(AND(ISTEXT(KOL_Source_Data!$T$7),KOL_Source_Data!$T$7<>"N/A"),KOL_Source_Data!$T$7,"")&" | "&IF(AND(ISTEXT(KOL_Source_Data!$N$7),KOL_Source_Data!$N$7<>"N/A"),KOL_Source_Data!$N$7,"")&" | "&IF(AND(ISTEXT(KOL_Source_Data!$O$7),KOL_Source_Data!$O$7<>"N/A"),KOL_Source_Data!$O$7,"")&" | "&IF(AND(ISTEXT(KOL_Source_Data!$S$7),KOL_Source_Data!$S$7<>"N/A"),KOL_Source_Data!$S$7,"") | BF7: =IF(AND(ISTEXT(KOL_Source_Data!$U$7),KOL_Source_Data!$U$7<>"N/A"),KOL_Source_Data!$U$7,"") | BG7: =Matching_Engine!$A$7&"|"&Matching_Engine!$C$7
A8: BR-01 | B8: =Brand_Profile!$E$6 | C8: =KOL_Source_Data!$A$8 | D8: =KOL_Source_Data!$C$8 | E8: =KOL_Source_Data!$D$8 | F8: =KOL_Source_Data!$E$8 | G8: =KOL_Source_Data!$K$8 | H8: =KOL_Source_Data!$G$8 | I8: =KOL_Source_Data!$BG$8 | J8: =IF(NOT(AND(ISTEXT(KOL_Source_Data!$K$8),KOL_Source_Data!$K$8<>"N/A")),Lookup_Lists!$D$150,IF(Brand_Profile!$E$7=KOL_Source_Data!$K$8,100,IFERROR(INDEX(Lookup_Lists!$B$349:$J$357,MATCH(Brand_Profile!$E$7,Lookup_Lists!$A$349:$A$357,0),MATCH(KOL_Source_Data!$K$8,Lookup_Lists!$B$348:$J$348,0)),Lookup_Lists!$D$151))) | K8: =IF(LEN(TRIM(SUBSTITUTE(Matching_Engine!$BD$8,"|","")))=0,"N/A",IF(Brand_Profile!$E$47=0,Lookup_Lists!$D$150,ROUND((IF(Brand_Profile!$E$41="",0,IF(ISNUMBER(SEARCH(Brand_Profile!$E$41,Matching_Engine!$BD$8)),1,0))+IF(Brand_Profile!$E$42="",0,IF(ISNUMBER(SEARCH(Brand_Profile!$E$42,Matching_Engine!$BD$8)),1,0))+IF(Brand_Profile!$E$43="",0,IF(ISNUMBER(SEARCH(Brand_Profile!$E$43,Matching_Engine!$BD$8)),1,0))+IF(Brand_Profile!$E$44="",0,IF(ISNUMBER(SEARCH(Brand_Profile!$E$44,Matching_Engine!$BD$8)),1,0))+IF(Brand_Profile!$E$45="",0,IF(ISNUMBER(SEARCH(Brand_Profile!$E$45,Matching_Engine!$BD$8)),1,0))+IF(Brand_Profile!$E$46="",0,IF(ISNUMBER(SEARCH(Brand_Profile!$E$46,Matching_Engine!$BD$8)),1,0)))/Brand_Profile!$E$47*100,0))) | L8: =IF(NOT(AND(ISTEXT(KOL_Source_Data!$U$8),KOL_Source_Data!$U$8<>"N/A")),"N/A",IF(Brand_Profile!$E$53=0,Lookup_Lists!$D$150,ROUND((IF(Brand_Profile!$E$48="",0,IF(ISNUMBER(SEARCH(Brand_Profile!$E$48,Matching_Engine!$BF$8)),1,0))+IF(Brand_Profile!$E$49="",0,IF(ISNUMBER(SEARCH(Brand_Profile!$E$49,Matching_Engine!$BF$8)),1,0))+IF(Brand_Profile!$E$50="",0,IF(ISNUMBER(SEARCH(Brand_Profile!$E$50,Matching_Engine!$BF$8)),1,0))+IF(Brand_Profile!$E$51="",0,IF(ISNUMBER(SEARCH(Brand_Profile!$E$51,Matching_Engine!$BF$8)),1,0))+IF(Brand_Profile!$E$52="",0,IF(ISNUMBER(SEARCH(Brand_Profile!$E$52,Matching_Engine!$BF$8)),1,0)))/Brand_Profile!$E$53*100,0))) | M8: =IF((IF(ISNUMBER(Matching_Engine!$J$8),Lookup_Lists!$D$332,0)+IF(ISNUMBER(Matching_Engine!$K$8),Lookup_Lists!$D$333,0)+IF(ISNUMBER(Matching_Engine!$L$8),Lookup_Lists!$D$334,0))=0,"N/A",ROUND((IF(ISNUMBER(Matching_Engine!$J$8),Matching_Engine!$J$8*Lookup_Lists!$D$332,0)+IF(ISNUMBER(Matching_Engine!$K$8),Matching_Engine!$K$8*Lookup_Lists!$D$333,0)+IF(ISNUMBER(Matching_Engine!$L$8),Matching_Engine!$L$8*Lookup_Lists!$D$334,0))/(IF(ISNUMBER(Matching_Engine!$J$8),Lookup_Lists!$D$332,0)+IF(ISNUMBER(Matching_Engine!$K$8),Lookup_Lists!$D$333,0)+IF(ISNUMBER(Matching_Engine!$L$8),Lookup_Lists!$D$334,0)),0)) | N8: =IF(ISNUMBER(Matching_Engine!$M$8),1,0) | O8: =IF(NOT(ISNUMBER(IFERROR(INDEX(KOL_Source_Data!$V$8:KOL_Source_Data!$Z$8,1,MATCH(Brand_Profile!$E$11,Lookup_Lists!$F$6:$F$10,0)),""))),"N/A",MIN(100,ROUND((IFERROR(INDEX(KOL_Source_Data!$V$8:KOL_Source_Data!$Z$8,1,MATCH(Brand_Profile!$E$11,Lookup_Lists!$F$6:$F$10,0)),"")+0.5*IF(ISNUMBER(IFERROR(INDEX(KOL_Source_Data!$V$8:KOL_Source_Data!$Z$8,1,MATCH(Brand_Profile!$E$12,Lookup_Lists!$F$6:$F$10,0)),"")),IFERROR(INDEX(KOL_Source_Data!$V$8:KOL_Source_Data!$Z$8,1,MATCH(Brand_Profile!$E$12,Lookup_Lists!$F$6:$F$10,0)),""),0))/Lookup_Lists!$D$142*100,0))) | P8: =IF(Brand_Profile!$E$13="Any",100,IF(NOT(ISNUMBER(KOL_Source_Data!$AA$8)),"N/A",IF(Brand_Profile!$E$13="Female",MIN(100,ROUND(KOL_Source_Data!$AA$8/Lookup_Lists!$D$143*100,0)),IF(Brand_Profile!$E$13="Male",MIN(100,ROUND(IF(ISNUMBER(KOL_Source_Data!$AB$8),KOL_Source_Data!$AB$8,100-KOL_Source_Data!$AA$8)/Lookup_Lists!$D$143*100,0)),MAX(0,ROUND(100-ABS(KOL_Source_Data!$AA$8-50)*2,0)))))) | Q8: =IF((IF(ISNUMBER(IF(NOT(ISNUMBER(KOL_Source_Data!$AE$8)),"N/A",IF(KOL_Source_Data!$AD$8<>Brand_Profile!$E$14,Lookup_Lists!$D$151,MIN(100,ROUND(KOL_Source_Data!$AE$8/Lookup_Lists!$D$316*100,0))))),Lookup_Lists!$D$118,0)+IF(ISNUMBER(IF(NOT(ISNUMBER(KOL_Source_Data!$AM$8)),"N/A",MIN(100,ROUND((IF(KOL_Source_Data!$AG$8=Brand_Profile!$E$15,IF(ISNUMBER(KOL_Source_Data!$AH$8),KOL_Source_Data!$AH$8,0),0)+IF(KOL_Source_Data!$AI$8=Brand_Profile!$E$15,IF(ISNUMBER(KOL_Source_Data!$AJ$8),KOL_Source_Data!$AJ$8,0),0)+IF(KOL_Source_Data!$AK$8=Brand_Profile!$E$15,IF(ISNUMBER(KOL_Source_Data!$AL$8),KOL_Source_Data!$AL$8,0),0))/Lookup_Lists!$D$317*100,0)))),Lookup_Lists!$D$120,0))=0,"N/A",ROUND((IF(ISNUMBER(IF(NOT(ISNUMBER(KOL_Source_Data!$AE$8)),"N/A",IF(KOL_Source_Data!$AD$8<>Brand_Profile!$E$14,Lookup_Lists!$D$151,MIN(100,ROUND(KOL_Source_Data!$AE$8/Lookup_Lists!$D$316*100,0))))),IF(NOT(ISNUMBER(KOL_Source_Data!$AE$8)),"N/A",IF(KOL_Source_Data!$AD$8<>Brand_Profile!$E$14,Lookup_Lists!$D$151,MIN(100,ROUND(KOL_Source_Data!$AE$8/Lookup_Lists!$D$316*100,0))))*Lookup_Lists!$D$118,0)+IF(ISNUMBER(IF(NOT(ISNUMBER(KOL_Source_Data!$AM$8)),"N/A",MIN(100,ROUND((IF(KOL_Source_Data!$AG$8=Brand_Profile!$E$15,IF(ISNUMBER(KOL_Source_Data!$AH$8),KOL_Source_Data!$AH$8,0),0)+IF(KOL_Source_Data!$AI$8=Brand_Profile!$E$15,IF(ISNUMBER(KOL_Source_Data!$AJ$8),KOL_Source_Data!$AJ$8,0),0)+IF(KOL_Source_Data!$AK$8=Brand_Profile!$E$15,IF(ISNUMBER(KOL_Source_Data!$AL$8),KOL_Source_Data!$AL$8,0),0))/Lookup_Lists!$D$317*100,0)))),IF(NOT(ISNUMBER(KOL_Source_Data!$AM$8)),"N/A",MIN(100,ROUND((IF(KOL_Source_Data!$AG$8=Brand_Profile!$E$15,IF(ISNUMBER(KOL_Source_Data!$AH$8),KOL_Source_Data!$AH$8,0),0)+IF(KOL_Source_Data!$AI$8=Brand_Profile!$E$15,IF(ISNUMBER(KOL_Source_Data!$AJ$8),KOL_Source_Data!$AJ$8,0),0)+IF(KOL_Source_Data!$AK$8=Brand_Profile!$E$15,IF(ISNUMBER(KOL_Source_Data!$AL$8),KOL_Source_Data!$AL$8,0),0))/Lookup_Lists!$D$317*100,0)))*Lookup_Lists!$D$120,0))/(IF(ISNUMBER(IF(NOT(ISNUMBER(KOL_Source_Data!$AE$8)),"N/A",IF(KOL_Source_Data!$AD$8<>Brand_Profile!$E$14,Lookup_Lists!$D$151,MIN(100,ROUND(KOL_Source_Data!$AE$8/Lookup_Lists!$D$316*100,0))))),Lookup_Lists!$D$118,0)+IF(ISNUMBER(IF(NOT(ISNUMBER(KOL_Source_Data!$AM$8)),"N/A",MIN(100,ROUND((IF(KOL_Source_Data!$AG$8=Brand_Profile!$E$15,IF(ISNUMBER(KOL_Source_Data!$AH$8),KOL_Source_Data!$AH$8,0),0)+IF(KOL_Source_Data!$AI$8=Brand_Profile!$E$15,IF(ISNUMBER(KOL_Source_Data!$AJ$8),KOL_Source_Data!$AJ$8,0),0)+IF(KOL_Source_Data!$AK$8=Brand_Profile!$E$15,IF(ISNUMBER(KOL_Source_Data!$AL$8),KOL_Source_Data!$AL$8,0),0))/Lookup_Lists!$D$317*100,0)))),Lookup_Lists!$D$120,0)),0)) | R8: =IF(NOT(ISNUMBER(KOL_Source_Data!$AN$8)),"N/A",MIN(100,ROUND((IF(ISNUMBER(KOL_Source_Data!$AO$8),KOL_Source_Data!$AO$8*Brand_Profile!$E$17,0)+IF(ISNUMBER(KOL_Source_Data!$AP$8),KOL_Source_Data!$AP$8*Brand_Profile!$E$18,0)+IF(ISNUMBER(KOL_Source_Data!$AQ$8),KOL_Source_Data!$AQ$8*Brand_Profile!$E$19,0)+IF(ISNUMBER(KOL_Source_Data!$AR$8),KOL_Source_Data!$AR$8*Brand_Profile!$E$20,0)+IF(ISNUMBER(KOL_Source_Data!$AS$8),KOL_Source_Data!$AS$8*Brand_Profile!$E$21,0)+IF(ISNUMBER(KOL_Source_Data!$AT$8),KOL_Source_Data!$AT$8*Brand_Profile!$E$22,0)+IF(ISNUMBER(KOL_Source_Data!$AU$8),KOL_Source_Data!$AU$8*Brand_Profile!$E$23,0)+IF(ISNUMBER(KOL_Source_Data!$AV$8),KOL_Source_Data!$AV$8*Brand_Profile!$E$24,0)+IF(ISNUMBER(KOL_Source_Data!$AW$8),KOL_Source_Data!$AW$8*Brand_Profile!$E$25,0)+IF(ISNUMBER(KOL_Source_Data!$AX$8),KOL_Source_Data!$AX$8*Brand_Profile!$E$26,0)+IF(ISNUMBER(KOL_Source_Data!$AY$8),KOL_Source_Data!$AY$8*Brand_Profile!$E$27,0)+IF(ISNUMBER(KOL_Source_Data!$AZ$8),KOL_Source_Data!$AZ$8*Brand_Profile!$E$28,0)+IF(ISNUMBER(KOL_Source_Data!$BA$8),KOL_Source_Data!$BA$8*Brand_Profile!$E$29,0)+IF(ISNUMBER(KOL_Source_Data!$BB$8),KOL_Source_Data!$BB$8*Brand_Profile!$E$30,0)+IF(ISNUMBER(KOL_Source_Data!$BC$8),KOL_Source_Data!$BC$8*Brand_Profile!$E$31,0)+IF(ISNUMBER(KOL_Source_Data!$BD$8),KOL_Source_Data!$BD$8*Brand_Profile!$E$32,0)+IF(ISNUMBER(KOL_Source_Data!$BE$8),KOL_Source_Data!$BE$8*Brand_Profile!$E$33,0)+IF(ISNUMBER(KOL_Source_Data!$BF$8),KOL_Source_Data!$BF$8*Brand_Profile!$E$34,0))/Lookup_Lists!$D$318*100,0))) | S8: =IF((IF(ISNUMBER(Matching_Engine!$O$8),Lookup_Lists!$D$113,0)+IF(ISNUMBER(Matching_Engine!$P$8),Lookup_Lists!$D$114,0)+IF(ISNUMBER(Matching_Engine!$Q$8),Lookup_Lists!$D$115,0)+IF(ISNUMBER(Matching_Engine!$R$8),Lookup_Lists!$D$116,0))=0,"N/A",ROUND((IF(ISNUMBER(Matching_Engine!$O$8),Matching_Engine!$O$8*Lookup_Lists!$D$113,0)+IF(ISNUMBER(Matching_Engine!$P$8),Matching_Engine!$P$8*Lookup_Lists!$D$114,0)+IF(ISNUMBER(Matching_Engine!$Q$8),Matching_Engine!$Q$8*Lookup_Lists!$D$115,0)+IF(ISNUMBER(Matching_Engine!$R$8),Matching_Engine!$R$8*Lookup_Lists!$D$116,0))/(IF(ISNUMBER(Matching_Engine!$O$8),Lookup_Lists!$D$113,0)+IF(ISNUMBER(Matching_Engine!$P$8),Lookup_Lists!$D$114,0)+IF(ISNUMBER(Matching_Engine!$Q$8),Lookup_Lists!$D$115,0)+IF(ISNUMBER(Matching_Engine!$R$8),Lookup_Lists!$D$116,0)),0)) | T8: =IF(ISNUMBER(Matching_Engine!$S$8),1,0) | U8: =IF(NOT(AND(ISTEXT(KOL_Source_Data!$M$8),KOL_Source_Data!$M$8<>"N/A")),Lookup_Lists!$D$150,IF(Brand_Profile!$E$7=KOL_Source_Data!$M$8,100,IFERROR(INDEX(Lookup_Lists!$B$349:$J$357,MATCH(Brand_Profile!$E$7,Lookup_Lists!$A$349:$A$357,0),MATCH(KOL_Source_Data!$M$8,Lookup_Lists!$B$348:$J$348,0)),Lookup_Lists!$D$151))) | V8: =IF(NOT(AND(ISTEXT(KOL_Source_Data!$P$8),KOL_Source_Data!$P$8<>"N/A")),"N/A",IFERROR(INDEX(Lookup_Lists!$B$349:$J$357,MATCH(Brand_Profile!$E$7,Lookup_Lists!$A$349:$A$357,0),MATCH(KOL_Source_Data!$P$8,Lookup_Lists!$B$348:$J$348,0)),Lookup_Lists!$D$151)) | W8: =IF(LEN(TRIM(SUBSTITUTE(Matching_Engine!$BE$8,"|","")))=0,"N/A",IF(Brand_Profile!$E$60=0,Lookup_Lists!$D$150,ROUND((IF(Brand_Profile!$E$54="",0,IF(ISNUMBER(SEARCH(Brand_Profile!$E$54,Matching_Engine!$BE$8)),1,0))+IF(Brand_Profile!$E$55="",0,IF(ISNUMBER(SEARCH(Brand_Profile!$E$55,Matching_Engine!$BE$8)),1,0))+IF(Brand_Profile!$E$56="",0,IF(ISNUMBER(SEARCH(Brand_Profile!$E$56,Matching_Engine!$BE$8)),1,0))+IF(Brand_Profile!$E$57="",0,IF(ISNUMBER(SEARCH(Brand_Profile!$E$57,Matching_Engine!$BE$8)),1,0))+IF(Brand_Profile!$E$58="",0,IF(ISNUMBER(SEARCH(Brand_Profile!$E$58,Matching_Engine!$BE$8)),1,0))+IF(Brand_Profile!$E$59="",0,IF(ISNUMBER(SEARCH(Brand_Profile!$E$59,Matching_Engine!$BE$8)),1,0)))/Brand_Profile!$E$60*100,0))) | X8: =IF(NOT(AND(ISTEXT(KOL_Source_Data!$Q$8),KOL_Source_Data!$Q$8<>"N/A")),"N/A",Lookup_Lists!$D$150) | Y8: =IF((IF(ISNUMBER(Matching_Engine!$U$8),Lookup_Lists!$D$335,0)+IF(ISNUMBER(Matching_Engine!$V$8),Lookup_Lists!$D$122,0)+IF(ISNUMBER(Matching_Engine!$W$8),Lookup_Lists!$D$336,0)+IF(ISNUMBER(Matching_Engine!$X$8),Lookup_Lists!$D$124,0))=0,"N/A",ROUND((IF(ISNUMBER(Matching_Engine!$U$8),Matching_Engine!$U$8*Lookup_Lists!$D$335,0)+IF(ISNUMBER(Matching_Engine!$V$8),Matching_Engine!$V$8*Lookup_Lists!$D$122,0)+IF(ISNUMBER(Matching_Engine!$W$8),Matching_Engine!$W$8*Lookup_Lists!$D$336,0)+IF(ISNUMBER(Matching_Engine!$X$8),Matching_Engine!$X$8*Lookup_Lists!$D$124,0))/(IF(ISNUMBER(Matching_Engine!$U$8),Lookup_Lists!$D$335,0)+IF(ISNUMBER(Matching_Engine!$V$8),Lookup_Lists!$D$122,0)+IF(ISNUMBER(Matching_Engine!$W$8),Lookup_Lists!$D$336,0)+IF(ISNUMBER(Matching_Engine!$X$8),Lookup_Lists!$D$124,0)),0)) | Z8: =IF(ISNUMBER(Matching_Engine!$Y$8),1,0) | AA8: =IF(NOT(AND(ISTEXT(KOL_Source_Data!$Q$8),KOL_Source_Data!$Q$8<>"N/A")),"N/A",Lookup_Lists!$D$150) | AB8: =IF(NOT(AND(ISTEXT(KOL_Source_Data!$Q$8),KOL_Source_Data!$Q$8<>"N/A")),"N/A",Lookup_Lists!$D$150) | AC8: ="N/A" | AD8: =IF(NOT(AND(ISTEXT(KOL_Source_Data!$Q$8),KOL_Source_Data!$Q$8<>"N/A")),"N/A",Lookup_Lists!$D$150) | AE8: =IF((IF(ISNUMBER(Matching_Engine!$AA$8),Lookup_Lists!$D$125,0)+IF(ISNUMBER(Matching_Engine!$AB$8),Lookup_Lists!$D$126,0)+IF(ISNUMBER(Matching_Engine!$AC$8),Lookup_Lists!$D$127,0)+IF(ISNUMBER(Matching_Engine!$AD$8),Lookup_Lists!$D$128,0))=0,"N/A",ROUND((IF(ISNUMBER(Matching_Engine!$AA$8),Matching_Engine!$AA$8*Lookup_Lists!$D$125,0)+IF(ISNUMBER(Matching_Engine!$AB$8),Matching_Engine!$AB$8*Lookup_Lists!$D$126,0)+IF(ISNUMBER(Matching_Engine!$AC$8),Matching_Engine!$AC$8*Lookup_Lists!$D$127,0)+IF(ISNUMBER(Matching_Engine!$AD$8),Matching_Engine!$AD$8*Lookup_Lists!$D$128,0))/(IF(ISNUMBER(Matching_Engine!$AA$8),Lookup_Lists!$D$125,0)+IF(ISNUMBER(Matching_Engine!$AB$8),Lookup_Lists!$D$126,0)+IF(ISNUMBER(Matching_Engine!$AC$8),Lookup_Lists!$D$127,0)+IF(ISNUMBER(Matching_Engine!$AD$8),Lookup_Lists!$D$128,0)),0)) | AF8: =IF(ISNUMBER(Matching_Engine!$AE$8),1,0) | AG8: =IF(NOT(ISNUMBER(KOL_Source_Data!$BG$8)),"N/A",MIN(100,ROUND(KOL_Source_Data!$BG$8/IFERROR(INDEX(Lookup_Lists!$B$340:$B$344,MATCH(KOL_Source_Data!$H$8,Lookup_Lists!$A$340:$A$344,0)),Lookup_Lists!$D$141)*100,0))) | AH8: =IF(NOT(ISNUMBER(KOL_Source_Data!$BS$8)),"N/A",MIN(100,MAX(0,KOL_Source_Data!$BS$8))) | AI8: =IF(OR(NOT(ISNUMBER(KOL_Source_Data!$BM$8)),NOT(ISNUMBER(KOL_Source_Data!$BN$8)),KOL_Source_Data!$BN$8<Lookup_Lists!$D$320),"N/A",MIN(100,ROUND(KOL_Source_Data!$BM$8/Lookup_Lists!$D$319*100,0))) | AJ8: =IF(NOT(ISNUMBER(KOL_Source_Data!$BR$8)),"N/A",KOL_Source_Data!$BR$8) | AK8: =IF(NOT(ISNUMBER(KOL_Source_Data!$BK$8)),"N/A",MIN(100,ROUND(KOL_Source_Data!$BK$8/Lookup_Lists!$D$321*100,0))) | AL8: =IF(NOT(ISNUMBER(KOL_Source_Data!$BP$8)),"N/A",MIN(100,MAX(0,ROUND((KOL_Source_Data!$BP$8+2)/(Lookup_Lists!$D$145+2)*100,0)))) | AM8: =IF((IF(ISNUMBER(Matching_Engine!$AG$8),Lookup_Lists!$D$129,0)+IF(ISNUMBER(Matching_Engine!$AH$8),Lookup_Lists!$D$130,0)+IF(ISNUMBER(Matching_Engine!$AI$8),Lookup_Lists!$D$131,0)+IF(ISNUMBER(Matching_Engine!$AJ$8),Lookup_Lists!$D$132,0)+IF(ISNUMBER(Matching_Engine!$AK$8),Lookup_Lists!$D$133,0)+IF(ISNUMBER(Matching_Engine!$AL$8),Lookup_Lists!$D$134,0))=0,"N/A",ROUND((IF(ISNUMBER(Matching_Engine!$AG$8),Matching_Engine!$AG$8*Lookup_Lists!$D$129,0)+IF(ISNUMBER(Matching_Engine!$AH$8),Matching_Engine!$AH$8*Lookup_Lists!$D$130,0)+IF(ISNUMBER(Matching_Engine!$AI$8),Matching_Engine!$AI$8*Lookup_Lists!$D$131,0)+IF(ISNUMBER(Matching_Engine!$AJ$8),Matching_Engine!$AJ$8*Lookup_Lists!$D$132,0)+IF(ISNUMBER(Matching_Engine!$AK$8),Matching_Engine!$AK$8*Lookup_Lists!$D$133,0)+IF(ISNUMBER(Matching_Engine!$AL$8),Matching_Engine!$AL$8*Lookup_Lists!$D$134,0))/(IF(ISNUMBER(Matching_Engine!$AG$8),Lookup_Lists!$D$129,0)+IF(ISNUMBER(Matching_Engine!$AH$8),Lookup_Lists!$D$130,0)+IF(ISNUMBER(Matching_Engine!$AI$8),Lookup_Lists!$D$131,0)+IF(ISNUMBER(Matching_Engine!$AJ$8),Lookup_Lists!$D$132,0)+IF(ISNUMBER(Matching_Engine!$AK$8),Lookup_Lists!$D$133,0)+IF(ISNUMBER(Matching_Engine!$AL$8),Lookup_Lists!$D$134,0)),0)) | AN8: =IF(ISNUMBER(Matching_Engine!$AM$8),1,0) | AO8: =IF(NOT(ISNUMBER(KOL_Source_Data!$BT$8)),"N/A",MIN(100,MAX(0,KOL_Source_Data!$BT$8))) | AP8: =IF(NOT(ISNUMBER(KOL_Source_Data!$BU$8)),"N/A",MIN(100,MAX(0,KOL_Source_Data!$BU$8))) | AQ8: =IF(KOL_Source_Data!$I$8="Yes",Lookup_Lists!$D$326,IF(KOL_Source_Data!$I$8="No",Lookup_Lists!$D$327,"N/A")) | AR8: =IF(NOT(ISNUMBER(KOL_Source_Data!$BQ$8)),"N/A",MAX(0,ROUND(100-KOL_Source_Data!$BQ$8/Lookup_Lists!$D$328*100,0))) | AS8: =IF(NOT(AND(ISTEXT(KOL_Source_Data!$BV$8),KOL_Source_Data!$BV$8<>"N/A")),"N/A",KOL_Source_Data!$BV$8) | AT8: =IF((IF(ISNUMBER(Matching_Engine!$AO$8),Lookup_Lists!$D$322,0)+IF(ISNUMBER(Matching_Engine!$AP$8),Lookup_Lists!$D$323,0)+IF(ISNUMBER(Matching_Engine!$AQ$8),Lookup_Lists!$D$324,0)+IF(ISNUMBER(Matching_Engine!$AR$8),Lookup_Lists!$D$325,0))=0,"N/A",ROUND((IF(ISNUMBER(Matching_Engine!$AO$8),Matching_Engine!$AO$8*Lookup_Lists!$D$322,0)+IF(ISNUMBER(Matching_Engine!$AP$8),Matching_Engine!$AP$8*Lookup_Lists!$D$323,0)+IF(ISNUMBER(Matching_Engine!$AQ$8),Matching_Engine!$AQ$8*Lookup_Lists!$D$324,0)+IF(ISNUMBER(Matching_Engine!$AR$8),Matching_Engine!$AR$8*Lookup_Lists!$D$325,0))/(IF(ISNUMBER(Matching_Engine!$AO$8),Lookup_Lists!$D$322,0)+IF(ISNUMBER(Matching_Engine!$AP$8),Lookup_Lists!$D$323,0)+IF(ISNUMBER(Matching_Engine!$AQ$8),Lookup_Lists!$D$324,0)+IF(ISNUMBER(Matching_Engine!$AR$8),Lookup_Lists!$D$325,0)),0)) | AU8: =IF(ISNUMBER(Matching_Engine!$AT$8),1,0) | AV8: =IF(NOT(ISNUMBER(Matching_Engine!$AT$8)),"Not Screened",IF(Matching_Engine!$AT$8>=Lookup_Lists!$D$329,"Low Risk",IF(Matching_Engine!$AT$8>=Lookup_Lists!$D$330,"Moderate Risk",IF(Matching_Engine!$AT$8>=Lookup_Lists!$D$331,"Elevated Risk","High Risk")))) | AW8: =IF(NOT(ISNUMBER(Matching_Engine!$AT$8)),"No integrity signal: no audience-analysis row for this account.","Integrity screen only — no content-risk reading exists (comments_analysis: 0 rows). "&IF(ISNUMBER(Matching_Engine!$AO$8),"Authenticity "&Matching_Engine!$AO$8&". ","Authenticity N/A. ")&IF(ISNUMBER(Matching_Engine!$AP$8),"Follower quality "&Matching_Engine!$AP$8&". ","Follower quality N/A. ")&IF(KOL_Source_Data!$I$8="Yes","Platform-verified.","Not platform-verified.")) | AX8: =Matching_Engine!$N$8*Lookup_Lists!$D$104+Matching_Engine!$T$8*Lookup_Lists!$D$105+Matching_Engine!$Z$8*Lookup_Lists!$D$106+Matching_Engine!$AF$8*Lookup_Lists!$D$107+Matching_Engine!$AN$8*Lookup_Lists!$D$108+Matching_Engine!$AU$8*Lookup_Lists!$D$109 | AY8: =IF(Matching_Engine!$AX$8=0,"N/A",ROUND((IF(Matching_Engine!$N$8=1,Matching_Engine!$M$8*Lookup_Lists!$D$104,0)+IF(Matching_Engine!$T$8=1,Matching_Engine!$S$8*Lookup_Lists!$D$105,0)+IF(Matching_Engine!$Z$8=1,Matching_Engine!$Y$8*Lookup_Lists!$D$106,0)+IF(Matching_Engine!$AF$8=1,Matching_Engine!$AE$8*Lookup_Lists!$D$107,0)+IF(Matching_Engine!$AN$8=1,Matching_Engine!$AM$8*Lookup_Lists!$D$108,0)+IF(Matching_Engine!$AU$8=1,Matching_Engine!$AT$8*Lookup_Lists!$D$109,0))/Matching_Engine!$AX$8,0)) | AZ8: =IF(NOT(ISNUMBER(Matching_Engine!$AY$8)),"Not Scored",IF(Matching_Engine!$AY$8>=Lookup_Lists!$D$152,"Excellent Match",IF(Matching_Engine!$AY$8>=Lookup_Lists!$D$153,"Strong Match",IF(Matching_Engine!$AY$8>=Lookup_Lists!$D$154,"Good Match",IF(Matching_Engine!$AY$8>=Lookup_Lists!$D$155,"Moderate Match","Low Match"))))) | BA8: =KOL_Source_Data!$BW$8 | BB8: =KOL_Source_Data!$BX$8 | BC8: =IF(NOT(ISNUMBER(Matching_Engine!$AY$8)),-1,Matching_Engine!$AY$8*1000+22) | BD8: =IF(AND(ISTEXT(KOL_Source_Data!$S$8),KOL_Source_Data!$S$8<>"N/A"),KOL_Source_Data!$S$8,"")&" | "&IF(AND(ISTEXT(KOL_Source_Data!$T$8),KOL_Source_Data!$T$8<>"N/A"),KOL_Source_Data!$T$8,"")&" | "&IF(AND(ISTEXT(KOL_Source_Data!$N$8),KOL_Source_Data!$N$8<>"N/A"),KOL_Source_Data!$N$8,"")&" | "&IF(AND(ISTEXT(KOL_Source_Data!$K$8),KOL_Source_Data!$K$8<>"N/A"),KOL_Source_Data!$K$8,"")&" | "&IF(AND(ISTEXT(KOL_Source_Data!$J$8),KOL_Source_Data!$J$8<>"N/A"),KOL_Source_Data!$J$8,"") | BE8: =IF(AND(ISTEXT(KOL_Source_Data!$T$8),KOL_Source_Data!$T$8<>"N/A"),KOL_Source_Data!$T$8,"")&" | "&IF(AND(ISTEXT(KOL_Source_Data!$N$8),KOL_Source_Data!$N$8<>"N/A"),KOL_Source_Data!$N$8,"")&" | "&IF(AND(ISTEXT(KOL_Source_Data!$O$8),KOL_Source_Data!$O$8<>"N/A"),KOL_Source_Data!$O$8,"")&" | "&IF(AND(ISTEXT(KOL_Source_Data!$S$8),KOL_Source_Data!$S$8<>"N/A"),KOL_Source_Data!$S$8,"") | BF8: =IF(AND(ISTEXT(KOL_Source_Data!$U$8),KOL_Source_Data!$U$8<>"N/A"),KOL_Source_Data!$U$8,"") | BG8: =Matching_Engine!$A$8&"|"&Matching_Engine!$C$8
A9: BR-01 | B9: =Brand_Profile!$E$6 | C9: =KOL_Source_Data!$A$9 | D9: =KOL_Source_Data!$C$9 | E9: =KOL_Source_Data!$D$9 | F9: =KOL_Source_Data!$E$9 | G9: =KOL_Source_Data!$K$9 | H9: =KOL_Source_Data!$G$9 | I9: =KOL_Source_Data!$BG$9 | J9: =IF(NOT(AND(ISTEXT(KOL_Source_Data!$K$9),KOL_Source_Data!$K$9<>"N/A")),Lookup_Lists!$D$150,IF(Brand_Profile!$E$7=KOL_Source_Data!$K$9,100,IFERROR(INDEX(Lookup_Lists!$B$349:$J$357,MATCH(Brand_Profile!$E$7,Lookup_Lists!$A$349:$A$357,0),MATCH(KOL_Source_Data!$K$9,Lookup_Lists!$B$348:$J$348,0)),Lookup_Lists!$D$151))) | K9: =IF(LEN(TRIM(SUBSTITUTE(Matching_Engine!$BD$9,"|","")))=0,"N/A",IF(Brand_Profile!$E$47=0,Lookup_Lists!$D$150,ROUND((IF(Brand_Profile!$E$41="",0,IF(ISNUMBER(SEARCH(Brand_Profile!$E$41,Matching_Engine!$BD$9)),1,0))+IF(Brand_Profile!$E$42="",0,IF(ISNUMBER(SEARCH(Brand_Profile!$E$42,Matching_Engine!$BD$9)),1,0))+IF(Brand_Profile!$E$43="",0,IF(ISNUMBER(SEARCH(Brand_Profile!$E$43,Matching_Engine!$BD$9)),1,0))+IF(Brand_Profile!$E$44="",0,IF(ISNUMBER(SEARCH(Brand_Profile!$E$44,Matching_Engine!$BD$9)),1,0))+IF(Brand_Profile!$E$45="",0,IF(ISNUMBER(SEARCH(Brand_Profile!$E$45,Matching_Engine!$BD$9)),1,0))+IF(Brand_Profile!$E$46="",0,IF(ISNUMBER(SEARCH(Brand_Profile!$E$46,Matching_Engine!$BD$9)),1,0)))/Brand_Profile!$E$47*100,0))) | L9: =IF(NOT(AND(ISTEXT(KOL_Source_Data!$U$9),KOL_Source_Data!$U$9<>"N/A")),"N/A",IF(Brand_Profile!$E$53=0,Lookup_Lists!$D$150,ROUND((IF(Brand_Profile!$E$48="",0,IF(ISNUMBER(SEARCH(Brand_Profile!$E$48,Matching_Engine!$BF$9)),1,0))+IF(Brand_Profile!$E$49="",0,IF(ISNUMBER(SEARCH(Brand_Profile!$E$49,Matching_Engine!$BF$9)),1,0))+IF(Brand_Profile!$E$50="",0,IF(ISNUMBER(SEARCH(Brand_Profile!$E$50,Matching_Engine!$BF$9)),1,0))+IF(Brand_Profile!$E$51="",0,IF(ISNUMBER(SEARCH(Brand_Profile!$E$51,Matching_Engine!$BF$9)),1,0))+IF(Brand_Profile!$E$52="",0,IF(ISNUMBER(SEARCH(Brand_Profile!$E$52,Matching_Engine!$BF$9)),1,0)))/Brand_Profile!$E$53*100,0))) | M9: =IF((IF(ISNUMBER(Matching_Engine!$J$9),Lookup_Lists!$D$332,0)+IF(ISNUMBER(Matching_Engine!$K$9),Lookup_Lists!$D$333,0)+IF(ISNUMBER(Matching_Engine!$L$9),Lookup_Lists!$D$334,0))=0,"N/A",ROUND((IF(ISNUMBER(Matching_Engine!$J$9),Matching_Engine!$J$9*Lookup_Lists!$D$332,0)+IF(ISNUMBER(Matching_Engine!$K$9),Matching_Engine!$K$9*Lookup_Lists!$D$333,0)+IF(ISNUMBER(Matching_Engine!$L$9),Matching_Engine!$L$9*Lookup_Lists!$D$334,0))/(IF(ISNUMBER(Matching_Engine!$J$9),Lookup_Lists!$D$332,0)+IF(ISNUMBER(Matching_Engine!$K$9),Lookup_Lists!$D$333,0)+IF(ISNUMBER(Matching_Engine!$L$9),Lookup_Lists!$D$334,0)),0)) | N9: =IF(ISNUMBER(Matching_Engine!$M$9),1,0) | O9: =IF(NOT(ISNUMBER(IFERROR(INDEX(KOL_Source_Data!$V$9:KOL_Source_Data!$Z$9,1,MATCH(Brand_Profile!$E$11,Lookup_Lists!$F$6:$F$10,0)),""))),"N/A",MIN(100,ROUND((IFERROR(INDEX(KOL_Source_Data!$V$9:KOL_Source_Data!$Z$9,1,MATCH(Brand_Profile!$E$11,Lookup_Lists!$F$6:$F$10,0)),"")+0.5*IF(ISNUMBER(IFERROR(INDEX(KOL_Source_Data!$V$9:KOL_Source_Data!$Z$9,1,MATCH(Brand_Profile!$E$12,Lookup_Lists!$F$6:$F$10,0)),"")),IFERROR(INDEX(KOL_Source_Data!$V$9:KOL_Source_Data!$Z$9,1,MATCH(Brand_Profile!$E$12,Lookup_Lists!$F$6:$F$10,0)),""),0))/Lookup_Lists!$D$142*100,0))) | P9: =IF(Brand_Profile!$E$13="Any",100,IF(NOT(ISNUMBER(KOL_Source_Data!$AA$9)),"N/A",IF(Brand_Profile!$E$13="Female",MIN(100,ROUND(KOL_Source_Data!$AA$9/Lookup_Lists!$D$143*100,0)),IF(Brand_Profile!$E$13="Male",MIN(100,ROUND(IF(ISNUMBER(KOL_Source_Data!$AB$9),KOL_Source_Data!$AB$9,100-KOL_Source_Data!$AA$9)/Lookup_Lists!$D$143*100,0)),MAX(0,ROUND(100-ABS(KOL_Source_Data!$AA$9-50)*2,0)))))) | Q9: =IF((IF(ISNUMBER(IF(NOT(ISNUMBER(KOL_Source_Data!$AE$9)),"N/A",IF(KOL_Source_Data!$AD$9<>Brand_Profile!$E$14,Lookup_Lists!$D$151,MIN(100,ROUND(KOL_Source_Data!$AE$9/Lookup_Lists!$D$316*100,0))))),Lookup_Lists!$D$118,0)+IF(ISNUMBER(IF(NOT(ISNUMBER(KOL_Source_Data!$AM$9)),"N/A",MIN(100,ROUND((IF(KOL_Source_Data!$AG$9=Brand_Profile!$E$15,IF(ISNUMBER(KOL_Source_Data!$AH$9),KOL_Source_Data!$AH$9,0),0)+IF(KOL_Source_Data!$AI$9=Brand_Profile!$E$15,IF(ISNUMBER(KOL_Source_Data!$AJ$9),KOL_Source_Data!$AJ$9,0),0)+IF(KOL_Source_Data!$AK$9=Brand_Profile!$E$15,IF(ISNUMBER(KOL_Source_Data!$AL$9),KOL_Source_Data!$AL$9,0),0))/Lookup_Lists!$D$317*100,0)))),Lookup_Lists!$D$120,0))=0,"N/A",ROUND((IF(ISNUMBER(IF(NOT(ISNUMBER(KOL_Source_Data!$AE$9)),"N/A",IF(KOL_Source_Data!$AD$9<>Brand_Profile!$E$14,Lookup_Lists!$D$151,MIN(100,ROUND(KOL_Source_Data!$AE$9/Lookup_Lists!$D$316*100,0))))),IF(NOT(ISNUMBER(KOL_Source_Data!$AE$9)),"N/A",IF(KOL_Source_Data!$AD$9<>Brand_Profile!$E$14,Lookup_Lists!$D$151,MIN(100,ROUND(KOL_Source_Data!$AE$9/Lookup_Lists!$D$316*100,0))))*Lookup_Lists!$D$118,0)+IF(ISNUMBER(IF(NOT(ISNUMBER(KOL_Source_Data!$AM$9)),"N/A",MIN(100,ROUND((IF(KOL_Source_Data!$AG$9=Brand_Profile!$E$15,IF(ISNUMBER(KOL_Source_Data!$AH$9),KOL_Source_Data!$AH$9,0),0)+IF(KOL_Source_Data!$AI$9=Brand_Profile!$E$15,IF(ISNUMBER(KOL_Source_Data!$AJ$9),KOL_Source_Data!$AJ$9,0),0)+IF(KOL_Source_Data!$AK$9=Brand_Profile!$E$15,IF(ISNUMBER(KOL_Source_Data!$AL$9),KOL_Source_Data!$AL$9,0),0))/Lookup_Lists!$D$317*100,0)))),IF(NOT(ISNUMBER(KOL_Source_Data!$AM$9)),"N/A",MIN(100,ROUND((IF(KOL_Source_Data!$AG$9=Brand_Profile!$E$15,IF(ISNUMBER(KOL_Source_Data!$AH$9),KOL_Source_Data!$AH$9,0),0)+IF(KOL_Source_Data!$AI$9=Brand_Profile!$E$15,IF(ISNUMBER(KOL_Source_Data!$AJ$9),KOL_Source_Data!$AJ$9,0),0)+IF(KOL_Source_Data!$AK$9=Brand_Profile!$E$15,IF(ISNUMBER(KOL_Source_Data!$AL$9),KOL_Source_Data!$AL$9,0),0))/Lookup_Lists!$D$317*100,0)))*Lookup_Lists!$D$120,0))/(IF(ISNUMBER(IF(NOT(ISNUMBER(KOL_Source_Data!$AE$9)),"N/A",IF(KOL_Source_Data!$AD$9<>Brand_Profile!$E$14,Lookup_Lists!$D$151,MIN(100,ROUND(KOL_Source_Data!$AE$9/Lookup_Lists!$D$316*100,0))))),Lookup_Lists!$D$118,0)+IF(ISNUMBER(IF(NOT(ISNUMBER(KOL_Source_Data!$AM$9)),"N/A",MIN(100,ROUND((IF(KOL_Source_Data!$AG$9=Brand_Profile!$E$15,IF(ISNUMBER(KOL_Source_Data!$AH$9),KOL_Source_Data!$AH$9,0),0)+IF(KOL_Source_Data!$AI$9=Brand_Profile!$E$15,IF(ISNUMBER(KOL_Source_Data!$AJ$9),KOL_Source_Data!$AJ$9,0),0)+IF(KOL_Source_Data!$AK$9=Brand_Profile!$E$15,IF(ISNUMBER(KOL_Source_Data!$AL$9),KOL_Source_Data!$AL$9,0),0))/Lookup_Lists!$D$317*100,0)))),Lookup_Lists!$D$120,0)),0)) | R9: =IF(NOT(ISNUMBER(KOL_Source_Data!$AN$9)),"N/A",MIN(100,ROUND((IF(ISNUMBER(KOL_Source_Data!$AO$9),KOL_Source_Data!$AO$9*Brand_Profile!$E$17,0)+IF(ISNUMBER(KOL_Source_Data!$AP$9),KOL_Source_Data!$AP$9*Brand_Profile!$E$18,0)+IF(ISNUMBER(KOL_Source_Data!$AQ$9),KOL_Source_Data!$AQ$9*Brand_Profile!$E$19,0)+IF(ISNUMBER(KOL_Source_Data!$AR$9),KOL_Source_Data!$AR$9*Brand_Profile!$E$20,0)+IF(ISNUMBER(KOL_Source_Data!$AS$9),KOL_Source_Data!$AS$9*Brand_Profile!$E$21,0)+IF(ISNUMBER(KOL_Source_Data!$AT$9),KOL_Source_Data!$AT$9*Brand_Profile!$E$22,0)+IF(ISNUMBER(KOL_Source_Data!$AU$9),KOL_Source_Data!$AU$9*Brand_Profile!$E$23,0)+IF(ISNUMBER(KOL_Source_Data!$AV$9),KOL_Source_Data!$AV$9*Brand_Profile!$E$24,0)+IF(ISNUMBER(KOL_Source_Data!$AW$9),KOL_Source_Data!$AW$9*Brand_Profile!$E$25,0)+IF(ISNUMBER(KOL_Source_Data!$AX$9),KOL_Source_Data!$AX$9*Brand_Profile!$E$26,0)+IF(ISNUMBER(KOL_Source_Data!$AY$9),KOL_Source_Data!$AY$9*Brand_Profile!$E$27,0)+IF(ISNUMBER(KOL_Source_Data!$AZ$9),KOL_Source_Data!$AZ$9*Brand_Profile!$E$28,0)+IF(ISNUMBER(KOL_Source_Data!$BA$9),KOL_Source_Data!$BA$9*Brand_Profile!$E$29,0)+IF(ISNUMBER(KOL_Source_Data!$BB$9),KOL_Source_Data!$BB$9*Brand_Profile!$E$30,0)+IF(ISNUMBER(KOL_Source_Data!$BC$9),KOL_Source_Data!$BC$9*Brand_Profile!$E$31,0)+IF(ISNUMBER(KOL_Source_Data!$BD$9),KOL_Source_Data!$BD$9*Brand_Profile!$E$32,0)+IF(ISNUMBER(KOL_Source_Data!$BE$9),KOL_Source_Data!$BE$9*Brand_Profile!$E$33,0)+IF(ISNUMBER(KOL_Source_Data!$BF$9),KOL_Source_Data!$BF$9*Brand_Profile!$E$34,0))/Lookup_Lists!$D$318*100,0))) | S9: =IF((IF(ISNUMBER(Matching_Engine!$O$9),Lookup_Lists!$D$113,0)+IF(ISNUMBER(Matching_Engine!$P$9),Lookup_Lists!$D$114,0)+IF(ISNUMBER(Matching_Engine!$Q$9),Lookup_Lists!$D$115,0)+IF(ISNUMBER(Matching_Engine!$R$9),Lookup_Lists!$D$116,0))=0,"N/A",ROUND((IF(ISNUMBER(Matching_Engine!$O$9),Matching_Engine!$O$9*Lookup_Lists!$D$113,0)+IF(ISNUMBER(Matching_Engine!$P$9),Matching_Engine!$P$9*Lookup_Lists!$D$114,0)+IF(ISNUMBER(Matching_Engine!$Q$9),Matching_Engine!$Q$9*Lookup_Lists!$D$115,0)+IF(ISNUMBER(Matching_Engine!$R$9),Matching_Engine!$R$9*Lookup_Lists!$D$116,0))/(IF(ISNUMBER(Matching_Engine!$O$9),Lookup_Lists!$D$113,0)+IF(ISNUMBER(Matching_Engine!$P$9),Lookup_Lists!$D$114,0)+IF(ISNUMBER(Matching_Engine!$Q$9),Lookup_Lists!$D$115,0)+IF(ISNUMBER(Matching_Engine!$R$9),Lookup_Lists!$D$116,0)),0)) | T9: =IF(ISNUMBER(Matching_Engine!$S$9),1,0) | U9: =IF(NOT(AND(ISTEXT(KOL_Source_Data!$M$9),KOL_Source_Data!$M$9<>"N/A")),Lookup_Lists!$D$150,IF(Brand_Profile!$E$7=KOL_Source_Data!$M$9,100,IFERROR(INDEX(Lookup_Lists!$B$349:$J$357,MATCH(Brand_Profile!$E$7,Lookup_Lists!$A$349:$A$357,0),MATCH(KOL_Source_Data!$M$9,Lookup_Lists!$B$348:$J$348,0)),Lookup_Lists!$D$151))) | V9: =IF(NOT(AND(ISTEXT(KOL_Source_Data!$P$9),KOL_Source_Data!$P$9<>"N/A")),"N/A",IFERROR(INDEX(Lookup_Lists!$B$349:$J$357,MATCH(Brand_Profile!$E$7,Lookup_Lists!$A$349:$A$357,0),MATCH(KOL_Source_Data!$P$9,Lookup_Lists!$B$348:$J$348,0)),Lookup_Lists!$D$151)) | W9: =IF(LEN(TRIM(SUBSTITUTE(Matching_Engine!$BE$9,"|","")))=0,"N/A",IF(Brand_Profile!$E$60=0,Lookup_Lists!$D$150,ROUND((IF(Brand_Profile!$E$54="",0,IF(ISNUMBER(SEARCH(Brand_Profile!$E$54,Matching_Engine!$BE$9)),1,0))+IF(Brand_Profile!$E$55="",0,IF(ISNUMBER(SEARCH(Brand_Profile!$E$55,Matching_Engine!$BE$9)),1,0))+IF(Brand_Profile!$E$56="",0,IF(ISNUMBER(SEARCH(Brand_Profile!$E$56,Matching_Engine!$BE$9)),1,0))+IF(Brand_Profile!$E$57="",0,IF(ISNUMBER(SEARCH(Brand_Profile!$E$57,Matching_Engine!$BE$9)),1,0))+IF(Brand_Profile!$E$58="",0,IF(ISNUMBER(SEARCH(Brand_Profile!$E$58,Matching_Engine!$BE$9)),1,0))+IF(Brand_Profile!$E$59="",0,IF(ISNUMBER(SEARCH(Brand_Profile!$E$59,Matching_Engine!$BE$9)),1,0)))/Brand_Profile!$E$60*100,0))) | X9: =IF(NOT(AND(ISTEXT(KOL_Source_Data!$Q$9),KOL_Source_Data!$Q$9<>"N/A")),"N/A",Lookup_Lists!$D$150) | Y9: =IF((IF(ISNUMBER(Matching_Engine!$U$9),Lookup_Lists!$D$335,0)+IF(ISNUMBER(Matching_Engine!$V$9),Lookup_Lists!$D$122,0)+IF(ISNUMBER(Matching_Engine!$W$9),Lookup_Lists!$D$336,0)+IF(ISNUMBER(Matching_Engine!$X$9),Lookup_Lists!$D$124,0))=0,"N/A",ROUND((IF(ISNUMBER(Matching_Engine!$U$9),Matching_Engine!$U$9*Lookup_Lists!$D$335,0)+IF(ISNUMBER(Matching_Engine!$V$9),Matching_Engine!$V$9*Lookup_Lists!$D$122,0)+IF(ISNUMBER(Matching_Engine!$W$9),Matching_Engine!$W$9*Lookup_Lists!$D$336,0)+IF(ISNUMBER(Matching_Engine!$X$9),Matching_Engine!$X$9*Lookup_Lists!$D$124,0))/(IF(ISNUMBER(Matching_Engine!$U$9),Lookup_Lists!$D$335,0)+IF(ISNUMBER(Matching_Engine!$V$9),Lookup_Lists!$D$122,0)+IF(ISNUMBER(Matching_Engine!$W$9),Lookup_Lists!$D$336,0)+IF(ISNUMBER(Matching_Engine!$X$9),Lookup_Lists!$D$124,0)),0)) | Z9: =IF(ISNUMBER(Matching_Engine!$Y$9),1,0) | AA9: =IF(NOT(AND(ISTEXT(KOL_Source_Data!$Q$9),KOL_Source_Data!$Q$9<>"N/A")),"N/A",Lookup_Lists!$D$150) | AB9: =IF(NOT(AND(ISTEXT(KOL_Source_Data!$Q$9),KOL_Source_Data!$Q$9<>"N/A")),"N/A",Lookup_Lists!$D$150) | AC9: ="N/A" | AD9: =IF(NOT(AND(ISTEXT(KOL_Source_Data!$Q$9),KOL_Source_Data!$Q$9<>"N/A")),"N/A",Lookup_Lists!$D$150) | AE9: =IF((IF(ISNUMBER(Matching_Engine!$AA$9),Lookup_Lists!$D$125,0)+IF(ISNUMBER(Matching_Engine!$AB$9),Lookup_Lists!$D$126,0)+IF(ISNUMBER(Matching_Engine!$AC$9),Lookup_Lists!$D$127,0)+IF(ISNUMBER(Matching_Engine!$AD$9),Lookup_Lists!$D$128,0))=0,"N/A",ROUND((IF(ISNUMBER(Matching_Engine!$AA$9),Matching_Engine!$AA$9*Lookup_Lists!$D$125,0)+IF(ISNUMBER(Matching_Engine!$AB$9),Matching_Engine!$AB$9*Lookup_Lists!$D$126,0)+IF(ISNUMBER(Matching_Engine!$AC$9),Matching_Engine!$AC$9*Lookup_Lists!$D$127,0)+IF(ISNUMBER(Matching_Engine!$AD$9),Matching_Engine!$AD$9*Lookup_Lists!$D$128,0))/(IF(ISNUMBER(Matching_Engine!$AA$9),Lookup_Lists!$D$125,0)+IF(ISNUMBER(Matching_Engine!$AB$9),Lookup_Lists!$D$126,0)+IF(ISNUMBER(Matching_Engine!$AC$9),Lookup_Lists!$D$127,0)+IF(ISNUMBER(Matching_Engine!$AD$9),Lookup_Lists!$D$128,0)),0)) | AF9: =IF(ISNUMBER(Matching_Engine!$AE$9),1,0) | AG9: =IF(NOT(ISNUMBER(KOL_Source_Data!$BG$9)),"N/A",MIN(100,ROUND(KOL_Source_Data!$BG$9/IFERROR(INDEX(Lookup_Lists!$B$340:$B$344,MATCH(KOL_Source_Data!$H$9,Lookup_Lists!$A$340:$A$344,0)),Lookup_Lists!$D$141)*100,0))) | AH9: =IF(NOT(ISNUMBER(KOL_Source_Data!$BS$9)),"N/A",MIN(100,MAX(0,KOL_Source_Data!$BS$9))) | AI9: =IF(OR(NOT(ISNUMBER(KOL_Source_Data!$BM$9)),NOT(ISNUMBER(KOL_Source_Data!$BN$9)),KOL_Source_Data!$BN$9<Lookup_Lists!$D$320),"N/A",MIN(100,ROUND(KOL_Source_Data!$BM$9/Lookup_Lists!$D$319*100,0))) | AJ9: =IF(NOT(ISNUMBER(KOL_Source_Data!$BR$9)),"N/A",KOL_Source_Data!$BR$9) | AK9: =IF(NOT(ISNUMBER(KOL_Source_Data!$BK$9)),"N/A",MIN(100,ROUND(KOL_Source_Data!$BK$9/Lookup_Lists!$D$321*100,0))) | AL9: =IF(NOT(ISNUMBER(KOL_Source_Data!$BP$9)),"N/A",MIN(100,MAX(0,ROUND((KOL_Source_Data!$BP$9+2)/(Lookup_Lists!$D$145+2)*100,0)))) | AM9: =IF((IF(ISNUMBER(Matching_Engine!$AG$9),Lookup_Lists!$D$129,0)+IF(ISNUMBER(Matching_Engine!$AH$9),Lookup_Lists!$D$130,0)+IF(ISNUMBER(Matching_Engine!$AI$9),Lookup_Lists!$D$131,0)+IF(ISNUMBER(Matching_Engine!$AJ$9),Lookup_Lists!$D$132,0)+IF(ISNUMBER(Matching_Engine!$AK$9),Lookup_Lists!$D$133,0)+IF(ISNUMBER(Matching_Engine!$AL$9),Lookup_Lists!$D$134,0))=0,"N/A",ROUND((IF(ISNUMBER(Matching_Engine!$AG$9),Matching_Engine!$AG$9*Lookup_Lists!$D$129,0)+IF(ISNUMBER(Matching_Engine!$AH$9),Matching_Engine!$AH$9*Lookup_Lists!$D$130,0)+IF(ISNUMBER(Matching_Engine!$AI$9),Matching_Engine!$AI$9*Lookup_Lists!$D$131,0)+IF(ISNUMBER(Matching_Engine!$AJ$9),Matching_Engine!$AJ$9*Lookup_Lists!$D$132,0)+IF(ISNUMBER(Matching_Engine!$AK$9),Matching_Engine!$AK$9*Lookup_Lists!$D$133,0)+IF(ISNUMBER(Matching_Engine!$AL$9),Matching_Engine!$AL$9*Lookup_Lists!$D$134,0))/(IF(ISNUMBER(Matching_Engine!$AG$9),Lookup_Lists!$D$129,0)+IF(ISNUMBER(Matching_Engine!$AH$9),Lookup_Lists!$D$130,0)+IF(ISNUMBER(Matching_Engine!$AI$9),Lookup_Lists!$D$131,0)+IF(ISNUMBER(Matching_Engine!$AJ$9),Lookup_Lists!$D$132,0)+IF(ISNUMBER(Matching_Engine!$AK$9),Lookup_Lists!$D$133,0)+IF(ISNUMBER(Matching_Engine!$AL$9),Lookup_Lists!$D$134,0)),0)) | AN9: =IF(ISNUMBER(Matching_Engine!$AM$9),1,0) | AO9: =IF(NOT(ISNUMBER(KOL_Source_Data!$BT$9)),"N/A",MIN(100,MAX(0,KOL_Source_Data!$BT$9))) | AP9: =IF(NOT(ISNUMBER(KOL_Source_Data!$BU$9)),"N/A",MIN(100,MAX(0,KOL_Source_Data!$BU$9))) | AQ9: =IF(KOL_Source_Data!$I$9="Yes",Lookup_Lists!$D$326,IF(KOL_Source_Data!$I$9="No",Lookup_Lists!$D$327,"N/A")) | AR9: =IF(NOT(ISNUMBER(KOL_Source_Data!$BQ$9)),"N/A",MAX(0,ROUND(100-KOL_Source_Data!$BQ$9/Lookup_Lists!$D$328*100,0))) | AS9: =IF(NOT(AND(ISTEXT(KOL_Source_Data!$BV$9),KOL_Source_Data!$BV$9<>"N/A")),"N/A",KOL_Source_Data!$BV$9) | AT9: =IF((IF(ISNUMBER(Matching_Engine!$AO$9),Lookup_Lists!$D$322,0)+IF(ISNUMBER(Matching_Engine!$AP$9),Lookup_Lists!$D$323,0)+IF(ISNUMBER(Matching_Engine!$AQ$9),Lookup_Lists!$D$324,0)+IF(ISNUMBER(Matching_Engine!$AR$9),Lookup_Lists!$D$325,0))=0,"N/A",ROUND((IF(ISNUMBER(Matching_Engine!$AO$9),Matching_Engine!$AO$9*Lookup_Lists!$D$322,0)+IF(ISNUMBER(Matching_Engine!$AP$9),Matching_Engine!$AP$9*Lookup_Lists!$D$323,0)+IF(ISNUMBER(Matching_Engine!$AQ$9),Matching_Engine!$AQ$9*Lookup_Lists!$D$324,0)+IF(ISNUMBER(Matching_Engine!$AR$9),Matching_Engine!$AR$9*Lookup_Lists!$D$325,0))/(IF(ISNUMBER(Matching_Engine!$AO$9),Lookup_Lists!$D$322,0)+IF(ISNUMBER(Matching_Engine!$AP$9),Lookup_Lists!$D$323,0)+IF(ISNUMBER(Matching_Engine!$AQ$9),Lookup_Lists!$D$324,0)+IF(ISNUMBER(Matching_Engine!$AR$9),Lookup_Lists!$D$325,0)),0)) | AU9: =IF(ISNUMBER(Matching_Engine!$AT$9),1,0) | AV9: =IF(NOT(ISNUMBER(Matching_Engine!$AT$9)),"Not Screened",IF(Matching_Engine!$AT$9>=Lookup_Lists!$D$329,"Low Risk",IF(Matching_Engine!$AT$9>=Lookup_Lists!$D$330,"Moderate Risk",IF(Matching_Engine!$AT$9>=Lookup_Lists!$D$331,"Elevated Risk","High Risk")))) | AW9: =IF(NOT(ISNUMBER(Matching_Engine!$AT$9)),"No integrity signal: no audience-analysis row for this account.","Integrity screen only — no content-risk reading exists (comments_analysis: 0 rows). "&IF(ISNUMBER(Matching_Engine!$AO$9),"Authenticity "&Matching_Engine!$AO$9&". ","Authenticity N/A. ")&IF(ISNUMBER(Matching_Engine!$AP$9),"Follower quality "&Matching_Engine!$AP$9&". ","Follower quality N/A. ")&IF(KOL_Source_Data!$I$9="Yes","Platform-verified.","Not platform-verified.")) | AX9: =Matching_Engine!$N$9*Lookup_Lists!$D$104+Matching_Engine!$T$9*Lookup_Lists!$D$105+Matching_Engine!$Z$9*Lookup_Lists!$D$106+Matching_Engine!$AF$9*Lookup_Lists!$D$107+Matching_Engine!$AN$9*Lookup_Lists!$D$108+Matching_Engine!$AU$9*Lookup_Lists!$D$109 | AY9: =IF(Matching_Engine!$AX$9=0,"N/A",ROUND((IF(Matching_Engine!$N$9=1,Matching_Engine!$M$9*Lookup_Lists!$D$104,0)+IF(Matching_Engine!$T$9=1,Matching_Engine!$S$9*Lookup_Lists!$D$105,0)+IF(Matching_Engine!$Z$9=1,Matching_Engine!$Y$9*Lookup_Lists!$D$106,0)+IF(Matching_Engine!$AF$9=1,Matching_Engine!$AE$9*Lookup_Lists!$D$107,0)+IF(Matching_Engine!$AN$9=1,Matching_Engine!$AM$9*Lookup_Lists!$D$108,0)+IF(Matching_Engine!$AU$9=1,Matching_Engine!$AT$9*Lookup_Lists!$D$109,0))/Matching_Engine!$AX$9,0)) | AZ9: =IF(NOT(ISNUMBER(Matching_Engine!$AY$9)),"Not Scored",IF(Matching_Engine!$AY$9>=Lookup_Lists!$D$152,"Excellent Match",IF(Matching_Engine!$AY$9>=Lookup_Lists!$D$153,"Strong Match",IF(Matching_Engine!$AY$9>=Lookup_Lists!$D$154,"Good Match",IF(Matching_Engine!$AY$9>=Lookup_Lists!$D$155,"Moderate Match","Low Match"))))) | BA9: =KOL_Source_Data!$BW$9 | BB9: =KOL_Source_Data!$BX$9 | BC9: =IF(NOT(ISNUMBER(Matching_Engine!$AY$9)),-1,Matching_Engine!$AY$9*1000+21) | BD9: =IF(AND(ISTEXT(KOL_Source_Data!$S$9),KOL_Source_Data!$S$9<>"N/A"),KOL_Source_Data!$S$9,"")&" | "&IF(AND(ISTEXT(KOL_Source_Data!$T$9),KOL_Source_Data!$T$9<>"N/A"),KOL_Source_Data!$T$9,"")&" | "&IF(AND(ISTEXT(KOL_Source_Data!$N$9),KOL_Source_Data!$N$9<>"N/A"),KOL_Source_Data!$N$9,"")&" | "&IF(AND(ISTEXT(KOL_Source_Data!$K$9),KOL_Source_Data!$K$9<>"N/A"),KOL_Source_Data!$K$9,"")&" | "&IF(AND(ISTEXT(KOL_Source_Data!$J$9),KOL_Source_Data!$J$9<>"N/A"),KOL_Source_Data!$J$9,"") | BE9: =IF(AND(ISTEXT(KOL_Source_Data!$T$9),KOL_Source_Data!$T$9<>"N/A"),KOL_Source_Data!$T$9,"")&" | "&IF(AND(ISTEXT(KOL_Source_Data!$N$9),KOL_Source_Data!$N$9<>"N/A"),KOL_Source_Data!$N$9,"")&" | "&IF(AND(ISTEXT(KOL_Source_Data!$O$9),KOL_Source_Data!$O$9<>"N/A"),KOL_Source_Data!$O$9,"")&" | "&IF(AND(ISTEXT(KOL_Source_Data!$S$9),KOL_Source_Data!$S$9<>"N/A"),KOL_Source_Data!$S$9,"") | BF9: =IF(AND(ISTEXT(KOL_Source_Data!$U$9),KOL_Source_Data!$U$9<>"N/A"),KOL_Source_Data!$U$9,"") | BG9: =Matching_Engine!$A$9&"|"&Matching_Engine!$C$9
